Workbook

Sheet README
A1: Software Valuation Model — owner-FCF DCF with durability-weighted buy prices
A3: HOW TO UPDATE AFTER A NEW FILING
A4: 1. Go to 'Inputs'. Change only BLUE cells (yellow = key judgment calls).
A5: 2. From the 10-Q / 10-K / earnings release, update: price, diluted shares, total debt, cash & investments, FCF (OCF − capex), SBC.
A6: 3. Put any one-time cash items (tax catch-ups, legal settlements, working-capital swings) in 'One-time items to remove'.
A7: 4. Revisit the judgment cells: starting growth (anchor to guidance) and P(durable).
A8: 5. Read results on 'Summary'. Use 'Sensitivity' (pick a ticker in the yellow cell) to see how r and g move value.
A9: 6. Record what changed on 'Filing Log' so you can see how your target evolved.
A11: ADDING A COMPANY
A12: Fill an empty column (G or H) on 'Inputs'. Everything else picks it up automatically (6 slots total).
A14: COLOR LEGEND
A15: Blue text = hardcoded input you edit · Black = formula (do not edit) · Green = link from another sheet · Yellow fill = key judgment assumption
... A27: Cells marked EST in the source notes are analyst estimates. P(durable) is a judgment, not data. This is analysis, not personal financial advice.

Sheet Summary
A1: Summary — price targets (all formulas; edit 'Inputs')
A2: ="Base r "&TEXT(Inputs!B4,"0.0%")&" · Conservative r "&TEXT(Inputs!B5,"0.0%")&" · Terminal g "&TEXT(Inputs!B6,"0.0%")&" · Bear decline "&TEXT(Inputs!B7,"0.0%")&" · MOS "&TEXT(Inputs!B8,"0%")
A4: Slot | B4: Ticker | C4: Price | D4: EV / owner FCF | E4: SBC % of FCF | F4: Starting growth | G4: Going-concern value (base r) | H4: Going-concern value (cons. r) | I4: Bear value (cons. r) | J4: P(durable) | K4: Weighted value (cons. r) | L4: Going-concern × (1−MOS) | M4: BUY BELOW | N4: Price vs buy-below | O4: Implied growth (base r) | P4: Implied growth (cons. r) | Q4: Verdict
A5: 1 | B5: =IF(INDEX(Inputs!$C$12:$H$12,$A5)="","",INDEX(Inputs!$C$12:$H$12,$A5)) | C5: =IF($B5="","",INDEX(Inputs!$C$14:$H$14,$A5)) | D5: =IF($B5="","",(INDEX(Inputs!$C$14:$H$14,$A5)*INDEX(Inputs!$C$15:$H$15,$A5)+INDEX(Inputs!$C$19:$H$19,$A5))/INDEX(Inputs!$C$25:$H$25,$A5)) | E5: =IF($B5="","",INDEX(Inputs!$C$24:$H$24,$A5)/INDEX(Inputs!$C$23:$H$23,$A5)) | F5: =IF($B5="","",INDEX(Inputs!$C$26:$H$26,$A5)) | G5: =IF($B5="","",INDEX(DCF!$C$60:$H$60,$A5)) | H5: =IF($B5="","",INDEX(DCF!$C$65:$H$65,$A5)) | I5: =IF($B5="","",INDEX(DCF!$C$66:$H$66,$A5)) | J5: =IF($B5="","",INDEX(Inputs!$C$27:$H$27,$A5)) | K5: =IF($B5="","",J5*H5+(1-J5)*I5) | L5: =IF($B5="","",H5*(1-Inputs!$B$8)) | M5: =IF($B5="","",MIN(K5,L5)) | N5: =IF($B5="","",M5/C5-1) | O5: =IF($B5="","",IF((INDEX(Inputs!$C$14:$H$14,$A5)*INDEX(Inputs!$C$15:$H$15,$A5)+INDEX(Inputs!$C$19:$H$19,$A5))/INDEX(Inputs!$C$25:$H$25,$A5)<ImpliedCalc!$L$4,"< -20%",IF((INDEX(Inputs!$C$14:$H$14,$A5)*INDEX(Inputs!$C$15:$H$15,$A5)+INDEX(Inputs!$C$19:$H$19,$A5))/INDEX(Inputs!$C$25:$H$25,$A5)>ImpliedCalc!$L$124,"> 40%",INDEX(ImpliedCalc!$A$4:$A$124,MATCH((INDEX(Inputs!$C$14:$H$14,$A5)*INDEX(Inputs!$C$15:$H$15,$A5)+INDEX(Inputs!$C$19:$H$19,$A5))/INDEX(Inputs!$C$25:$H$25,$A5),ImpliedCalc!$L$4:$L$124,1))))) | P5: =IF($B5="","",IF((INDEX(Inputs!$C$14:$H$14,$A5)*INDEX(Inputs!$C$15:$H$15,$A5)+INDEX(Inputs!$C$19:$H$19,$A5))/INDEX(Inputs!$C$25:$H$25,$A5)<ImpliedCalc!$M$4,"< -20%",IF((INDEX(Inputs!$C$14:$H$14,$A5)*INDEX(Inputs!$C$15:$H$15,$A5)+INDEX(Inputs!$C$19:$H$19,$A5))/INDEX(Inputs!$C$25:$H$25,$A5)>ImpliedCalc!$M$124,"> 40%",INDEX(ImpliedCalc!$A$4:$A$124,MATCH((INDEX(Inputs!$C$14:$H$14,$A5)*INDEX(Inputs!$C$15:$H$15,$A5)+INDEX(Inputs!$C$19:$H$19,$A5))/INDEX(Inputs!$C$25:$H$25,$A5),ImpliedCalc!$M$4:$M$124,1))))) | Q5: =IF($B5="","",IF(C5<=M5,"BUY ZONE",IF(C5<=M5*1.1,"WATCH","NO BUY")))
A6: 2 | B6: =IF(INDEX(Inputs!$C$12:$H$12,$A6)="","",INDEX(Inputs!$C$12:$H$12,$A6)) | C6: =IF($B6="","",INDEX(Inputs!$C$14:$H$14,$A6)) | D6: =IF($B6="","",(INDEX(Inputs!$C$14:$H$14,$A6)*INDEX(Inputs!$C$15:$H$15,$A6)+INDEX(Inputs!$C$19:$H$19,$A6))/INDEX(Inputs!$C$25:$H$25,$A6)) | E6: =IF($B6="","",INDEX(Inputs!$C$24:$H$24,$A6)/INDEX(Inputs!$C$23:$H$23,$A6)) | F6: =IF($B6="","",INDEX(Inputs!$C$26:$H$26,$A6)) | G6: =IF($B6="","",INDEX(DCF!$C$60:$H$60,$A6)) | H6: =IF($B6="","",INDEX(DCF!$C$65:$H$65,$A6)) | I6: =IF($B6="","",INDEX(DCF!$C$66:$H$66,$A6)) | J6: =IF($B6="","",INDEX(Inputs!$C$27:$H$27,$A6)) | K6: =IF($B6="","",J6*H6+(1-J6)*I6) | L6: =IF($B6="","",H6*(1-Inputs!$B$8)) | M6: =IF($B6="","",MIN(K6,L6)) | N6: =IF($B6="","",M6/C6-1) | O6: =IF($B6="","",IF((INDEX(Inputs!$C$14:$H$14,$A6)*INDEX(Inputs!$C$15:$H$15,$A6)+INDEX(Inputs!$C$19:$H$19,$A6))/INDEX(Inputs!$C$25:$H$25,$A6)<ImpliedCalc!$L$4,"< -20%",IF((INDEX(Inputs!$C$14:$H$14,$A6)*INDEX(Inputs!$C$15:$H$15,$A6)+INDEX(Inputs!$C$19:$H$19,$A6))/INDEX(Inputs!$C$25:$H$25,$A6)>ImpliedCalc!$L$124,"> 40%",INDEX(ImpliedCalc!$A$4:$A$124,MATCH((INDEX(Inputs!$C$14:$H$14,$A6)*INDEX(Inputs!$C$15:$H$15,$A6)+INDEX(Inputs!$C$19:$H$19,$A6))/INDEX(Inputs!$C$25:$H$25,$A6),ImpliedCalc!$L$4:$L$124,1))))) | P6: =IF($B6="","",IF((INDEX(Inputs!$C$14:$H$14,$A6)*INDEX(Inputs!$C$15:$H$15,$A6)+INDEX(Inputs!$C$19:$H$19,$A6))/INDEX(Inputs!$C$25:$H$25,$A6)<ImpliedCalc!$M$4,"< -20%",IF((INDEX(Inputs!$C$14:$H$14,$A6)*INDEX(Inputs!$C$15:$H$15,$A6)+INDEX(Inputs!$C$19:$H$19,$A6))/INDEX(Inputs!$C$25:$H$25,$A6)>ImpliedCalc!$M$124,"> 40%",INDEX(ImpliedCalc!$A$4:$A$124,MATCH((INDEX(Inputs!$C$14:$H$14,$A6)*INDEX(Inputs!$C$15:$H$15,$A6)+INDEX(Inputs!$C$19:$H$19,$A6))/INDEX(Inputs!$C$25:$H$25,$A6),ImpliedCalc!$M$4:$M$124,1))))) | Q6: =IF($B6="","",IF(C6<=M6,"BUY ZONE",IF(C6<=M6*1.1,"WATCH","NO BUY")))
A7: 3 | B7: =IF(INDEX(Inputs!$C$12:$H$12,$A7)="","",INDEX(Inputs!$C$12:$H$12,$A7)) | C7: =IF($B7="","",INDEX(Inputs!$C$14:$H$14,$A7)) | D7: =IF($B7="","",(INDEX(Inputs!$C$14:$H$14,$A7)*INDEX(Inputs!$C$15:$H$15,$A7)+INDEX(Inputs!$C$19:$H$19,$A7))/INDEX(Inputs!$C$25:$H$25,$A7)) | E7: =IF($B7="","",INDEX(Inputs!$C$24:$H$24,$A7)/INDEX(Inputs!$C$23:$H$23,$A7)) | F7: =IF($B7="","",INDEX(Inputs!$C$26:$H$26,$A7)) | G7: =IF($B7="","",INDEX(DCF!$C$60:$H$60,$A7)) | H7: =IF($B7="","",INDEX(DCF!$C$65:$H$65,$A7)) | I7: =IF($B7="","",INDEX(DCF!$C$66:$H$66,$A7)) | J7: =IF($B7="","",INDEX(Inputs!$C$27:$H$27,$A7)) | K7: =IF($B7="","",J7*H7+(1-J7)*I7) | L7: =IF($B7="","",H7*(1-Inputs!$B$8)) | M7: =IF($B7="","",MIN(K7,L7)) | N7: =IF($B7="","",M7/C7-1) | O7: =IF($B7="","",IF((INDEX(Inputs!$C$14:$H$14,$A7)*INDEX(Inputs!$C$15:$H$15,$A7)+INDEX(Inputs!$C$19:$H$19,$A7))/INDEX(Inputs!$C$25:$H$25,$A7)<ImpliedCalc!$L$4,"< -20%",IF((INDEX(Inputs!$C$14:$H$14,$A7)*INDEX(Inputs!$C$15:$H$15,$A7)+INDEX(Inputs!$C$19:$H$19,$A7))/INDEX(Inputs!$C$25:$H$25,$A7)>ImpliedCalc!$L$124,"> 40%",INDEX(ImpliedCalc!$A$4:$A$124,MATCH((INDEX(Inputs!$C$14:$H$14,$A7)*INDEX(Inputs!$C$15:$H$15,$A7)+INDEX(Inputs!$C$19:$H$19,$A7))/INDEX(Inputs!$C$25:$H$25,$A7),ImpliedCalc!$L$4:$L$124,1))))) | P7: =IF($B7="","",IF((INDEX(Inputs!$C$14:$H$14,$A7)*INDEX(Inputs!$C$15:$H$15,$A7)+INDEX(Inputs!$C$19:$H$19,$A7))/INDEX(Inputs!$C$25:$H$25,$A7)<ImpliedCalc!$M$4,"< -20%",IF((INDEX(Inputs!$C$14:$H$14,$A7)*INDEX(Inputs!$C$15:$H$15,$A7)+INDEX(Inputs!$C$19:$H$19,$A7))/INDEX(Inputs!$C$25:$H$25,$A7)>ImpliedCalc!$M$124,"> 40%",INDEX(ImpliedCalc!$A$4:$A$124,MATCH((INDEX(Inputs!$C$14:$H$14,$A7)*INDEX(Inputs!$C$15:$H$15,$A7)+INDEX(Inputs!$C$19:$H$19,$A7))/INDEX(Inputs!$C$25:$H$25,$A7),ImpliedCalc!$M$4:$M$124,1))))) | Q7: =IF($B7="","",IF(C7<=M7,"BUY ZONE",IF(C7<=M7*1.1,"WATCH","NO BUY")))
A8: 4 | B8: =IF(INDEX(Inputs!$C$12:$H$12,$A8)="","",INDEX(Inputs!$C$12:$H$12,$A8)) | C8: =IF($B8="","",INDEX(Inputs!$C$14:$H$14,$A8)) | D8: =IF($B8="","",(INDEX(Inputs!$C$14:$H$14,$A8)*INDEX(Inputs!$C$15:$H$15,$A8)+INDEX(Inputs!$C$19:$H$19,$A8))/INDEX(Inputs!$C$25:$H$25,$A8)) | E8: =IF($B8="","",INDEX(Inputs!$C$24:$H$24,$A8)/INDEX(Inputs!$C$23:$H$23,$A8)) | F8: =IF($B8="","",INDEX(Inputs!$C$26:$H$26,$A8)) | G8: =IF($B8="","",INDEX(DCF!$C$60:$H$60,$A8)) | H8: =IF($B8="","",INDEX(DCF!$C$65:$H$65,$A8)) | I8: =IF($B8="","",INDEX(DCF!$C$66:$H$66,$A8)) | J8: =IF($B8="","",INDEX(Inputs!$C$27:$H$27,$A8)) | K8: =IF($B8="","",J8*H8+(1-J8)*I8) | L8: =IF($B8="","",H8*(1-Inputs!$B$8)) | M8: =IF($B8="","",MIN(K8,L8)) | N8: =IF($B8="","",M8/C8-1) | O8: =IF($B8="","",IF((INDEX(Inputs!$C$14:$H$14,$A8)*INDEX(Inputs!$C$15:$H$15,$A8)+INDEX(Inputs!$C$19:$H$19,$A8))/INDEX(Inputs!$C$25:$H$25,$A8)<ImpliedCalc!$L$4,"< -20%",IF((INDEX(Inputs!$C$14:$H$14,$A8)*INDEX(Inputs!$C$15:$H$15,$A8)+INDEX(Inputs!$C$19:$H$19,$A8))/INDEX(Inputs!$C$25:$H$25,$A8)>ImpliedCalc!$L$124,"> 40%",INDEX(ImpliedCalc!$A$4:$A$124,MATCH((INDEX(Inputs!$C$14:$H$14,$A8)*INDEX(Inputs!$C$15:$H$15,$A8)+INDEX(Inputs!$C$19:$H$19,$A8))/INDEX(Inputs!$C$25:$H$25,$A8),ImpliedCalc!$L$4:$L$124,1))))) | P8: =IF($B8="","",IF((INDEX(Inputs!$C$14:$H$14,$A8)*INDEX(Inputs!$C$15:$H$15,$A8)+INDEX(Inputs!$C$19:$H$19,$A8))/INDEX(Inputs!$C$25:$H$25,$A8)<ImpliedCalc!$M$4,"< -20%",IF((INDEX(Inputs!$C$14:$H$14,$A8)*INDEX(Inputs!$C$15:$H$15,$A8)+INDEX(Inputs!$C$19:$H$19,$A8))/INDEX(Inputs!$C$25:$H$25,$A8)>ImpliedCalc!$M$124,"> 40%",INDEX(ImpliedCalc!$A$4:$A$124,MATCH((INDEX(Inputs!$C$14:$H$14,$A8)*INDEX(Inputs!$C$15:$H$15,$A8)+INDEX(Inputs!$C$19:$H$19,$A8))/INDEX(Inputs!$C$25:$H$25,$A8),ImpliedCalc!$M$4:$M$124,1))))) | Q8: =IF($B8="","",IF(C8<=M8,"BUY ZONE",IF(C8<=M8*1.1,"WATCH","NO BUY")))
A9: 5 | B9: =IF(INDEX(Inputs!$C$12:$H$12,$A9)="","",INDEX(Inputs!$C$12:$H$12,$A9)) | C9: =IF($B9="","",INDEX(Inputs!$C$14:$H$14,$A9)) | D9: =IF($B9="","",(INDEX(Inputs!$C$14:$H$14,$A9)*INDEX(Inputs!$C$15:$H$15,$A9)+INDEX(Inputs!$C$19:$H$19,$A9))/INDEX(Inputs!$C$25:$H$25,$A9)) | E9: =IF($B9="","",INDEX(Inputs!$C$24:$H$24,$A9)/INDEX(Inputs!$C$23:$H$23,$A9)) | F9: =IF($B9="","",INDEX(Inputs!$C$26:$H$26,$A9)) | G9: =IF($B9="","",INDEX(DCF!$C$60:$H$60,$A9)) | H9: =IF($B9="","",INDEX(DCF!$C$65:$H$65,$A9)) | I9: =IF($B9="","",INDEX(DCF!$C$66:$H$66,$A9)) | J9: =IF($B9="","",INDEX(Inputs!$C$27:$H$27,$A9)) | K9: =IF($B9="","",J9*H9+(1-J9)*I9) | L9: =IF($B9="","",H9*(1-Inputs!$B$8)) | M9: =IF($B9="","",MIN(K9,L9)) | N9: =IF($B9="","",M9/C9-1) | O9: =IF($B9="","",IF((INDEX(Inputs!$C$14:$H$14,$A9)*INDEX(Inputs!$C$15:$H$15,$A9)+INDEX(Inputs!$C$19:$H$19,$A9))/INDEX(Inputs!$C$25:$H$25,$A9)<ImpliedCalc!$L$4,"< -20%",IF((INDEX(Inputs!$C$14:$H$14,$A9)*INDEX(Inputs!$C$15:$H$15,$A9)+INDEX(Inputs!$C$19:$H$19,$A9))/INDEX(Inputs!$C$25:$H$25,$A9)>ImpliedCalc!$L$124,"> 40%",INDEX(ImpliedCalc!$A$4:$A$124,MATCH((INDEX(Inputs!$C$14:$H$14,$A9)*INDEX(Inputs!$C$15:$H$15,$A9)+INDEX(Inputs!$C$19:$H$19,$A9))/INDEX(Inputs!$C$25:$H$25,$A9),ImpliedCalc!$L$4:$L$124,1))))) | P9: =IF($B9="","",IF((INDEX(Inputs!$C$14:$H$14,$A9)*INDEX(Inputs!$C$15:$H$15,$A9)+INDEX(Inputs!$C$19:$H$19,$A9))/INDEX(Inputs!$C$25:$H$25,$A9)<ImpliedCalc!$M$4,"< -20%",IF((INDEX(Inputs!$C$14:$H$14,$A9)*INDEX(Inputs!$C$15:$H$15,$A9)+INDEX(Inputs!$C$19:$H$19,$A9))/INDEX(Inputs!$C$25:$H$25,$A9)>ImpliedCalc!$M$124,"> 40%",INDEX(ImpliedCalc!$A$4:$A$124,MATCH((INDEX(Inputs!$C$14:$H$14,$A9)*INDEX(Inputs!$C$15:$H$15,$A9)+INDEX(Inputs!$C$19:$H$19,$A9))/INDEX(Inputs!$C$25:$H$25,$A9),ImpliedCalc!$M$4:$M$124,1))))) | Q9: =IF($B9="","",IF(C9<=M9,"BUY ZONE",IF(C9<=M9*1.1,"WATCH","NO BUY")))
A10: 6 | B10: =IF(INDEX(Inputs!$C$12:$H$12,$A10)="","",INDEX(Inputs!$C$12:$H$12,$A10)) | C10: =IF($B10="","",INDEX(Inputs!$C$14:$H$14,$A10)) | D10: =IF($B10="","",(INDEX(Inputs!$C$14:$H$14,$A10)*INDEX(Inputs!$C$15:$H$15,$A10)+INDEX(Inputs!$C$19:$H$19,$A10))/INDEX(Inputs!$C$25:$H$25,$A10)) | E10: =IF($B10="","",INDEX(Inputs!$C$24:$H$24,$A10)/INDEX(Inputs!$C$23:$H$23,$A10)) | F10: =IF($B10="","",INDEX(Inputs!$C$26:$H$26,$A10)) | G10: =IF($B10="","",INDEX(DCF!$C$60:$H$60,$A10)) | H10: =IF($B10="","",INDEX(DCF!$C$65:$H$65,$A10)) | I10: =IF($B10="","",INDEX(DCF!$C$66:$H$66,$A10)) | J10: =IF($B10="","",INDEX(Inputs!$C$27:$H$27,$A10)) | K10: =IF($B10="","",J10*H10+(1-J10)*I10) | L10: =IF($B10="","",H10*(1-Inputs!$B$8)) | M10: =IF($B10="","",MIN(K10,L10)) | N10: =IF($B10="","",M10/C10-1) | O10: =IF($B10="","",IF((INDEX(Inputs!$C$14:$H$14,$A10)*INDEX(Inputs!$C$15:$H$15,$A10)+INDEX(Inputs!$C$19:$H$19,$A10))/INDEX(Inputs!$C$25:$H$25,$A10)<ImpliedCalc!$L$4,"< -20%",IF((INDEX(Inputs!$C$14:$H$14,$A10)*INDEX(Inputs!$C$15:$H$15,$A10)+INDEX(Inputs!$C$19:$H$19,$A10))/INDEX(Inputs!$C$25:$H$25,$A10)>ImpliedCalc!$L$124,"> 40%",INDEX(ImpliedCalc!$A$4:$A$124,MATCH((INDEX(Inputs!$C$14:$H$14,$A10)*INDEX(Inputs!$C$15:$H$15,$A10)+INDEX(Inputs!$C$19:$H$19,$A10))/INDEX(Inputs!$C$25:$H$25,$A10),ImpliedCalc!$L$4:$L$124,1))))) | P10: =IF($B10="","",IF((INDEX(Inputs!$C$14:$H$14,$A10)*INDEX(Inputs!$C$15:$H$15,$A10)+INDEX(Inputs!$C$19:$H$19,$A10))/INDEX(Inputs!$C$25:$H$25,$A10)<ImpliedCalc!$M$4,"< -20%",IF((INDEX(Inputs!$C$14:$H$14,$A10)*INDEX(Inputs!$C$15:$H$15,$A10)+INDEX(Inputs!$C$19:$H$19,$A10))/INDEX(Inputs!$C$25:$H$25,$A10)>ImpliedCalc!$M$124,"> 40%",INDEX(ImpliedCalc!$A$4:$A$124,MATCH((INDEX(Inputs!$C$14:$H$14,$A10)*INDEX(Inputs!$C$15:$H$15,$A10)+INDEX(Inputs!$C$19:$H$19,$A10))/INDEX(Inputs!$C$25:$H$25,$A10),ImpliedCalc!$M$4:$M$124,1))))) | Q10: =IF($B10="","",IF(C10<=M10,"BUY ZONE",IF(C10<=M10*1.1,"WATCH","NO BUY")))
A12: Buy below = MIN(weighted value, going-concern × (1 − MOS)), both at the conservative discount rate. Verdict: BUY ZONE if price ≤ buy-below; WATCH if within 10% above; else NO BUY.
A13: Implied growth = starting growth at which going-concern value equals today's price (0.5% steps). Compare with guidance: far above guidance = market optimistic; below = market pessimistic.
A15: P(durable) sensitivity of weighted value (cons. r)
B16: Ticker | C16: 0.3 | D16: 0.5 | E16: 0.7 | F16: 0.9
B17: =B5 | C17: =IF($B17="","",C$16*$H5+(1-C$16)*$I5) | D17: =IF($B17="","",D$16*$H5+(1-D$16)*$I5) | E17: =IF($B17="","",E$16*$H5+(1-E$16)*$I5) | F17: =IF($B17="","",F$16*$H5+(1-F$16)*$I5)
B18: =B6 | C18: =IF($B18="","",C$16*$H6+(1-C$16)*$I6) | D18: =IF($B18="","",D$16*$H6+(1-D$16)*$I6) | E18: =IF($B18="","",E$16*$H6+(1-E$16)*$I6) | F18: =IF($B18="","",F$16*$H6+(1-F$16)*$I6)
B19: =B7 | C19: =IF($B19="","",C$16*$H7+(1-C$16)*$I7) | D19: =IF($B19="","",D$16*$H7+(1-D$16)*$I7) | E19: =IF($B19="","",E$16*$H7+(1-E$16)*$I7) | F19: =IF($B19="","",F$16*$H7+(1-F$16)*$I7)
B20: =B8 | C20: =IF($B20="","",C$16*$H8+(1-C$16)*$I8) | D20: =IF($B20="","",D$16*$H8+(1-D$16)*$I8) | E20: =IF($B20="","",E$16*$H8+(1-E$16)*$I8) | F20: =IF($B20="","",F$16*$H8+(1-F$16)*$I8)
B21: =B9 | C21: =IF($B21="","",C$16*$H9+(1-C$16)*$I9) | D21: =IF($B21="","",D$16*$H9+(1-D$16)*$I9) | E21: =IF($B21="","",E$16*$H9+(1-E$16)*$I9) | F21: =IF($B21="","",F$16*$H9+(1-F$16)*$I9)
B22: =B10 | C22: =IF($B22="","",C$16*$H10+(1-C$16)*$I10) | D22: =IF($B22="","",D$16*$H10+(1-D$16)*$I10) | E22: =IF($B22="","",E$16*$H10+(1-E$16)*$I10) | F22: =IF($B22="","",F$16*$H10+(1-F$16)*$I10)

Sheet Sensitivity
A1: Sensitivity — going-concern value per share
A3: Pick ticker: | B3: INTU
A4: Slot | B4: =MATCH(B3,Inputs!$C$12:$H$12,0)
A5: Price | B5: =INDEX(Inputs!$C$14:$H$14,B4)
A6: Owner FCF ($mm) | B6: =INDEX(Inputs!$C$25:$H$25,B4)
A7: Net debt ($mm) | B7: =INDEX(Inputs!$C$19:$H$19,B4)
A8: Shares (mm) | B8: =INDEX(Inputs!$C$15:$H$15,B4)
A10: Discount rate ↓ / Starting growth → (edit the blue/yellow cells)
B11: -0.05 | C11: 0 | D11: 0.05 | E11: 0.09 | F11: 0.13 | G11: 0.17
A12: 0.085 | B12: =IF($B$4="","",($B$6*(SUMPRODUCT(B$27:B$36,1/(1+$A12)^$A$27:$A$36)+B$36*(1+Inputs!$B$6)/($A12-Inputs!$B$6)/(1+$A12)^10)-$B$7)/$B$8) | C12: =IF($B$4="","",($B$6*(SUMPRODUCT(C$27:C$36,1/(1+$A12)^$A$27:$A$36)+C$36*(1+Inputs!$B$6)/($A12-Inputs!$B$6)/(1+$A12)^10)-$B$7)/$B$8) | D12: =IF($B$4="","",($B$6*(SUMPRODUCT(D$27:D$36,1/(1+$A12)^$A$27:$A$36)+D$36*(1+Inputs!$B$6)/($A12-Inputs!$B$6)/(1+$A12)^10)-$B$7)/$B$8) | E12: =IF($B$4="","",($B$6*(SUMPRODUCT(E$27:E$36,1/(1+$A12)^$A$27:$A$36)+E$36*(1+Inputs!$B$6)/($A12-Inputs!$B$6)/(1+$A12)^10)-$B$7)/$B$8) | F12: =IF($B$4="","",($B$6*(SUMPRODUCT(F$27:F$36,1/(1+$A12)^$A$27:$A$36)+F$36*(1+Inputs!$B$6)/($A12-Inputs!$B$6)/(1+$A12)^10)-$B$7)/$B$8) | G12: =IF($B$4="","",($B$6*(SUMPRODUCT(G$27:G$36,1/(1+$A12)^$A$27:$A$36)+G$36*(1+Inputs!$B$6)/($A12-Inputs!$B$6)/(1+$A12)^10)-$B$7)/$B$8)
A13: 0.095 | B13: =IF($B$4="","",($B$6*(SUMPRODUCT(B$27:B$36,1/(1+$A13)^$A$27:$A$36)+B$36*(1+Inputs!$B$6)/($A13-Inputs!$B$6)/(1+$A13)^10)-$B$7)/$B$8) | C13: =IF($B$4="","",($B$6*(SUMPRODUCT(C$27:C$36,1/(1+$A13)^$A$27:$A$36)+C$36*(1+Inputs!$B$6)/($A13-Inputs!$B$6)/(1+$A13)^10)-$B$7)/$B$8) | D13: =IF($B$4="","",($B$6*(SUMPRODUCT(D$27:D$36,1/(1+$A13)^$A$27:$A$36)+D$36*(1+Inputs!$B$6)/($A13-Inputs!$B$6)/(1+$A13)^10)-$B$7)/$B$8) | E13: =IF($B$4="","",($B$6*(SUMPRODUCT(E$27:E$36,1/(1+$A13)^$A$27:$A$36)+E$36*(1+Inputs!$B$6)/($A13-Inputs!$B$6)/(1+$A13)^10)-$B$7)/$B$8) | F13: =IF($B$4="","",($B$6*(SUMPRODUCT(F$27:F$36,1/(1+$A13)^$A$27:$A$36)+F$36*(1+Inputs!$B$6)/($A13-Inputs!$B$6)/(1+$A13)^10)-$B$7)/$B$8) | G13: =IF($B$4="","",($B$6*(SUMPRODUCT(G$27:G$36,1/(1+$A13)^$A$27:$A$36)+G$36*(1+Inputs!$B$6)/($A13-Inputs!$B$6)/(1+$A13)^10)-$B$7)/$B$8)
A14: 0.105 | B14: =IF($B$4="","",($B$6*(SUMPRODUCT(B$27:B$36,1/(1+$A14)^$A$27:$A$36)+B$36*(1+Inputs!$B$6)/($A14-Inputs!$B$6)/(1+$A14)^10)-$B$7)/$B$8) | C14: =IF($B$4="","",($B$6*(SUMPRODUCT(C$27:C$36,1/(1+$A14)^$A$27:$A$36)+C$36*(1+Inputs!$B$6)/($A14-Inputs!$B$6)/(1+$A14)^10)-$B$7)/$B$8) | D14: =IF($B$4="","",($B$6*(SUMPRODUCT(D$27:D$36,1/(1+$A14)^$A$27:$A$36)+D$36*(1+Inputs!$B$6)/($A14-Inputs!$B$6)/(1+$A14)^10)-$B$7)/$B$8) | E14: =IF($B$4="","",($B$6*(SUMPRODUCT(E$27:E$36,1/(1+$A14)^$A$27:$A$36)+E$36*(1+Inputs!$B$6)/($A14-Inputs!$B$6)/(1+$A14)^10)-$B$7)/$B$8) | F14: =IF($B$4="","",($B$6*(SUMPRODUCT(F$27:F$36,1/(1+$A14)^$A$27:$A$36)+F$36*(1+Inputs!$B$6)/($A14-Inputs!$B$6)/(1+$A14)^10)-$B$7)/$B$8) | G14: =IF($B$4="","",($B$6*(SUMPRODUCT(G$27:G$36,1/(1+$A14)^$A$27:$A$36)+G$36*(1+Inputs!$B$6)/($A14-Inputs!$B$6)/(1+$A14)^10)-$B$7)/$B$8)
A15: 0.115 | B15: =IF($B$4="","",($B$6*(SUMPRODUCT(B$27:B$36,1/(1+$A15)^$A$27:$A$36)+B$36*(1+Inputs!$B$6)/($A15-Inputs!$B$6)/(1+$A15)^10)-$B$7)/$B$8) | C15: =IF($B$4="","",($B$6*(SUMPRODUCT(C$27:C$36,1/(1+$A15)^$A$27:$A$36)+C$36*(1+Inputs!$B$6)/($A15-Inputs!$B$6)/(1+$A15)^10)-$B$7)/$B$8) | D15: =IF($B$4="","",($B$6*(SUMPRODUCT(D$27:D$36,1/(1+$A15)^$A$27:$A$36)+D$36*(1+Inputs!$B$6)/($A15-Inputs!$B$6)/(1+$A15)^10)-$B$7)/$B$8) | E15: =IF($B$4="","",($B$6*(SUMPRODUCT(E$27:E$36,1/(1+$A15)^$A$27:$A$36)+E$36*(1+Inputs!$B$6)/($A15-Inputs!$B$6)/(1+$A15)^10)-$B$7)/$B$8) | F15: =IF($B$4="","",($B$6*(SUMPRODUCT(F$27:F$36,1/(1+$A15)^$A$27:$A$36)+F$36*(1+Inputs!$B$6)/($A15-Inputs!$B$6)/(1+$A15)^10)-$B$7)/$B$8) | G15: =IF($B$4="","",($B$6*(SUMPRODUCT(G$27:G$36,1/(1+$A15)^$A$27:$A$36)+G$36*(1+Inputs!$B$6)/($A15-Inputs!$B$6)/(1+$A15)^10)-$B$7)/$B$8)
A16: 0.125 | B16: =IF($B$4="","",($B$6*(SUMPRODUCT(B$27:B$36,1/(1+$A16)^$A$27:$A$36)+B$36*(1+Inputs!$B$6)/($A16-Inputs!$B$6)/(1+$A16)^10)-$B$7)/$B$8) | C16: =IF($B$4="","",($B$6*(SUMPRODUCT(C$27:C$36,1/(1+$A16)^$A$27:$A$36)+C$36*(1+Inputs!$B$6)/($A16-Inputs!$B$6)/(1+$A16)^10)-$B$7)/$B$8) | D16: =IF($B$4="","",($B$6*(SUMPRODUCT(D$27:D$36,1/(1+$A16)^$A$27:$A$36)+D$36*(1+Inputs!$B$6)/($A16-Inputs!$B$6)/(1+$A16)^10)-$B$7)/$B$8) | E16: =IF($B$4="","",($B$6*(SUMPRODUCT(E$27:E$36,1/(1+$A16)^$A$27:$A$36)+E$36*(1+Inputs!$B$6)/($A16-Inputs!$B$6)/(1+$A16)^10)-$B$7)/$B$8) | F16: =IF($B$4="","",($B$6*(SUMPRODUCT(F$27:F$36,1/(1+$A16)^$A$27:$A$36)+F$36*(1+Inputs!$B$6)/($A16-Inputs!$B$6)/(1+$A16)^10)-$B$7)/$B$8) | G16: =IF($B$4="","",($B$6*(SUMPRODUCT(G$27:G$36,1/(1+$A16)^$A$27:$A$36)+G$36*(1+Inputs!$B$6)/($A16-Inputs!$B$6)/(1+$A16)^10)-$B$7)/$B$8)
A18: Green = value above today's price; red = below. Terminal growth comes from Inputs!B6; change it there to test 2% vs 3%.
A25: Helper: cumulative growth factors per column (do not edit)
A26: Year | B26: =B11 | C26: =C11 | D26: =D11 | E26: =E11 | F26: =F11 | G26: =G11
A27: 1 | B27: =1*(1+B$11+(Inputs!$B$6-B$11)*($A27-1)/9) | C27: =1*(1+C$11+(Inputs!$B$6-C$11)*($A27-1)/9) | D27: =1*(1+D$11+(Inputs!$B$6-D$11)*($A27-1)/9) | E27: =1*(1+E$11+(Inputs!$B$6-E$11)*($A27-1)/9) | F27: =1*(1+F$11+(Inputs!$B$6-F$11)*($A27-1)/9) | G27: =1*(1+G$11+(Inputs!$B$6-G$11)*($A27-1)/9)
A28: 2 | B28: =B27*(1+B$11+(Inputs!$B$6-B$11)*($A28-1)/9) | C28: =C27*(1+C$11+(Inputs!$B$6-C$11)*($A28-1)/9) | D28: =D27*(1+D$11+(Inputs!$B$6-D$11)*($A28-1)/9) | E28: =E27*(1+E$11+(Inputs!$B$6-E$11)*($A28-1)/9) | F28: =F27*(1+F$11+(Inputs!$B$6-F$11)*($A28-1)/9) | G28: =G27*(1+G$11+(Inputs!$B$6-G$11)*($A28-1)/9)
A29: 3 | B29: =B28*(1+B$11+(Inputs!$B$6-B$11)*($A29-1)/9) | C29: =C28*(1+C$11+(Inputs!$B$6-C$11)*($A29-1)/9) | D29: =D28*(1+D$11+(Inputs!$B$6-D$11)*($A29-1)/9) | E29: =E28*(1+E$11+(Inputs!$B$6-E$11)*($A29-1)/9) | F29: =F28*(1+F$11+(Inputs!$B$6-F$11)*($A29-1)/9) | G29: =G28*(1+G$11+(Inputs!$B$6-G$11)*($A29-1)/9)
A30: 4 | B30: =B29*(1+B$11+(Inputs!$B$6-B$11)*($A30-1)/9) | C30: =C29*(1+C$11+(Inputs!$B$6-C$11)*($A30-1)/9) | D30: =D29*(1+D$11+(Inputs!$B$6-D$11)*($A30-1)/9) | E30: =E29*(1+E$11+(Inputs!$B$6-E$11)*($A30-1)/9) | F30: =F29*(1+F$11+(Inputs!$B$6-F$11)*($A30-1)/9) | G30: =G29*(1+G$11+(Inputs!$B$6-G$11)*($A30-1)/9)
A31: 5 | B31: =B30*(1+B$11+(Inputs!$B$6-B$11)*($A31-1)/9) | C31: =C30*(1+C$11+(Inputs!$B$6-C$11)*($A31-1)/9) | D31: =D30*(1+D$11+(Inputs!$B$6-D$11)*($A31-1)/9) | E31: =E30*(1+E$11+(Inputs!$B$6-E$11)*($A31-1)/9) | F31: =F30*(1+F$11+(Inputs!$B$6-F$11)*($A31-1)/9) | G31: =G30*(1+G$11+(Inputs!$B$6-G$11)*($A31-1)/9)
A32: 6 | B32: =B31*(1+B$11+(Inputs!$B$6-B$11)*($A32-1)/9) | C32: =C31*(1+C$11+(Inputs!$B$6-C$11)*($A32-1)/9) | D32: =D31*(1+D$11+(Inputs!$B$6-D$11)*($A32-1)/9) | E32: =E31*(1+E$11+(Inputs!$B$6-E$11)*($A32-1)/9) | F32: =F31*(1+F$11+(Inputs!$B$6-F$11)*($A32-1)/9) | G32: =G31*(1+G$11+(Inputs!$B$6-G$11)*($A32-1)/9)
A33: 7 | B33: =B32*(1+B$11+(Inputs!$B$6-B$11)*($A33-1)/9) | C33: =C32*(1+C$11+(Inputs!$B$6-C$11)*($A33-1)/9) | D33: =D32*(1+D$11+(Inputs!$B$6-D$11)*($A33-1)/9) | E33: =E32*(1+E$11+(Inputs!$B$6-E$11)*($A33-1)/9) | F33: =F32*(1+F$11+(Inputs!$B$6-F$11)*($A33-1)/9) | G33: =G32*(1+G$11+(Inputs!$B$6-G$11)*($A33-1)/9)
A34: 8 | B34: =B33*(1+B$11+(Inputs!$B$6-B$11)*($A34-1)/9) | C34: =C33*(1+C$11+(Inputs!$B$6-C$11)*($A34-1)/9) | D34: =D33*(1+D$11+(Inputs!$B$6-D$11)*($A34-1)/9) | E34: =E33*(1+E$11+(Inputs!$B$6-E$11)*($A34-1)/9) | F34: =F33*(1+F$11+(Inputs!$B$6-F$11)*($A34-1)/9) | G34: =G33*(1+G$11+(Inputs!$B$6-G$11)*($A34-1)/9)
A35: 9 | B35: =B34*(1+B$11+(Inputs!$B$6-B$11)*($A35-1)/9) | C35: =C34*(1+C$11+(Inputs!$B$6-C$11)*($A35-1)/9) | D35: =D34*(1+D$11+(Inputs!$B$6-D$11)*($A35-1)/9) | E35: =E34*(1+E$11+(Inputs!$B$6-E$11)*($A35-1)/9) | F35: =F34*(1+F$11+(Inputs!$B$6-F$11)*($A35-1)/9) | G35: =G34*(1+G$11+(Inputs!$B$6-G$11)*($A35-1)/9)
A36: 10 | B36: =B35*(1+B$11+(Inputs!$B$6-B$11)*($A36-1)/9) | C36: =C35*(1+C$11+(Inputs!$B$6-C$11)*($A36-1)/9) | D36: =D35*(1+D$11+(Inputs!$B$6-D$11)*($A36-1)/9) | E36: =E35*(1+E$11+(Inputs!$B$6-E$11)*($A36-1)/9) | F36: =F35*(1+F$11+(Inputs!$B$6-F$11)*($A36-1)/9) | G36: =G35*(1+G$11+(Inputs!$B$6-G$11)*($A36-1)/9)

Sheet Inputs
A1: Inputs — edit BLUE cells only
A3: GLOBAL ASSUMPTIONS
A4: Base discount rate | B4: 0.095 | I4: Typical large-cap software cost of equity; CAPM with raw betas 1.3–1.5 gives ~10–11%.
A5: Conservative discount rate (used for buy price) | B5: 0.105 | I5: Higher hurdle used for weighted value and buy-below price.
A6: Terminal growth | B6: 0.03 | I6: Perpetual growth after year 10. 2% cuts value ~11% vs 3%.
A7: Bear case: annual owner-FCF decline | B7: 0.05 | I7: Structural-decline scenario (e.g., AI disruption).
A8: Margin of safety on going-concern value | B8: 0.3 | I8: Buy-below cross-check: going-concern × (1 − this).
A10: COMPANY INPUTS
A11: Item | B11: Units | C11: Slot 1 | D11: Slot 2 | E11: Slot 3 | F11: Slot 4 | G11: Slot 5 | H11: Slot 6 | I11: Notes
A12: Ticker | B12: text | C12: INTU | D12: ADBE | E12: ADSK | F12: CRM
A13: Price date | B13: text | C13: 2026-09-26 | D13: 2026-09-26 | E13: 2026-09-26 | F13: 2026-09-26
A14: Share price | B14: $ | C14: 275.79 | D14: 235.47 | E14: 209.4 | F14: 234.02
A15: Diluted shares | B15: mm | C15: 267 | D15: 396 | E15: 214 | F15: 821 | I15: Use latest diluted count (CRM fell 962M→821M after the ASR).
A16: Total debt | B16: $mm | C16: 7700 | D16: 6360 | E16: 3980 | F16: 39500
A17: Cash & investments | B17: $mm | C17: 7200 | D17: 5640 | E17: 1830 | F17: 11400
A18: Other claims (pending deals, etc.) | B18: $mm | C18: 0 | D18: 0 | E18: 0 | F18: 1500 | I18: Pending cash acquisitions, underfunded pensions, etc.
A19: Net debt | B19: $mm | C19: =IF(C12="","",C16-C17+C18) | D19: =IF(D12="","",D16-D17+D18) | E19: =IF(E12="","",E16-E17+E18) | F19: =IF(F12="","",F16-F17+F18) | G19: =IF(G12="","",G16-G17+G18) | H19: =IF(H12="","",H16-H17+H18)
A20: Reported FCF (OCF − capex), TTM or guided | B20: $mm | C20: 8620 | D20: 10500 | E20: 2740 | F20: 15050
A21: One-time items to remove | B21: $mm | C21: 1120 | D21: 0 | E21: 0 | F21: 0 | I21: Remove non-recurring cash (e.g., INTU FY26 R&D tax catch-up, EST $1.12B).
A22: After-tax net interest add-back (unlevered) | B22: $mm | C22: 0 | D22: 0 | E22: 0 | F22: 950 | I22: Use if FCF is after big interest costs and you subtract net debt (avoids double count).
A23: Normalized FCF | B23: $mm | C23: =IF(C12="","",C20-C21+C22) | D23: =IF(D12="","",D20-D21+D22) | E23: =IF(E12="","",E20-E21+E22) | F23: =IF(F12="","",F20-F21+F22) | G23: =IF(G12="","",G20-G21+G22) | H23: =IF(H12="","",H20-H21+H22)
A24: Stock-based compensation | B24: $mm | C24: 1900 | D24: 2100 | E24: 850 | F24: 3600
A25: Owner FCF (normalized FCF − SBC) | B25: $mm | C25: =IF(C12="","",C23-C24) | D25: =IF(D12="","",D23-D24) | E25: =IF(E12="","",E23-E24) | F25: =IF(F12="","",F23-F24) | G25: =IF(G12="","",G23-G24) | H25: =IF(H12="","",H23-H24)
A26: Starting growth (year 1) | B26: % | C26: 0.09 | D26: 0.1 | E26: 0.12 | F26: 0.09 | I26: Anchor to revenue/FCF guidance; fades linearly to terminal growth by year 10.
A27: P(durable) — judgment | B27: % | C27: 0.5 | D27: 0.5 | E27: 0.8 | F27: 0.8 | I27: Your probability the business stays a durable going concern (vs structural decline). Biggest driver for INTU/ADBE.
A28: FCF period / basis | B28: text | C28: FY26 (Jul-26) reported | D28: TTM to Aug-26 (est.) | E28: FY27 (Jan-27) guidance midpoint | F28: FY27 (Jan-27) guidance (+4-5%)
A29: Last updated | B29: text | C29: 2026-09-27 | D29: 2026-09-27 | E29: 2026-09-27 | F29: 2026-09-27
A30: Source notes | B30: text | C30: FY26 10-K/Q4 release: OCF $8.84B, capex $221M, cash+inv $7.2B, debt $7.7B. One-time = EST R&D-expensing tax catch-up. SBC ~$1.7-2.1B. FY27 rev guide +9-10%. | D30: Q3 FY26 10-Q (Aug-28-26): cash $4.36B + ST inv $1.28B; debt $6.36B. TTM FCF ~$10.3-10.5B. SBC ~$2.1B/yr. FY26 rev ~+12%, ARR +11.2%. | E30: Q2 FY27 10-Q: cash $4.36B, debt $2.98B; then MaintainX $3.53B paid Aug-3 with $1.0B term loan (EST post-deal). FY27 FCF guide $2.725-2.75B; SBC FY26 $788M. | F30: Q2 FY27: cash $8.31B + securities $3.09B; debt ~$39.5B after $25B ASR; Contentful $1.5B pending. FY27 FCF guide +4-5% on $14.4B. Interest add-back EST. Diluted shares 821M.

Sheet DCF
A1: DCF engine — all formulas (no inputs here)
A3: Line | B3: Year | C3: Slot 1 | D3: Slot 2 | E3: Slot 3 | F3: Slot 4 | G3: Slot 5 | H3: Slot 6
A4: Ticker | C4: =IF(Inputs!C12="","",Inputs!C12) | D4: =IF(Inputs!D12="","",Inputs!D12) | E4: =IF(Inputs!E12="","",Inputs!E12) | F4: =IF(Inputs!F12="","",Inputs!F12) | G4: =IF(Inputs!G12="","",Inputs!G12) | H4: =IF(Inputs!H12="","",Inputs!H12)
A5: Owner FCF, year 0 ($mm) | C5: =IF(C$4="","",Inputs!C25) | D5: =IF(D$4="","",Inputs!D25) | E5: =IF(E$4="","",Inputs!E25) | F5: =IF(F$4="","",Inputs!F25) | G5: =IF(G$4="","",Inputs!G25) | H5: =IF(H$4="","",Inputs!H25)
A6: Starting growth | C6: =IF(C$4="","",Inputs!C26) | D6: =IF(D$4="","",Inputs!D26) | E6: =IF(E$4="","",Inputs!E26) | F6: =IF(F$4="","",Inputs!F26) | G6: =IF(G$4="","",Inputs!G26) | H6: =IF(H$4="","",Inputs!H26)
A8: Growth rate by year
A9: Year 1 | B9: 1 | C9: =IF(C$4="","",C$6+(Inputs!$B$6-C$6)*($B9-1)/9) | D9: =IF(D$4="","",D$6+(Inputs!$B$6-D$6)*($B9-1)/9) | E9: =IF(E$4="","",E$6+(Inputs!$B$6-E$6)*($B9-1)/9) | F9: =IF(F$4="","",F$6+(Inputs!$B$6-F$6)*($B9-1)/9) | G9: =IF(G$4="","",G$6+(Inputs!$B$6-G$6)*($B9-1)/9) | H9: =IF(H$4="","",H$6+(Inputs!$B$6-H$6)*($B9-1)/9)
A10: Year 2 | B10: 2 | C10: =IF(C$4="","",C$6+(Inputs!$B$6-C$6)*($B10-1)/9) | D10: =IF(D$4="","",D$6+(Inputs!$B$6-D$6)*($B10-1)/9) | E10: =IF(E$4="","",E$6+(Inputs!$B$6-E$6)*($B10-1)/9) | F10: =IF(F$4="","",F$6+(Inputs!$B$6-F$6)*($B10-1)/9) | G10: =IF(G$4="","",G$6+(Inputs!$B$6-G$6)*($B10-1)/9) | H10: =IF(H$4="","",H$6+(Inputs!$B$6-H$6)*($B10-1)/9)
A11: Year 3 | B11: 3 | C11: =IF(C$4="","",C$6+(Inputs!$B$6-C$6)*($B11-1)/9) | D11: =IF(D$4="","",D$6+(Inputs!$B$6-D$6)*($B11-1)/9) | E11: =IF(E$4="","",E$6+(Inputs!$B$6-E$6)*($B11-1)/9) | F11: =IF(F$4="","",F$6+(Inputs!$B$6-F$6)*($B11-1)/9) | G11: =IF(G$4="","",G$6+(Inputs!$B$6-G$6)*($B11-1)/9) | H11: =IF(H$4="","",H$6+(Inputs!$B$6-H$6)*($B11-1)/9)
A12: Year 4 | B12: 4 | C12: =IF(C$4="","",C$6+(Inputs!$B$6-C$6)*($B12-1)/9) | D12: =IF(D$4="","",D$6+(Inputs!$B$6-D$6)*($B12-1)/9) | E12: =IF(E$4="","",E$6+(Inputs!$B$6-E$6)*($B12-1)/9) | F12: =IF(F$4="","",F$6+(Inputs!$B$6-F$6)*($B12-1)/9) | G12: =IF(G$4="","",G$6+(Inputs!$B$6-G$6)*($B12-1)/9) | H12: =IF(H$4="","",H$6+(Inputs!$B$6-H$6)*($B12-1)/9)
A13: Year 5 | B13: 5 | C13: =IF(C$4="","",C$6+(Inputs!$B$6-C$6)*($B13-1)/9) | D13: =IF(D$4="","",D$6+(Inputs!$B$6-D$6)*($B13-1)/9) | E13: =IF(E$4="","",E$6+(Inputs!$B$6-E$6)*($B13-1)/9) | F13: =IF(F$4="","",F$6+(Inputs!$B$6-F$6)*($B13-1)/9) | G13: =IF(G$4="","",G$6+(Inputs!$B$6-G$6)*($B13-1)/9) | H13: =IF(H$4="","",H$6+(Inputs!$B$6-H$6)*($B13-1)/9)
A14: Year 6 | B14: 6 | C14: =IF(C$4="","",C$6+(Inputs!$B$6-C$6)*($B14-1)/9) | D14: =IF(D$4="","",D$6+(Inputs!$B$6-D$6)*($B14-1)/9) | E14: =IF(E$4="","",E$6+(Inputs!$B$6-E$6)*($B14-1)/9) | F14: =IF(F$4="","",F$6+(Inputs!$B$6-F$6)*($B14-1)/9) | G14: =IF(G$4="","",G$6+(Inputs!$B$6-G$6)*($B14-1)/9) | H14: =IF(H$4="","",H$6+(Inputs!$B$6-H$6)*($B14-1)/9)
A15: Year 7 | B15: 7 | C15: =IF(C$4="","",C$6+(Inputs!$B$6-C$6)*($B15-1)/9) | D15: =IF(D$4="","",D$6+(Inputs!$B$6-D$6)*($B15-1)/9) | E15: =IF(E$4="","",E$6+(Inputs!$B$6-E$6)*($B15-1)/9) | F15: =IF(F$4="","",F$6+(Inputs!$B$6-F$6)*($B15-1)/9) | G15: =IF(G$4="","",G$6+(Inputs!$B$6-G$6)*($B15-1)/9) | H15: =IF(H$4="","",H$6+(Inputs!$B$6-H$6)*($B15-1)/9)
A16: Year 8 | B16: 8 | C16: =IF(C$4="","",C$6+(Inputs!$B$6-C$6)*($B16-1)/9) | D16: =IF(D$4="","",D$6+(Inputs!$B$6-D$6)*($B16-1)/9) | E16: =IF(E$4="","",E$6+(Inputs!$B$6-E$6)*($B16-1)/9) | F16: =IF(F$4="","",F$6+(Inputs!$B$6-F$6)*($B16-1)/9) | G16: =IF(G$4="","",G$6+(Inputs!$B$6-G$6)*($B16-1)/9) | H16: =IF(H$4="","",H$6+(Inputs!$B$6-H$6)*($B16-1)/9)
A17: Year 9 | B17: 9 | C17: =IF(C$4="","",C$6+(Inputs!$B$6-C$6)*($B17-1)/9) | D17: =IF(D$4="","",D$6+(Inputs!$B$6-D$6)*($B17-1)/9) | E17: =IF(E$4="","",E$6+(Inputs!$B$6-E$6)*($B17-1)/9) | F17: =IF(F$4="","",F$6+(Inputs!$B$6-F$6)*($B17-1)/9) | G17: =IF(G$4="","",G$6+(Inputs!$B$6-G$6)*($B17-1)/9) | H17: =IF(H$4="","",H$6+(Inputs!$B$6-H$6)*($B17-1)/9)
A18: Year 10 | B18: 10 | C18: =IF(C$4="","",C$6+(Inputs!$B$6-C$6)*($B18-1)/9) | D18: =IF(D$4="","",D$6+(Inputs!$B$6-D$6)*($B18-1)/9) | E18: =IF(E$4="","",E$6+(Inputs!$B$6-E$6)*($B18-1)/9) | F18: =IF(F$4="","",F$6+(Inputs!$B$6-F$6)*($B18-1)/9) | G18: =IF(G$4="","",G$6+(Inputs!$B$6-G$6)*($B18-1)/9) | H18: =IF(H$4="","",H$6+(Inputs!$B$6-H$6)*($B18-1)/9)
A20: Owner FCF ($mm)
A21: Year 1 | B21: 1 | C21: =IF(C$4="","",C$5*(1+C9)) | D21: =IF(D$4="","",D$5*(1+D9)) | E21: =IF(E$4="","",E$5*(1+E9)) | F21: =IF(F$4="","",F$5*(1+F9)) | G21: =IF(G$4="","",G$5*(1+G9)) | H21: =IF(H$4="","",H$5*(1+H9))
A22: Year 2 | B22: 2 | C22: =IF(C$4="","",C21*(1+C10)) | D22: =IF(D$4="","",D21*(1+D10)) | E22: =IF(E$4="","",E21*(1+E10)) | F22: =IF(F$4="","",F21*(1+F10)) | G22: =IF(G$4="","",G21*(1+G10)) | H22: =IF(H$4="","",H21*(1+H10))
A23: Year 3 | B23: 3 | C23: =IF(C$4="","",C22*(1+C11)) | D23: =IF(D$4="","",D22*(1+D11)) | E23: =IF(E$4="","",E22*(1+E11)) | F23: =IF(F$4="","",F22*(1+F11)) | G23: =IF(G$4="","",G22*(1+G11)) | H23: =IF(H$4="","",H22*(1+H11))
A24: Year 4 | B24: 4 | C24: =IF(C$4="","",C23*(1+C12)) | D24: =IF(D$4="","",D23*(1+D12)) | E24: =IF(E$4="","",E23*(1+E12)) | F24: =IF(F$4="","",F23*(1+F12)) | G24: =IF(G$4="","",G23*(1+G12)) | H24: =IF(H$4="","",H23*(1+H12))
A25: Year 5 | B25: 5 | C25: =IF(C$4="","",C24*(1+C13)) | D25: =IF(D$4="","",D24*(1+D13)) | E25: =IF(E$4="","",E24*(1+E13)) | F25: =IF(F$4="","",F24*(1+F13)) | G25: =IF(G$4="","",G24*(1+G13)) | H25: =IF(H$4="","",H24*(1+H13))
A26: Year 6 | B26: 6 | C26: =IF(C$4="","",C25*(1+C14)) | D26: =IF(D$4="","",D25*(1+D14)) | E26: =IF(E$4="","",E25*(1+E14)) | F26: =IF(F$4="","",F25*(1+F14)) | G26: =IF(G$4="","",G25*(1+G14)) | H26: =IF(H$4="","",H25*(1+H14))
A27: Year 7 | B27: 7 | C27: =IF(C$4="","",C26*(1+C15)) | D27: =IF(D$4="","",D26*(1+D15)) | E27: =IF(E$4="","",E26*(1+E15)) | F27: =IF(F$4="","",F26*(1+F15)) | G27: =IF(G$4="","",G26*(1+G15)) | H27: =IF(H$4="","",H26*(1+H15))
A28: Year 8 | B28: 8 | C28: =IF(C$4="","",C27*(1+C16)) | D28: =IF(D$4="","",D27*(1+D16)) | E28: =IF(E$4="","",E27*(1+E16)) | F28: =IF(F$4="","",F27*(1+F16)) | G28: =IF(G$4="","",G27*(1+G16)) | H28: =IF(H$4="","",H27*(1+H16))
A29: Year 9 | B29: 9 | C29: =IF(C$4="","",C28*(1+C17)) | D29: =IF(D$4="","",D28*(1+D17)) | E29: =IF(E$4="","",E28*(1+E17)) | F29: =IF(F$4="","",F28*(1+F17)) | G29: =IF(G$4="","",G28*(1+G17)) | H29: =IF(H$4="","",H28*(1+H17))
A30: Year 10 | B30: 10 | C30: =IF(C$4="","",C29*(1+C18)) | D30: =IF(D$4="","",D29*(1+D18)) | E30: =IF(E$4="","",E29*(1+E18)) | F30: =IF(F$4="","",F29*(1+F18)) | G30: =IF(G$4="","",G29*(1+G18)) | H30: =IF(H$4="","",H29*(1+H18))
A32: PV of owner FCF @ base discount rate ($mm)
A33: Year 1 | B33: 1 | C33: =IF(C$4="","",C21/(1+Inputs!$B$4)^$B33) | D33: =IF(D$4="","",D21/(1+Inputs!$B$4)^$B33) | E33: =IF(E$4="","",E21/(1+Inputs!$B$4)^$B33) | F33: =IF(F$4="","",F21/(1+Inputs!$B$4)^$B33) | G33: =IF(G$4="","",G21/(1+Inputs!$B$4)^$B33) | H33: =IF(H$4="","",H21/(1+Inputs!$B$4)^$B33)
A34: Year 2 | B34: 2 | C34: =IF(C$4="","",C22/(1+Inputs!$B$4)^$B34) | D34: =IF(D$4="","",D22/(1+Inputs!$B$4)^$B34) | E34: =IF(E$4="","",E22/(1+Inputs!$B$4)^$B34) | F34: =IF(F$4="","",F22/(1+Inputs!$B$4)^$B34) | G34: =IF(G$4="","",G22/(1+Inputs!$B$4)^$B34) | H34: =IF(H$4="","",H22/(1+Inputs!$B$4)^$B34)
A35: Year 3 | B35: 3 | C35: =IF(C$4="","",C23/(1+Inputs!$B$4)^$B35) | D35: =IF(D$4="","",D23/(1+Inputs!$B$4)^$B35) | E35: =IF(E$4="","",E23/(1+Inputs!$B$4)^$B35) | F35: =IF(F$4="","",F23/(1+Inputs!$B$4)^$B35) | G35: =IF(G$4="","",G23/(1+Inputs!$B$4)^$B35) | H35: =IF(H$4="","",H23/(1+Inputs!$B$4)^$B35)
A36: Year 4 | B36: 4 | C36: =IF(C$4="","",C24/(1+Inputs!$B$4)^$B36) | D36: =IF(D$4="","",D24/(1+Inputs!$B$4)^$B36) | E36: =IF(E$4="","",E24/(1+Inputs!$B$4)^$B36) | F36: =IF(F$4="","",F24/(1+Inputs!$B$4)^$B36) | G36: =IF(G$4="","",G24/(1+Inputs!$B$4)^$B36) | H36: =IF(H$4="","",H24/(1+Inputs!$B$4)^$B36)
A37: Year 5 | B37: 5 | C37: =IF(C$4="","",C25/(1+Inputs!$B$4)^$B37) | D37: =IF(D$4="","",D25/(1+Inputs!$B$4)^$B37) | E37: =IF(E$4="","",E25/(1+Inputs!$B$4)^$B37) | F37: =IF(F$4="","",F25/(1+Inputs!$B$4)^$B37) | G37: =IF(G$4="","",G25/(1+Inputs!$B$4)^$B37) | H37: =IF(H$4="","",H25/(1+Inputs!$B$4)^$B37)
A38: Year 6 | B38: 6 | C38: =IF(C$4="","",C26/(1+Inputs!$B$4)^$B38) | D38: =IF(D$4="","",D26/(1+Inputs!$B$4)^$B38) | E38: =IF(E$4="","",E26/(1+Inputs!$B$4)^$B38) | F38: =IF(F$4="","",F26/(1+Inputs!$B$4)^$B38) | G38: =IF(G$4="","",G26/(1+Inputs!$B$4)^$B38) | H38: =IF(H$4="","",H26/(1+Inputs!$B$4)^$B38)
A39: Year 7 | B39: 7 | C39: =IF(C$4="","",C27/(1+Inputs!$B$4)^$B39) | D39: =IF(D$4="","",D27/(1+Inputs!$B$4)^$B39) | E39: =IF(E$4="","",E27/(1+Inputs!$B$4)^$B39) | F39: =IF(F$4="","",F27/(1+Inputs!$B$4)^$B39) | G39: =IF(G$4="","",G27/(1+Inputs!$B$4)^$B39) | H39: =IF(H$4="","",H27/(1+Inputs!$B$4)^$B39)
A40: Year 8 | B40: 8 | C40: =IF(C$4="","",C28/(1+Inputs!$B$4)^$B40) | D40: =IF(D$4="","",D28/(1+Inputs!$B$4)^$B40) | E40: =IF(E$4="","",E28/(1+Inputs!$B$4)^$B40) | F40: =IF(F$4="","",F28/(1+Inputs!$B$4)^$B40) | G40: =IF(G$4="","",G28/(1+Inputs!$B$4)^$B40) | H40: =IF(H$4="","",H28/(1+Inputs!$B$4)^$B40)
A41: Year 9 | B41: 9 | C41: =IF(C$4="","",C29/(1+Inputs!$B$4)^$B41) | D41: =IF(D$4="","",D29/(1+Inputs!$B$4)^$B41) | E41: =IF(E$4="","",E29/(1+Inputs!$B$4)^$B41) | F41: =IF(F$4="","",F29/(1+Inputs!$B$4)^$B41) | G41: =IF(G$4="","",G29/(1+Inputs!$B$4)^$B41) | H41: =IF(H$4="","",H29/(1+Inputs!$B$4)^$B41)
A42: Year 10 | B42: 10 | C42: =IF(C$4="","",C30/(1+Inputs!$B$4)^$B42) | D42: =IF(D$4="","",D30/(1+Inputs!$B$4)^$B42) | E42: =IF(E$4="","",E30/(1+Inputs!$B$4)^$B42) | F42: =IF(F$4="","",F30/(1+Inputs!$B$4)^$B42) | G42: =IF(G$4="","",G30/(1+Inputs!$B$4)^$B42) | H42: =IF(H$4="","",H30/(1+Inputs!$B$4)^$B42)
A44: PV of owner FCF @ conservative discount rate ($mm)
A45: Year 1 | B45: 1 | C45: =IF(C$4="","",C21/(1+Inputs!$B$5)^$B45) | D45: =IF(D$4="","",D21/(1+Inputs!$B$5)^$B45) | E45: =IF(E$4="","",E21/(1+Inputs!$B$5)^$B45) | F45: =IF(F$4="","",F21/(1+Inputs!$B$5)^$B45) | G45: =IF(G$4="","",G21/(1+Inputs!$B$5)^$B45) | H45: =IF(H$4="","",H21/(1+Inputs!$B$5)^$B45)
A46: Year 2 | B46: 2 | C46: =IF(C$4="","",C22/(1+Inputs!$B$5)^$B46) | D46: =IF(D$4="","",D22/(1+Inputs!$B$5)^$B46) | E46: =IF(E$4="","",E22/(1+Inputs!$B$5)^$B46) | F46: =IF(F$4="","",F22/(1+Inputs!$B$5)^$B46) | G46: =IF(G$4="","",G22/(1+Inputs!$B$5)^$B46) | H46: =IF(H$4="","",H22/(1+Inputs!$B$5)^$B46)
A47: Year 3 | B47: 3 | C47: =IF(C$4="","",C23/(1+Inputs!$B$5)^$B47) | D47: =IF(D$4="","",D23/(1+Inputs!$B$5)^$B47) | E47: =IF(E$4="","",E23/(1+Inputs!$B$5)^$B47) | F47: =IF(F$4="","",F23/(1+Inputs!$B$5)^$B47) | G47: =IF(G$4="","",G23/(1+Inputs!$B$5)^$B47) | H47: =IF(H$4="","",H23/(1+Inputs!$B$5)^$B47)
A48: Year 4 | B48: 4 | C48: =IF(C$4="","",C24/(1+Inputs!$B$5)^$B48) | D48: =IF(D$4="","",D24/(1+Inputs!$B$5)^$B48) | E48: =IF(E$4="","",E24/(1+Inputs!$B$5)^$B48) | F48: =IF(F$4="","",F24/(1+Inputs!$B$5)^$B48) | G48: =IF(G$4="","",G24/(1+Inputs!$B$5)^$B48) | H48: =IF(H$4="","",H24/(1+Inputs!$B$5)^$B48)
A49: Year 5 | B49: 5 | C49: =IF(C$4="","",C25/(1+Inputs!$B$5)^$B49) | D49: =IF(D$4="","",D25/(1+Inputs!$B$5)^$B49) | E49: =IF(E$4="","",E25/(1+Inputs!$B$5)^$B49) | F49: =IF(F$4="","",F25/(1+Inputs!$B$5)^$B49) | G49: =IF(G$4="","",G25/(1+Inputs!$B$5)^$B49) | H49: =IF(H$4="","",H25/(1+Inputs!$B$5)^$B49)
A50: Year 6 | B50: 6 | C50: =IF(C$4="","",C26/(1+Inputs!$B$5)^$B50) | D50: =IF(D$4="","",D26/(1+Inputs!$B$5)^$B50) | E50: =IF(E$4="","",E26/(1+Inputs!$B$5)^$B50) | F50: =IF(F$4="","",F26/(1+Inputs!$B$5)^$B50) | G50: =IF(G$4="","",G26/(1+Inputs!$B$5)^$B50) | H50: =IF(H$4="","",H26/(1+Inputs!$B$5)^$B50)
A51: Year 7 | B51: 7 | C51: =IF(C$4="","",C27/(1+Inputs!$B$5)^$B51) | D51: =IF(D$4="","",D27/(1+Inputs!$B$5)^$B51) | E51: =IF(E$4="","",E27/(1+Inputs!$B$5)^$B51) | F51: =IF(F$4="","",F27/(1+Inputs!$B$5)^$B51) | G51: =IF(G$4="","",G27/(1+Inputs!$B$5)^$B51) | H51: =IF(H$4="","",H27/(1+Inputs!$B$5)^$B51)
A52: Year 8 | B52: 8 | C52: =IF(C$4="","",C28/(1+Inputs!$B$5)^$B52) | D52: =IF(D$4="","",D28/(1+Inputs!$B$5)^$B52) | E52: =IF(E$4="","",E28/(1+Inputs!$B$5)^$B52) | F52: =IF(F$4="","",F28/(1+Inputs!$B$5)^$B52) | G52: =IF(G$4="","",G28/(1+Inputs!$B$5)^$B52) | H52: =IF(H$4="","",H28/(1+Inputs!$B$5)^$B52)
A53: Year 9 | B53: 9 | C53: =IF(C$4="","",C29/(1+Inputs!$B$5)^$B53) | D53: =IF(D$4="","",D29/(1+Inputs!$B$5)^$B53) | E53: =IF(E$4="","",E29/(1+Inputs!$B$5)^$B53) | F53: =IF(F$4="","",F29/(1+Inputs!$B$5)^$B53) | G53: =IF(G$4="","",G29/(1+Inputs!$B$5)^$B53) | H53: =IF(H$4="","",H29/(1+Inputs!$B$5)^$B53)
A54: Year 10 | B54: 10 | C54: =IF(C$4="","",C30/(1+Inputs!$B$5)^$B54) | D54: =IF(D$4="","",D30/(1+Inputs!$B$5)^$B54) | E54: =IF(E$4="","",E30/(1+Inputs!$B$5)^$B54) | F54: =IF(F$4="","",F30/(1+Inputs!$B$5)^$B54) | G54: =IF(G$4="","",G30/(1+Inputs!$B$5)^$B54) | H54: =IF(H$4="","",H30/(1+Inputs!$B$5)^$B54)
A56: Valuation
A57: Sum PV years 1-10 (base) | C57: =IF(C$4="","",SUM(C33:C42)) | D57: =IF(D$4="","",SUM(D33:D42)) | E57: =IF(E$4="","",SUM(E33:E42)) | F57: =IF(F$4="","",SUM(F33:F42)) | G57: =IF(G$4="","",SUM(G33:G42)) | H57: =IF(H$4="","",SUM(H33:H42))
A58: PV terminal value (base) | C58: =IF(C$4="","",C30*(1+Inputs!$B$6)/(Inputs!$B$4-Inputs!$B$6)/(1+Inputs!$B$4)^10) | D58: =IF(D$4="","",D30*(1+Inputs!$B$6)/(Inputs!$B$4-Inputs!$B$6)/(1+Inputs!$B$4)^10) | E58: =IF(E$4="","",E30*(1+Inputs!$B$6)/(Inputs!$B$4-Inputs!$B$6)/(1+Inputs!$B$4)^10) | F58: =IF(F$4="","",F30*(1+Inputs!$B$6)/(Inputs!$B$4-Inputs!$B$6)/(1+Inputs!$B$4)^10) | G58: =IF(G$4="","",G30*(1+Inputs!$B$6)/(Inputs!$B$4-Inputs!$B$6)/(1+Inputs!$B$4)^10) | H58: =IF(H$4="","",H30*(1+Inputs!$B$6)/(Inputs!$B$4-Inputs!$B$6)/(1+Inputs!$B$4)^10)
A59: Enterprise value (base) | C59: =IF(C$4="","",C57+C58) | D59: =IF(D$4="","",D57+D58) | E59: =IF(E$4="","",E57+E58) | F59: =IF(F$4="","",F57+F58) | G59: =IF(G$4="","",G57+G58) | H59: =IF(H$4="","",H57+H58)
A60: Going-concern value / share (base) | C60: =IF(C$4="","",(C59-Inputs!C19)/Inputs!C15) | D60: =IF(D$4="","",(D59-Inputs!D19)/Inputs!D15) | E60: =IF(E$4="","",(E59-Inputs!E19)/Inputs!E15) | F60: =IF(F$4="","",(F59-Inputs!F19)/Inputs!F15) | G60: =IF(G$4="","",(G59-Inputs!G19)/Inputs!G15) | H60: =IF(H$4="","",(H59-Inputs!H19)/Inputs!H15)
A61: Terminal value % of EV (base) | C61: =IF(C$4="","",C58/C59) | D61: =IF(D$4="","",D58/D59) | E61: =IF(E$4="","",E58/E59) | F61: =IF(F$4="","",F58/F59) | G61: =IF(G$4="","",G58/G59) | H61: =IF(H$4="","",H58/H59)
A62: Sum PV years 1-10 (conservative) | C62: =IF(C$4="","",SUM(C45:C54)) | D62: =IF(D$4="","",SUM(D45:D54)) | E62: =IF(E$4="","",SUM(E45:E54)) | F62: =IF(F$4="","",SUM(F45:F54)) | G62: =IF(G$4="","",SUM(G45:G54)) | H62: =IF(H$4="","",SUM(H45:H54))
A63: PV terminal value (conservative) | C63: =IF(C$4="","",C30*(1+Inputs!$B$6)/(Inputs!$B$5-Inputs!$B$6)/(1+Inputs!$B$5)^10) | D63: =IF(D$4="","",D30*(1+Inputs!$B$6)/(Inputs!$B$5-Inputs!$B$6)/(1+Inputs!$B$5)^10) | E63: =IF(E$4="","",E30*(1+Inputs!$B$6)/(Inputs!$B$5-Inputs!$B$6)/(1+Inputs!$B$5)^10) | F63: =IF(F$4="","",F30*(1+Inputs!$B$6)/(Inputs!$B$5-Inputs!$B$6)/(1+Inputs!$B$5)^10) | G63: =IF(G$4="","",G30*(1+Inputs!$B$6)/(Inputs!$B$5-Inputs!$B$6)/(1+Inputs!$B$5)^10) | H63: =IF(H$4="","",H30*(1+Inputs!$B$6)/(Inputs!$B$5-Inputs!$B$6)/(1+Inputs!$B$5)^10)
A64: Enterprise value (conservative) | C64: =IF(C$4="","",C62+C63) | D64: =IF(D$4="","",D62+D63) | E64: =IF(E$4="","",E62+E63) | F64: =IF(F$4="","",F62+F63) | G64: =IF(G$4="","",G62+G63) | H64: =IF(H$4="","",H62+H63)
A65: Going-concern value / share (conservative) | C65: =IF(C$4="","",(C64-Inputs!C19)/Inputs!C15) | D65: =IF(D$4="","",(D64-Inputs!D19)/Inputs!D15) | E65: =IF(E$4="","",(E64-Inputs!E19)/Inputs!E15) | F65: =IF(F$4="","",(F64-Inputs!F19)/Inputs!F15) | G65: =IF(G$4="","",(G64-Inputs!G19)/Inputs!G15) | H65: =IF(H$4="","",(H64-Inputs!H19)/Inputs!H15)
A66: Bear value / share (conservative) | C66: =IF(C$4="","",(C$5*(1-Inputs!$B$7)/(Inputs!$B$5+Inputs!$B$7)-Inputs!C19)/Inputs!C15) | D66: =IF(D$4="","",(D$5*(1-Inputs!$B$7)/(Inputs!$B$5+Inputs!$B$7)-Inputs!D19)/Inputs!D15) | E66: =IF(E$4="","",(E$5*(1-Inputs!$B$7)/(Inputs!$B$5+Inputs!$B$7)-Inputs!E19)/Inputs!E15) | F66: =IF(F$4="","",(F$5*(1-Inputs!$B$7)/(Inputs!$B$5+Inputs!$B$7)-Inputs!F19)/Inputs!F15) | G66: =IF(G$4="","",(G$5*(1-Inputs!$B$7)/(Inputs!$B$5+Inputs!$B$7)-Inputs!G19)/Inputs!G15) | H66: =IF(H$4="","",(H$5*(1-Inputs!$B$7)/(Inputs!$B$5+Inputs!$B$7)-Inputs!H19)/Inputs!H15)
A67: Bear value / share (base) | C67: =IF(C$4="","",(C$5*(1-Inputs!$B$7)/(Inputs!$B$4+Inputs!$B$7)-Inputs!C19)/Inputs!C15) | D67: =IF(D$4="","",(D$5*(1-Inputs!$B$7)/(Inputs!$B$4+Inputs!$B$7)-Inputs!D19)/Inputs!D15) | E67: =IF(E$4="","",(E$5*(1-Inputs!$B$7)/(Inputs!$B$4+Inputs!$B$7)-Inputs!E19)/Inputs!E15) | F67: =IF(F$4="","",(F$5*(1-Inputs!$B$7)/(Inputs!$B$4+Inputs!$B$7)-Inputs!F19)/Inputs!F15) | G67: =IF(G$4="","",(G$5*(1-Inputs!$B$7)/(Inputs!$B$4+Inputs!$B$7)-Inputs!G19)/Inputs!G15) | H67: =IF(H$4="","",(H$5*(1-Inputs!$B$7)/(Inputs!$B$4+Inputs!$B$7)-Inputs!H19)/Inputs!H15)

Sheet ImpliedCalc
A1: Helper: value multiple of year-0 owner FCF for each starting growth (do not edit)
L2: Years 1-10 = cumulative growth factors
A3: Start g | B3: 1 | C3: 2 | D3: 3 | E3: 4 | F3: 5 | G3: 6 | H3: 7 | I3: 8 | J3: 9 | K3: 10 | L3: Mult @ base r | M3: Mult @ cons r
A4: =ROUND(-0.2+0*0.005,4) | B4: =1*(1+$A4+(Inputs!$B$6-$A4)*(B$3-1)/9) | C4: =B4*(1+$A4+(Inputs!$B$6-$A4)*(C$3-1)/9) | D4: =C4*(1+$A4+(Inputs!$B$6-$A4)*(D$3-1)/9) | E4: =D4*(1+$A4+(Inputs!$B$6-$A4)*(E$3-1)/9) | F4: =E4*(1+$A4+(Inputs!$B$6-$A4)*(F$3-1)/9) | G4: =F4*(1+$A4+(Inputs!$B$6-$A4)*(G$3-1)/9) | H4: =G4*(1+$A4+(Inputs!$B$6-$A4)*(H$3-1)/9) | I4: =H4*(1+$A4+(Inputs!$B$6-$A4)*(I$3-1)/9) | J4: =I4*(1+$A4+(Inputs!$B$6-$A4)*(J$3-1)/9) | K4: =J4*(1+$A4+(Inputs!$B$6-$A4)*(K$3-1)/9) | L4: =SUMPRODUCT(B4:K4,1/(1+Inputs!$B$4)^$B$3:$K$3)+K4*(1+Inputs!$B$6)/(Inputs!$B$4-Inputs!$B$6)/(1+Inputs!$B$4)^10 | M4: =SUMPRODUCT(B4:K4,1/(1+Inputs!$B$5)^$B$3:$K$3)+K4*(1+Inputs!$B$6)/(Inputs!$B$5-Inputs!$B$6)/(1+Inputs!$B$5)^10
A5: =ROUND(-0.2+1*0.005,4) | B5: =1*(1+$A5+(Inputs!$B$6-$A5)*(B$3-1)/9) | C5: =B5*(1+$A5+(Inputs!$B$6-$A5)*(C$3-1)/9) | D5: =C5*(1+$A5+(Inputs!$B$6-$A5)*(D$3-1)/9) | E5: =D5*(1+$A5+(Inputs!$B$6-$A5)*(E$3-1)/9) | F5: =E5*(1+$A5+(Inputs!$B$6-$A5)*(F$3-1)/9) | G5: =F5*(1+$A5+(Inputs!$B$6-$A5)*(G$3-1)/9) | H5: =G5*(1+$A5+(Inputs!$B$6-$A5)*(H$3-1)/9) | I5: =H5*(1+$A5+(Inputs!$B$6-$A5)*(I$3-1)/9) | J5: =I5*(1+$A5+(Inputs!$B$6-$A5)*(J$3-1)/9) | K5: =J5*(1+$A5+(Inputs!$B$6-$A5)*(K$3-1)/9) | L5: =SUMPRODUCT(B5:K5,1/(1+Inputs!$B$4)^$B$3:$K$3)+K5*(1+Inputs!$B$6)/(Inputs!$B$4-Inputs!$B$6)/(1+Inputs!$B$4)^10 | M5: =SUMPRODUCT(B5:K5,1/(1+Inputs!$B$5)^$B$3:$K$3)+K5*(1+Inputs!$B$6)/(Inputs!$B$5-Inputs!$B$6)/(1+Inputs!$B$5)^10
A6: =ROUND(-0.2+2*0.005,4) | B6: =1*(1+$A6+(Inputs!$B$6-$A6)*(B$3-1)/9) | C6: =B6*(1+$A6+(Inputs!$B$6-$A6)*(C$3-1)/9) | D6: =C6*(1+$A6+(Inputs!$B$6-$A6)*(D$3-1)/9) | E6: =D6*(1+$A6+(Inputs!$B$6-$A6)*(E$3-1)/9) | F6: =E6*(1+$A6+(Inputs!$B$6-$A6)*(F$3-1)/9) | G6: =F6*(1+$A6+(Inputs!$B$6-$A6)*(G$3-1)/9) | H6: =G6*(1+$A6+(Inputs!$B$6-$A6)*(H$3-1)/9) | I6: =H6*(1+$A6+(Inputs!$B$6-$A6)*(I$3-1)/9) | J6: =I6*(1+$A6+(Inputs!$B$6-$A6)*(J$3-1)/9) | K6: =J6*(1+$A6+(Inputs!$B$6-$A6)*(K$3-1)/9) | L6: =SUMPRODUCT(B6:K6,1/(1+Inputs!$B$4)^$B$3:$K$3)+K6*(1+Inputs!$B$6)/(Inputs!$B$4-Inputs!$B$6)/(1+Inputs!$B$4)^10 | M6: =SUMPRODUCT(B6:K6,1/(1+Inputs!$B$5)^$B$3:$K$3)+K6*(1+Inputs!$B$6)/(Inputs!$B$5-Inputs!$B$6)/(1+Inputs!$B$5)^10
A7: =ROUND(-0.2+3*0.005,4) | B7: =1*(1+$A7+(Inputs!$B$6-$A7)*(B$3-1)/9) | C7: =B7*(1+$A7+(Inputs!$B$6-$A7)*(C$3-1)/9) | D7: =C7*(1+$A7+(Inputs!$B$6-$A7)*(D$3-1)/9) | E7: =D7*(1+$A7+(Inputs!$B$6-$A7)*(E$3-1)/9) | F7: =E7*(1+$A7+(Inputs!$B$6-$A7)*(F$3-1)/9) | G7: =F7*(1+$A7+(Inputs!$B$6-$A7)*(G$3-1)/9) | H7: =G7*(1+$A7+(Inputs!$B$6-$A7)*(H$3-1)/9) | I7: =H7*(1+$A7+(Inputs!$B$6-$A7)*(I$3-1)/9) | J7: =I7*(1+$A7+(Inputs!$B$6-$A7)*(J$3-1)/9) | K7: =J7*(1+$A7+(Inputs!$B$6-$A7)*(K$3-1)/9) | L7: =SUMPRODUCT(B7:K7,1/(1+Inputs!$B$4)^$B$3:$K$3)+K7*(1+Inputs!$B$6)/(Inputs!$B$4-Inputs!$B$6)/(1+Inputs!$B$4)^10 | M7: =SUMPRODUCT(B7:K7,1/(1+Inputs!$B$5)^$B$3:$K$3)+K7*(1+Inputs!$B$6)/(Inputs!$B$5-Inputs!$B$6)/(1+Inputs!$B$5)^10
A8: =ROUND(-0.2+4*0.005,4) | B8: =1*(1+$A8+(Inputs!$B$6-$A8)*(B$3-1)/9) | C8: =B8*(1+$A8+(Inputs!$B$6-$A8)*(C$3-1)/9) | D8: =C8*(1+$A8+(Inputs!$B$6-$A8)*(D$3-1)/9) | E8: =D8*(1+$A8+(Inputs!$B$6-$A8)*(E$3-1)/9) | F8: =E8*(1+$A8+(Inputs!$B$6-$A8)*(F$3-1)/9) | G8: =F8*(1+$A8+(Inputs!$B$6-$A8)*(G$3-1)/9) | H8: =G8*(1+$A8+(Inputs!$B$6-$A8)*(H$3-1)/9) | I8: =H8*(1+$A8+(Inputs!$B$6-$A8)*(I$3-1)/9) | J8: =I8*(1+$A8+(Inputs!$B$6-$A8)*(J$3-1)/9) | K8: =J8*(1+$A8+(Inputs!$B$6-$A8)*(K$3-1)/9) | L8: =SUMPRODUCT(B8:K8,1/(1+Inputs!$B$4)^$B$3:$K$3)+K8*(1+Inputs!$B$6)/(Inputs!$B$4-Inputs!$B$6)/(1+Inputs!$B$4)^10 | M8: =SUMPRODUCT(B8:K8,1/(1+Inputs!$B$5)^$B$3:$K$3)+K8*(1+Inputs!$B$6)/(Inputs!$B$5-Inputs!$B$6)/(1+Inputs!$B$5)^10
A9: =ROUND(-0.2+5*0.005,4) | B9: =1*(1+$A9+(Inputs!$B$6-$A9)*(B$3-1)/9) | C9: =B9*(1+$A9+(Inputs!$B$6-$A9)*(C$3-1)/9) | D9: =C9*(1+$A9+(Inputs!$B$6-$A9)*(D$3-1)/9) | E9: =D9*(1+$A9+(Inputs!$B$6-$A9)*(E$3-1)/9) | F9: =E9*(1+$A9+(Inputs!$B$6-$A9)*(F$3-1)/9) | G9: =F9*(1+$A9+(Inputs!$B$6-$A9)*(G$3-1)/9) | H9: =G9*(1+$A9+(Inputs!$B$6-$A9)*(H$3-1)/9) | I9: =H9*(1+$A9+(Inputs!$B$6-$A9)*(I$3-1)/9) | J9: =I9*(1+$A9+(Inputs!$B$6-$A9)*(J$3-1)/9) | K9: =J9*(1+$A9+(Inputs!$B$6-$A9)*(K$3-1)/9) | L9: =SUMPRODUCT(B9:K9,1/(1+Inputs!$B$4)^$B$3:$K$3)+K9*(1+Inputs!$B$6)/(Inputs!$B$4-Inputs!$B$6)/(1+Inputs!$B$4)^10 | M9: =SUMPRODUCT(B9:K9,1/(1+Inputs!$B$5)^$B$3:$K$3)+K9*(1+Inputs!$B$6)/(Inputs!$B$5-Inputs!$B$6)/(1+Inputs!$B$5)^10
A10: =ROUND(-0.2+6*0.005,4) | B10: =1*(1+$A10+(Inputs!$B$6-$A10)*(B$3-1)/9) | C10: =B10*(1+$A10+(Inputs!$B$6-$A10)*(C$3-1)/9) | D10: =C10*(1+$A10+(Inputs!$B$6-$A10)*(D$3-1)/9) | E10: =D10*(1+$A10+(Inputs!$B$6-$A10)*(E$3-1)/9) | F10: =E10*(1+$A10+(Inputs!$B$6-$A10)*(F$3-1)/9) | G10: =F10*(1+$A10+(Inputs!$B$6-$A10)*(G$3-1)/9) | H10: =G10*(1+$A10+(Inputs!$B$6-$A10)*(H$3-1)/9) | I10: =H10*(1+$A10+(Inputs!$B$6-$A10)*(I$3-1)/9) | J10: =I10*(1+$A10+(Inputs!$B$6-$A10)*(J$3-1)/9) | K10: =J10*(1+$A10+(Inputs!$B$6-$A10)*(K$3-1)/9) | L10: =SUMPRODUCT(B10:K10,1/(1+Inputs!$B$4)^$B$3:$K$3)+K10*(1+Inputs!$B$6)/(Inputs!$B$4-Inputs!$B$6)/(1+Inputs!$B$4)^10 | M10: =SUMPRODUCT(B10:K10,1/(1+Inputs!$B$5)^$B$3:$K$3)+K10*(1+Inputs!$B$6)/(Inputs!$B$5-Inputs!$B$6)/(1+Inputs!$B$5)^10
A11: =ROUND(-0.2+7*0.005,4) | B11: =1*(1+$A11+(Inputs!$B$6-$A11)*(B$3-1)/9) | C11: =B11*(1+$A11+(Inputs!$B$6-$A11)*(C$3-1)/9) | D11: =C11*(1+$A11+(Inputs!$B$6-$A11)*(D$3-1)/9) | E11: =D11*(1+$A11+(Inputs!$B$6-$A11)*(E$3-1)/9) | F11: =E11*(1+$A11+(Inputs!$B$6-$A11)*(F$3-1)/9) | G11: =F11*(1+$A11+(Inputs!$B$6-$A11)*(G$3-1)/9) | H11: =G11*(1+$A11+(Inputs!$B$6-$A11)*(H$3-1)/9) | I11: =H11*(1+$A11+(Inputs!$B$6-$A11)*(I$3-1)/9) | J11: =I11*(1+$A11+(Inputs!$B$6-$A11)*(J$3-1)/9) | K11: =J11*(1+$A11+(Inputs!$B$6-$A11)*(K$3-1)/9) | L11: =SUMPRODUCT(B11:K11,1/(1+Inputs!$B$4)^$B$3:$K$3)+K11*(1+Inputs!$B$6)/(Inputs!$B$4-Inputs!$B$6)/(1+Inputs!$B$4)^10 | M11: =SUMPRODUCT(B11:K11,1/(1+Inputs!$B$5)^$B$3:$K$3)+K11*(1+Inputs!$B$6)/(Inputs!$B$5-Inputs!$B$6)/(1+Inputs!$B$5)^10
A12: =ROUND(-0.2+8*0.005,4) | B12: =1*(1+$A12+(Inputs!$B$6-$A12)*(B$3-1)/9) | C12: =B12*(1+$A12+(Inputs!$B$6-$A12)*(C$3-1)/9) | D12: =C12*(1+$A12+(Inputs!$B$6-$A12)*(D$3-1)/9) | E12: =D12*(1+$A12+(Inputs!$B$6-$A12)*(E$3-1)/9) | F12: =E12*(1+$A12+(Inputs!$B$6-$A12)*(F$3-1)/9) | G12: =F12*(1+$A12+(Inputs!$B$6-$A12)*(G$3-1)/9) | H12: =G12*(1+$A12+(Inputs!$B$6-$A12)*(H$3-1)/9) | I12: =H12*(1+$A12+(Inputs!$B$6-$A12)*(I$3-1)/9) | J12: =I12*(1+$A12+(Inputs!$B$6-$A12)*(J$3-1)/9) | K12: =J12*(1+$A12+(Inputs!$B$6-$A12)*(K$3-1)/9) | L12: =SUMPRODUCT(B12:K12,1/(1+Inputs!$B$4)^$B$3:$K$3)+K12*(1+Inputs!$B$6)/(Inputs!$B$4-Inputs!$B$6)/(1+Inputs!$B$4)^10 | M12: =SUMPRODUCT(B12:K12,1/(1+Inputs!$B$5)^$B$3:$K$3)+K12*(1+Inputs!$B$6)/(Inputs!$B$5-Inputs!$B$6)/(1+Inputs!$B$5)^10
A13: =ROUND(-0.2+9*0.005,4) | B13: =1*(1+$A13+(Inputs!$B$6-$A13)*(B$3-1)/9) | C13: =B13*(1+$A13+(Inputs!$B$6-$A13)*(C$3-1)/9) | D13: =C13*(1+$A13+(Inputs!$B$6-$A13)*(D$3-1)/9) | E13: =D13*(1+$A13+(Inputs!$B$6-$A13)*(E$3-1)/9) | F13: =E13*(1+$A13+(Inputs!$B$6-$A13)*(F$3-1)/9) | G13: =F13*(1+$A13+(Inputs!$B$6-$A13)*(G$3-1)/9) | H13: =G13*(1+$A13+(Inputs!$B$6-$A13)*(H$3-1)/9) | I13: =H13*(1+$A13+(Inputs!$B$6-$A13)*(I$3-1)/9) | J13: =I13*(1+$A13+(Inputs!$B$6-$A13)*(J$3-1)/9) | K13: =J13*(1+$A13+(Inputs!$B$6-$A13)*(K$3-1)/9) | L13: =SUMPRODUCT(B13:K13,1/(1+Inputs!$B$4)^$B$3:$K$3)+K13*(1+Inputs!$B$6)/(Inputs!$B$4-Inputs!$B$6)/(1+Inputs!$B$4)^10 | M13: =SUMPRODUCT(B13:K13,1/(1+Inputs!$B$5)^$B$3:$K$3)+K13*(1+Inputs!$B$6)/(Inputs!$B$5-Inputs!$B$6)/(1+Inputs!$B$5)^10
A14: =ROUND(-0.2+10*0.005,4) | B14: =1*(1+$A14+(Inputs!$B$6-$A14)*(B$3-1)/9) | C14: =B14*(1+$A14+(Inputs!$B$6-$A14)*(C$3-1)/9) | D14: =C14*(1+$A14+(Inputs!$B$6-$A14)*(D$3-1)/9) | E14: =D14*(1+$A14+(Inputs!$B$6-$A14)*(E$3-1)/9) | F14: =E14*(1+$A14+(Inputs!$B$6-$A14)*(F$3-1)/9) | G14: =F14*(1+$A14+(Inputs!$B$6-$A14)*(G$3-1)/9) | H14: =G14*(1+$A14+(Inputs!$B$6-$A14)*(H$3-1)/9) | I14: =H14*(1+$A14+(Inputs!$B$6-$A14)*(I$3-1)/9) | J14: =I14*(1+$A14+(Inputs!$B$6-$A14)*(J$3-1)/9) | K14: =J14*(1+$A14+(Inputs!$B$6-$A14)*(K$3-1)/9) | L14: =SUMPRODUCT(B14:K14,1/(1+Inputs!$B$4)^$B$3:$K$3)+K14*(1+Inputs!$B$6)/(Inputs!$B$4-Inputs!$B$6)/(1+Inputs!$B$4)^10 | M14: =SUMPRODUCT(B14:K14,1/(1+Inputs!$B$5)^$B$3:$K$3)+K14*(1+Inputs!$B$6)/(Inputs!$B$5-Inputs!$B$6)/(1+Inputs!$B$5)^10
A15: =ROUND(-0.2+11*0.005,4) | B15: =1*(1+$A15+(Inputs!$B$6-$A15)*(B$3-1)/9) | C15: =B15*(1+$A15+(Inputs!$B$6-$A15)*(C$3-1)/9) | D15: =C15*(1+$A15+(Inputs!$B$6-$A15)*(D$3-1)/9) | E15: =D15*(1+$A15+(Inputs!$B$6-$A15)*(E$3-1)/9) | F15: =E15*(1+$A15+(Inputs!$B$6-$A15)*(F$3-1)/9) | G15: =F15*(1+$A15+(Inputs!$B$6-$A15)*(G$3-1)/9) | H15: =G15*(1+$A15+(Inputs!$B$6-$A15)*(H$3-1)/9) | I15: =H15*(1+$A15+(Inputs!$B$6-$A15)*(I$3-1)/9) | J15: =I15*(1+$A15+(Inputs!$B$6-$A15)*(J$3-1)/9) | K15: =J15*(1+$A15+(Inputs!$B$6-$A15)*(K$3-1)/9) | L15: =SUMPRODUCT(B15:K15,1/(1+Inputs!$B$4)^$B$3:$K$3)+K15*(1+Inputs!$B$6)/(Inputs!$B$4-Inputs!$B$6)/(1+Inputs!$B$4)^10 | M15: =SUMPRODUCT(B15:K15,1/(1+Inputs!$B$5)^$B$3:$K$3)+K15*(1+Inputs!$B$6)/(Inputs!$B$5-Inputs!$B$6)/(1+Inputs!$B$5)^10
A16: =ROUND(-0.2+12*0.005,4) | B16: =1*(1+$A16+(Inputs!$B$6-$A16)*(B$3-1)/9) | C16: =B16*(1+$A16+(Inputs!$B$6-$A16)*(C$3-1)/9) | D16: =C16*(1+$A16+(Inputs!$B$6-$A16)*(D$3-1)/9) | E16: =D16*(1+$A16+(Inputs!$B$6-$A16)*(E$3-1)/9) | F16: =E16*(1+$A16+(Inputs!$B$6-$A16)*(F$3-1)/9) | G16: =F16*(1+$A16+(Inputs!$B$6-$A16)*(G$3-1)/9) | H16: =G16*(1+$A16+(Inputs!$B$6-$A16)*(H$3-1)/9) | I16: =H16*(1+$A16+(Inputs!$B$6-$A16)*(I$3-1)/9) | J16: =I16*(1+$A16+(Inputs!$B$6-$A16)*(J$3-1)/9) | K16: =J16*(1+$A16+(Inputs!$B$6-$A16)*(K$3-1)/9) | L16: =SUMPRODUCT(B16:K16,1/(1+Inputs!$B$4)^$B$3:$K$3)+K16*(1+Inputs!$B$6)/(Inputs!$B$4-Inputs!$B$6)/(1+Inputs!$B$4)^10 | M16: =SUMPRODUCT(B16:K16,1/(1+Inputs!$B$5)^$B$3:$K$3)+K16*(1+Inputs!$B$6)/(Inputs!$B$5-Inputs!$B$6)/(1+Inputs!$B$5)^10
A17: =ROUND(-0.2+13*0.005,4) | B17: =1*(1+$A17+(Inputs!$B$6-$A17)*(B$3-1)/9) | C17: =B17*(1+$A17+(Inputs!$B$6-$A17)*(C$3-1)/9) | D17: =C17*(1+$A17+(Inputs!$B$6-$A17)*(D$3-1)/9) | E17: =D17*(1+$A17+(Inputs!$B$6-$A17)*(E$3-1)/9) | F17: =E17*(1+$A17+(Inputs!$B$6-$A17)*(F$3-1)/9) | G17: =F17*(1+$A17+(Inputs!$B$6-$A17)*(G$3-1)/9) | H17: =G17*(1+$A17+(Inputs!$B$6-$A17)*(H$3-1)/9) | I17: =H17*(1+$A17+(Inputs!$B$6-$A17)*(I$3-1)/9) | J17: =I17*(1+$A17+(Inputs!$B$6-$A17)*(J$3-1)/9) | K17: =J17*(1+$A17+(Inputs!$B$6-$A17)*(K$3-1)/9) | L17: =SUMPRODUCT(B17:K17,1/(1+Inputs!$B$4)^$B$3:$K$3)+K17*(1+Inputs!$B$6)/(Inputs!$B$4-Inputs!$B$6)/(1+Inputs!$B$4)^10 | M17: =SUMPRODUCT(B17:K17,1/(1+Inputs!$B$5)^$B$3:$K$3)+K17*(1+Inputs!$B$6)/(Inputs!$B$5-Inputs!$B$6)/(1+Inputs!$B$5)^10
A18: =ROUND(-0.2+14*0.005,4) | B18: =1*(1+$A18+(Inputs!$B$6-$A18)*(B$3-1)/9) | C18: =B18*(1+$A18+(Inputs!$B$6-$A18)*(C$3-1)/9) | D18: =C18*(1+$A18+(Inputs!$B$6-$A18)*(D$3-1)/9) | E18: =D18*(1+$A18+(Inputs!$B$6-$A18)*(E$3-1)/9) | F18: =E18*(1+$A18+(Inputs!$B$6-$A18)*(F$3-1)/9) | G18: =F18*(1+$A18+(Inputs!$B$6-$A18)*(G$3-1)/9) | H18: =G18*(1+$A18+(Inputs!$B$6-$A18)*(H$3-1)/9) | I18: =H18*(1+$A18+(Inputs!$B$6-$A18)*(I$3-1)/9) | J18: =I18*(1+$A18+(Inputs!$B$6-$A18)*(J$3-1)/9) | K18: =J18*(1+$A18+(Inputs!$B$6-$A18)*(K$3-1)/9) | L18: =SUMPRODUCT(B18:K18,1/(1+Inputs!$B$4)^$B$3:$K$3)+K18*(1+Inputs!$B$6)/(Inputs!$B$4-Inputs!$B$6)/(1+Inputs!$B$4)^10 | M18: =SUMPRODUCT(B18:K18,1/(1+Inputs!$B$5)^$B$3:$K$3)+K18*(1+Inputs!$B$6)/(Inputs!$B$5-Inputs!$B$6)/(1+Inputs!$B$5)^10
A19: =ROUND(-0.2+15*0.005,4) | B19: =1*(1+$A19+(Inputs!$B$6-$A19)*(B$3-1)/9) | C19: =B19*(1+$A19+(Inputs!$B$6-$A19)*(C$3-1)/9) | D19: =C19*(1+$A19+(Inputs!$B$6-$A19)*(D$3-1)/9) | E19: =D19*(1+$A19+(Inputs!$B$6-$A19)*(E$3-1)/9) | F19: =E19*(1+$A19+(Inputs!$B$6-$A19)*(F$3-1)/9) | G19: =F19*(1+$A19+(Inputs!$B$6-$A19)*(G$3-1)/9) | H19: =G19*(1+$A19+(Inputs!$B$6-$A19)*(H$3-1)/9) | I19: =H19*(1+$A19+(Inputs!$B$6-$A19)*(I$3-1)/9) | J19: =I19*(1+$A19+(Inputs!$B$6-$A19)*(J$3-1)/9) | K19: =J19*(1+$A19+(Inputs!$B$6-$A19)*(K$3-1)/9) | L19: =SUMPRODUCT(B19:K19,1/(1+Inputs!$B$4)^$B$3:$K$3)+K19*(1+Inputs!$B$6)/(Inputs!$B$4-Inputs!$B$6)/(1+Inputs!$B$4)^10 | M19: =SUMPRODUCT(B19:K19,1/(1+Inputs!$B$5)^$B$3:$K$3)+K19*(1+Inputs!$B$6)/(Inputs!$B$5-Inputs!$B$6)/(1+Inputs!$B$5)^10
A20: =ROUND(-0.2+16*0.005,4) | B20: =1*(1+$A20+(Inputs!$B$6-$A20)*(B$3-1)/9) | C20: =B20*(1+$A20+(Inputs!$B$6-$A20)*(C$3-1)/9) | D20: =C20*(1+$A20+(Inputs!$B$6-$A20)*(D$3-1)/9) | E20: =D20*(1+$A20+(Inputs!$B$6-$A20)*(E$3-1)/9) | F20: =E20*(1+$A20+(Inputs!$B$6-$A20)*(F$3-1)/9) | G20: =F20*(1+$A20+(Inputs!$B$6-$A20)*(G$3-1)/9) | H20: =G20*(1+$A20+(Inputs!$B$6-$A20)*(H$3-1)/9) | I20: =H20*(1+$A20+(Inputs!$B$6-$A20)*(I$3-1)/9) | J20: =I20*(1+$A20+(Inputs!$B$6-$A20)*(J$3-1)/9) | K20: =J20*(1+$A20+(Inputs!$B$6-$A20)*(K$3-1)/9) | L20: =SUMPRODUCT(B20:K20,1/(1+Inputs!$B$4)^$B$3:$K$3)+K20*(1+Inputs!$B$6)/(Inputs!$B$4-Inputs!$B$6)/(1+Inputs!$B$4)^10 | M20: =SUMPRODUCT(B20:K20,1/(1+Inputs!$B$5)^$B$3:$K$3)+K20*(1+Inputs!$B$6)/(Inputs!$B$5-Inputs!$B$6)/(1+Inputs!$B$5)^10
A21: =ROUND(-0.2+17*0.005,4) | B21: =1*(1+$A21+(Inputs!$B$6-$A21)*(B$3-1)/9) | C21: =B21*(1+$A21+(Inputs!$B$6-$A21)*(C$3-1)/9) | D21: =C21*(1+$A21+(Inputs!$B$6-$A21)*(D$3-1)/9) | E21: =D21*(1+$A21+(Inputs!$B$6-$A21)*(E$3-1)/9) | F21: =E21*(1+$A21+(Inputs!$B$6-$A21)*(F$3-1)/9) | G21: =F21*(1+$A21+(Inputs!$B$6-$A21)*(G$3-1)/9) | H21: =G21*(1+$A21+(Inputs!$B$6-$A21)*(H$3-1)/9) | I21: =H21*(1+$A21+(Inputs!$B$6-$A21)*(I$3-1)/9) | J21: =I21*(1+$A21+(Inputs!$B$6-$A21)*(J$3-1)/9) | K21: =J21*(1+$A21+(Inputs!$B$6-$A21)*(K$3-1)/9) | L21: =SUMPRODUCT(B21:K21,1/(1+Inputs!$B$4)^$B$3:$K$3)+K21*(1+Inputs!$B$6)/(Inputs!$B$4-Inputs!$B$6)/(1+Inputs!$B$4)^10 | M21: =SUMPRODUCT(B21:K21,1/(1+Inputs!$B$5)^$B$3:$K$3)+K21*(1+Inputs!$B$6)/(Inputs!$B$5-Inputs!$B$6)/(1+Inputs!$B$5)^10
A22: =ROUND(-0.2+18*0.005,4) | B22: =1*(1+$A22+(Inputs!$B$6-$A22)*(B$3-1)/9) | C22: =B22*(1+$A22+(Inputs!$B$6-$A22)*(C$3-1)/9) | D22: =C22*(1+$A22+(Inputs!$B$6-$A22)*(D$3-1)/9) | E22: =D22*(1+$A22+(Inputs!$B$6-$A22)*(E$3-1)/9) | F22: =E22*(1+$A22+(Inputs!$B$6-$A22)*(F$3-1)/9) | G22: =F22*(1+$A22+(Inputs!$B$6-$A22)*(G$3-1)/9) | H22: =G22*(1+$A22+(Inputs!$B$6-$A22)*(H$3-1)/9) | I22: =H22*(1+$A22+(Inputs!$B$6-$A22)*(I$3-1)/9) | J22: =I22*(1+$A22+(Inputs!$B$6-$A22)*(J$3-1)/9) | K22: =J22*(1+$A22+(Inputs!$B$6-$A22)*(K$3-1)/9) | L22: =SUMPRODUCT(B22:K22,1/(1+Inputs!$B$4)^$B$3:$K$3)+K22*(1+Inputs!$B$6)/(Inputs!$B$4-Inputs!$B$6)/(1+Inputs!$B$4)^10 | M22: =SUMPRODUCT(B22:K22,1/(1+Inputs!$B$5)^$B$3:$K$3)+K22*(1+Inputs!$B$6)/(Inputs!$B$5-Inputs!$B$6)/(1+Inputs!$B$5)^10
A23: =ROUND(-0.2+19*0.005,4) | B23: =1*(1+$A23+(Inputs!$B$6-$A23)*(B$3-1)/9) | C23: =B23*(1+$A23+(Inputs!$B$6-$A23)*(C$3-1)/9) | D23: =C23*(1+$A23+(Inputs!$B$6-$A23)*(D$3-1)/9) | E23: =D23*(1+$A23+(Inputs!$B$6-$A23)*(E$3-1)/9) | F23: =E23*(1+$A23+(Inputs!$B$6-$A23)*(F$3-1)/9) | G23: =F23*(1+$A23+(Inputs!$B$6-$A23)*(G$3-1)/9) | H23: =G23*(1+$A23+(Inputs!$B$6-$A23)*(H$3-1)/9) | I23: =H23*(1+$A23+(Inputs!$B$6-$A23)*(I$3-1)/9) | J23: =I23*(1+$A23+(Inputs!$B$6-$A23)*(J$3-1)/9) | K23: =J23*(1+$A23+(Inputs!$B$6-$A23)*(K$3-1)/9) | L23: =SUMPRODUCT(B23:K23,1/(1+Inputs!$B$4)^$B$3:$K$3)+K23*(1+Inputs!$B$6)/(Inputs!$B$4-Inputs!$B$6)/(1+Inputs!$B$4)^10 | M23: =SUMPRODUCT(B23:K23,1/(1+Inputs!$B$5)^$B$3:$K$3)+K23*(1+Inputs!$B$6)/(Inputs!$B$5-Inputs!$B$6)/(1+Inputs!$B$5)^10
A24: =ROUND(-0.2+20*0.005,4) | B24: =1*(1+$A24+(Inputs!$B$6-$A24)*(B$3-1)/9) | C24: =B24*(1+$A24+(Inputs!$B$6-$A24)*(C$3-1)/9) | D24: =C24*(1+$A24+(Inputs!$B$6-$A24)*(D$3-1)/9) | E24: =D24*(1+$A24+(Inputs!$B$6-$A24)*(E$3-1)/9) | F24: =E24*(1+$A24+(Inputs!$B$6-$A24)*(F$3-1)/9) | G24: =F24*(1+$A24+(Inputs!$B$6-$A24)*(G$3-1)/9) | H24: =G24*(1+$A24+(Inputs!$B$6-$A24)*(H$3-1)/9) | I24: =H24*(1+$A24+(Inputs!$B$6-$A24)*(I$3-1)/9) | J24: =I24*(1+$A24+(Inputs!$B$6-$A24)*(J$3-1)/9) | K24: =J24*(1+$A24+(Inputs!$B$6-$A24)*(K$3-1)/9) | L24: =SUMPRODUCT(B24:K24,1/(1+Inputs!$B$4)^$B$3:$K$3)+K24*(1+Inputs!$B$6)/(Inputs!$B$4-Inputs!$B$6)/(1+Inputs!$B$4)^10 | M24: =SUMPRODUCT(B24:K24,1/(1+Inputs!$B$5)^$B$3:$K$3)+K24*(1+Inputs!$B$6)/(Inputs!$B$5-Inputs!$B$6)/(1+Inputs!$B$5)^10
A25: =ROUND(-0.2+21*0.005,4) | B25: =1*(1+$A25+(Inputs!$B$6-$A25)*(B$3-1)/9) | C25: =B25*(1+$A25+(Inputs!$B$6-$A25)*(C$3-1)/9) | D25: =C25*(1+$A25+(Inputs!$B$6-$A25)*(D$3-1)/9) | E25: =D25*(1+$A25+(Inputs!$B$6-$A25)*(E$3-1)/9) | F25: =E25*(1+$A25+(Inputs!$B$6-$A25)*(F$3-1)/9) | G25: =F25*(1+$A25+(Inputs!$B$6-$A25)*(G$3-1)/9) | H25: =G25*(1+$A25+(Inputs!$B$6-$A25)*(H$3-1)/9) | I25: =H25*(1+$A25+(Inputs!$B$6-$A25)*(I$3-1)/9) | J25: =I25*(1+$A25+(Inputs!$B$6-$A25)*(J$3-1)/9) | K25: =J25*(1+$A25+(Inputs!$B$6-$A25)*(K$3-1)/9) | L25: =SUMPRODUCT(B25:K25,1/(1+Inputs!$B$4)^$B$3:$K$3)+K25*(1+Inputs!$B$6)/(Inputs!$B$4-Inputs!$B$6)/(1+Inputs!$B$4)^10 | M25: =SUMPRODUCT(B25:K25,1/(1+Inputs!$B$5)^$B$3:$K$3)+K25*(1+Inputs!$B$6)/(Inputs!$B$5-Inputs!$B$6)/(1+Inputs!$B$5)^10
A26: =ROUND(-0.2+22*0.005,4) | B26: =1*(1+$A26+(Inputs!$B$6-$A26)*(B$3-1)/9) | C26: =B26*(1+$A26+(Inputs!$B$6-$A26)*(C$3-1)/9) | D26: =C26*(1+$A26+(Inputs!$B$6-$A26)*(D$3-1)/9) | E26: =D26*(1+$A26+(Inputs!$B$6-$A26)*(E$3-1)/9) | F26: =E26*(1+$A26+(Inputs!$B$6-$A26)*(F$3-1)/9) | G26: =F26*(1+$A26+(Inputs!$B$6-$A26)*(G$3-1)/9) | H26: =G26*(1+$A26+(Inputs!$B$6-$A26)*(H$3-1)/9) | I26: =H26*(1+$A26+(Inputs!$B$6-$A26)*(I$3-1)/9) | J26: =I26*(1+$A26+(Inputs!$B$6-$A26)*(J$3-1)/9) | K26: =J26*(1+$A26+(Inputs!$B$6-$A26)*(K$3-1)/9) | L26: =SUMPRODUCT(B26:K26,1/(1+Inputs!$B$4)^$B$3:$K$3)+K26*(1+Inputs!$B$6)/(Inputs!$B$4-Inputs!$B$6)/(1+Inputs!$B$4)^10 | M26: =SUMPRODUCT(B26:K26,1/(1+Inputs!$B$5)^$B$3:$K$3)+K26*(1+Inputs!$B$6)/(Inputs!$B$5-Inputs!$B$6)/(1+Inputs!$B$5)^10
A27: =ROUND(-0.2+23*0.005,4) | B27: =1*(1+$A27+(Inputs!$B$6-$A27)*(B$3-1)/9) | C27: =B27*(1+$A27+(Inputs!$B$6-$A27)*(C$3-1)/9) | D27: =C27*(1+$A27+(Inputs!$B$6-$A27)*(D$3-1)/9) | E27: =D27*(1+$A27+(Inputs!$B$6-$A27)*(E$3-1)/9) | F27: =E27*(1+$A27+(Inputs!$B$6-$A27)*(F$3-1)/9) | G27: =F27*(1+$A27+(Inputs!$B$6-$A27)*(G$3-1)/9) | H27: =G27*(1+$A27+(Inputs!$B$6-$A27)*(H$3-1)/9) | I27: =H27*(1+$A27+(Inputs!$B$6-$A27)*(I$3-1)/9) | J27: =I27*(1+$A27+(Inputs!$B$6-$A27)*(J$3-1)/9) | K27: =J27*(1+$A27+(Inputs!$B$6-$A27)*(K$3-1)/9) | L27: =SUMPRODUCT(B27:K27,1/(1+Inputs!$B$4)^$B$3:$K$3)+K27*(1+Inputs!$B$6)/(Inputs!$B$4-Inputs!$B$6)/(1+Inputs!$B$4)^10 | M27: =SUMPRODUCT(B27:K27,1/(1+Inputs!$B$5)^$B$3:$K$3)+K27*(1+Inputs!$B$6)/(Inputs!$B$5-Inputs!$B$6)/(1+Inputs!$B$5)^10
A28: =ROUND(-0.2+24*0.005,4) | B28: =1*(1+$A28+(Inputs!$B$6-$A28)*(B$3-1)/9) | C28: =B28*(1+$A28+(Inputs!$B$6-$A28)*(C$3-1)/9) | D28: =C28*(1+$A28+(Inputs!$B$6-$A28)*(D$3-1)/9) | E28: =D28*(1+$A28+(Inputs!$B$6-$A28)*(E$3-1)/9) | F28: =E28*(1+$A28+(Inputs!$B$6-$A28)*(F$3-1)/9) | G28: =F28*(1+$A28+(Inputs!$B$6-$A28)*(G$3-1)/9) | H28: =G28*(1+$A28+(Inputs!$B$6-$A28)*(H$3-1)/9) | I28: =H28*(1+$A28+(Inputs!$B$6-$A28)*(I$3-1)/9) | J28: =I28*(1+$A28+(Inputs!$B$6-$A28)*(J$3-1)/9) | K28: =J28*(1+$A28+(Inputs!$B$6-$A28)*(K$3-1)/9) | L28: =SUMPRODUCT(B28:K28,1/(1+Inputs!$B$4)^$B$3:$K$3)+K28*(1+Inputs!$B$6)/(Inputs!$B$4-Inputs!$B$6)/(1+Inputs!$B$4)^10 | M28: =SUMPRODUCT(B28:K28,1/(1+Inputs!$B$5)^$B$3:$K$3)+K28*(1+Inputs!$B$6)/(Inputs!$B$5-Inputs!$B$6)/(1+Inputs!$B$5)^10
A29: =ROUND(-0.2+25*0.005,4) | B29: =1*(1+$A29+(Inputs!$B$6-$A29)*(B$3-1)/9) | C29: =B29*(1+$A29+(Inputs!$B$6-$A29)*(C$3-1)/9) | D29: =C29*(1+$A29+(Inputs!$B$6-$A29)*(D$3-1)/9) | E29: =D29*(1+$A29+(Inputs!$B$6-$A29)*(E$3-1)/9) | F29: =E29*(1+$A29+(Inputs!$B$6-$A29)*(F$3-1)/9) | G29: =F29*(1+$A29+(Inputs!$B$6-$A29)*(G$3-1)/9) | H29: =G29*(1+$A29+(Inputs!$B$6-$A29)*(H$3-1)/9) | I29: =H29*(1+$A29+(Inputs!$B$6-$A29)*(I$3-1)/9) | J29: =I29*(1+$A29+(Inputs!$B$6-$A29)*(J$3-1)/9) | K29: =J29*(1+$A29+(Inputs!$B$6-$A29)*(K$3-1)/9) | L29: =SUMPRODUCT(B29:K29,1/(1+Inputs!$B$4)^$B$3:$K$3)+K29*(1+Inputs!$B$6)/(Inputs!$B$4-Inputs!$B$6)/(1+Inputs!$B$4)^10 | M29: =SUMPRODUCT(B29:K29,1/(1+Inputs!$B$5)^$B$3:$K$3)+K29*(1+Inputs!$B$6)/(Inputs!$B$5-Inputs!$B$6)/(1+Inputs!$B$5)^10
A30: =ROUND(-0.2+26*0.005,4) | B30: =1*(1+$A30+(Inputs!$B$6-$A30)*(B$3-1)/9) | C30: =B30*(1+$A30+(Inputs!$B$6-$A30)*(C$3-1)/9) | D30: =C30*(1+$A30+(Inputs!$B$6-$A30)*(D$3-1)/9) | E30: =D30*(1+$A30+(Inputs!$B$6-$A30)*(E$3-1)/9) | F30: =E30*(1+$A30+(Inputs!$B$6-$A30)*(F$3-1)/9) | G30: =F30*(1+$A30+(Inputs!$B$6-$A30)*(G$3-1)/9) | H30: =G30*(1+$A30+(Inputs!$B$6-$A30)*(H$3-1)/9) | I30: =H30*(1+$A30+(Inputs!$B$6-$A30)*(I$3-1)/9) | J30: =I30*(1+$A30+(Inputs!$B$6-$A30)*(J$3-1)/9) | K30: =J30*(1+$A30+(Inputs!$B$6-$A30)*(K$3-1)/9) | L30: =SUMPRODUCT(B30:K30,1/(1+Inputs!$B$4)^$B$3:$K$3)+K30*(1+Inputs!$B$6)/(Inputs!$B$4-Inputs!$B$6)/(1+Inputs!$B$4)^10 | M30: =SUMPRODUCT(B30:K30,1/(1+Inputs!$B$5)^$B$3:$K$3)+K30*(1+Inputs!$B$6)/(Inputs!$B$5-Inputs!$B$6)/(1+Inputs!$B$5)^10
A31: =ROUND(-0.2+27*0.005,4) | B31: =1*(1+$A31+(Inputs!$B$6-$A31)*(B$3-1)/9) | C31: =B31*(1+$A31+(Inputs!$B$6-$A31)*(C$3-1)/9) | D31: =C31*(1+$A31+(Inputs!$B$6-$A31)*(D$3-1)/9) | E31: =D31*(1+$A31+(Inputs!$B$6-$A31)*(E$3-1)/9) | F31: =E31*(1+$A31+(Inputs!$B$6-$A31)*(F$3-1)/9) | G31: =F31*(1+$A31+(Inputs!$B$6-$A31)*(G$3-1)/9) | H31: =G31*(1+$A31+(Inputs!$B$6-$A31)*(H$3-1)/9) | I31: =H31*(1+$A31+(Inputs!$B$6-$A31)*(I$3-1)/9) | J31: =I31*(1+$A31+(Inputs!$B$6-$A31)*(J$3-1)/9) | K31: =J31*(1+$A31+(Inputs!$B$6-$A31)*(K$3-1)/9) | L31: =SUMPRODUCT(B31:K31,1/(1+Inputs!$B$4)^$B$3:$K$3)+K31*(1+Inputs!$B$6)/(Inputs!$B$4-Inputs!$B$6)/(1+Inputs!$B$4)^10 | M31: =SUMPRODUCT(B31:K31,1/(1+Inputs!$B$5)^$B$3:$K$3)+K31*(1+Inputs!$B$6)/(Inputs!$B$5-Inputs!$B$6)/(1+Inputs!$B$5)^10
A32: =ROUND(-0.2+28*0.005,4) | B32: =1*(1+$A32+(Inputs!$B$6-$A32)*(B$3-1)/9) | C32: =B32*(1+$A32+(Inputs!$B$6-$A32)*(C$3-1)/9) | D32: =C32*(1+$A32+(Inputs!$B$6-$A32)*(D$3-1)/9) | E32: =D32*(1+$A32+(Inputs!$B$6-$A32)*(E$3-1)/9) | F32: =E32*(1+$A32+(Inputs!$B$6-$A32)*(F$3-1)/9) | G32: =F32*(1+$A32+(Inputs!$B$6-$A32)*(G$3-1)/9) | H32: =G32*(1+$A32+(Inputs!$B$6-$A32)*(H$3-1)/9) | I32: =H32*(1+$A32+(Inputs!$B$6-$A32)*(I$3-1)/9) | J32: =I32*(1+$A32+(Inputs!$B$6-$A32)*(J$3-1)/9) | K32: =J32*(1+$A32+(Inputs!$B$6-$A32)*(K$3-1)/9) | L32: =SUMPRODUCT(B32:K32,1/(1+Inputs!$B$4)^$B$3:$K$3)+K32*(1+Inputs!$B$6)/(Inputs!$B$4-Inputs!$B$6)/(1+Inputs!$B$4)^10 | M32: =SUMPRODUCT(B32:K32,1/(1+Inputs!$B$5)^$B$3:$K$3)+K32*(1+Inputs!$B$6)/(Inputs!$B$5-Inputs!$B$6)/(1+Inputs!$B$5)^10
A33: =ROUND(-0.2+29*0.005,4) | B33: =1*(1+$A33+(Inputs!$B$6-$A33)*(B$3-1)/9) | C33: =B33*(1+$A33+(Inputs!$B$6-$A33)*(C$3-1)/9) | D33: =C33*(1+$A33+(Inputs!$B$6-$A33)*(D$3-1)/9) | E33: =D33*(1+$A33+(Inputs!$B$6-$A33)*(E$3-1)/9) | F33: =E33*(1+$A33+(Inputs!$B$6-$A33)*(F$3-1)/9) | G33: =F33*(1+$A33+(Inputs!$B$6-$A33)*(G$3-1)/9) | H33: =G33*(1+$A33+(Inputs!$B$6-$A33)*(H$3-1)/9) | I33: =H33*(1+$A33+(Inputs!$B$6-$A33)*(I$3-1)/9) | J33: =I33*(1+$A33+(Inputs!$B$6-$A33)*(J$3-1)/9) | K33: =J33*(1+$A33+(Inputs!$B$6-$A33)*(K$3-1)/9) | L33: =SUMPRODUCT(B33:K33,1/(1+Inputs!$B$4)^$B$3:$K$3)+K33*(1+Inputs!$B$6)/(Inputs!$B$4-Inputs!$B$6)/(1+Inputs!$B$4)^10 | M33: =SUMPRODUCT(B33:K33,1/(1+Inputs!$B$5)^$B$3:$K$3)+K33*(1+Inputs!$B$6)/(Inputs!$B$5-Inputs!$B$6)/(1+Inputs!$B$5)^10
A34: =ROUND(-0.2+30*0.005,4) | B34: =1*(1+$A34+(Inputs!$B$6-$A34)*(B$3-1)/9) | C34: =B34*(1+$A34+(Inputs!$B$6-$A34)*(C$3-1)/9) | D34: =C34*(1+$A34+(Inputs!$B$6-$A34)*(D$3-1)/9) | E34: =D34*(1+$A34+(Inputs!$B$6-$A34)*(E$3-1)/9) | F34: =E34*(1+$A34+(Inputs!$B$6-$A34)*(F$3-1)/9) | G34: =F34*(1+$A34+(Inputs!$B$6-$A34)*(G$3-1)/9) | H34: =G34*(1+$A34+(Inputs!$B$6-$A34)*(H$3-1)/9) | I34: =H34*(1+$A34+(Inputs!$B$6-$A34)*(I$3-1)/9) | J34: =I34*(1+$A34+(Inputs!$B$6-$A34)*(J$3-1)/9) | K34: =J34*(1+$A34+(Inputs!$B$6-$A34)*(K$3-1)/9) | L34: =SUMPRODUCT(B34:K34,1/(1+Inputs!$B$4)^$B$3:$K$3)+K34*(1+Inputs!$B$6)/(Inputs!$B$4-Inputs!$B$6)/(1+Inputs!$B$4)^10 | M34: =SUMPRODUCT(B34:K34,1/(1+Inputs!$B$5)^$B$3:$K$3)+K34*(1+Inputs!$B$6)/(Inputs!$B$5-Inputs!$B$6)/(1+Inputs!$B$5)^10
A35: =ROUND(-0.2+31*0.005,4) | B35: =1*(1+$A35+(Inputs!$B$6-$A35)*(B$3-1)/9) | C35: =B35*(1+$A35+(Inputs!$B$6-$A35)*(C$3-1)/9) | D35: =C35*(1+$A35+(Inputs!$B$6-$A35)*(D$3-1)/9) | E35: =D35*(1+$A35+(Inputs!$B$6-$A35)*(E$3-1)/9) | F35: =E35*(1+$A35+(Inputs!$B$6-$A35)*(F$3-1)/9) | G35: =F35*(1+$A35+(Inputs!$B$6-$A35)*(G$3-1)/9) | H35: =G35*(1+$A35+(Inputs!$B$6-$A35)*(H$3-1)/9) | I35: =H35*(1+$A35+(Inputs!$B$6-$A35)*(I$3-1)/9) | J35: =I35*(1+$A35+(Inputs!$B$6-$A35)*(J$3-1)/9) | K35: =J35*(1+$A35+(Inputs!$B$6-$A35)*(K$3-1)/9) | L35: =SUMPRODUCT(B35:K35,1/(1+Inputs!$B$4)^$B$3:$K$3)+K35*(1+Inputs!$B$6)/(Inputs!$B$4-Inputs!$B$6)/(1+Inputs!$B$4)^10 | M35: =SUMPRODUCT(B35:K35,1/(1+Inputs!$B$5)^$B$3:$K$3)+K35*(1+Inputs!$B$6)/(Inputs!$B$5-Inputs!$B$6)/(1+Inputs!$B$5)^10
A36: =ROUND(-0.2+32*0.005,4) | B36: =1*(1+$A36+(Inputs!$B$6-$A36)*(B$3-1)/9) | C36: =B36*(1+$A36+(Inputs!$B$6-$A36)*(C$3-1)/9) | D36: =C36*(1+$A36+(Inputs!$B$6-$A36)*(D$3-1)/9) | E36: =D36*(1+$A36+(Inputs!$B$6-$A36)*(E$3-1)/9) | F36: =E36*(1+$A36+(Inputs!$B$6-$A36)*(F$3-1)/9) | G36: =F36*(1+$A36+(Inputs!$B$6-$A36)*(G$3-1)/9) | H36: =G36*(1+$A36+(Inputs!$B$6-$A36)*(H$3-1)/9) | I36: =H36*(1+$A36+(Inputs!$B$6-$A36)*(I$3-1)/9) | J36: =I36*(1+$A36+(Inputs!$B$6-$A36)*(J$3-1)/9) | K36: =J36*(1+$A36+(Inputs!$B$6-$A36)*(K$3-1)/9) | L36: =SUMPRODUCT(B36:K36,1/(1+Inputs!$B$4)^$B$3:$K$3)+K36*(1+Inputs!$B$6)/(Inputs!$B$4-Inputs!$B$6)/(1+Inputs!$B$4)^10 | M36: =SUMPRODUCT(B36:K36,1/(1+Inputs!$B$5)^$B$3:$K$3)+K36*(1+Inputs!$B$6)/(Inputs!$B$5-Inputs!$B$6)/(1+Inputs!$B$5)^10
A37: =ROUND(-0.2+33*0.005,4) | B37: =1*(1+$A37+(Inputs!$B$6-$A37)*(B$3-1)/9) | C37: =B37*(1+$A37+(Inputs!$B$6-$A37)*(C$3-1)/9) | D37: =C37*(1+$A37+(Inputs!$B$6-$A37)*(D$3-1)/9) | E37: =D37*(1+$A37+(Inputs!$B$6-$A37)*(E$3-1)/9) | F37: =E37*(1+$A37+(Inputs!$B$6-$A37)*(F$3-1)/9) | G37: =F37*(1+$A37+(Inputs!$B$6-$A37)*(G$3-1)/9) | H37: =G37*(1+$A37+(Inputs!$B$6-$A37)*(H$3-1)/9) | I37: =H37*(1+$A37+(Inputs!$B$6-$A37)*(I$3-1)/9) | J37: =I37*(1+$A37+(Inputs!$B$6-$A37)*(J$3-1)/9) | K37: =J37*(1+$A37+(Inputs!$B$6-$A37)*(K$3-1)/9) | L37: =SUMPRODUCT(B37:K37,1/(1+Inputs!$B$4)^$B$3:$K$3)+K37*(1+Inputs!$B$6)/(Inputs!$B$4-Inputs!$B$6)/(1+Inputs!$B$4)^10 | M37: =SUMPRODUCT(B37:K37,1/(1+Inputs!$B$5)^$B$3:$K$3)+K37*(1+Inputs!$B$6)/(Inputs!$B$5-Inputs!$B$6)/(1+Inputs!$B$5)^10
A38: =ROUND(-0.2+34*0.005,4) | B38: =1*(1+$A38+(Inputs!$B$6-$A38)*(B$3-1)/9) | C38: =B38*(1+$A38+(Inputs!$B$6-$A38)*(C$3-1)/9) | D38: =C38*(1+$A38+(Inputs!$B$6-$A38)*(D$3-1)/9) | E38: =D38*(1+$A38+(Inputs!$B$6-$A38)*(E$3-1)/9) | F38: =E38*(1+$A38+(Inputs!$B$6-$A38)*(F$3-1)/9) | G38: =F38*(1+$A38+(Inputs!$B$6-$A38)*(G$3-1)/9) | H38: =G38*(1+$A38+(Inputs!$B$6-$A38)*(H$3-1)/9) | I38: =H38*(1+$A38+(Inputs!$B$6-$A38)*(I$3-1)/9) | J38: =I38*(1+$A38+(Inputs!$B$6-$A38)*(J$3-1)/9) | K38: =J38*(1+$A38+(Inputs!$B$6-$A38)*(K$3-1)/9) | L38: =SUMPRODUCT(B38:K38,1/(1+Inputs!$B$4)^$B$3:$K$3)+K38*(1+Inputs!$B$6)/(Inputs!$B$4-Inputs!$B$6)/(1+Inputs!$B$4)^10 | M38: =SUMPRODUCT(B38:K38,1/(1+Inputs!$B$5)^$B$3:$K$3)+K38*(1+Inputs!$B$6)/(Inputs!$B$5-Inputs!$B$6)/(1+Inputs!$B$5)^10
A39: =ROUND(-0.2+35*0.005,4) | B39: =1*(1+$A39+(Inputs!$B$6-$A39)*(B$3-1)/9) | C39: =B39*(1+$A39+(Inputs!$B$6-$A39)*(C$3-1)/9) | D39: =C39*(1+$A39+(Inputs!$B$6-$A39)*(D$3-1)/9) | E39: =D39*(1+$A39+(Inputs!$B$6-$A39)*(E$3-1)/9) | F39: =E39*(1+$A39+(Inputs!$B$6-$A39)*(F$3-1)/9) | G39: =F39*(1+$A39+(Inputs!$B$6-$A39)*(G$3-1)/9) | H39: =G39*(1+$A39+(Inputs!$B$6-$A39)*(H$3-1)/9) | I39: =H39*(1+$A39+(Inputs!$B$6-$A39)*(I$3-1)/9) | J39: =I39*(1+$A39+(Inputs!$B$6-$A39)*(J$3-1)/9) | K39: =J39*(1+$A39+(Inputs!$B$6-$A39)*(K$3-1)/9) | L39: =SUMPRODUCT(B39:K39,1/(1+Inputs!$B$4)^$B$3:$K$3)+K39*(1+Inputs!$B$6)/(Inputs!$B$4-Inputs!$B$6)/(1+Inputs!$B$4)^10 | M39: =SUMPRODUCT(B39:K39,1/(1+Inputs!$B$5)^$B$3:$K$3)+K39*(1+Inputs!$B$6)/(Inputs!$B$5-Inputs!$B$6)/(1+Inputs!$B$5)^10
A40: =ROUND(-0.2+36*0.005,4) | B40: =1*(1+$A40+(Inputs!$B$6-$A40)*(B$3-1)/9) | C40: =B40*(1+$A40+(Inputs!$B$6-$A40)*(C$3-1)/9) | D40: =C40*(1+$A40+(Inputs!$B$6-$A40)*(D$3-1)/9) | E40: =D40*(1+$A40+(Inputs!$B$6-$A40)*(E$3-1)/9) | F40: =E40*(1+$A40+(Inputs!$B$6-$A40)*(F$3-1)/9) | G40: =F40*(1+$A40+(Inputs!$B$6-$A40)*(G$3-1)/9) | H40: =G40*(1+$A40+(Inputs!$B$6-$A40)*(H$3-1)/9) | I40: =H40*(1+$A40+(Inputs!$B$6-$A40)*(I$3-1)/9) | J40: =I40*(1+$A40+(Inputs!$B$6-$A40)*(J$3-1)/9) | K40: =J40*(1+$A40+(Inputs!$B$6-$A40)*(K$3-1)/9) | L40: =SUMPRODUCT(B40:K40,1/(1+Inputs!$B$4)^$B$3:$K$3)+K40*(1+Inputs!$B$6)/(Inputs!$B$4-Inputs!$B$6)/(1+Inputs!$B$4)^10 | M40: =SUMPRODUCT(B40:K40,1/(1+Inputs!$B$5)^$B$3:$K$3)+K40*(1+Inputs!$B$6)/(Inputs!$B$5-Inputs!$B$6)/(1+Inputs!$B$5)^10
A41: =ROUND(-0.2+37*0.005,4) | B41: =1*(1+$A41+(Inputs!$B$6-$A41)*(B$3-1)/9) | C41: =B41*(1+$A41+(Inputs!$B$6-$A41)*(C$3-1)/9) | D41: =C41*(1+$A41+(Inputs!$B$6-$A41)*(D$3-1)/9) | E41: =D41*(1+$A41+(Inputs!$B$6-$A41)*(E$3-1)/9) | F41: =E41*(1+$A41+(Inputs!$B$6-$A41)*(F$3-1)/9) | G41: =F41*(1+$A41+(Inputs!$B$6-$A41)*(G$3-1)/9) | H41: =G41*(1+$A41+(Inputs!$B$6-$A41)*(H$3-1)/9) | I41: =H41*(1+$A41+(Inputs!$B$6-$A41)*(I$3-1)/9) | J41: =I41*(1+$A41+(Inputs!$B$6-$A41)*(J$3-1)/9) | K41: =J41*(1+$A41+(Inputs!$B$6-$A41)*(K$3-1)/9) | L41: =SUMPRODUCT(B41:K41,1/(1+Inputs!$B$4)^$B$3:$K$3)+K41*(1+Inputs!$B$6)/(Inputs!$B$4-Inputs!$B$6)/(1+Inputs!$B$4)^10 | M41: =SUMPRODUCT(B41:K41,1/(1+Inputs!$B$5)^$B$3:$K$3)+K41*(1+Inputs!$B$6)/(Inputs!$B$5-Inputs!$B$6)/(1+Inputs!$B$5)^10
A42: =ROUND(-0.2+38*0.005,4) | B42: =1*(1+$A42+(Inputs!$B$6-$A42)*(B$3-1)/9) | C42: =B42*(1+$A42+(Inputs!$B$6-$A42)*(C$3-1)/9) | D42: =C42*(1+$A42+(Inputs!$B$6-$A42)*(D$3-1)/9) | E42: =D42*(1+$A42+(Inputs!$B$6-$A42)*(E$3-1)/9) | F42: =E42*(1+$A42+(Inputs!$B$6-$A42)*(F$3-1)/9) | G42: =F42*(1+$A42+(Inputs!$B$6-$A42)*(G$3-1)/9) | H42: =G42*(1+$A42+(Inputs!$B$6-$A42)*(H$3-1)/9) | I42: =H42*(1+$A42+(Inputs!$B$6-$A42)*(I$3-1)/9) | J42: =I42*(1+$A42+(Inputs!$B$6-$A42)*(J$3-1)/9) | K42: =J42*(1+$A42+(Inputs!$B$6-$A42)*(K$3-1)/9) | L42: =SUMPRODUCT(B42:K42,1/(1+Inputs!$B$4)^$B$3:$K$3)+K42*(1+Inputs!$B$6)/(Inputs!$B$4-Inputs!$B$6)/(1+Inputs!$B$4)^10 | M42: =SUMPRODUCT(B42:K42,1/(1+Inputs!$B$5)^$B$3:$K$3)+K42*(1+Inputs!$B$6)/(Inputs!$B$5-Inputs!$B$6)/(1+Inputs!$B$5)^10
A43: =ROUND(-0.2+39*0.005,4) | B43: =1*(1+$A43+(Inputs!$B$6-$A43)*(B$3-1)/9) | C43: =B43*(1+$A43+(Inputs!$B$6-$A43)*(C$3-1)/9) | D43: =C43*(1+$A43+(Inputs!$B$6-$A43)*(D$3-1)/9) | E43: =D43*(1+$A43+(Inputs!$B$6-$A43)*(E$3-1)/9) | F43: =E43*(1+$A43+(Inputs!$B$6-$A43)*(F$3-1)/9) | G43: =F43*(1+$A43+(Inputs!$B$6-$A43)*(G$3-1)/9) | H43: =G43*(1+$A43+(Inputs!$B$6-$A43)*(H$3-1)/9) | I43: =H43*(1+$A43+(Inputs!$B$6-$A43)*(I$3-1)/9) | J43: =I43*(1+$A43+(Inputs!$B$6-$A43)*(J$3-1)/9) | K43: =J43*(1+$A43+(Inputs!$B$6-$A43)*(K$3-1)/9) | L43: =SUMPRODUCT(B43:K43,1/(1+Inputs!$B$4)^$B$3:$K$3)+K43*(1+Inputs!$B$6)/(Inputs!$B$4-Inputs!$B$6)/(1+Inputs!$B$4)^10 | M43: =SUMPRODUCT(B43:K43,1/(1+Inputs!$B$5)^$B$3:$K$3)+K43*(1+Inputs!$B$6)/(Inputs!$B$5-Inputs!$B$6)/(1+Inputs!$B$5)^10
A44: =ROUND(-0.2+40*0.005,4) | B44: =1*(1+$A44+(Inputs!$B$6-$A44)*(B$3-1)/9) | C44: =B44*(1+$A44+(Inputs!$B$6-$A44)*(C$3-1)/9) | D44: =C44*(1+$A44+(Inputs!$B$6-$A44)*(D$3-1)/9) | E44: =D44*(1+$A44+(Inputs!$B$6-$A44)*(E$3-1)/9) | F44: =E44*(1+$A44+(Inputs!$B$6-$A44)*(F$3-1)/9) | G44: =F44*(1+$A44+(Inputs!$B$6-$A44)*(G$3-1)/9) | H44: =G44*(1+$A44+(Inputs!$B$6-$A44)*(H$3-1)/9) | I44: =H44*(1+$A44+(Inputs!$B$6-$A44)*(I$3-1)/9) | J44: =I44*(1+$A44+(Inputs!$B$6-$A44)*(J$3-1)/9) | K44: =J44*(1+$A44+(Inputs!$B$6-$A44)*(K$3-1)/9) | L44: =SUMPRODUCT(B44:K44,1/(1+Inputs!$B$4)^$B$3:$K$3)+K44*(1+Inputs!$B$6)/(Inputs!$B$4-Inputs!$B$6)/(1+Inputs!$B$4)^10 | M44: =SUMPRODUCT(B44:K44,1/(1+Inputs!$B$5)^$B$3:$K$3)+K44*(1+Inputs!$B$6)/(Inputs!$B$5-Inputs!$B$6)/(1+Inputs!$B$5)^10
A45: =ROUND(-0.2+41*0.005,4) | B45: =1*(1+$A45+(Inputs!$B$6-$A45)*(B$3-1)/9) | C45: =B45*(1+$A45+(Inputs!$B$6-$A45)*(C$3-1)/9) | D45: =C45*(1+$A45+(Inputs!$B$6-$A45)*(D$3-1)/9) | E45: =D45*(1+$A45+(Inputs!$B$6-$A45)*(E$3-1)/9) | F45: =E45*(1+$A45+(Inputs!$B$6-$A45)*(F$3-1)/9) | G45: =F45*(1+$A45+(Inputs!$B$6-$A45)*(G$3-1)/9) | H45: =G45*(1+$A45+(Inputs!$B$6-$A45)*(H$3-1)/9) | I45: =H45*(1+$A45+(Inputs!$B$6-$A45)*(I$3-1)/9) | J45: =I45*(1+$A45+(Inputs!$B$6-$A45)*(J$3-1)/9) | K45: =J45*(1+$A45+(Inputs!$B$6-$A45)*(K$3-1)/9) | L45: =SUMPRODUCT(B45:K45,1/(1+Inputs!$B$4)^$B$3:$K$3)+K45*(1+Inputs!$B$6)/(Inputs!$B$4-Inputs!$B$6)/(1+Inputs!$B$4)^10 | M45: =SUMPRODUCT(B45:K45,1/(1+Inputs!$B$5)^$B$3:$K$3)+K45*(1+Inputs!$B$6)/(Inputs!$B$5-Inputs!$B$6)/(1+Inputs!$B$5)^10
A46: =ROUND(-0.2+42*0.005,4) | B46: =1*(1+$A46+(Inputs!$B$6-$A46)*(B$3-1)/9) | C46: =B46*(1+$A46+(Inputs!$B$6-$A46)*(C$3-1)/9) | D46: =C46*(1+$A46+(Inputs!$B$6-$A46)*(D$3-1)/9) | E46: =D46*(1+$A46+(Inputs!$B$6-$A46)*(E$3-1)/9) | F46: =E46*(1+$A46+(Inputs!$B$6-$A46)*(F$3-1)/9) | G46: =F46*(1+$A46+(Inputs!$B$6-$A46)*(G$3-1)/9) | H46: =G46*(1+$A46+(Inputs!$B$6-$A46)*(H$3-1)/9) | I46: =H46*(1+$A46+(Inputs!$B$6-$A46)*(I$3-1)/9) | J46: =I46*(1+$A46+(Inputs!$B$6-$A46)*(J$3-1)/9) | K46: =J46*(1+$A46+(Inputs!$B$6-$A46)*(K$3-1)/9) | L46: =SUMPRODUCT(B46:K46,1/(1+Inputs!$B$4)^$B$3:$K$3)+K46*(1+Inputs!$B$6)/(Inputs!$B$4-Inputs!$B$6)/(1+Inputs!$B$4)^10 | M46: =SUMPRODUCT(B46:K46,1/(1+Inputs!$B$5)^$B$3:$K$3)+K46*(1+Inputs!$B$6)/(Inputs!$B$5-Inputs!$B$6)/(1+Inputs!$B$5)^10
A47: =ROUND(-0.2+43*0.005,4) | B47: =1*(1+$A47+(Inputs!$B$6-$A47)*(B$3-1)/9) | C47: =B47*(1+$A47+(Inputs!$B$6-$A47)*(C$3-1)/9) | D47: =C47*(1+$A47+(Inputs!$B$6-$A47)*(D$3-1)/9) | E47: =D47*(1+$A47+(Inputs!$B$6-$A47)*(E$3-1)/9) | F47: =E47*(1+$A47+(Inputs!$B$6-$A47)*(F$3-1)/9) | G47: =F47*(1+$A47+(Inputs!$B$6-$A47)*(G$3-1)/9) | H47: =G47*(1+$A47+(Inputs!$B$6-$A47)*(H$3-1)/9) | I47: =H47*(1+$A47+(Inputs!$B$6-$A47)*(I$3-1)/9) | J47: =I47*(1+$A47+(Inputs!$B$6-$A47)*(J$3-1)/9) | K47: =J47*(1+$A47+(Inputs!$B$6-$A47)*(K$3-1)/9) | L47: =SUMPRODUCT(B47:K47,1/(1+Inputs!$B$4)^$B$3:$K$3)+K47*(1+Inputs!$B$6)/(Inputs!$B$4-Inputs!$B$6)/(1+Inputs!$B$4)^10 | M47: =SUMPRODUCT(B47:K47,1/(1+Inputs!$B$5)^$B$3:$K$3)+K47*(1+Inputs!$B$6)/(Inputs!$B$5-Inputs!$B$6)/(1+Inputs!$B$5)^10
A48: =ROUND(-0.2+44*0.005,4) | B48: =1*(1+$A48+(Inputs!$B$6-$A48)*(B$3-1)/9) | C48: =B48*(1+$A48+(Inputs!$B$6-$A48)*(C$3-1)/9) | D48: =C48*(1+$A48+(Inputs!$B$6-$A48)*(D$3-1)/9) | E48: =D48*(1+$A48+(Inputs!$B$6-$A48)*(E$3-1)/9) | F48: =E48*(1+$A48+(Inputs!$B$6-$A48)*(F$3-1)/9) | G48: =F48*(1+$A48+(Inputs!$B$6-$A48)*(G$3-1)/9) | H48: =G48*(1+$A48+(Inputs!$B$6-$A48)*(H$3-1)/9) | I48: =H48*(1+$A48+(Inputs!$B$6-$A48)*(I$3-1)/9) | J48: =I48*(1+$A48+(Inputs!$B$6-$A48)*(J$3-1)/9) | K48: =J48*(1+$A48+(Inputs!$B$6-$A48)*(K$3-1)/9) | L48: =SUMPRODUCT(B48:K48,1/(1+Inputs!$B$4)^$B$3:$K$3)+K48*(1+Inputs!$B$6)/(Inputs!$B$4-Inputs!$B$6)/(1+Inputs!$B$4)^10 | M48: =SUMPRODUCT(B48:K48,1/(1+Inputs!$B$5)^$B$3:$K$3)+K48*(1+Inputs!$B$6)/(Inputs!$B$5-Inputs!$B$6)/(1+Inputs!$B$5)^10
A49: =ROUND(-0.2+45*0.005,4) | B49: =1*(1+$A49+(Inputs!$B$6-$A49)*(B$3-1)/9) | C49: =B49*(1+$A49+(Inputs!$B$6-$A49)*(C$3-1)/9) | D49: =C49*(1+$A49+(Inputs!$B$6-$A49)*(D$3-1)/9) | E49: =D49*(1+$A49+(Inputs!$B$6-$A49)*(E$3-1)/9) | F49: =E49*(1+$A49+(Inputs!$B$6-$A49)*(F$3-1)/9) | G49: =F49*(1+$A49+(Inputs!$B$6-$A49)*(G$3-1)/9) | H49: =G49*(1+$A49+(Inputs!$B$6-$A49)*(H$3-1)/9) | I49: =H49*(1+$A49+(Inputs!$B$6-$A49)*(I$3-1)/9) | J49: =I49*(1+$A49+(Inputs!$B$6-$A49)*(J$3-1)/9) | K49: =J49*(1+$A49+(Inputs!$B$6-$A49)*(K$3-1)/9) | L49: =SUMPRODUCT(B49:K49,1/(1+Inputs!$B$4)^$B$3:$K$3)+K49*(1+Inputs!$B$6)/(Inputs!$B$4-Inputs!$B$6)/(1+Inputs!$B$4)^10 | M49: =SUMPRODUCT(B49:K49,1/(1+Inputs!$B$5)^$B$3:$K$3)+K49*(1+Inputs!$B$6)/(Inputs!$B$5-Inputs!$B$6)/(1+Inputs!$B$5)^10
A50: =ROUND(-0.2+46*0.005,4) | B50: =1*(1+$A50+(Inputs!$B$6-$A50)*(B$3-1)/9) | C50: =B50*(1+$A50+(Inputs!$B$6-$A50)*(C$3-1)/9) | D50: =C50*(1+$A50+(Inputs!$B$6-$A50)*(D$3-1)/9) | E50: =D50*(1+$A50+(Inputs!$B$6-$A50)*(E$3-1)/9) | F50: =E50*(1+$A50+(Inputs!$B$6-$A50)*(F$3-1)/9) | G50: =F50*(1+$A50+(Inputs!$B$6-$A50)*(G$3-1)/9) | H50: =G50*(1+$A50+(Inputs!$B$6-$A50)*(H$3-1)/9) | I50: =H50*(1+$A50+(Inputs!$B$6-$A50)*(I$3-1)/9) | J50: =I50*(1+$A50+(Inputs!$B$6-$A50)*(J$3-1)/9) | K50: =J50*(1+$A50+(Inputs!$B$6-$A50)*(K$3-1)/9) | L50: =SUMPRODUCT(B50:K50,1/(1+Inputs!$B$4)^$B$3:$K$3)+K50*(1+Inputs!$B$6)/(Inputs!$B$4-Inputs!$B$6)/(1+Inputs!$B$4)^10 | M50: =SUMPRODUCT(B50:K50,1/(1+Inputs!$B$5)^$B$3:$K$3)+K50*(1+Inputs!$B$6)/(Inputs!$B$5-Inputs!$B$6)/(1+Inputs!$B$5)^10
A51: =ROUND(-0.2+47*0.005,4) | B51: =1*(1+$A51+(Inputs!$B$6-$A51)*(B$3-1)/9) | C51: =B51*(1+$A51+(Inputs!$B$6-$A51)*(C$3-1)/9) | D51: =C51*(1+$A51+(Inputs!$B$6-$A51)*(D$3-1)/9) | E51: =D51*(1+$A51+(Inputs!$B$6-$A51)*(E$3-1)/9) | F51: =E51*(1+$A51+(Inputs!$B$6-$A51)*(F$3-1)/9) | G51: =F51*(1+$A51+(Inputs!$B$6-$A51)*(G$3-1)/9) | H51: =G51*(1+$A51+(Inputs!$B$6-$A51)*(H$3-1)/9) | I51: =H51*(1+$A51+(Inputs!$B$6-$A51)*(I$3-1)/9) | J51: =I51*(1+$A51+(Inputs!$B$6-$A51)*(J$3-1)/9) | K51: =J51*(1+$A51+(Inputs!$B$6-$A51)*(K$3-1)/9) | L51: =SUMPRODUCT(B51:K51,1/(1+Inputs!$B$4)^$B$3:$K$3)+K51*(1+Inputs!$B$6)/(Inputs!$B$4-Inputs!$B$6)/(1+Inputs!$B$4)^10 | M51: =SUMPRODUCT(B51:K51,1/(1+Inputs!$B$5)^$B$3:$K$3)+K51*(1+Inputs!$B$6)/(Inputs!$B$5-Inputs!$B$6)/(1+Inputs!$B$5)^10
A52: =ROUND(-0.2+48*0.005,4) | B52: =1*(1+$A52+(Inputs!$B$6-$A52)*(B$3-1)/9) | C52: =B52*(1+$A52+(Inputs!$B$6-$A52)*(C$3-1)/9) | D52: =C52*(1+$A52+(Inputs!$B$6-$A52)*(D$3-1)/9) | E52: =D52*(1+$A52+(Inputs!$B$6-$A52)*(E$3-1)/9) | F52: =E52*(1+$A52+(Inputs!$B$6-$A52)*(F$3-1)/9) | G52: =F52*(1+$A52+(Inputs!$B$6-$A52)*(G$3-1)/9) | H52: =G52*(1+$A52+(Inputs!$B$6-$A52)*(H$3-1)/9) | I52: =H52*(1+$A52+(Inputs!$B$6-$A52)*(I$3-1)/9) | J52: =I52*(1+$A52+(Inputs!$B$6-$A52)*(J$3-1)/9) | K52: =J52*(1+$A52+(Inputs!$B$6-$A52)*(K$3-1)/9) | L52: =SUMPRODUCT(B52:K52,1/(1+Inputs!$B$4)^$B$3:$K$3)+K52*(1+Inputs!$B$6)/(Inputs!$B$4-Inputs!$B$6)/(1+Inputs!$B$4)^10 | M52: =SUMPRODUCT(B52:K52,1/(1+Inputs!$B$5)^$B$3:$K$3)+K52*(1+Inputs!$B$6)/(Inputs!$B$5-Inputs!$B$6)/(1+Inputs!$B$5)^10
A53: =ROUND(-0.2+49*0.005,4) | B53: =1*(1+$A53+(Inputs!$B$6-$A53)*(B$3-1)/9) | C53: =B53*(1+$A53+(Inputs!$B$6-$A53)*(C$3-1)/9) | D53: =C53*(1+$A53+(Inputs!$B$6-$A53)*(D$3-1)/9) | E53: =D53*(1+$A53+(Inputs!$B$6-$A53)*(E$3-1)/9) | F53: =E53*(1+$A53+(Inputs!$B$6-$A53)*(F$3-1)/9) | G53: =F53*(1+$A53+(Inputs!$B$6-$A53)*(G$3-1)/9) | H53: =G53*(1+$A53+(Inputs!$B$6-$A53)*(H$3-1)/9) | I53: =H53*(1+$A53+(Inputs!$B$6-$A53)*(I$3-1)/9) | J53: =I53*(1+$A53+(Inputs!$B$6-$A53)*(J$3-1)/9) | K53: =J53*(1+$A53+(Inputs!$B$6-$A53)*(K$3-1)/9) | L53: =SUMPRODUCT(B53:K53,1/(1+Inputs!$B$4)^$B$3:$K$3)+K53*(1+Inputs!$B$6)/(Inputs!$B$4-Inputs!$B$6)/(1+Inputs!$B$4)^10 | M53: =SUMPRODUCT(B53:K53,1/(1+Inputs!$B$5)^$B$3:$K$3)+K53*(1+Inputs!$B$6)/(Inputs!$B$5-Inputs!$B$6)/(1+Inputs!$B$5)^10
A54: =ROUND(-0.2+50*0.005,4) | B54: =1*(1+$A54+(Inputs!$B$6-$A54)*(B$3-1)/9) | C54: =B54*(1+$A54+(Inputs!$B$6-$A54)*(C$3-1)/9) | D54: =C54*(1+$A54+(Inputs!$B$6-$A54)*(D$3-1)/9) | E54: =D54*(1+$A54+(Inputs!$B$6-$A54)*(E$3-1)/9) | F54: =E54*(1+$A54+(Inputs!$B$6-$A54)*(F$3-1)/9) | G54: =F54*(1+$A54+(Inputs!$B$6-$A54)*(G$3-1)/9) | H54: =G54*(1+$A54+(Inputs!$B$6-$A54)*(H$3-1)/9) | I54: =H54*(1+$A54+(Inputs!$B$6-$A54)*(I$3-1)/9) | J54: =I54*(1+$A54+(Inputs!$B$6-$A54)*(J$3-1)/9) | K54: =J54*(1+$A54+(Inputs!$B$6-$A54)*(K$3-1)/9) | L54: =SUMPRODUCT(B54:K54,1/(1+Inputs!$B$4)^$B$3:$K$3)+K54*(1+Inputs!$B$6)/(Inputs!$B$4-Inputs!$B$6)/(1+Inputs!$B$4)^10 | M54: =SUMPRODUCT(B54:K54,1/(1+Inputs!$B$5)^$B$3:$K$3)+K54*(1+Inputs!$B$6)/(Inputs!$B$5-Inputs!$B$6)/(1+Inputs!$B$5)^10
A55: =ROUND(-0.2+51*0.005,4) | B55: =1*(1+$A55+(Inputs!$B$6-$A55)*(B$3-1)/9) | C55: =B55*(1+$A55+(Inputs!$B$6-$A55)*(C$3-1)/9) | D55: =C55*(1+$A55+(Inputs!$B$6-$A55)*(D$3-1)/9) | E55: =D55*(1+$A55+(Inputs!$B$6-$A55)*(E$3-1)/9) | F55: =E55*(1+$A55+(Inputs!$B$6-$A55)*(F$3-1)/9) | G55: =F55*(1+$A55+(Inputs!$B$6-$A55)*(G$3-1)/9) | H55: =G55*(1+$A55+(Inputs!$B$6-$A55)*(H$3-1)/9) | I55: =H55*(1+$A55+(Inputs!$B$6-$A55)*(I$3-1)/9) | J55: =I55*(1+$A55+(Inputs!$B$6-$A55)*(J$3-1)/9) | K55: =J55*(1+$A55+(Inputs!$B$6-$A55)*(K$3-1)/9) | L55: =SUMPRODUCT(B55:K55,1/(1+Inputs!$B$4)^$B$3:$K$3)+K55*(1+Inputs!$B$6)/(Inputs!$B$4-Inputs!$B$6)/(1+Inputs!$B$4)^10 | M55: =SUMPRODUCT(B55:K55,1/(1+Inputs!$B$5)^$B$3:$K$3)+K55*(1+Inputs!$B$6)/(Inputs!$B$5-Inputs!$B$6)/(1+Inputs!$B$5)^10
A56: =ROUND(-0.2+52*0.005,4) | B56: =1*(1+$A56+(Inputs!$B$6-$A56)*(B$3-1)/9) | C56: =B56*(1+$A56+(Inputs!$B$6-$A56)*(C$3-1)/9) | D56: =C56*(1+$A56+(Inputs!$B$6-$A56)*(D$3-1)/9) | E56: =D56*(1+$A56+(Inputs!$B$6-$A56)*(E$3-1)/9) | F56: =E56*(1+$A56+(Inputs!$B$6-$A56)*(F$3-1)/9) | G56: =F56*(1+$A56+(Inputs!$B$6-$A56)*(G$3-1)/9) | H56: =G56*(1+$A56+(Inputs!$B$6-$A56)*(H$3-1)/9) | I56: =H56*(1+$A56+(Inputs!$B$6-$A56)*(I$3-1)/9) | J56: =I56*(1+$A56+(Inputs!$B$6-$A56)*(J$3-1)/9) | K56: =J56*(1+$A56+(Inputs!$B$6-$A56)*(K$3-1)/9) | L56: =SUMPRODUCT(B56:K56,1/(1+Inputs!$B$4)^$B$3:$K$3)+K56*(1+Inputs!$B$6)/(Inputs!$B$4-Inputs!$B$6)/(1+Inputs!$B$4)^10 | M56: =SUMPRODUCT(B56:K56,1/(1+Inputs!$B$5)^$B$3:$K$3)+K56*(1+Inputs!$B$6)/(Inputs!$B$5-Inputs!$B$6)/(1+Inputs!$B$5)^10
A57: =ROUND(-0.2+53*0.005,4) | B57: =1*(1+$A57+(Inputs!$B$6-$A57)*(B$3-1)/9) | C57: =B57*(1+$A57+(Inputs!$B$6-$A57)*(C$3-1)/9) | D57: =C57*(1+$A57+(Inputs!$B$6-$A57)*(D$3-1)/9) | E57: =D57*(1+$A57+(Inputs!$B$6-$A57)*(E$3-1)/9) | F57: =E57*(1+$A57+(Inputs!$B$6-$A57)*(F$3-1)/9) | G57: =F57*(1+$A57+(Inputs!$B$6-$A57)*(G$3-1)/9) | H57: =G57*(1+$A57+(Inputs!$B$6-$A57)*(H$3-1)/9) | I57: =H57*(1+$A57+(Inputs!$B$6-$A57)*(I$3-1)/9) | J57: =I57*(1+$A57+(Inputs!$B$6-$A57)*(J$3-1)/9) | K57: =J57*(1+$A57+(Inputs!$B$6-$A57)*(K$3-1)/9) | L57: =SUMPRODUCT(B57:K57,1/(1+Inputs!$B$4)^$B$3:$K$3)+K57*(1+Inputs!$B$6)/(Inputs!$B$4-Inputs!$B$6)/(1+Inputs!$B$4)^10 | M57: =SUMPRODUCT(B57:K57,1/(1+Inputs!$B$5)^$B$3:$K$3)+K57*(1+Inputs!$B$6)/(Inputs!$B$5-Inputs!$B$6)/(1+Inputs!$B$5)^10
A58: =ROUND(-0.2+54*0.005,4) | B58: =1*(1+$A58+(Inputs!$B$6-$A58)*(B$3-1)/9) | C58: =B58*(1+$A58+(Inputs!$B$6-$A58)*(C$3-1)/9) | D58: =C58*(1+$A58+(Inputs!$B$6-$A58)*(D$3-1)/9) | E58: =D58*(1+$A58+(Inputs!$B$6-$A58)*(E$3-1)/9) | F58: =E58*(1+$A58+(Inputs!$B$6-$A58)*(F$3-1)/9) | G58: =F58*(1+$A58+(Inputs!$B$6-$A58)*(G$3-1)/9) | H58: =G58*(1+$A58+(Inputs!$B$6-$A58)*(H$3-1)/9) | I58: =H58*(1+$A58+(Inputs!$B$6-$A58)*(I$3-1)/9) | J58: =I58*(1+$A58+(Inputs!$B$6-$A58)*(J$3-1)/9) | K58: =J58*(1+$A58+(Inputs!$B$6-$A58)*(K$3-1)/9) | L58: =SUMPRODUCT(B58:K58,1/(1+Inputs!$B$4)^$B$3:$K$3)+K58*(1+Inputs!$B$6)/(Inputs!$B$4-Inputs!$B$6)/(1+Inputs!$B$4)^10 | M58: =SUMPRODUCT(B58:K58,1/(1+Inputs!$B$5)^$B$3:$K$3)+K58*(1+Inputs!$B$6)/(Inputs!$B$5-Inputs!$B$6)/(1+Inputs!$B$5)^10
A59: =ROUND(-0.2+55*0.005,4) | B59: =1*(1+$A59+(Inputs!$B$6-$A59)*(B$3-1)/9) | C59: =B59*(1+$A59+(Inputs!$B$6-$A59)*(C$3-1)/9) | D59: =C59*(1+$A59+(Inputs!$B$6-$A59)*(D$3-1)/9) | E59: =D59*(1+$A59+(Inputs!$B$6-$A59)*(E$3-1)/9) | F59: =E59*(1+$A59+(Inputs!$B$6-$A59)*(F$3-1)/9) | G59: =F59*(1+$A59+(Inputs!$B$6-$A59)*(G$3-1)/9) | H59: =G59*(1+$A59+(Inputs!$B$6-$A59)*(H$3-1)/9) | I59: =H59*(1+$A59+(Inputs!$B$6-$A59)*(I$3-1)/9) | J59: =I59*(1+$A59+(Inputs!$B$6-$A59)*(J$3-1)/9) | K59: =J59*(1+$A59+(Inputs!$B$6-$A59)*(K$3-1)/9) | L59: =SUMPRODUCT(B59:K59,1/(1+Inputs!$B$4)^$B$3:$K$3)+K59*(1+Inputs!$B$6)/(Inputs!$B$4-Inputs!$B$6)/(1+Inputs!$B$4)^10 | M59: =SUMPRODUCT(B59:K59,1/(1+Inputs!$B$5)^$B$3:$K$3)+K59*(1+Inputs!$B$6)/(Inputs!$B$5-Inputs!$B$6)/(1+Inputs!$B$5)^10
A60: =ROUND(-0.2+56*0.005,4) | B60: =1*(1+$A60+(Inputs!$B$6-$A60)*(B$3-1)/9) | C60: =B60*(1+$A60+(Inputs!$B$6-$A60)*(C$3-1)/9) | D60: =C60*(1+$A60+(Inputs!$B$6-$A60)*(D$3-1)/9) | E60: =D60*(1+$A60+(Inputs!$B$6-$A60)*(E$3-1)/9) | F60: =E60*(1+$A60+(Inputs!$B$6-$A60)*(F$3-1)/9) | G60: =F60*(1+$A60+(Inputs!$B$6-$A60)*(G$3-1)/9) | H60: =G60*(1+$A60+(Inputs!$B$6-$A60)*(H$3-1)/9) | I60: =H60*(1+$A60+(Inputs!$B$6-$A60)*(I$3-1)/9) | J60: =I60*(1+$A60+(Inputs!$B$6-$A60)*(J$3-1)/9) | K60: =J60*(1+$A60+(Inputs!$B$6-$A60)*(K$3-1)/9) | L60: =SUMPRODUCT(B60:K60,1/(1+Inputs!$B$4)^$B$3:$K$3)+K60*(1+Inputs!$B$6)/(Inputs!$B$4-Inputs!$B$6)/(1+Inputs!$B$4)^10 | M60: =SUMPRODUCT(B60:K60,1/(1+Inputs!$B$5)^$B$3:$K$3)+K60*(1+Inputs!$B$6)/(Inputs!$B$5-Inputs!$B$6)/(1+Inputs!$B$5)^10
A61: =ROUND(-0.2+57*0.005,4) | B61: =1*(1+$A61+(Inputs!$B$6-$A61)*(B$3-1)/9) | C61: =B61*(1+$A61+(Inputs!$B$6-$A61)*(C$3-1)/9) | D61: =C61*(1+$A61+(Inputs!$B$6-$A61)*(D$3-1)/9) | E61: =D61*(1+$A61+(Inputs!$B$6-$A61)*(E$3-1)/9) | F61: =E61*(1+$A61+(Inputs!$B$6-$A61)*(F$3-1)/9) | G61: =F61*(1+$A61+(Inputs!$B$6-$A61)*(G$3-1)/9) | H61: =G61*(1+$A61+(Inputs!$B$6-$A61)*(H$3-1)/9) | I61: =H61*(1+$A61+(Inputs!$B$6-$A61)*(I$3-1)/9) | J61: =I61*(1+$A61+(Inputs!$B$6-$A61)*(J$3-1)/9) | K61: =J61*(1+$A61+(Inputs!$B$6-$A61)*(K$3-1)/9) | L61: =SUMPRODUCT(B61:K61,1/(1+Inputs!$B$4)^$B$3:$K$3)+K61*(1+Inputs!$B$6)/(Inputs!$B$4-Inputs!$B$6)/(1+Inputs!$B$4)^10 | M61: =SUMPRODUCT(B61:K61,1/(1+Inputs!$B$5)^$B$3:$K$3)+K61*(1+Inputs!$B$6)/(Inputs!$B$5-Inputs!$B$6)/(1+Inputs!$B$5)^10
A62: =ROUND(-0.2+58*0.005,4) | B62: =1*(1+$A62+(Inputs!$B$6-$A62)*(B$3-1)/9) | C62: =B62*(1+$A62+(Inputs!$B$6-$A62)*(C$3-1)/9) | D62: =C62*(1+$A62+(Inputs!$B$6-$A62)*(D$3-1)/9) | E62: =D62*(1+$A62+(Inputs!$B$6-$A62)*(E$3-1)/9) | F62: =E62*(1+$A62+(Inputs!$B$6-$A62)*(F$3-1)/9) | G62: =F62*(1+$A62+(Inputs!$B$6-$A62)*(G$3-1)/9) | H62: =G62*(1+$A62+(Inputs!$B$6-$A62)*(H$3-1)/9) | I62: =H62*(1+$A62+(Inputs!$B$6-$A62)*(I$3-1)/9) | J62: =I62*(1+$A62+(Inputs!$B$6-$A62)*(J$3-1)/9) | K62: =J62*(1+$A62+(Inputs!$B$6-$A62)*(K$3-1)/9) | L62: =SUMPRODUCT(B62:K62,1/(1+Inputs!$B$4)^$B$3:$K$3)+K62*(1+Inputs!$B$6)/(Inputs!$B$4-Inputs!$B$6)/(1+Inputs!$B$4)^10 | M62: =SUMPRODUCT(B62:K62,1/(1+Inputs!$B$5)^$B$3:$K$3)+K62*(1+Inputs!$B$6)/(Inputs!$B$5-Inputs!$B$6)/(1+Inputs!$B$5)^10
A63: =ROUND(-0.2+59*0.005,4) | B63: =1*(1+$A63+(Inputs!$B$6-$A63)*(B$3-1)/9) | C63: =B63*(1+$A63+(Inputs!$B$6-$A63)*(C$3-1)/9) | D63: =C63*(1+$A63+(Inputs!$B$6-$A63)*(D$3-1)/9) | E63: =D63*(1+$A63+(Inputs!$B$6-$A63)*(E$3-1)/9) | F63: =E63*(1+$A63+(Inputs!$B$6-$A63)*(F$3-1)/9) | G63: =F63*(1+$A63+(Inputs!$B$6-$A63)*(G$3-1)/9) | H63: =G63*(1+$A63+(Inputs!$B$6-$A63)*(H$3-1)/9) | I63: =H63*(1+$A63+(Inputs!$B$6-$A63)*(I$3-1)/9) | J63: =I63*(1+$A63+(Inputs!$B$6-$A63)*(J$3-1)/9) | K63: =J63*(1+$A63+(Inputs!$B$6-$A63)*(K$3-1)/9) | L63: =SUMPRODUCT(B63:K63,1/(1+Inputs!$B$4)^$B$3:$K$3)+K63*(1+Inputs!$B$6)/(Inputs!$B$4-Inputs!$B$6)/(1+Inputs!$B$4)^10 | M63: =SUMPRODUCT(B63:K63,1/(1+Inputs!$B$5)^$B$3:$K$3)+K63*(1+Inputs!$B$6)/(Inputs!$B$5-Inputs!$B$6)/(1+Inputs!$B$5)^10
A64: =ROUND(-0.2+60*0.005,4) | B64: =1*(1+$A64+(Inputs!$B$6-$A64)*(B$3-1)/9) | C64: =B64*(1+$A64+(Inputs!$B$6-$A64)*(C$3-1)/9) | D64: =C64*(1+$A64+(Inputs!$B$6-$A64)*(D$3-1)/9) | E64: =D64*(1+$A64+(Inputs!$B$6-$A64)*(E$3-1)/9) | F64: =E64*(1+$A64+(Inputs!$B$6-$A64)*(F$3-1)/9) | G64: =F64*(1+$A64+(Inputs!$B$6-$A64)*(G$3-1)/9) | H64: =G64*(1+$A64+(Inputs!$B$6-$A64)*(H$3-1)/9) | I64: =H64*(1+$A64+(Inputs!$B$6-$A64)*(I$3-1)/9) | J64: =I64*(1+$A64+(Inputs!$B$6-$A64)*(J$3-1)/9) | K64: =J64*(1+$A64+(Inputs!$B$6-$A64)*(K$3-1)/9) | L64: =SUMPRODUCT(B64:K64,1/(1+Inputs!$B$4)^$B$3:$K$3)+K64*(1+Inputs!$B$6)/(Inputs!$B$4-Inputs!$B$6)/(1+Inputs!$B$4)^10 | M64: =SUMPRODUCT(B64:K64,1/(1+Inputs!$B$5)^$B$3:$K$3)+K64*(1+Inputs!$B$6)/(Inputs!$B$5-Inputs!$B$6)/(1+Inputs!$B$5)^10
A65: =ROUND(-0.2+61*0.005,4) | B65: =1*(1+$A65+(Inputs!$B$6-$A65)*(B$3-1)/9) | C65: =B65*(1+$A65+(Inputs!$B$6-$A65)*(C$3-1)/9) | D65: =C65*(1+$A65+(Inputs!$B$6-$A65)*(D$3-1)/9) | E65: =D65*(1+$A65+(Inputs!$B$6-$A65)*(E$3-1)/9) | F65: =E65*(1+$A65+(Inputs!$B$6-$A65)*(F$3-1)/9) | G65: =F65*(1+$A65+(Inputs!$B$6-$A65)*(G$3-1)/9) | H65: =G65*(1+$A65+(Inputs!$B$6-$A65)*(H$3-1)/9) | I65: =H65*(1+$A65+(Inputs!$B$6-$A65)*(I$3-1)/9) | J65: =I65*(1+$A65+(Inputs!$B$6-$A65)*(J$3-1)/9) | K65: =J65*(1+$A65+(Inputs!$B$6-$A65)*(K$3-1)/9) | L65: =SUMPRODUCT(B65:K65,1/(1+Inputs!$B$4)^$B$3:$K$3)+K65*(1+Inputs!$B$6)/(Inputs!$B$4-Inputs!$B$6)/(1+Inputs!$B$4)^10 | M65: =SUMPRODUCT(B65:K65,1/(1+Inputs!$B$5)^$B$3:$K$3)+K65*(1+Inputs!$B$6)/(Inputs!$B$5-Inputs!$B$6)/(1+Inputs!$B$5)^10
A66: =ROUND(-0.2+62*0.005,4) | B66: =1*(1+$A66+(Inputs!$B$6-$A66)*(B$3-1)/9) | C66: =B66*(1+$A66+(Inputs!$B$6-$A66)*(C$3-1)/9) | D66: =C66*(1+$A66+(Inputs!$B$6-$A66)*(D$3-1)/9) | E66: =D66*(1+$A66+(Inputs!$B$6-$A66)*(E$3-1)/9) | F66: =E66*(1+$A66+(Inputs!$B$6-$A66)*(F$3-1)/9) | G66: =F66*(1+$A66+(Inputs!$B$6-$A66)*(G$3-1)/9) | H66: =G66*(1+$A66+(Inputs!$B$6-$A66)*(H$3-1)/9) | I66: =H66*(1+$A66+(Inputs!$B$6-$A66)*(I$3-1)/9) | J66: =I66*(1+$A66+(Inputs!$B$6-$A66)*(J$3-1)/9) | K66: =J66*(1+$A66+(Inputs!$B$6-$A66)*(K$3-1)/9) | L66: =SUMPRODUCT(B66:K66,1/(1+Inputs!$B$4)^$B$3:$K$3)+K66*(1+Inputs!$B$6)/(Inputs!$B$4-Inputs!$B$6)/(1+Inputs!$B$4)^10 | M66: =SUMPRODUCT(B66:K66,1/(1+Inputs!$B$5)^$B$3:$K$3)+K66*(1+Inputs!$B$6)/(Inputs!$B$5-Inputs!$B$6)/(1+Inputs!$B$5)^10
A67: =ROUND(-0.2+63*0.005,4) | B67: =1*(1+$A67+(Inputs!$B$6-$A67)*(B$3-1)/9) | C67: =B67*(1+$A67+(Inputs!$B$6-$A67)*(C$3-1)/9) | D67: =C67*(1+$A67+(Inputs!$B$6-$A67)*(D$3-1)/9) | E67: =D67*(1+$A67+(Inputs!$B$6-$A67)*(E$3-1)/9) | F67: =E67*(1+$A67+(Inputs!$B$6-$A67)*(F$3-1)/9) | G67: =F67*(1+$A67+(Inputs!$B$6-$A67)*(G$3-1)/9) | H67: =G67*(1+$A67+(Inputs!$B$6-$A67)*(H$3-1)/9) | I67: =H67*(1+$A67+(Inputs!$B$6-$A67)*(I$3-1)/9) | J67: =I67*(1+$A67+(Inputs!$B$6-$A67)*(J$3-1)/9) | K67: =J67*(1+$A67+(Inputs!$B$6-$A67)*(K$3-1)/9) | L67: =SUMPRODUCT(B67:K67,1/(1+Inputs!$B$4)^$B$3:$K$3)+K67*(1+Inputs!$B$6)/(Inputs!$B$4-Inputs!$B$6)/(1+Inputs!$B$4)^10 | M67: =SUMPRODUCT(B67:K67,1/(1+Inputs!$B$5)^$B$3:$K$3)+K67*(1+Inputs!$B$6)/(Inputs!$B$5-Inputs!$B$6)/(1+Inputs!$B$5)^10
A68: =ROUND(-0.2+64*0.005,4) | B68: =1*(1+$A68+(Inputs!$B$6-$A68)*(B$3-1)/9) | C68: =B68*(1+$A68+(Inputs!$B$6-$A68)*(C$3-1)/9) | D68: =C68*(1+$A68+(Inputs!$B$6-$A68)*(D$3-1)/9) | E68: =D68*(1+$A68+(Inputs!$B$6-$A68)*(E$3-1)/9) | F68: =E68*(1+$A68+(Inputs!$B$6-$A68)*(F$3-1)/9) | G68: =F68*(1+$A68+(Inputs!$B$6-$A68)*(G$3-1)/9) | H68: =G68*(1+$A68+(Inputs!$B$6-$A68)*(H$3-1)/9) | I68: =H68*(1+$A68+(Inputs!$B$6-$A68)*(I$3-1)/9) | J68: =I68*(1+$A68+(Inputs!$B$6-$A68)*(J$3-1)/9) | K68: =J68*(1+$A68+(Inputs!$B$6-$A68)*(K$3-1)/9) | L68: =SUMPRODUCT(B68:K68,1/(1+Inputs!$B$4)^$B$3:$K$3)+K68*(1+Inputs!$B$6)/(Inputs!$B$4-Inputs!$B$6)/(1+Inputs!$B$4)^10 | M68: =SUMPRODUCT(B68:K68,1/(1+Inputs!$B$5)^$B$3:$K$3)+K68*(1+Inputs!$B$6)/(Inputs!$B$5-Inputs!$B$6)/(1+Inputs!$B$5)^10
A69: =ROUND(-0.2+65*0.005,4) | B69: =1*(1+$A69+(Inputs!$B$6-$A69)*(B$3-1)/9) | C69: =B69*(1+$A69+(Inputs!$B$6-$A69)*(C$3-1)/9) | D69: =C69*(1+$A69+(Inputs!$B$6-$A69)*(D$3-1)/9) | E69: =D69*(1+$A69+(Inputs!$B$6-$A69)*(E$3-1)/9) | F69: =E69*(1+$A69+(Inputs!$B$6-$A69)*(F$3-1)/9) | G69: =F69*(1+$A69+(Inputs!$B$6-$A69)*(G$3-1)/9) | H69: =G69*(1+$A69+(Inputs!$B$6-$A69)*(H$3-1)/9) | I69: =H69*(1+$A69+(Inputs!$B$6-$A69)*(I$3-1)/9) | J69: =I69*(1+$A69+(Inputs!$B$6-$A69)*(J$3-1)/9) | K69: =J69*(1+$A69+(Inputs!$B$6-$A69)*(K$3-1)/9) | L69: =SUMPRODUCT(B69:K69,1/(1+Inputs!$B$4)^$B$3:$K$3)+K69*(1+Inputs!$B$6)/(Inputs!$B$4-Inputs!$B$6)/(1+Inputs!$B$4)^10 | M69: =SUMPRODUCT(B69:K69,1/(1+Inputs!$B$5)^$B$3:$K$3)+K69*(1+Inputs!$B$6)/(Inputs!$B$5-Inputs!$B$6)/(1+Inputs!$B$5)^10
A70: =ROUND(-0.2+66*0.005,4) | B70: =1*(1+$A70+(Inputs!$B$6-$A70)*(B$3-1)/9) | C70: =B70*(1+$A70+(Inputs!$B$6-$A70)*(C$3-1)/9) | D70: =C70*(1+$A70+(Inputs!$B$6-$A70)*(D$3-1)/9) | E70: =D70*(1+$A70+(Inputs!$B$6-$A70)*(E$3-1)/9) | F70: =E70*(1+$A70+(Inputs!$B$6-$A70)*(F$3-1)/9) | G70: =F70*(1+$A70+(Inputs!$B$6-$A70)*(G$3-1)/9) | H70: =G70*(1+$A70+(Inputs!$B$6-$A70)*(H$3-1)/9) | I70: =H70*(1+$A70+(Inputs!$B$6-$A70)*(I$3-1)/9) | J70: =I70*(1+$A70+(Inputs!$B$6-$A70)*(J$3-1)/9) | K70: =J70*(1+$A70+(Inputs!$B$6-$A70)*(K$3-1)/9) | L70: =SUMPRODUCT(B70:K70,1/(1+Inputs!$B$4)^$B$3:$K$3)+K70*(1+Inputs!$B$6)/(Inputs!$B$4-Inputs!$B$6)/(1+Inputs!$B$4)^10 | M70: =SUMPRODUCT(B70:K70,1/(1+Inputs!$B$5)^$B$3:$K$3)+K70*(1+Inputs!$B$6)/(Inputs!$B$5-Inputs!$B$6)/(1+Inputs!$B$5)^10
A71: =ROUND(-0.2+67*0.005,4) | B71: =1*(1+$A71+(Inputs!$B$6-$A71)*(B$3-1)/9) | C71: =B71*(1+$A71+(Inputs!$B$6-$A71)*(C$3-1)/9) | D71: =C71*(1+$A71+(Inputs!$B$6-$A71)*(D$3-1)/9) | E71: =D71*(1+$A71+(Inputs!$B$6-$A71)*(E$3-1)/9) | F71: =E71*(1+$A71+(Inputs!$B$6-$A71)*(F$3-1)/9) | G71: =F71*(1+$A71+(Inputs!$B$6-$A71)*(G$3-1)/9) | H71: =G71*(1+$A71+(Inputs!$B$6-$A71)*(H$3-1)/9) | I71: =H71*(1+$A71+(Inputs!$B$6-$A71)*(I$3-1)/9) | J71: =I71*(1+$A71+(Inputs!$B$6-$A71)*(J$3-1)/9) | K71: =J71*(1+$A71+(Inputs!$B$6-$A71)*(K$3-1)/9) | L71: =SUMPRODUCT(B71:K71,1/(1+Inputs!$B$4)^$B$3:$K$3)+K71*(1+Inputs!$B$6)/(Inputs!$B$4-Inputs!$B$6)/(1+Inputs!$B$4)^10 | M71: =SUMPRODUCT(B71:K71,1/(1+Inputs!$B$5)^$B$3:$K$3)+K71*(1+Inputs!$B$6)/(Inputs!$B$5-Inputs!$B$6)/(1+Inputs!$B$5)^10
A72: =ROUND(-0.2+68*0.005,4) | B72: =1*(1+$A72+(Inputs!$B$6-$A72)*(B$3-1)/9) | C72: =B72*(1+$A72+(Inputs!$B$6-$A72)*(C$3-1)/9) | D72: =C72*(1+$A72+(Inputs!$B$6-$A72)*(D$3-1)/9) | E72: =D72*(1+$A72+(Inputs!$B$6-$A72)*(E$3-1)/9) | F72: =E72*(1+$A72+(Inputs!$B$6-$A72)*(F$3-1)/9) | G72: =F72*(1+$A72+(Inputs!$B$6-$A72)*(G$3-1)/9) | H72: =G72*(1+$A72+(Inputs!$B$6-$A72)*(H$3-1)/9) | I72: =H72*(1+$A72+(Inputs!$B$6-$A72)*(I$3-1)/9) | J72: =I72*(1+$A72+(Inputs!$B$6-$A72)*(J$3-1)/9) | K72: =J72*(1+$A72+(Inputs!$B$6-$A72)*(K$3-1)/9) | L72: =SUMPRODUCT(B72:K72,1/(1+Inputs!$B$4)^$B$3:$K$3)+K72*(1+Inputs!$B$6)/(Inputs!$B$4-Inputs!$B$6)/(1+Inputs!$B$4)^10 | M72: =SUMPRODUCT(B72:K72,1/(1+Inputs!$B$5)^$B$3:$K$3)+K72*(1+Inputs!$B$6)/(Inputs!$B$5-Inputs!$B$6)/(1+Inputs!$B$5)^10
A73: =ROUND(-0.2+69*0.005,4) | B73: =1*(1+$A73+(Inputs!$B$6-$A73)*(B$3-1)/9) | C73: =B73*(1+$A73+(Inputs!$B$6-$A73)*(C$3-1)/9) | D73: =C73*(1+$A73+(Inputs!$B$6-$A73)*(D$3-1)/9) | E73: =D73*(1+$A73+(Inputs!$B$6-$A73)*(E$3-1)/9) | F73: =E73*(1+$A73+(Inputs!$B$6-$A73)*(F$3-1)/9) | G73: =F73*(1+$A73+(Inputs!$B$6-$A73)*(G$3-1)/9) | H73: =G73*(1+$A73+(Inputs!$B$6-$A73)*(H$3-1)/9) | I73: =H73*(1+$A73+(Inputs!$B$6-$A73)*(I$3-1)/9) | J73: =I73*(1+$A73+(Inputs!$B$6-$A73)*(J$3-1)/9) | K73: =J73*(1+$A73+(Inputs!$B$6-$A73)*(K$3-1)/9) | L73: =SUMPRODUCT(B73:K73,1/(1+Inputs!$B$4)^$B$3:$K$3)+K73*(1+Inputs!$B$6)/(Inputs!$B$4-Inputs!$B$6)/(1+Inputs!$B$4)^10 | M73: =SUMPRODUCT(B73:K73,1/(1+Inputs!$B$5)^$B$3:$K$3)+K73*(1+Inputs!$B$6)/(Inputs!$B$5-Inputs!$B$6)/(1+Inputs!$B$5)^10
A74: =ROUND(-0.2+70*0.005,4) | B74: =1*(1+$A74+(Inputs!$B$6-$A74)*(B$3-1)/9) | C74: =B74*(1+$A74+(Inputs!$B$6-$A74)*(C$3-1)/9) | D74: =C74*(1+$A74+(Inputs!$B$6-$A74)*(D$3-1)/9) | E74: =D74*(1+$A74+(Inputs!$B$6-$A74)*(E$3-1)/9) | F74: =E74*(1+$A74+(Inputs!$B$6-$A74)*(F$3-1)/9) | G74: =F74*(1+$A74+(Inputs!$B$6-$A74)*(G$3-1)/9) | H74: =G74*(1+$A74+(Inputs!$B$6-$A74)*(H$3-1)/9) | I74: =H74*(1+$A74+(Inputs!$B$6-$A74)*(I$3-1)/9) | J74: =I74*(1+$A74+(Inputs!$B$6-$A74)*(J$3-1)/9) | K74: =J74*(1+$A74+(Inputs!$B$6-$A74)*(K$3-1)/9) | L74: =SUMPRODUCT(B74:K74,1/(1+Inputs!$B$4)^$B$3:$K$3)+K74*(1+Inputs!$B$6)/(Inputs!$B$4-Inputs!$B$6)/(1+Inputs!$B$4)^10 | M74: =SUMPRODUCT(B74:K74,1/(1+Inputs!$B$5)^$B$3:$K$3)+K74*(1+Inputs!$B$6)/(Inputs!$B$5-Inputs!$B$6)/(1+Inputs!$B$5)^10
A75: =ROUND(-0.2+71*0.005,4) | B75: =1*(1+$A75+(Inputs!$B$6-$A75)*(B$3-1)/9) | C75: =B75*(1+$A75+(Inputs!$B$6-$A75)*(C$3-1)/9) | D75: =C75*(1+$A75+(Inputs!$B$6-$A75)*(D$3-1)/9) | E75: =D75*(1+$A75+(Inputs!$B$6-$A75)*(E$3-1)/9) | F75: =E75*(1+$A75+(Inputs!$B$6-$A75)*(F$3-1)/9) | G75: =F75*(1+$A75+(Inputs!$B$6-$A75)*(G$3-1)/9) | H75: =G75*(1+$A75+(Inputs!$B$6-$A75)*(H$3-1)/9) | I75: =H75*(1+$A75+(Inputs!$B$6-$A75)*(I$3-1)/9) | J75: =I75*(1+$A75+(Inputs!$B$6-$A75)*(J$3-1)/9) | K75: =J75*(1+$A75+(Inputs!$B$6-$A75)*(K$3-1)/9) | L75: =SUMPRODUCT(B75:K75,1/(1+Inputs!$B$4)^$B$3:$K$3)+K75*(1+Inputs!$B$6)/(Inputs!$B$4-Inputs!$B$6)/(1+Inputs!$B$4)^10 | M75: =SUMPRODUCT(B75:K75,1/(1+Inputs!$B$5)^$B$3:$K$3)+K75*(1+Inputs!$B$6)/(Inputs!$B$5-Inputs!$B$6)/(1+Inputs!$B$5)^10
A76: =ROUND(-0.2+72*0.005,4) | B76: =1*(1+$A76+(Inputs!$B$6-$A76)*(B$3-1)/9) | C76: =B76*(1+$A76+(Inputs!$B$6-$A76)*(C$3-1)/9) | D76: =C76*(1+$A76+(Inputs!$B$6-$A76)*(D$3-1)/9) | E76: =D76*(1+$A76+(Inputs!$B$6-$A76)*(E$3-1)/9) | F76: =E76*(1+$A76+(Inputs!$B$6-$A76)*(F$3-1)/9) | G76: =F76*(1+$A76+(Inputs!$B$6-$A76)*(G$3-1)/9) | H76: =G76*(1+$A76+(Inputs!$B$6-$A76)*(H$3-1)/9) | I76: =H76*(1+$A76+(Inputs!$B$6-$A76)*(I$3-1)/9) | J76: =I76*(1+$A76+(Inputs!$B$6-$A76)*(J$3-1)/9) | K76: =J76*(1+$A76+(Inputs!$B$6-$A76)*(K$3-1)/9) | L76: =SUMPRODUCT(B76:K76,1/(1+Inputs!$B$4)^$B$3:$K$3)+K76*(1+Inputs!$B$6)/(Inputs!$B$4-Inputs!$B$6)/(1+Inputs!$B$4)^10 | M76: =SUMPRODUCT(B76:K76,1/(1+Inputs!$B$5)^$B$3:$K$3)+K76*(1+Inputs!$B$6)/(Inputs!$B$5-Inputs!$B$6)/(1+Inputs!$B$5)^10
A77: =ROUND(-0.2+73*0.005,4) | B77: =1*(1+$A77+(Inputs!$B$6-$A77)*(B$3-1)/9) | C77: =B77*(1+$A77+(Inputs!$B$6-$A77)*(C$3-1)/9) | D77: =C77*(1+$A77+(Inputs!$B$6-$A77)*(D$3-1)/9) | E77: =D77*(1+$A77+(Inputs!$B$6-$A77)*(E$3-1)/9) | F77: =E77*(1+$A77+(Inputs!$B$6-$A77)*(F$3-1)/9) | G77: =F77*(1+$A77+(Inputs!$B$6-$A77)*(G$3-1)/9) | H77: =G77*(1+$A77+(Inputs!$B$6-$A77)*(H$3-1)/9) | I77: =H77*(1+$A77+(Inputs!$B$6-$A77)*(I$3-1)/9) | J77: =I77*(1+$A77+(Inputs!$B$6-$A77)*(J$3-1)/9) | K77: =J77*(1+$A77+(Inputs!$B$6-$A77)*(K$3-1)/9) | L77: =SUMPRODUCT(B77:K77,1/(1+Inputs!$B$4)^$B$3:$K$3)+K77*(1+Inputs!$B$6)/(Inputs!$B$4-Inputs!$B$6)/(1+Inputs!$B$4)^10 | M77: =SUMPRODUCT(B77:K77,1/(1+Inputs!$B$5)^$B$3:$K$3)+K77*(1+Inputs!$B$6)/(Inputs!$B$5-Inputs!$B$6)/(1+Inputs!$B$5)^10
A78: =ROUND(-0.2+74*0.005,4) | B78: =1*(1+$A78+(Inputs!$B$6-$A78)*(B$3-1)/9) | C78: =B78*(1+$A78+(Inputs!$B$6-$A78)*(C$3-1)/9) | D78: =C78*(1+$A78+(Inputs!$B$6-$A78)*(D$3-1)/9) | E78: =D78*(1+$A78+(Inputs!$B$6-$A78)*(E$3-1)/9) | F78: =E78*(1+$A78+(Inputs!$B$6-$A78)*(F$3-1)/9) | G78: =F78*(1+$A78+(Inputs!$B$6-$A78)*(G$3-1)/9) | H78: =G78*(1+$A78+(Inputs!$B$6-$A78)*(H$3-1)/9) | I78: =H78*(1+$A78+(Inputs!$B$6-$A78)*(I$3-1)/9) | J78: =I78*(1+$A78+(Inputs!$B$6-$A78)*(J$3-1)/9) | K78: =J78*(1+$A78+(Inputs!$B$6-$A78)*(K$3-1)/9) | L78: =SUMPRODUCT(B78:K78,1/(1+Inputs!$B$4)^$B$3:$K$3)+K78*(1+Inputs!$B$6)/(Inputs!$B$4-Inputs!$B$6)/(1+Inputs!$B$4)^10 | M78: =SUMPRODUCT(B78:K78,1/(1+Inputs!$B$5)^$B$3:$K$3)+K78*(1+Inputs!$B$6)/(Inputs!$B$5-Inputs!$B$6)/(1+Inputs!$B$5)^10
A79: =ROUND(-0.2+75*0.005,4) | B79: =1*(1+$A79+(Inputs!$B$6-$A79)*(B$3-1)/9) | C79: =B79*(1+$A79+(Inputs!$B$6-$A79)*(C$3-1)/9) | D79: =C79*(1+$A79+(Inputs!$B$6-$A79)*(D$3-1)/9) | E79: =D79*(1+$A79+(Inputs!$B$6-$A79)*(E$3-1)/9) | F79: =E79*(1+$A79+(Inputs!$B$6-$A79)*(F$3-1)/9) | G79: =F79*(1+$A79+(Inputs!$B$6-$A79)*(G$3-1)/9) | H79: =G79*(1+$A79+(Inputs!$B$6-$A79)*(H$3-1)/9) | I79: =H79*(1+$A79+(Inputs!$B$6-$A79)*(I$3-1)/9) | J79: =I79*(1+$A79+(Inputs!$B$6-$A79)*(J$3-1)/9) | K79: =J79*(1+$A79+(Inputs!$B$6-$A79)*(K$3-1)/9) | L79: =SUMPRODUCT(B79:K79,1/(1+Inputs!$B$4)^$B$3:$K$3)+K79*(1+Inputs!$B$6)/(Inputs!$B$4-Inputs!$B$6)/(1+Inputs!$B$4)^10 | M79: =SUMPRODUCT(B79:K79,1/(1+Inputs!$B$5)^$B$3:$K$3)+K79*(1+Inputs!$B$6)/(Inputs!$B$5-Inputs!$B$6)/(1+Inputs!$B$5)^10
A80: =ROUND(-0.2+76*0.005,4) | B80: =1*(1+$A80+(Inputs!$B$6-$A80)*(B$3-1)/9) | C80: =B80*(1+$A80+(Inputs!$B$6-$A80)*(C$3-1)/9) | D80: =C80*(1+$A80+(Inputs!$B$6-$A80)*(D$3-1)/9) | E80: =D80*(1+$A80+(Inputs!$B$6-$A80)*(E$3-1)/9) | F80: =E80*(1+$A80+(Inputs!$B$6-$A80)*(F$3-1)/9) | G80: =F80*(1+$A80+(Inputs!$B$6-$A80)*(G$3-1)/9) | H80: =G80*(1+$A80+(Inputs!$B$6-$A80)*(H$3-1)/9) | I80: =H80*(1+$A80+(Inputs!$B$6-$A80)*(I$3-1)/9) | J80: =I80*(1+$A80+(Inputs!$B$6-$A80)*(J$3-1)/9) | K80: =J80*(1+$A80+(Inputs!$B$6-$A80)*(K$3-1)/9) | L80: =SUMPRODUCT(B80:K80,1/(1+Inputs!$B$4)^$B$3:$K$3)+K80*(1+Inputs!$B$6)/(Inputs!$B$4-Inputs!$B$6)/(1+Inputs!$B$4)^10 | M80: =SUMPRODUCT(B80:K80,1/(1+Inputs!$B$5)^$B$3:$K$3)+K80*(1+Inputs!$B$6)/(Inputs!$B$5-Inputs!$B$6)/(1+Inputs!$B$5)^10
A81: =ROUND(-0.2+77*0.005,4) | B81: =1*(1+$A81+(Inputs!$B$6-$A81)*(B$3-1)/9) | C81: =B81*(1+$A81+(Inputs!$B$6-$A81)*(C$3-1)/9) | D81: =C81*(1+$A81+(Inputs!$B$6-$A81)*(D$3-1)/9) | E81: =D81*(1+$A81+(Inputs!$B$6-$A81)*(E$3-1)/9) | F81: =E81*(1+$A81+(Inputs!$B$6-$A81)*(F$3-1)/9) | G81: =F81*(1+$A81+(Inputs!$B$6-$A81)*(G$3-1)/9) | H81: =G81*(1+$A81+(Inputs!$B$6-$A81)*(H$3-1)/9) | I81: =H81*(1+$A81+(Inputs!$B$6-$A81)*(I$3-1)/9) | J81: =I81*(1+$A81+(Inputs!$B$6-$A81)*(J$3-1)/9) | K81: =J81*(1+$A81+(Inputs!$B$6-$A81)*(K$3-1)/9) | L81: =SUMPRODUCT(B81:K81,1/(1+Inputs!$B$4)^$B$3:$K$3)+K81*(1+Inputs!$B$6)/(Inputs!$B$4-Inputs!$B$6)/(1+Inputs!$B$4)^10 | M81: =SUMPRODUCT(B81:K81,1/(1+Inputs!$B$5)^$B$3:$K$3)+K81*(1+Inputs!$B$6)/(Inputs!$B$5-Inputs!$B$6)/(1+Inputs!$B$5)^10
A82: =ROUND(-0.2+78*0.005,4) | B82: =1*(1+$A82+(Inputs!$B$6-$A82)*(B$3-1)/9) | C82: =B82*(1+$A82+(Inputs!$B$6-$A82)*(C$3-1)/9) | D82: =C82*(1+$A82+(Inputs!$B$6-$A82)*(D$3-1)/9) | E82: =D82*(1+$A82+(Inputs!$B$6-$A82)*(E$3-1)/9) | F82: =E82*(1+$A82+(Inputs!$B$6-$A82)*(F$3-1)/9) | G82: =F82*(1+$A82+(Inputs!$B$6-$A82)*(G$3-1)/9) | H82: =G82*(1+$A82+(Inputs!$B$6-$A82)*(H$3-1)/9) | I82: =H82*(1+$A82+(Inputs!$B$6-$A82)*(I$3-1)/9) | J82: =I82*(1+$A82+(Inputs!$B$6-$A82)*(J$3-1)/9) | K82: =J82*(1+$A82+(Inputs!$B$6-$A82)*(K$3-1)/9) | L82: =SUMPRODUCT(B82:K82,1/(1+Inputs!$B$4)^$B$3:$K$3)+K82*(1+Inputs!$B$6)/(Inputs!$B$4-Inputs!$B$6)/(1+Inputs!$B$4)^10 | M82: =SUMPRODUCT(B82:K82,1/(1+Inputs!$B$5)^$B$3:$K$3)+K82*(1+Inputs!$B$6)/(Inputs!$B$5-Inputs!$B$6)/(1+Inputs!$B$5)^10
A83: =ROUND(-0.2+79*0.005,4) | B83: =1*(1+$A83+(Inputs!$B$6-$A83)*(B$3-1)/9) | C83: =B83*(1+$A83+(Inputs!$B$6-$A83)*(C$3-1)/9) | D83: =C83*(1+$A83+(Inputs!$B$6-$A83)*(D$3-1)/9) | E83: =D83*(1+$A83+(Inputs!$B$6-$A83)*(E$3-1)/9) | F83: =E83*(1+$A83+(Inputs!$B$6-$A83)*(F$3-1)/9) | G83: =F83*(1+$A83+(Inputs!$B$6-$A83)*(G$3-1)/9) | H83: =G83*(1+$A83+(Inputs!$B$6-$A83)*(H$3-1)/9) | I83: =H83*(1+$A83+(Inputs!$B$6-$A83)*(I$3-1)/9) | J83: =I83*(1+$A83+(Inputs!$B$6-$A83)*(J$3-1)/9) | K83: =J83*(1+$A83+(Inputs!$B$6-$A83)*(K$3-1)/9) | L83: =SUMPRODUCT(B83:K83,1/(1+Inputs!$B$4)^$B$3:$K$3)+K83*(1+Inputs!$B$6)/(Inputs!$B$4-Inputs!$B$6)/(1+Inputs!$B$4)^10 | M83: =SUMPRODUCT(B83:K83,1/(1+Inputs!$B$5)^$B$3:$K$3)+K83*(1+Inputs!$B$6)/(Inputs!$B$5-Inputs!$B$6)/(1+Inputs!$B$5)^10
A84: =ROUND(-0.2+80*0.005,4) | B84: =1*(1+$A84+(Inputs!$B$6-$A84)*(B$3-1)/9) | C84: =B84*(1+$A84+(Inputs!$B$6-$A84)*(C$3-1)/9) | D84: =C84*(1+$A84+(Inputs!$B$6-$A84)*(D$3-1)/9) | E84: =D84*(1+$A84+(Inputs!$B$6-$A84)*(E$3-1)/9) | F84: =E84*(1+$A84+(Inputs!$B$6-$A84)*(F$3-1)/9) | G84: =F84*(1+$A84+(Inputs!$B$6-$A84)*(G$3-1)/9) | H84: =G84*(1+$A84+(Inputs!$B$6-$A84)*(H$3-1)/9) | I84: =H84*(1+$A84+(Inputs!$B$6-$A84)*(I$3-1)/9) | J84: =I84*(1+$A84+(Inputs!$B$6-$A84)*(J$3-1)/9) | K84: =J84*(1+$A84+(Inputs!$B$6-$A84)*(K$3-1)/9) | L84: =SUMPRODUCT(B84:K84,1/(1+Inputs!$B$4)^$B$3:$K$3)+K84*(1+Inputs!$B$6)/(Inputs!$B$4-Inputs!$B$6)/(1+Inputs!$B$4)^10 | M84: =SUMPRODUCT(B84:K84,1/(1+Inputs!$B$5)^$B$3:$K$3)+K84*(1+Inputs!$B$6)/(Inputs!$B$5-Inputs!$B$6)/(1+Inputs!$B$5)^10
A85: =ROUND(-0.2+81*0.005,4) | B85: =1*(1+$A85+(Inputs!$B$6-$A85)*(B$3-1)/9) | C85: =B85*(1+$A85+(Inputs!$B$6-$A85)*(C$3-1)/9) | D85: =C85*(1+$A85+(Inputs!$B$6-$A85)*(D$3-1)/9) | E85: =D85*(1+$A85+(Inputs!$B$6-$A85)*(E$3-1)/9) | F85: =E85*(1+$A85+(Inputs!$B$6-$A85)*(F$3-1)/9) | G85: =F85*(1+$A85+(Inputs!$B$6-$A85)*(G$3-1)/9) | H85: =G85*(1+$A85+(Inputs!$B$6-$A85)*(H$3-1)/9) | I85: =H85*(1+$A85+(Inputs!$B$6-$A85)*(I$3-1)/9) | J85: =I85*(1+$A85+(Inputs!$B$6-$A85)*(J$3-1)/9) | K85: =J85*(1+$A85+(Inputs!$B$6-$A85)*(K$3-1)/9) | L85: =SUMPRODUCT(B85:K85,1/(1+Inputs!$B$4)^$B$3:$K$3)+K85*(1+Inputs!$B$6)/(Inputs!$B$4-Inputs!$B$6)/(1+Inputs!$B$4)^10 | M85: =SUMPRODUCT(B85:K85,1/(1+Inputs!$B$5)^$B$3:$K$3)+K85*(1+Inputs!$B$6)/(Inputs!$B$5-Inputs!$B$6)/(1+Inputs!$B$5)^10
A86: =ROUND(-0.2+82*0.005,4) | B86: =1*(1+$A86+(Inputs!$B$6-$A86)*(B$3-1)/9) | C86: =B86*(1+$A86+(Inputs!$B$6-$A86)*(C$3-1)/9) | D86: =C86*(1+$A86+(Inputs!$B$6-$A86)*(D$3-1)/9) | E86: =D86*(1+$A86+(Inputs!$B$6-$A86)*(E$3-1)/9) | F86: =E86*(1+$A86+(Inputs!$B$6-$A86)*(F$3-1)/9) | G86: =F86*(1+$A86+(Inputs!$B$6-$A86)*(G$3-1)/9) | H86: =G86*(1+$A86+(Inputs!$B$6-$A86)*(H$3-1)/9) | I86: =H86*(1+$A86+(Inputs!$B$6-$A86)*(I$3-1)/9) | J86: =I86*(1+$A86+(Inputs!$B$6-$A86)*(J$3-1)/9) | K86: =J86*(1+$A86+(Inputs!$B$6-$A86)*(K$3-1)/9) | L86: =SUMPRODUCT(B86:K86,1/(1+Inputs!$B$4)^$B$3:$K$3)+K86*(1+Inputs!$B$6)/(Inputs!$B$4-Inputs!$B$6)/(1+Inputs!$B$4)^10 | M86: =SUMPRODUCT(B86:K86,1/(1+Inputs!$B$5)^$B$3:$K$3)+K86*(1+Inputs!$B$6)/(Inputs!$B$5-Inputs!$B$6)/(1+Inputs!$B$5)^10
A87: =ROUND(-0.2+83*0.005,4) | B87: =1*(1+$A87+(Inputs!$B$6-$A87)*(B$3-1)/9) | C87: =B87*(1+$A87+(Inputs!$B$6-$A87)*(C$3-1)/9) | D87: =C87*(1+$A87+(Inputs!$B$6-$A87)*(D$3-1)/9) | E87: =D87*(1+$A87+(Inputs!$B$6-$A87)*(E$3-1)/9) | F87: =E87*(1+$A87+(Inputs!$B$6-$A87)*(F$3-1)/9) | G87: =F87*(1+$A87+(Inputs!$B$6-$A87)*(G$3-1)/9) | H87: =G87*(1+$A87+(Inputs!$B$6-$A87)*(H$3-1)/9) | I87: =H87*(1+$A87+(Inputs!$B$6-$A87)*(I$3-1)/9) | J87: =I87*(1+$A87+(Inputs!$B$6-$A87)*(J$3-1)/9) | K87: =J87*(1+$A87+(Inputs!$B$6-$A87)*(K$3-1)/9) | L87: =SUMPRODUCT(B87:K87,1/(1+Inputs!$B$4)^$B$3:$K$3)+K87*(1+Inputs!$B$6)/(Inputs!$B$4-Inputs!$B$6)/(1+Inputs!$B$4)^10 | M87: =SUMPRODUCT(B87:K87,1/(1+Inputs!$B$5)^$B$3:$K$3)+K87*(1+Inputs!$B$6)/(Inputs!$B$5-Inputs!$B$6)/(1+Inputs!$B$5)^10
A88: =ROUND(-0.2+84*0.005,4) | B88: =1*(1+$A88+(Inputs!$B$6-$A88)*(B$3-1)/9) | C88: =B88*(1+$A88+(Inputs!$B$6-$A88)*(C$3-1)/9) | D88: =C88*(1+$A88+(Inputs!$B$6-$A88)*(D$3-1)/9) | E88: =D88*(1+$A88+(Inputs!$B$6-$A88)*(E$3-1)/9) | F88: =E88*(1+$A88+(Inputs!$B$6-$A88)*(F$3-1)/9) | G88: =F88*(1+$A88+(Inputs!$B$6-$A88)*(G$3-1)/9) | H88: =G88*(1+$A88+(Inputs!$B$6-$A88)*(H$3-1)/9) | I88: =H88*(1+$A88+(Inputs!$B$6-$A88)*(I$3-1)/9) | J88: =I88*(1+$A88+(Inputs!$B$6-$A88)*(J$3-1)/9) | K88: =J88*(1+$A88+(Inputs!$B$6-$A88)*(K$3-1)/9) | L88: =SUMPRODUCT(B88:K88,1/(1+Inputs!$B$4)^$B$3:$K$3)+K88*(1+Inputs!$B$6)/(Inputs!$B$4-Inputs!$B$6)/(1+Inputs!$B$4)^10 | M88: =SUMPRODUCT(B88:K88,1/(1+Inputs!$B$5)^$B$3:$K$3)+K88*(1+Inputs!$B$6)/(Inputs!$B$5-Inputs!$B$6)/(1+Inputs!$B$5)^10
A89: =ROUND(-0.2+85*0.005,4) | B89: =1*(1+$A89+(Inputs!$B$6-$A89)*(B$3-1)/9) | C89: =B89*(1+$A89+(Inputs!$B$6-$A89)*(C$3-1)/9) | D89: =C89*(1+$A89+(Inputs!$B$6-$A89)*(D$3-1)/9) | E89: =D89*(1+$A89+(Inputs!$B$6-$A89)*(E$3-1)/9) | F89: =E89*(1+$A89+(Inputs!$B$6-$A89)*(F$3-1)/9) | G89: =F89*(1+$A89+(Inputs!$B$6-$A89)*(G$3-1)/9) | H89: =G89*(1+$A89+(Inputs!$B$6-$A89)*(H$3-1)/9) | I89: =H89*(1+$A89+(Inputs!$B$6-$A89)*(I$3-1)/9) | J89: =I89*(1+$A89+(Inputs!$B$6-$A89)*(J$3-1)/9) | K89: =J89*(1+$A89+(Inputs!$B$6-$A89)*(K$3-1)/9) | L89: =SUMPRODUCT(B89:K89,1/(1+Inputs!$B$4)^$B$3:$K$3)+K89*(1+Inputs!$B$6)/(Inputs!$B$4-Inputs!$B$6)/(1+Inputs!$B$4)^10 | M89: =SUMPRODUCT(B89:K89,1/(1+Inputs!$B$5)^$B$3:$K$3)+K89*(1+Inputs!$B$6)/(Inputs!$B$5-Inputs!$B$6)/(1+Inputs!$B$5)^10
A90: =ROUND(-0.2+86*0.005,4) | B90: =1*(1+$A90+(Inputs!$B$6-$A90)*(B$3-1)/9) | C90: =B90*(1+$A90+(Inputs!$B$6-$A90)*(C$3-1)/9) | D90: =C90*(1+$A90+(Inputs!$B$6-$A90)*(D$3-1)/9) | E90: =D90*(1+$A90+(Inputs!$B$6-$A90)*(E$3-1)/9) | F90: =E90*(1+$A90+(Inputs!$B$6-$A90)*(F$3-1)/9) | G90: =F90*(1+$A90+(Inputs!$B$6-$A90)*(G$3-1)/9) | H90: =G90*(1+$A90+(Inputs!$B$6-$A90)*(H$3-1)/9) | I90: =H90*(1+$A90+(Inputs!$B$6-$A90)*(I$3-1)/9) | J90: =I90*(1+$A90+(Inputs!$B$6-$A90)*(J$3-1)/9) | K90: =J90*(1+$A90+(Inputs!$B$6-$A90)*(K$3-1)/9) | L90: =SUMPRODUCT(B90:K90,1/(1+Inputs!$B$4)^$B$3:$K$3)+K90*(1+Inputs!$B$6)/(Inputs!$B$4-Inputs!$B$6)/(1+Inputs!$B$4)^10 | M90: =SUMPRODUCT(B90:K90,1/(1+Inputs!$B$5)^$B$3:$K$3)+K90*(1+Inputs!$B$6)/(Inputs!$B$5-Inputs!$B$6)/(1+Inputs!$B$5)^10
A91: =ROUND(-0.2+87*0.005,4) | B91: =1*(1+$A91+(Inputs!$B$6-$A91)*(B$3-1)/9) | C91: =B91*(1+$A91+(Inputs!$B$6-$A91)*(C$3-1)/9) | D91: =C91*(1+$A91+(Inputs!$B$6-$A91)*(D$3-1)/9) | E91: =D91*(1+$A91+(Inputs!$B$6-$A91)*(E$3-1)/9) | F91: =E91*(1+$A91+(Inputs!$B$6-$A91)*(F$3-1)/9) | G91: =F91*(1+$A91+(Inputs!$B$6-$A91)*(G$3-1)/9) | H91: =G91*(1+$A91+(Inputs!$B$6-$A91)*(H$3-1)/9) | I91: =H91*(1+$A91+(Inputs!$B$6-$A91)*(I$3-1)/9) | J91: =I91*(1+$A91+(Inputs!$B$6-$A91)*(J$3-1)/9) | K91: =J91*(1+$A91+(Inputs!$B$6-$A91)*(K$3-1)/9) | L91: =SUMPRODUCT(B91:K91,1/(1+Inputs!$B$4)^$B$3:$K$3)+K91*(1+Inputs!$B$6)/(Inputs!$B$4-Inputs!$B$6)/(1+Inputs!$B$4)^10 | M91: =SUMPRODUCT(B91:K91,1/(1+Inputs!$B$5)^$B$3:$K$3)+K91*(1+Inputs!$B$6)/(Inputs!$B$5-Inputs!$B$6)/(1+Inputs!$B$5)^10
A92: =ROUND(-0.2+88*0.005,4) | B92: =1*(1+$A92+(Inputs!$B$6-$A92)*(B$3-1)/9) | C92: =B92*(1+$A92+(Inputs!$B$6-$A92)*(C$3-1)/9) | D92: =C92*(1+$A92+(Inputs!$B$6-$A92)*(D$3-1)/9) | E92: =D92*(1+$A92+(Inputs!$B$6-$A92)*(E$3-1)/9) | F92: =E92*(1+$A92+(Inputs!$B$6-$A92)*(F$3-1)/9) | G92: =F92*(1+$A92+(Inputs!$B$6-$A92)*(G$3-1)/9) | H92: =G92*(1+$A92+(Inputs!$B$6-$A92)*(H$3-1)/9) | I92: =H92*(1+$A92+(Inputs!$B$6-$A92)*(I$3-1)/9) | J92: =I92*(1+$A92+(Inputs!$B$6-$A92)*(J$3-1)/9) | K92: =J92*(1+$A92+(Inputs!$B$6-$A92)*(K$3-1)/9) | L92: =SUMPRODUCT(B92:K92,1/(1+Inputs!$B$4)^$B$3:$K$3)+K92*(1+Inputs!$B$6)/(Inputs!$B$4-Inputs!$B$6)/(1+Inputs!$B$4)^10 | M92: =SUMPRODUCT(B92:K92,1/(1+Inputs!$B$5)^$B$3:$K$3)+K92*(1+Inputs!$B$6)/(Inputs!$B$5-Inputs!$B$6)/(1+Inputs!$B$5)^10
A93: =ROUND(-0.2+89*0.005,4) | B93: =1*(1+$A93+(Inputs!$B$6-$A93)*(B$3-1)/9) | C93: =B93*(1+$A93+(Inputs!$B$6-$A93)*(C$3-1)/9) | D93: =C93*(1+$A93+(Inputs!$B$6-$A93)*(D$3-1)/9) | E93: =D93*(1+$A93+(Inputs!$B$6-$A93)*(E$3-1)/9) | F93: =E93*(1+$A93+(Inputs!$B$6-$A93)*(F$3-1)/9) | G93: =F93*(1+$A93+(Inputs!$B$6-$A93)*(G$3-1)/9) | H93: =G93*(1+$A93+(Inputs!$B$6-$A93)*(H$3-1)/9) | I93: =H93*(1+$A93+(Inputs!$B$6-$A93)*(I$3-1)/9) | J93: =I93*(1+$A93+(Inputs!$B$6-$A93)*(J$3-1)/9) | K93: =J93*(1+$A93+(Inputs!$B$6-$A93)*(K$3-1)/9) | L93: =SUMPRODUCT(B93:K93,1/(1+Inputs!$B$4)^$B$3:$K$3)+K93*(1+Inputs!$B$6)/(Inputs!$B$4-Inputs!$B$6)/(1+Inputs!$B$4)^10 | M93: =SUMPRODUCT(B93:K93,1/(1+Inputs!$B$5)^$B$3:$K$3)+K93*(1+Inputs!$B$6)/(Inputs!$B$5-Inputs!$B$6)/(1+Inputs!$B$5)^10
A94: =ROUND(-0.2+90*0.005,4) | B94: =1*(1+$A94+(Inputs!$B$6-$A94)*(B$3-1)/9) | C94: =B94*(1+$A94+(Inputs!$B$6-$A94)*(C$3-1)/9) | D94: =C94*(1+$A94+(Inputs!$B$6-$A94)*(D$3-1)/9) | E94: =D94*(1+$A94+(Inputs!$B$6-$A94)*(E$3-1)/9) | F94: =E94*(1+$A94+(Inputs!$B$6-$A94)*(F$3-1)/9) | G94: =F94*(1+$A94+(Inputs!$B$6-$A94)*(G$3-1)/9) | H94: =G94*(1+$A94+(Inputs!$B$6-$A94)*(H$3-1)/9) | I94: =H94*(1+$A94+(Inputs!$B$6-$A94)*(I$3-1)/9) | J94: =I94*(1+$A94+(Inputs!$B$6-$A94)*(J$3-1)/9) | K94: =J94*(1+$A94+(Inputs!$B$6-$A94)*(K$3-1)/9) | L94: =SUMPRODUCT(B94:K94,1/(1+Inputs!$B$4)^$B$3:$K$3)+K94*(1+Inputs!$B$6)/(Inputs!$B$4-Inputs!$B$6)/(1+Inputs!$B$4)^10 | M94: =SUMPRODUCT(B94:K94,1/(1+Inputs!$B$5)^$B$3:$K$3)+K94*(1+Inputs!$B$6)/(Inputs!$B$5-Inputs!$B$6)/(1+Inputs!$B$5)^10
A95: =ROUND(-0.2+91*0.005,4) | B95: =1*(1+$A95+(Inputs!$B$6-$A95)*(B$3-1)/9) | C95: =B95*(1+$A95+(Inputs!$B$6-$A95)*(C$3-1)/9) | D95: =C95*(1+$A95+(Inputs!$B$6-$A95)*(D$3-1)/9) | E95: =D95*(1+$A95+(Inputs!$B$6-$A95)*(E$3-1)/9) | F95: =E95*(1+$A95+(Inputs!$B$6-$A95)*(F$3-1)/9) | G95: =F95*(1+$A95+(Inputs!$B$6-$A95)*(G$3-1)/9) | H95: =G95*(1+$A95+(Inputs!$B$6-$A95)*(H$3-1)/9) | I95: =H95*(1+$A95+(Inputs!$B$6-$A95)*(I$3-1)/9) | J95: =I95*(1+$A95+(Inputs!$B$6-$A95)*(J$3-1)/9) | K95: =J95*(1+$A95+(Inputs!$B$6-$A95)*(K$3-1)/9) | L95: =SUMPRODUCT(B95:K95,1/(1+Inputs!$B$4)^$B$3:$K$3)+K95*(1+Inputs!$B$6)/(Inputs!$B$4-Inputs!$B$6)/(1+Inputs!$B$4)^10 | M95: =SUMPRODUCT(B95:K95,1/(1+Inputs!$B$5)^$B$3:$K$3)+K95*(1+Inputs!$B$6)/(Inputs!$B$5-Inputs!$B$6)/(1+Inputs!$B$5)^10
A96: =ROUND(-0.2+92*0.005,4) | B96: =1*(1+$A96+(Inputs!$B$6-$A96)*(B$3-1)/9) | C96: =B96*(1+$A96+(Inputs!$B$6-$A96)*(C$3-1)/9) | D96: =C96*(1+$A96+(Inputs!$B$6-$A96)*(D$3-1)/9) | E96: =D96*(1+$A96+(Inputs!$B$6-$A96)*(E$3-1)/9) | F96: =E96*(1+$A96+(Inputs!$B$6-$A96)*(F$3-1)/9) | G96: =F96*(1+$A96+(Inputs!$B$6-$A96)*(G$3-1)/9) | H96: =G96*(1+$A96+(Inputs!$B$6-$A96)*(H$3-1)/9) | I96: =H96*(1+$A96+(Inputs!$B$6-$A96)*(I$3-1)/9) | J96: =I96*(1+$A96+(Inputs!$B$6-$A96)*(J$3-1)/9) | K96: =J96*(1+$A96+(Inputs!$B$6-$A96)*(K$3-1)/9) | L96: =SUMPRODUCT(B96:K96,1/(1+Inputs!$B$4)^$B$3:$K$3)+K96*(1+Inputs!$B$6)/(Inputs!$B$4-Inputs!$B$6)/(1+Inputs!$B$4)^10 | M96: =SUMPRODUCT(B96:K96,1/(1+Inputs!$B$5)^$B$3:$K$3)+K96*(1+Inputs!$B$6)/(Inputs!$B$5-Inputs!$B$6)/(1+Inputs!$B$5)^10
A97: =ROUND(-0.2+93*0.005,4) | B97: =1*(1+$A97+(Inputs!$B$6-$A97)*(B$3-1)/9) | C97: =B97*(1+$A97+(Inputs!$B$6-$A97)*(C$3-1)/9) | D97: =C97*(1+$A97+(Inputs!$B$6-$A97)*(D$3-1)/9) | E97: =D97*(1+$A97+(Inputs!$B$6-$A97)*(E$3-1)/9) | F97: =E97*(1+$A97+(Inputs!$B$6-$A97)*(F$3-1)/9) | G97: =F97*(1+$A97+(Inputs!$B$6-$A97)*(G$3-1)/9) | H97: =G97*(1+$A97+(Inputs!$B$6-$A97)*(H$3-1)/9) | I97: =H97*(1+$A97+(Inputs!$B$6-$A97)*(I$3-1)/9) | J97: =I97*(1+$A97+(Inputs!$B$6-$A97)*(J$3-1)/9) | K97: =J97*(1+$A97+(Inputs!$B$6-$A97)*(K$3-1)/9) | L97: =SUMPRODUCT(B97:K97,1/(1+Inputs!$B$4)^$B$3:$K$3)+K97*(1+Inputs!$B$6)/(Inputs!$B$4-Inputs!$B$6)/(1+Inputs!$B$4)^10 | M97: =SUMPRODUCT(B97:K97,1/(1+Inputs!$B$5)^$B$3:$K$3)+K97*(1+Inputs!$B$6)/(Inputs!$B$5-Inputs!$B$6)/(1+Inputs!$B$5)^10
A98: =ROUND(-0.2+94*0.005,4) | B98: =1*(1+$A98+(Inputs!$B$6-$A98)*(B$3-1)/9) | C98: =B98*(1+$A98+(Inputs!$B$6-$A98)*(C$3-1)/9) | D98: =C98*(1+$A98+(Inputs!$B$6-$A98)*(D$3-1)/9) | E98: =D98*(1+$A98+(Inputs!$B$6-$A98)*(E$3-1)/9) | F98: =E98*(1+$A98+(Inputs!$B$6-$A98)*(F$3-1)/9) | G98: =F98*(1+$A98+(Inputs!$B$6-$A98)*(G$3-1)/9) | H98: =G98*(1+$A98+(Inputs!$B$6-$A98)*(H$3-1)/9) | I98: =H98*(1+$A98+(Inputs!$B$6-$A98)*(I$3-1)/9) | J98: =I98*(1+$A98+(Inputs!$B$6-$A98)*(J$3-1)/9) | K98: =J98*(1+$A98+(Inputs!$B$6-$A98)*(K$3-1)/9) | L98: =SUMPRODUCT(B98:K98,1/(1+Inputs!$B$4)^$B$3:$K$3)+K98*(1+Inputs!$B$6)/(Inputs!$B$4-Inputs!$B$6)/(1+Inputs!$B$4)^10 | M98: =SUMPRODUCT(B98:K98,1/(1+Inputs!$B$5)^$B$3:$K$3)+K98*(1+Inputs!$B$6)/(Inputs!$B$5-Inputs!$B$6)/(1+Inputs!$B$5)^10
A99: =ROUND(-0.2+95*0.005,4) | B99: =1*(1+$A99+(Inputs!$B$6-$A99)*(B$3-1)/9) | C99: =B99*(1+$A99+(Inputs!$B$6-$A99)*(C$3-1)/9) | D99: =C99*(1+$A99+(Inputs!$B$6-$A99)*(D$3-1)/9) | E99: =D99*(1+$A99+(Inputs!$B$6-$A99)*(E$3-1)/9) | F99: =E99*(1+$A99+(Inputs!$B$6-$A99)*(F$3-1)/9) | G99: =F99*(1+$A99+(Inputs!$B$6-$A99)*(G$3-1)/9) | H99: =G99*(1+$A99+(Inputs!$B$6-$A99)*(H$3-1)/9) | I99: =H99*(1+$A99+(Inputs!$B$6-$A99)*(I$3-1)/9) | J99: =I99*(1+$A99+(Inputs!$B$6-$A99)*(J$3-1)/9) | K99: =J99*(1+$A99+(Inputs!$B$6-$A99)*(K$3-1)/9) | L99: =SUMPRODUCT(B99:K99,1/(1+Inputs!$B$4)^$B$3:$K$3)+K99*(1+Inputs!$B$6)/(Inputs!$B$4-Inputs!$B$6)/(1+Inputs!$B$4)^10 | M99: =SUMPRODUCT(B99:K99,1/(1+Inputs!$B$5)^$B$3:$K$3)+K99*(1+Inputs!$B$6)/(Inputs!$B$5-Inputs!$B$6)/(1+Inputs!$B$5)^10
A100: =ROUND(-0.2+96*0.005,4) | B100: =1*(1+$A100+(Inputs!$B$6-$A100)*(B$3-1)/9) | C100: =B100*(1+$A100+(Inputs!$B$6-$A100)*(C$3-1)/9) | D100: =C100*(1+$A100+(Inputs!$B$6-$A100)*(D$3-1)/9) | E100: =D100*(1+$A100+(Inputs!$B$6-$A100)*(E$3-1)/9) | F100: =E100*(1+$A100+(Inputs!$B$6-$A100)*(F$3-1)/9) | G100: =F100*(1+$A100+(Inputs!$B$6-$A100)*(G$3-1)/9) | H100: =G100*(1+$A100+(Inputs!$B$6-$A100)*(H$3-1)/9) | I100: =H100*(1+$A100+(Inputs!$B$6-$A100)*(I$3-1)/9) | J100: =I100*(1+$A100+(Inputs!$B$6-$A100)*(J$3-1)/9) | K100: =J100*(1+$A100+(Inputs!$B$6-$A100)*(K$3-1)/9) | L100: =SUMPRODUCT(B100:K100,1/(1+Inputs!$B$4)^$B$3:$K$3)+K100*(1+Inputs!$B$6)/(Inputs!$B$4-Inputs!$B$6)/(1+Inputs!$B$4)^10 | M100: =SUMPRODUCT(B100:K100,1/(1+Inputs!$B$5)^$B$3:$K$3)+K100*(1+Inputs!$B$6)/(Inputs!$B$5-Inputs!$B$6)/(1+Inputs!$B$5)^10
...

Sheet Filing Log
A1: Filing log — record every update
A3: Date | B3: Ticker | C3: Filing / event | D3: What changed (inputs) | E3: Old buy-below | F3: New buy-below | G3: Price on date | H3: Thesis status / notes
A4: 2026-09-27 | B4: ALL | C4: Initial build (Q2/Q3 filings, Sep-26 prices) | D4: Baseline inputs; INTU FCF normalized for tax catch-up; CRM post-ASR shares/debt; ADSK post-MaintainX debt | H4: INTU watch ~$245; ADBE buy small ~$255; ADSK/CRM no buy
A6: Tip: copy the Summary 'BUY BELOW' value as a number into 'New buy-below' each time, so history is preserved.
