Workbook

Sheet Summary
A1: SUMMARY - price target, NAV, FCF and replacement cost (recalculates from Inputs)
A2: ="Active scenario: "&Scenario&" | price shift $"&TEXT(PriceShift,"0.0")&"/MWh | gas shift $"&TEXT(GasShift,"0.00")&"/MMBtu | nuclear replacement $"&TEXT(NucRC,"#,##0")&"/kW" -> Active scenario: Base | price shift $0.0/MWh | gas shift $0.00/MMBtu | nuclear replacement $4,500/kW
A4: Item | B4: CEG | C4: VST | E4: Notes
A6: Market
A7: Share price ($) | B7: =CEG_Price -> 263.93 | C7: =VST_Price -> 138.76
A8: Shares incl. pending issuance (mm) | B8: =CEG_Shares+CEG_ExtraShares -> 354.307 | C8: =VST_Shares+VST_ExtraShares -> 341
A9: Market cap ($mm) | B9: =B7*B8 -> 93512.247 | C9: =C7*C8 -> 47317.16
A10: Net debt, preferred & other claims ($mm) | B10: =CEG_Claims*1000 -> 14958 | C10: =VST_Claims*1000 -> 26586
A11: Enterprise value ($mm) | B11: =B9+B10 -> 108470.25 | C11: =C9+C10 -> 73903.16
A12: Owned MW (pro forma) | B12: =CEG_Assets!D20 -> 49970 | C12: =VST_Assets!D16 -> 49141
A13: EV per kW ($) | B13: =B11/B12*1000 -> 2170.7074 | C13: =C11/C12*1000 -> 1503.9002
A15: 1. Asset NAV (sum of asset cash-flow values)
A16: Gross asset value ($mm) | B16: =SUMIF(CEG_Model!$B$35:$B$574,"pv_m",CEG_Model!$C$35:$C$574)+SUMIF(CEG_Model!$B$35:$B$574,"pv_c",CEG_Model!$C$35:$C$574)+SUMIF(CEG_Model!$B$35:$B$574,"fixedval",CEG_Model!$C$35:$C$574) -> 81018.946 | C16: =SUMIF(VST_Model!$B$35:$B$454,"pv_m",VST_Model!$C$35:$C$454)+SUMIF(VST_Model!$B$35:$B$454,"pv_c",VST_Model!$C$35:$C$454)+SUMIF(VST_Model!$B$35:$B$454,"fixedval",VST_Model!$C$35:$C$454) -> 49570.659
A17: GAV per kW ($) | B17: =B16/B12*1000 -> 1621.3517 | C17: =C16/C12*1000 -> 1008.7434
A18: Less: capitalised corporate overhead ($mm) | B18: =CEG_Model!$C$30 -> 4862.064 | C18: =VST_Model!$C$30 -> 3781.6053
A19: Equity NAV - generation only ($mm) | B19: =B16-B18-B10 -> 61198.882 | C19: =C16-C18-C10 -> 19203.054
A20: NAV per share - generation only ($) | B20: =B19/B8 -> 172.7284 | C20: =C19/C8 -> 56.31394
A21: Add: retail/platform value ($mm) | B21: =CEG_PlatEBITDA*CEG_PlatMult -> 6000 | C21: =VST_PlatEBITDA*VST_PlatMult -> 8778 | E21: Earnings-based; shown separately
A22: Add: other value - growth / site options ($mm) | B22: =CEG_OtherVal -> 0 | C22: =VST_OtherVal -> 0 | E22: Input on Inputs; 0 by default
A23: NAV per share incl. platform & other ($) | B23: =(B19+B21+B22)/B8 -> 189.66287 | C23: =(C19+C21+C22)/C8 -> 82.055875
A25: 2. Forward value: FCF generated to horizon + NAV at horizon
A26: Cumulative equity FCF to horizon ($mm, after haircut) | B26: =SUMIF(CEG_Model!$G$3:$AS$3,"<="&Horizon,CEG_Model!$G$29:$AS$29) -> 31012.282 | C26: =SUMIF(VST_Model!$G$3:$AS$3,"<="&Horizon,VST_Model!$G$29:$AS$29) -> 20146.242
A27: Gross asset value at horizon ($mm) | B27: =SUMIF(CEG_Model!$B$35:$B$574,"pv_m",CEG_Model!$E$35:$E$574)+SUMIF(CEG_Model!$B$35:$B$574,"pv_c",CEG_Model!$E$35:$E$574)+SUMIF(CEG_Model!$B$35:$B$574,"fixedval",CEG_Model!$E$35:$E$574) -> 75825.055 | C27: =SUMIF(VST_Model!$B$35:$B$454,"pv_m",VST_Model!$E$35:$E$454)+SUMIF(VST_Model!$B$35:$B$454,"pv_c",VST_Model!$E$35:$E$454)+SUMIF(VST_Model!$B$35:$B$454,"fixedval",VST_Model!$E$35:$E$454) -> 45300.151
A28: Less: overhead at horizon ($mm) | B28: =CEG_Model!$C$31 -> 5371.2924 | C28: =VST_Model!$C$31 -> 4177.6719
A29: Add: platform value at horizon ($mm) | B29: =B21*(1+Infl)^(Horizon-2026) -> 6494.593 | C29: =C21*(1+Infl)^(Horizon-2026) -> 9501.5895
A30: Equity NAV at horizon incl. other value ($mm) | B30: =B27-B28-B10+B29+B22 -> 61990.356 | C30: =C27-C28-C10+C29+C22 -> 24038.069
A31: Value per share at horizon = FCF + NAV ($) | B31: =(B26+B30)/B8 -> 262.49167 | C31: =(C26+C30)/C8 -> 129.57276
A32: Years to horizon | B32: =Horizon+1-ValDate -> 4.25 | C32: =Horizon+1-ValDate -> 4.25
A33: Implied annual return from current price | B33: =IF(B31>0,(B31/B7)^(1/B32)-1,-1) -> -0.0012849521 | C33: =IF(C31>0,(C31/C7)^(1/C32)-1,-1) -> -0.015989202
A34: LEVERED EQUITY VALUE today: PV of FCF to horizon + PV of NAV at horizon ($/share) | B34: =(SUMPRODUCT((CEG_Model!$G$3:$AS$3<=Horizon)*CEG_Model!$G$29:$AS$29*CEG_Model!$G$32:$AS$32)+B30*(1+EquityDisc)^-B32)/B8 -> 194.27658 | C34: =(SUMPRODUCT((VST_Model!$G$3:$AS$3<=Horizon)*VST_Model!$G$29:$AS$29*VST_Model!$G$32:$AS$32)+C30*(1+EquityDisc)^-C32)/C8 -> 98.326549 | E34: Discounted at the equity rate; credits cheap debt and the interest tax shield
A35: of which cheap debt & interest tax shield vs asset NAV ($/share) | B35: =B34-B23 -> 4.6137108 | C35: =C34-C23 -> 16.270673
A36: Entry price for target return (fat pitch, $) | B36: =MAX(0,B31)/(1+TargetReturn)^B32 -> 144.92714 | C36: =MAX(0,C31)/(1+TargetReturn)^C32 -> 71.539828
A38: 3. Replacement cost + FCF
A39: Depreciated replacement cost of fleet ($mm) | B39: =CEG_Assets!AM20 -> 67874.422 | C39: =VST_Assets!AM16 -> 49453.619
A40: Less claims, plus other value = equity replacement value ($mm) | B40: =B39-B10+B22 -> 52916.422 | C40: =C39-C10+C22 -> 22867.619
A41: PV of equity FCF over replacement lead time ($mm) | B41: =SUMPRODUCT((CEG_Model!$G$3:$AS$3<=2026+RCYears)*CEG_Model!$G$29:$AS$29*CEG_Model!$G$32:$AS$32) -> 30313.965 | C41: =SUMPRODUCT((VST_Model!$G$3:$AS$3<=2026+RCYears)*VST_Model!$G$29:$AS$29*VST_Model!$G$32:$AS$32) -> 19838.766
A42: Replacement cost + FCF per share ($) | B42: =(B40+B41)/B8 -> 234.91036 | C42: =(C40+C41)/C8 -> 125.23867
A43: Tobin's q (GAV / replacement cost) | B43: =B16/B39 -> 1.1936595 | C43: =C16/C39 -> 1.0023667
A44: Market EV / replacement cost | B44: =B11/B39 -> 1.598102 | C44: =C11/C39 -> 1.4943934
A46: 4. PRICE TARGET (weighted blend - weights on Inputs)
A47: PRICE TARGET ($) | B47: =(CEG_W1*B23+CEG_W2*B34+CEG_W3*B42)/MAX(0.0001,CEG_W1+CEG_W2+CEG_W3) -> 206.28327 | C47: =(VST_W1*C23+VST_W2*C34+VST_W3*C42)/MAX(0.0001,VST_W1+VST_W2+VST_W3) -> 101.8737
A48: Upside / (downside) vs current price | B48: =B47/B7-1 -> -0.21841674 | C48: =C47/C7-1 -> -0.26582807
A50: 5. Revenue, margins and FCF by year ($mm)
A51: Line | B51: 2027 | C51: 2028 | D51: 2029 | E51: 2030 | F51: 2035 | G51: 2040
A52: CEG
A53: Revenue | B53: =CEG_Model!G10 -> 21383.59 | C53: =CEG_Model!H10 -> 22372.346 | D53: =CEG_Model!I10 -> 21049.47 | E53: =CEG_Model!J10 -> 20214.44 | F53: =CEG_Model!O10 -> 22057.468 | G53: =CEG_Model!T10 -> 23586.232
A54: Gross margin | B54: =CEG_Model!G12 -> 17363.432 | C54: =CEG_Model!H12 -> 18227.192 | D54: =CEG_Model!I12 -> 16753.187 | E54: =CEG_Model!J12 -> 15826.699 | F54: =CEG_Model!O12 -> 17182.052 | G54: =CEG_Model!T12 -> 18294.551
A55: Gross margin % | B55: =CEG_Model!G13 -> 0.81199798 | C55: =CEG_Model!H13 -> 0.81471973 | D55: =CEG_Model!I13 -> 0.79589592 | E55: =CEG_Model!J13 -> 0.78294025 | F55: =CEG_Model!O13 -> 0.77896755 | G55: =CEG_Model!T13 -> 0.77564532
A56: Asset EBITDA | B56: =CEG_Model!G15 -> 12290.667 | C56: =CEG_Model!H15 -> 12871.08 | D56: =CEG_Model!I15 -> 11266.953 | E56: =CEG_Model!J15 -> 10207.163 | F56: =CEG_Model!O15 -> 10845.558 | G56: =CEG_Model!T15 -> 11240.773
A57: EBITDA margin % | B57: =CEG_Model!G16 -> 0.574771 | C57: =CEG_Model!H16 -> 0.57531203 | D57: =CEG_Model!I16 -> 0.53526063 | E57: =CEG_Model!J16 -> 0.50494417 | F57: =CEG_Model!O16 -> 0.49169549 | G57: =CEG_Model!T16 -> 0.47658198
A58: Asset cash margin | B58: =CEG_Model!G21 -> 10203.275 | C58: =CEG_Model!H21 -> 11187.971 | D58: =CEG_Model!I21 -> 9541.0856 | E58: =CEG_Model!J21 -> 8437.4942 | F58: =CEG_Model!O21 -> 8840.2971 | G58: =CEG_Model!T21 -> 8995.1583
A59: Equity FCF | B59: =CEG_Model!G29 -> 8028.081 | C59: =CEG_Model!H29 -> 8824.8134 | D59: =CEG_Model!I29 -> 7516.4608 | E59: =CEG_Model!J29 -> 6642.9263 | F59: =CEG_Model!O29 -> 7014.7392 | G59: =CEG_Model!T29 -> 7193.3581
A60: FCF yield on market cap | B60: =B59/$B$9 -> 0.085850584 | C60: =C59/$B$9 -> 0.094370671 | D60: =D59/$B$9 -> 0.080379427 | E60: =E59/$B$9 -> 0.071038036 | F60: =F59/$B$9 -> 0.075014123 | G60: =G59/$B$9 -> 0.076924235
A61: VST
A62: Revenue | B62: =VST_Model!G10 -> 16997.887 | C62: =VST_Model!H10 -> 15567.431 | D62: =VST_Model!I10 -> 14935.159 | E62: =VST_Model!J10 -> 14833.178 | F62: =VST_Model!O10 -> 16261.366 | G62: =VST_Model!T10 -> 15923.754
A63: Gross margin | B63: =VST_Model!G12 -> 11247.408 | C63: =VST_Model!H12 -> 10249.959 | D63: =VST_Model!I12 -> 9413.7976 | E63: =VST_Model!J12 -> 9199.825 | F63: =VST_Model!O12 -> 10032.927 | G63: =VST_Model!T12 -> 9863.573
A64: Gross margin % | B64: =VST_Model!G13 -> 0.66169446 | C64: =VST_Model!H13 -> 0.65842324 | D64: =VST_Model!I13 -> 0.63031118 | E64: =VST_Model!J13 -> 0.62021944 | F64: =VST_Model!O13 -> 0.61697938 | G64: =VST_Model!T13 -> 0.6194251
A65: Asset EBITDA | B65: =VST_Model!G15 -> 8599.3255 | C65: =VST_Model!H15 -> 7763.5999 | D65: =VST_Model!I15 -> 6871.525 | E65: =VST_Model!J15 -> 6600.3656 | F65: =VST_Model!O15 -> 7127.3885 | G65: =VST_Model!T15 -> 6976.6529
A66: EBITDA margin % | B66: =VST_Model!G16 -> 0.50590556 | C66: =VST_Model!H16 -> 0.49870783 | D66: =VST_Model!I16 -> 0.46009052 | E66: =VST_Model!J16 -> 0.44497314 | F66: =VST_Model!O16 -> 0.43830197 | G66: =VST_Model!T16 -> 0.43812865
A67: Asset cash margin | B67: =VST_Model!G21 -> 7764.8031 | C67: =VST_Model!H21 -> 6974.9139 | D67: =VST_Model!I21 -> 6063.3238 | E67: =VST_Model!J21 -> 5772.2055 | F67: =VST_Model!O21 -> 6192.4125 | G67: =VST_Model!T21 -> 6029.0687
A68: Equity FCF | B68: =VST_Model!G29 -> 5905.7425 | C68: =VST_Model!H29 -> 5291.9953 | D68: =VST_Model!I29 -> 4581.2507 | E68: =VST_Model!J29 -> 4367.254 | F68: =VST_Model!O29 -> 4803.7324 | G68: =VST_Model!T29 -> 4783.8108
A69: FCF yield on market cap | B69: =B68/$C$9 -> 0.12481185 | C69: =C68/$C$9 -> 0.11184093 | D69: =D68/$C$9 -> 0.096820069 | E69: =E68/$C$9 -> 0.092297467 | F69: =F68/$C$9 -> 0.10152199 | G69: =G68/$C$9 -> 0.10110097
A71: 6. Scenario snapshot at default inputs (STATIC values - rerun excel_snapshot.py or switch the Scenario cell to update)
A72: CEG | B72: NAV/sh gen-only | C72: NAV/sh incl. platform | D72: Levered equity value | E72: FCF + NAV at horizon | F72: Implied return/yr | G72: Fat-pitch entry | H72: Replacement + FCF | I72: Price target | J72: Up/(down)side
A73: Low | B73: 76.7048 | C73: 93.6393 | D73: 100.4862 | E73: 128.4628 | F73: -0.1558 | G73: 70.927 | H73: 217.3647 | I73: 137.1634 | J73: -0.4803
A74: Base | B74: 172.7284 | C74: 189.6629 | D74: 194.2766 | E74: 262.4917 | F74: -0.0013 | G74: 144.9271 | H74: 234.9104 | I74: 206.2833 | J74: -0.2184
A75: High | B75: 270.0979 | C75: 287.0323 | D75: 289.5044 | E75: 398.5534 | F75: 0.1018 | G75: 220.0496 | H75: 253.2449 | I75: 276.5939 | J75: 0.048
A76: Extreme | B76: 414.606 | C76: 431.5405 | D76: 430.9156 | E76: 600.6342 | F76: 0.2135 | G76: 331.6227 | H76: 280.4891 | I76: 380.9818 | J76: 0.4435
A77: Base, ERCOT at High | B77: 187.9427 | C77: 204.8772 | D77: 209.6363 | E77: 284.3999 | F77: 0.0177 | G77: 157.0232 | H77: 238.4214 | I77: 217.645 | J77: -0.1754
A78: Bull bridge: Base, ERCOT High, retail 10x | B78: 187.9427 | C78: 216.1668 | D78: 218.1089 | E78: 296.6202 | F78: 0.0279 | G78: 163.7702 | H78: 238.4214 | I78: 224.2324 | J78: -0.1504
A80: VST | B80: NAV/sh gen-only | C80: NAV/sh incl. platform | D80: Levered equity value | E80: FCF + NAV at horizon | F80: Implied return/yr | G80: Fat-pitch entry | H80: Replacement + FCF | I80: Price target | J80: Up/(down)side
A81: Low | B81: 1.3276 | C81: 27.0695 | D81: 42.7584 | E81: 50.363 | F81: -0.2122 | G81: 27.8064 | H81: 112.409 | I81: 60.7457 | J81: -0.5622
A82: Base | B82: 56.3139 | C82: 82.0559 | D82: 98.3265 | E82: 129.5728 | F82: -0.016 | G82: 71.5398 | H82: 125.2387 | I82: 101.8737 | J82: -0.2658
A83: High | B83: 114.5474 | C83: 140.2893 | D83: 157.2361 | E83: 213.5256 | F83: 0.1067 | G83: 117.8919 | H83: 139.3437 | I83: 145.623 | J83: 0.0495
A84: Extreme | B84: 203.5726 | C84: 229.3146 | D84: 247.336 | E84: 341.9623 | F84: 0.2364 | G84: 188.8045 | H84: 160.9369 | I84: 212.5292 | J84: 0.5316
A85: Base, ERCOT at High | B85: 75.005 | C85: 100.7469 | D85: 117.3975 | E85: 156.7196 | F85: 0.0291 | G85: 86.5281 | H85: 130.327 | I85: 116.1571 | J85: -0.1629
A86: Bull bridge: Base, ERCOT High, retail 10x | B86: 75.005 | C86: 117.9082 | D86: 130.2767 | E86: 175.2955 | F86: 0.0565 | G86: 96.7843 | H86: 130.327 | I86: 126.1706 | J86: -0.0907

Sheet Inputs
A1: INPUTS - blue = input, yellow = key lever
A3: Control panel
A4: Scenario (Low / Base / High / Extreme) | B4: Base | G4: Selects heat rates, capacity prices, peaker scarcity from the scenario table
A5: ERCOT (Texas) scenario - 'Same' follows the main scenario | B5: Same | G5: Lets ERCOT tighten (or loosen) independently of PJM: sets ERCOT heat rate and ERCOT peaker scarcity
A6: Long-run power price shift ($/MWh, 2026$, all hubs) | B6: 0 | G6: Added to every hub's long-run ATC from 2030 (half in 2029)
A7: Henry Hub shift ($/MMBtu, all years) | B7: 0 | G7: Moves gas costs AND power prices (price = heat rate x gas)
A8: PJM capacity price override ($/MW-day, 2026$; blank = scenario)
A9: Nuclear replacement-cost basis (1-4, see table below) | B9: 2 | G9: 1 gas-equivalent / 2 gas + clean premium / 3 NOAK AP1000 / 4 EPRI next AP1000
A10: FCF / forward-value horizon (last year of FCF) | B10: 2030
A11: Replacement-cost FCF years added (build lead time) | B11: 5 | G11: Years of FCF added on top of depreciated replacement cost
A12: Target return for entry price (fat pitch) | B12: 0.15
A13: Equity discount rate (price-target forward leg, replacement FCF) | B13: 0.09
A15: Global economics
A16: Valuation date (fractional year) | B16: 2026.75 | G16: 30-Sep-2026
A17: Inflation / escalator | B17: 0.02
A18: Cash tax rate on asset cash flow | B18: 0.2 | G18: 21% federal + state less depreciation shield (assumption)
A19: Henry Hub 2027 (2026$/MMBtu) | B19: 3.9 | G19: Between Sep-26 prompt $2.79 and EIA STEO ~$4.60 for 2027
A20: Henry Hub 2028 (2026$/MMBtu) | B20: 3.9
A21: Henry Hub long run (2026$/MMBtu) | B21: 4
A22: Delivered-fuel adder for gas plants ($/MMBtu) | B22: 0.3 | G22: Transport + winter fuel/power mismatch (estimate)
A23: 45U max credit ($/MWh, 2024$) | B23: 15 | G23: CRS IN12557
A24: 45U gross-receipts threshold ($/MWh, 2024$) | B24: 25
A25: 45U base year | B25: 2024
A26: 45U last year | B26: 2032
A27: Corporate overhead discount rate | B27: 0.085
A28: Corporate overhead years capitalised | B28: 30
A30: Forward market (nominal $/MWh ATC; PJM capacity $/MW-day)
A31: Item | B31: 2027 | C31: 2028 | D31: 2029
A32: PJM West ATC forward | B32: 72 | C32: 73 | D32: 70 | G32: Derived from on-peak Cal-27 $83.90 / Cal-28 $85.35 / Cal-29 $81.50 (8-Sep-26) x ~0.86
A33: ERCOT North ATC forward | B33: 49 | C33: 51 | D33: 52 | G33: Estimate: EIA STEO 2027 $47.39; forwards reported >$50
A34: PJM capacity, calendar year (blend of delivery years) | B34: 331.66 | C34: 328.52 | D34: 325 | G34: PJM BRA: 26/27 $329.17, 27/28 $333.44, 28/29 $325 (cap)
A36: Scenario table (long-run, 2026$)
A37: Parameter | B37: Low | C37: Base | D37: High | E37: Extreme | F37: ACTIVE | G37: ACTIVE ERCOT
A38: Implied heat rate PJM (MMBtu/MWh) | B38: 13 | C38: 16.5 | D38: 20 | E38: 25 | F38: =INDEX(B38:E38,MATCH(Scenario,$B$37:$E$37,0)) -> 16.5
A39: Implied heat rate ERCOT | B39: 10.5 | C39: 13 | D39: 16 | E39: 21 | F39: =INDEX(B39:E39,MATCH(Scenario,$B$37:$E$37,0)) -> 13 | G39: =INDEX(B39:E39,MATCH(IF(ERCOTScen="Same",Scenario,ERCOTScen),$B$37:$E$37,0)) -> 13
A40: PJM capacity ($/MW-day) | B40: 120 | C40: 230 | D40: 325 | E40: 475 | F40: =INDEX(B40:E40,MATCH(Scenario,$B$37:$E$37,0)) -> 230
A41: NY/NE/MISO capacity ($/MW-day) | B41: 60 | C41: 110 | D41: 170 | E41: 250 | F41: =INDEX(B41:E41,MATCH(Scenario,$B$37:$E$37,0)) -> 110
A42: CAISO RA capacity ($/MW-day) | B42: 150 | C42: 220 | D42: 280 | E42: 350 | F42: =INDEX(B42:E42,MATCH(Scenario,$B$37:$E$37,0)) -> 220
A43: Peaker scarcity capture (x ATC) | B43: 2 | C43: 2.5 | D43: 3 | E43: 3.6 | F43: =INDEX(B43:E43,MATCH(Scenario,$B$37:$E$37,0)) -> 2.5 | G43: =INDEX(B43:E43,MATCH(IF(ERCOTScen="Same",Scenario,ERCOTScen),$B$37:$E$37,0)) -> 2.5
A44: US data-center TWh 2030 (memo) | B44: 300 | C44: 450 | D44: 650 | E44: 850 | F44: =INDEX(B44:E44,MATCH(Scenario,$B$37:$E$37,0)) -> 450
A45: US data-center TWh 2035 (memo) | B45: 380 | C45: 700 | D45: 1000 | E45: 1400 | F45: =INDEX(B45:E45,MATCH(Scenario,$B$37:$E$37,0)) -> 700
A46: PJM capacity - active (override if set) | F46: =IF(ISNUMBER(PJMCapOverride),PJMCapOverride,PJMCapScen) -> 230
A48: Hubs
A49: Hub | B49: Price ratio to PJM West | C49: Gas basis to HH ($/MMBtu) | D49: CCGT capacity factor | E49: CCGT capture (x ATC) | F49: Nuclear capture (x ATC)
A50: PJMW | B50: 1 | C50: -0.35 | D50: 0.5 | E50: 1.02 | F50: 0.99
A51: PJMA | B51: 0.97 | C51: -0.35 | D51: 0.5 | E51: 1.02 | F51: 0.99
A52: NIHUB | B52: 0.85 | C52: -0.25 | D52: 0.5 | E52: 1.02 | F52: 0.99
A53: MISO | B53: 0.83 | C53: -0.2 | D53: 0.45 | E53: 1.02 | F53: 0.99
A54: NY | B54: 0.9 | C54: 0 | D54: 0.45 | E54: 1.05 | F54: 0.99
A55: NE | B55: 1.08 | C55: 1.4 | D55: 0.45 | E55: 1.05 | F55: 0.99
A56: WEST | B56: 0.92 | C56: 0.6 | D56: 0.45 | E56: 1.15 | F56: 0.99
A57: ERCOT | C57: -0.15 | D57: 0.55 | E57: 1.2 | F57: 0.95 | G57: ERCOT prices use their own heat rate (no ratio)
A59: Technology defaults (asset sheets link here; overwrite per asset if you like)
A60: Tech | B60: Capacity factor | C60: Capture (x ATC) | D60: Heat rate | E60: Fuel price override (2026$/MMBtu) | F60: Variable O&M ($/MWh) | G60: Fuel ($/MWh) | H60: O&M ($/MWh) | I60: Capex ($/MWh) | J60: Per-MWh cost escalator | K60: Fixed O&M ($/kW-yr) | L60: Sust. capex ($/kW-yr) | M60: Capacity accreditation | N60: Merchant discount rate | O60: Contract discount rate | P60: Dispatch check (1/0) | Q60: Mothball floor (1/0) | R60: 45U eligible (1/0) | S60: Replacement cost ($/kW)
A61: nuclear | B61: 0.935 | C61: 0.99 | D61: 0 | F61: 0 | G61: 5.5 | H61: 22.3 | I61: 7.7 | J61: 0.025 | K61: 0 | L61: 0 | M61: 0.95 | N61: 0.08 | O61: 0.0675 | P61: 0 | Q61: 0 | R61: 1
A62: ccgt | D62: 7.2 | F62: 3.5 | G62: 0 | H62: 0 | I62: 0 | J62: 0 | K62: 32 | L62: 12 | M62: 0.78 | N62: 0.095 | O62: 0.095 | P62: 1 | Q62: 1 | R62: 0 | S62: 2350
A63: peaker | B63: 0.06 | D63: 10.5 | F63: 5 | G63: 0 | H63: 0 | I63: 0 | J63: 0 | K63: 18 | L63: 5 | M63: 0.6 | N63: 0.1 | O63: 0.1 | P63: 1 | Q63: 1 | R63: 0 | S63: 1970
A64: coal | B64: 0.5 | C64: 1.02 | D64: 10.4 | E64: 2.3 | F64: 4.5 | G64: 0 | H64: 0 | I64: 0 | J64: 0 | K64: 50 | L64: 15 | M64: 0.83 | N64: 0.12 | O64: 0.12 | P64: 1 | Q64: 1 | R64: 0 | S64: 2350
A65: hydro | B65: 0.2 | C65: 1.3 | D65: 0 | F65: 0 | G65: 0 | H65: 0 | I65: 0 | J65: 0 | K65: 40 | L65: 0 | M65: 0.7 | N65: 0.08 | O65: 0.08 | P65: 0 | Q65: 0 | R65: 0 | S65: 3500
A66: geothermal | B66: 0.85 | C66: 1.1 | D66: 0 | F66: 0 | G66: 0 | H66: 38 | I66: 0 | J66: 0.025 | K66: 0 | L66: 0 | M66: 0.9 | N66: 0.075 | O66: 0.075 | P66: 0 | Q66: 0 | R66: 0 | S66: 5500
A67: renewable | S67: 1600
A68: Notes: nuclear per-MWh cost $35.5 = fuel 5.5 + O&M 22.3 + capex 7.7 (split estimated from NEI 'Nuclear Costs in Context', 2025 avg $36.46/MWh). CCGT CF/capture come from the hub table; peaker capture = scenario scarcity multiple; coal uses a fixed fuel price.
A70: Nuclear replacement-cost basis ($/kW new build)
A71: # | B71: Basis | C71: $/kW
A72: 1 | B72: Gas-equivalent: new CCGT per accredited MW | C72: 2862 | G72: $2,350 x 0.95/0.78
A73: 2 | B73: Gas + clean premium (estimate) | C73: 4500 | G73: Gas-equivalent + PV of ~$15/MWh clean premium
A74: 3 | B74: Nth-of-a-kind AP1000 (MIT, 4th plant) | C74: 6200 | G74: MIT CANES 2024
A75: 4 | B75: EPRI next AP1000 (base) | C75: 12100 | G75: EPRI $9,700-15,100; Vogtle actual ~$17,500-21,700
B76: Selected | C76: =INDEX(C72:C75,NucBasis) -> 4500
A78: Company inputs
A79: Item | B79: CEG | C79: VST | G79: Source / note
A80: Share price ($) | B80: 263.93 | C80: 138.76 | G80: CEG 22-Sep-26; VST 25-Sep-26
A81: Shares outstanding (mm) | B81: 354.307 | C81: 336 | G81: CEG 10-Q cover 31-Jul-26; VST ~336mm Aug-26
A82: Additional shares from pending deals (mm) | B82: 0 | C82: 5 | G82: 5mm VST shares to Cogentrix sellers
A83: Corporate overhead ($mm/yr, 2026$) | B83: 450 | C83: 350 | G83: Estimate
A84: Retail/platform EBITDA ($mm/yr, 2026$) | B84: 1000 | C84: 1463 | G84: VST Retail FY25 $1,463mm reported; CEG estimate
A85: Platform value multiple (x EBITDA) | B85: 6 | C85: 6
A86: Net debt bearing interest ($bn) | B86: 13.758 | C86: 22.96 | G86: After pending-deal cash
A87: Cost of debt | B87: 0.053 | C87: 0.056 | G87: Estimate
A88: Preferred stock ($bn) | B88: 0 | C88: 2.476
A89: Preferred dividend rate | B89: 0 | C89: 0.075
A90: Renewables cash yield (% of $/kW value) | B90: 0.09 | C90: 0.09
A91: Revenue adjustment (all assets) | B91: 0 | C91: 0 | G91: +10% = every revenue line x1.10
A92: Fuel & variable cost adjustment | B92: 0 | C92: 0 | G92: Moves gross margin
A93: Fixed O&M adjustment | B93: 0 | C93: 0
A94: Capex adjustment (sustaining + one-off) | B94: 0 | C94: 0
A95: PPA price adjustment ($/MWh) | B95: 0 | C95: 0 | G95: Undisclosed contract prices - analyst estimates
A96: FCF haircut (years up to horizon) | B96: 0 | C96: 0 | G96: Model's 2027 FCF looks ~15-25% above guidance run-rate
A97: Other value ($mm): growth projects, site / data-center (Helix) options | B97: 0 | C97: 0 | G97: Not modelled by default. E.g. Talen sold its Cumulus data-center campus to Amazon for $650mm (2024)
A98: Price-target weight: NAV incl. platform | B98: 1 | C98: 1
A99: Price-target weight: levered equity value (FCF to horizon + NAV at horizon, PV at equity rate) | B99: 1 | C99: 1
A100: Price-target weight: replacement cost + FCF | B100: 1 | C100: 1
A102: Claims on the assets ($bn) - positive = liability, negative = asset
A103: Item | B103: $bn | G103: Source / note
A104: CEG
A105: Long-term debt incl. current (30-Jun-26; $14.6bn CEG Gen + $5.0bn Calpine) | B105: 19.6
A106: Cash (30-Jun-26) | B106: -0.697
A107: Proceeds: 4.4 GW PJM sale to LS Power (pending) | B107: -5
A108: Proceeds: Brazos Valley (606 MW ERCOT CCGT) sale to LS Power (pending; final DOJ divestiture) | B108: -0.86
A109: Purchase: RISEC from Shell (pending) | B109: 0.715
...

Sheet Prices
A1: PRICE DECK - formulas only (edit on Inputs)
A3: Key | B3: Year | G3: 2027 | H3: 2028 | I3: 2029 | J3: 2030 | K3: 2031 | L3: 2032 | M3: 2033 | N3: 2034 | O3: 2035 | P3: 2036 | Q3: 2037 | R3: 2038 | S3: 2039 | T3: 2040 | U3: 2041 | V3: 2042 | W3: 2043 | X3: 2044 | Y3: 2045 | Z3: 2046 | AA3: 2047 | AB3: 2048 | AC3: 2049 | AD3: 2050 | AE3: 2051 | AF3: 2052 | AG3: 2053 | AH3: 2054 | AI3: 2055 | AJ3: 2056 | AK3: 2057 | AL3: 2058 | AM3: 2059 | AN3: 2060 | AO3: 2061 | AP3: 2062 | AQ3: 2063 | AR3: 2064 | AS3: 2065
A4: INFL | B4: Inflation index (2026 = 1) | G4: =(1+Infl)^(G$3-2026) -> 1.02 | H4: =(1+Infl)^(H$3-2026) -> 1.0404 | I4: =(1+Infl)^(I$3-2026) -> 1.061208 | J4: =(1+Infl)^(J$3-2026) -> 1.0824322 | K4: =(1+Infl)^(K$3-2026) -> 1.1040808 | L4: =(1+Infl)^(L$3-2026) -> 1.1261624 | M4: =(1+Infl)^(M$3-2026) -> 1.1486857 | N4: =(1+Infl)^(N$3-2026) -> 1.1716594 | ... AS4: =(1+Infl)^(AS$3-2026) -> 2.1647448
A5: HH | B5: Henry Hub, real 2026$/MMBtu | G5: =IF(G$3=2027,HH27,IF(G$3=2028,HH28,HHLR))+GasShift -> 3.9 | H5: =IF(H$3=2027,HH27,IF(H$3=2028,HH28,HHLR))+GasShift -> 3.9 | I5: =IF(I$3=2027,HH27,IF(I$3=2028,HH28,HHLR))+GasShift -> 4 | J5: =IF(J$3=2027,HH27,IF(J$3=2028,HH28,HHLR))+GasShift -> 4 | K5: =IF(K$3=2027,HH27,IF(K$3=2028,HH28,HHLR))+GasShift -> 4 | L5: =IF(L$3=2027,HH27,IF(L$3=2028,HH28,HHLR))+GasShift -> 4 | M5: =IF(M$3=2027,HH27,IF(M$3=2028,HH28,HHLR))+GasShift -> 4 | N5: =IF(N$3=2027,HH27,IF(N$3=2028,HH28,HHLR))+GasShift -> 4 | O5: =IF(O$3=2027,HH27,IF(O$3=2028,HH28,HHLR))+GasShift -> 4 | P5: =IF(P$3=2027,HH27,IF(P$3=2028,HH28,HHLR))+GasShift -> 4 | Q5: =IF(Q$3=2027,HH27,IF(Q$3=2028,HH28,HHLR))+GasShift -> 4 | R5: =IF(R$3=2027,HH27,IF(R$3=2028,HH28,HHLR))+GasShift -> 4 | S5: =IF(S$3=2027,HH27,IF(S$3=2028,HH28,HHLR))+GasShift -> 4 | T5: =IF(T$3=2027,HH27,IF(T$3=2028,HH28,HHLR))+GasShift -> 4 | U5: =IF(U$3=2027,HH27,IF(U$3=2028,HH28,HHLR))+GasShift -> 4 | V5: =IF(V$3=2027,HH27,IF(V$3=2028,HH28,HHLR))+GasShift -> 4 | W5: =IF(W$3=2027,HH27,IF(W$3=2028,HH28,HHLR))+GasShift -> 4 | X5: =IF(X$3=2027,HH27,IF(X$3=2028,HH28,HHLR))+GasShift -> 4 | Y5: =IF(Y$3=2027,HH27,IF(Y$3=2028,HH28,HHLR))+GasShift -> 4 | Z5: =IF(Z$3=2027,HH27,IF(Z$3=2028,HH28,HHLR))+GasShift -> 4 | AA5: =IF(AA$3=2027,HH27,IF(AA$3=2028,HH28,HHLR))+GasShift -> 4 | AB5: =IF(AB$3=2027,HH27,IF(AB$3=2028,HH28,HHLR))+GasShift -> 4 | AC5: =IF(AC$3=2027,HH27,IF(AC$3=2028,HH28,HHLR))+GasShift -> 4 | AD5: =IF(AD$3=2027,HH27,IF(AD$3=2028,HH28,HHLR))+GasShift -> 4 | AE5: =IF(AE$3=2027,HH27,IF(AE$3=2028,HH28,HHLR))+GasShift -> 4 | AF5: =IF(AF$3=2027,HH27,IF(AF$3=2028,HH28,HHLR))+GasShift -> 4 | AG5: =IF(AG$3=2027,HH27,IF(AG$3=2028,HH28,HHLR))+GasShift -> 4 | AH5: =IF(AH$3=2027,HH27,IF(AH$3=2028,HH28,HHLR))+GasShift -> 4 | AI5: =IF(AI$3=2027,HH27,IF(AI$3=2028,HH28,HHLR))+GasShift -> 4 | AJ5: =IF(AJ$3=2027,HH27,IF(AJ$3=2028,HH28,HHLR))+GasShift -> 4 | AK5: =IF(AK$3=2027,HH27,IF(AK$3=2028,HH28,HHLR))+GasShift -> 4 | AL5: =IF(AL$3=2027,HH27,IF(AL$3=2028,HH28,HHLR))+GasShift -> 4 | AM5: =IF(AM$3=2027,HH27,IF(AM$3=2028,HH28,HHLR))+GasShift -> 4 | AN5: =IF(AN$3=2027,HH27,IF(AN$3=2028,HH28,HHLR))+GasShift -> 4 | AO5: =IF(AO$3=2027,HH27,IF(AO$3=2028,HH28,HHLR))+GasShift -> 4 | AP5: =IF(AP$3=2027,HH27,IF(AP$3=2028,HH28,HHLR))+GasShift -> 4 | AQ5: =IF(AQ$3=2027,HH27,IF(AQ$3=2028,HH28,HHLR))+GasShift -> 4 | AR5: =IF(AR$3=2027,HH27,IF(AR$3=2028,HH28,HHLR))+GasShift -> 4 | AS5: =IF(AS$3=2027,HH27,IF(AS$3=2028,HH28,HHLR))+GasShift -> 4
A7: Long-run ATC (2026$/MWh) by hub
A8: LR|PJMW | B8: PJMW long-run ATC, 2026$ | C8: =IHRPJM*(HHLR+GasShift+Inputs!$C$50)*Inputs!$B$50+PriceShift -> 60.225
A9: LR|PJMA | B9: PJMA long-run ATC, 2026$ | C9: =IHRPJM*(HHLR+GasShift+Inputs!$C$50)*Inputs!$B$51+PriceShift -> 58.41825
A10: LR|NIHUB | B10: NIHUB long-run ATC, 2026$ | C10: =IHRPJM*(HHLR+GasShift+Inputs!$C$50)*Inputs!$B$52+PriceShift -> 51.19125
A11: LR|MISO | B11: MISO long-run ATC, 2026$ | C11: =IHRPJM*(HHLR+GasShift+Inputs!$C$50)*Inputs!$B$53+PriceShift -> 49.98675
A12: LR|NY | B12: NY long-run ATC, 2026$ | C12: =IHRPJM*(HHLR+GasShift+Inputs!$C$50)*Inputs!$B$54+PriceShift -> 54.2025
A13: LR|NE | B13: NE long-run ATC, 2026$ | C13: =IHRPJM*(HHLR+GasShift+Inputs!$C$50)*Inputs!$B$55+PriceShift -> 65.043
A14: LR|WEST | B14: WEST long-run ATC, 2026$ | C14: =IHRPJM*(HHLR+GasShift+Inputs!$C$50)*Inputs!$B$56+PriceShift -> 55.407
A15: LR|ERCOT | B15: ERCOT long-run ATC, 2026$ | C15: =IHRERC*(HHLR+GasShift+Inputs!$C$57)+PriceShift -> 50.05
A16: LR|PJMW_BASE | B16: PJM West long-run ATC in Base scenario, no shifts (for $/kW-valued renewables) | C16: =IHRPJMBase*(HHLR+Inputs!$C$50) -> 60.225
A18: Annual deck (nominal)
A19: GAS|PJMW | B19: PJMW gas, nominal $/MMBtu | G19: =(G$5+Inputs!$C$50)*G$4 -> 3.621 | H19: =(H$5+Inputs!$C$50)*H$4 -> 3.69342 | I19: =(I$5+Inputs!$C$50)*I$4 -> 3.8734092 | J19: =(J$5+Inputs!$C$50)*J$4 -> 3.9508774 | K19: =(K$5+Inputs!$C$50)*K$4 -> 4.0298949 | L19: =(L$5+Inputs!$C$50)*L$4 -> 4.1104928 | M19: =(M$5+Inputs!$C$50)*M$4 -> 4.1927027 | N19: =(N$5+Inputs!$C$50)*N$4 -> 4.2765567 | ... AS19: =(AS$5+Inputs!$C$50)*AS$4 -> 7.9013184
A20: ATC|PJMW | B20: PJMW ATC power, nominal $/MWh | G20: =IF(G$3<=2028,IF(G$3=2027,FwdPJM27,FwdPJM28)*Inputs!$B$50,IF(G$3=2029,0.5*FwdPJM29*Inputs!$B$50+0.5*$C$8*G$4,$C$8*G$4)) -> 72 | H20: =IF(H$3<=2028,IF(H$3=2027,FwdPJM27,FwdPJM28)*Inputs!$B$50,IF(H$3=2029,0.5*FwdPJM29*Inputs!$B$50+0.5*$C$8*H$4,$C$8*H$4)) -> 73 | I20: =IF(I$3<=2028,IF(I$3=2027,FwdPJM27,FwdPJM28)*Inputs!$B$50,IF(I$3=2029,0.5*FwdPJM29*Inputs!$B$50+0.5*$C$8*I$4,$C$8*I$4)) -> 66.955626 | J20: =IF(J$3<=2028,IF(J$3=2027,FwdPJM27,FwdPJM28)*Inputs!$B$50,IF(J$3=2029,0.5*FwdPJM29*Inputs!$B$50+0.5*$C$8*J$4,$C$8*J$4)) -> 65.189477 | K20: =IF(K$3<=2028,IF(K$3=2027,FwdPJM27,FwdPJM28)*Inputs!$B$50,IF(K$3=2029,0.5*FwdPJM29*Inputs!$B$50+0.5*$C$8*K$4,$C$8*K$4)) -> 66.493266 | L20: =IF(L$3<=2028,IF(L$3=2027,FwdPJM27,FwdPJM28)*Inputs!$B$50,IF(L$3=2029,0.5*FwdPJM29*Inputs!$B$50+0.5*$C$8*L$4,$C$8*L$4)) -> 67.823132 | M20: =IF(M$3<=2028,IF(M$3=2027,FwdPJM27,FwdPJM28)*Inputs!$B$50,IF(M$3=2029,0.5*FwdPJM29*Inputs!$B$50+0.5*$C$8*M$4,$C$8*M$4)) -> 69.179594 | N20: =IF(N$3<=2028,IF(N$3=2027,FwdPJM27,FwdPJM28)*Inputs!$B$50,IF(N$3=2029,0.5*FwdPJM29*Inputs!$B$50+0.5*$C$8*N$4,$C$8*N$4)) -> 70.563186 | ... AS20: =IF(AS$3<=2028,IF(AS$3=2027,FwdPJM27,FwdPJM28)*Inputs!$B$50,IF(AS$3=2029,0.5*FwdPJM29*Inputs!$B$50+0.5*$C$8*AS$4,$C$8*AS$4)) -> 130.37175
A21: CAP|PJMW | B21: PJMW capacity, nominal $/MW-day | G21: =IF(G$3=2027,CapCY27,IF(G$3=2028,CapCY28,IF(G$3=2029,5/12*CapDY2829+7/12*PJMCap*G$4,PJMCap*G$4))) -> 331.66 | H21: =IF(H$3=2027,CapCY27,IF(H$3=2028,CapCY28,IF(H$3=2029,5/12*CapDY2829+7/12*PJMCap*H$4,PJMCap*H$4))) -> 328.52 | I21: =IF(I$3=2027,CapCY27,IF(I$3=2028,CapCY28,IF(I$3=2029,5/12*CapDY2829+7/12*PJMCap*I$4,PJMCap*I$4))) -> 277.79541 | J21: =IF(J$3=2027,CapCY27,IF(J$3=2028,CapCY28,IF(J$3=2029,5/12*CapDY2829+7/12*PJMCap*J$4,PJMCap*J$4))) -> 248.9594 | K21: =IF(K$3=2027,CapCY27,IF(K$3=2028,CapCY28,IF(K$3=2029,5/12*CapDY2829+7/12*PJMCap*K$4,PJMCap*K$4))) -> 253.93858 | L21: =IF(L$3=2027,CapCY27,IF(L$3=2028,CapCY28,IF(L$3=2029,5/12*CapDY2829+7/12*PJMCap*L$4,PJMCap*L$4))) -> 259.01736 | M21: =IF(M$3=2027,CapCY27,IF(M$3=2028,CapCY28,IF(M$3=2029,5/12*CapDY2829+7/12*PJMCap*M$4,PJMCap*M$4))) -> 264.1977 | N21: =IF(N$3=2027,CapCY27,IF(N$3=2028,CapCY28,IF(N$3=2029,5/12*CapDY2829+7/12*PJMCap*N$4,PJMCap*N$4))) -> 269.48166 | ... AS21: =IF(AS$3=2027,CapCY27,IF(AS$3=2028,CapCY28,IF(AS$3=2029,5/12*CapDY2829+7/12*PJMCap*AS$4,PJMCap*AS$4))) -> 497.8913
A22: GAS|PJMA | B22: PJMA gas, nominal $/MMBtu | G22: =(G$5+Inputs!$C$51)*G$4 -> 3.621 | H22: =(H$5+Inputs!$C$51)*H$4 -> 3.69342 | I22: =(I$5+Inputs!$C$51)*I$4 -> 3.8734092 | J22: =(J$5+Inputs!$C$51)*J$4 -> 3.9508774 | K22: =(K$5+Inputs!$C$51)*K$4 -> 4.0298949 | L22: =(L$5+Inputs!$C$51)*L$4 -> 4.1104928 | M22: =(M$5+Inputs!$C$51)*M$4 -> 4.1927027 | N22: =(N$5+Inputs!$C$51)*N$4 -> 4.2765567 | ... AS22: =(AS$5+Inputs!$C$51)*AS$4 -> 7.9013184
A23: ATC|PJMA | B23: PJMA ATC power, nominal $/MWh | G23: =IF(G$3<=2028,IF(G$3=2027,FwdPJM27,FwdPJM28)*Inputs!$B$51,IF(G$3=2029,0.5*FwdPJM29*Inputs!$B$51+0.5*$C$9*G$4,$C$9*G$4)) -> 69.84 | H23: =IF(H$3<=2028,IF(H$3=2027,FwdPJM27,FwdPJM28)*Inputs!$B$51,IF(H$3=2029,0.5*FwdPJM29*Inputs!$B$51+0.5*$C$9*H$4,$C$9*H$4)) -> 70.81 | I23: =IF(I$3<=2028,IF(I$3=2027,FwdPJM27,FwdPJM28)*Inputs!$B$51,IF(I$3=2029,0.5*FwdPJM29*Inputs!$B$51+0.5*$C$9*I$4,$C$9*I$4)) -> 64.946957 | J23: =IF(J$3<=2028,IF(J$3=2027,FwdPJM27,FwdPJM28)*Inputs!$B$51,IF(J$3=2029,0.5*FwdPJM29*Inputs!$B$51+0.5*$C$9*J$4,$C$9*J$4)) -> 63.233793 | K23: =IF(K$3<=2028,IF(K$3=2027,FwdPJM27,FwdPJM28)*Inputs!$B$51,IF(K$3=2029,0.5*FwdPJM29*Inputs!$B$51+0.5*$C$9*K$4,$C$9*K$4)) -> 64.498468 | L23: =IF(L$3<=2028,IF(L$3=2027,FwdPJM27,FwdPJM28)*Inputs!$B$51,IF(L$3=2029,0.5*FwdPJM29*Inputs!$B$51+0.5*$C$9*L$4,$C$9*L$4)) -> 65.788438 | M23: =IF(M$3<=2028,IF(M$3=2027,FwdPJM27,FwdPJM28)*Inputs!$B$51,IF(M$3=2029,0.5*FwdPJM29*Inputs!$B$51+0.5*$C$9*M$4,$C$9*M$4)) -> 67.104207 | N23: =IF(N$3<=2028,IF(N$3=2027,FwdPJM27,FwdPJM28)*Inputs!$B$51,IF(N$3=2029,0.5*FwdPJM29*Inputs!$B$51+0.5*$C$9*N$4,$C$9*N$4)) -> 68.446291 | ... AS23: =IF(AS$3<=2028,IF(AS$3=2027,FwdPJM27,FwdPJM28)*Inputs!$B$51,IF(AS$3=2029,0.5*FwdPJM29*Inputs!$B$51+0.5*$C$9*AS$4,$C$9*AS$4)) -> 126.4606
A24: CAP|PJMA | B24: PJMA capacity, nominal $/MW-day | G24: =IF(G$3=2027,CapCY27,IF(G$3=2028,CapCY28,IF(G$3=2029,5/12*CapDY2829+7/12*PJMCap*G$4,PJMCap*G$4))) -> 331.66 | H24: =IF(H$3=2027,CapCY27,IF(H$3=2028,CapCY28,IF(H$3=2029,5/12*CapDY2829+7/12*PJMCap*H$4,PJMCap*H$4))) -> 328.52 | I24: =IF(I$3=2027,CapCY27,IF(I$3=2028,CapCY28,IF(I$3=2029,5/12*CapDY2829+7/12*PJMCap*I$4,PJMCap*I$4))) -> 277.79541 | J24: =IF(J$3=2027,CapCY27,IF(J$3=2028,CapCY28,IF(J$3=2029,5/12*CapDY2829+7/12*PJMCap*J$4,PJMCap*J$4))) -> 248.9594 | K24: =IF(K$3=2027,CapCY27,IF(K$3=2028,CapCY28,IF(K$3=2029,5/12*CapDY2829+7/12*PJMCap*K$4,PJMCap*K$4))) -> 253.93858 | L24: =IF(L$3=2027,CapCY27,IF(L$3=2028,CapCY28,IF(L$3=2029,5/12*CapDY2829+7/12*PJMCap*L$4,PJMCap*L$4))) -> 259.01736 | M24: =IF(M$3=2027,CapCY27,IF(M$3=2028,CapCY28,IF(M$3=2029,5/12*CapDY2829+7/12*PJMCap*M$4,PJMCap*M$4))) -> 264.1977 | N24: =IF(N$3=2027,CapCY27,IF(N$3=2028,CapCY28,IF(N$3=2029,5/12*CapDY2829+7/12*PJMCap*N$4,PJMCap*N$4))) -> 269.48166 | ... AS24: =IF(AS$3=2027,CapCY27,IF(AS$3=2028,CapCY28,IF(AS$3=2029,5/12*CapDY2829+7/12*PJMCap*AS$4,PJMCap*AS$4))) -> 497.8913
A25: GAS|NIHUB | B25: NIHUB gas, nominal $/MMBtu | G25: =(G$5+Inputs!$C$52)*G$4 -> 3.723 | H25: =(H$5+Inputs!$C$52)*H$4 -> 3.79746 | I25: =(I$5+Inputs!$C$52)*I$4 -> 3.97953 | J25: =(J$5+Inputs!$C$52)*J$4 -> 4.0591206 | K25: =(K$5+Inputs!$C$52)*K$4 -> 4.140303 | L25: =(L$5+Inputs!$C$52)*L$4 -> 4.2231091 | M25: =(M$5+Inputs!$C$52)*M$4 -> 4.3075713 | N25: =(N$5+Inputs!$C$52)*N$4 -> 4.3937227 | ... AS25: =(AS$5+Inputs!$C$52)*AS$4 -> 8.1177929
A26: ATC|NIHUB | B26: NIHUB ATC power, nominal $/MWh | G26: =IF(G$3<=2028,IF(G$3=2027,FwdPJM27,FwdPJM28)*Inputs!$B$52,IF(G$3=2029,0.5*FwdPJM29*Inputs!$B$52+0.5*$C$10*G$4,$C$10*G$4)) -> 61.2 | H26: =IF(H$3<=2028,IF(H$3=2027,FwdPJM27,FwdPJM28)*Inputs!$B$52,IF(H$3=2029,0.5*FwdPJM29*Inputs!$B$52+0.5*$C$10*H$4,$C$10*H$4)) -> 62.05 | I26: =IF(I$3<=2028,IF(I$3=2027,FwdPJM27,FwdPJM28)*Inputs!$B$52,IF(I$3=2029,0.5*FwdPJM29*Inputs!$B$52+0.5*$C$10*I$4,$C$10*I$4)) -> 56.912282 | J26: =IF(J$3<=2028,IF(J$3=2027,FwdPJM27,FwdPJM28)*Inputs!$B$52,IF(J$3=2029,0.5*FwdPJM29*Inputs!$B$52+0.5*$C$10*J$4,$C$10*J$4)) -> 55.411055 | K26: =IF(K$3<=2028,IF(K$3=2027,FwdPJM27,FwdPJM28)*Inputs!$B$52,IF(K$3=2029,0.5*FwdPJM29*Inputs!$B$52+0.5*$C$10*K$4,$C$10*K$4)) -> 56.519276 | L26: =IF(L$3<=2028,IF(L$3=2027,FwdPJM27,FwdPJM28)*Inputs!$B$52,IF(L$3=2029,0.5*FwdPJM29*Inputs!$B$52+0.5*$C$10*L$4,$C$10*L$4)) -> 57.649662 | M26: =IF(M$3<=2028,IF(M$3=2027,FwdPJM27,FwdPJM28)*Inputs!$B$52,IF(M$3=2029,0.5*FwdPJM29*Inputs!$B$52+0.5*$C$10*M$4,$C$10*M$4)) -> 58.802655 | N26: =IF(N$3<=2028,IF(N$3=2027,FwdPJM27,FwdPJM28)*Inputs!$B$52,IF(N$3=2029,0.5*FwdPJM29*Inputs!$B$52+0.5*$C$10*N$4,$C$10*N$4)) -> 59.978708 | ... AS26: =IF(AS$3<=2028,IF(AS$3=2027,FwdPJM27,FwdPJM28)*Inputs!$B$52,IF(AS$3=2029,0.5*FwdPJM29*Inputs!$B$52+0.5*$C$10*AS$4,$C$10*AS$4)) -> 110.81599
A27: CAP|NIHUB | B27: NIHUB capacity, nominal $/MW-day | G27: =IF(G$3=2027,CapCY27,IF(G$3=2028,CapCY28,IF(G$3=2029,5/12*CapDY2829+7/12*PJMCap*G$4,PJMCap*G$4))) -> 331.66 | H27: =IF(H$3=2027,CapCY27,IF(H$3=2028,CapCY28,IF(H$3=2029,5/12*CapDY2829+7/12*PJMCap*H$4,PJMCap*H$4))) -> 328.52 | I27: =IF(I$3=2027,CapCY27,IF(I$3=2028,CapCY28,IF(I$3=2029,5/12*CapDY2829+7/12*PJMCap*I$4,PJMCap*I$4))) -> 277.79541 | J27: =IF(J$3=2027,CapCY27,IF(J$3=2028,CapCY28,IF(J$3=2029,5/12*CapDY2829+7/12*PJMCap*J$4,PJMCap*J$4))) -> 248.9594 | K27: =IF(K$3=2027,CapCY27,IF(K$3=2028,CapCY28,IF(K$3=2029,5/12*CapDY2829+7/12*PJMCap*K$4,PJMCap*K$4))) -> 253.93858 | L27: =IF(L$3=2027,CapCY27,IF(L$3=2028,CapCY28,IF(L$3=2029,5/12*CapDY2829+7/12*PJMCap*L$4,PJMCap*L$4))) -> 259.01736 | M27: =IF(M$3=2027,CapCY27,IF(M$3=2028,CapCY28,IF(M$3=2029,5/12*CapDY2829+7/12*PJMCap*M$4,PJMCap*M$4))) -> 264.1977 | N27: =IF(N$3=2027,CapCY27,IF(N$3=2028,CapCY28,IF(N$3=2029,5/12*CapDY2829+7/12*PJMCap*N$4,PJMCap*N$4))) -> 269.48166 | ... AS27: =IF(AS$3=2027,CapCY27,IF(AS$3=2028,CapCY28,IF(AS$3=2029,5/12*CapDY2829+7/12*PJMCap*AS$4,PJMCap*AS$4))) -> 497.8913
A28: GAS|MISO | B28: MISO gas, nominal $/MMBtu | G28: =(G$5+Inputs!$C$53)*G$4 -> 3.774 | H28: =(H$5+Inputs!$C$53)*H$4 -> 3.84948 | I28: =(I$5+Inputs!$C$53)*I$4 -> 4.0325904 | J28: =(J$5+Inputs!$C$53)*J$4 -> 4.1132422 | K28: =(K$5+Inputs!$C$53)*K$4 -> 4.1955071 | L28: =(L$5+Inputs!$C$53)*L$4 -> 4.2794172 | M28: =(M$5+Inputs!$C$53)*M$4 -> 4.3650055 | N28: =(N$5+Inputs!$C$53)*N$4 -> 4.4523056 | ... AS28: =(AS$5+Inputs!$C$53)*AS$4 -> 8.2260301
A29: ATC|MISO | B29: MISO ATC power, nominal $/MWh | G29: =IF(G$3<=2028,IF(G$3=2027,FwdPJM27,FwdPJM28)*Inputs!$B$53,IF(G$3=2029,0.5*FwdPJM29*Inputs!$B$53+0.5*$C$11*G$4,$C$11*G$4)) -> 59.76 | H29: =IF(H$3<=2028,IF(H$3=2027,FwdPJM27,FwdPJM28)*Inputs!$B$53,IF(H$3=2029,0.5*FwdPJM29*Inputs!$B$53+0.5*$C$11*H$4,$C$11*H$4)) -> 60.59 | I29: =IF(I$3<=2028,IF(I$3=2027,FwdPJM27,FwdPJM28)*Inputs!$B$53,IF(I$3=2029,0.5*FwdPJM29*Inputs!$B$53+0.5*$C$11*I$4,$C$11*I$4)) -> 55.573169 | J29: =IF(J$3<=2028,IF(J$3=2027,FwdPJM27,FwdPJM28)*Inputs!$B$53,IF(J$3=2029,0.5*FwdPJM29*Inputs!$B$53+0.5*$C$11*J$4,$C$11*J$4)) -> 54.107266 | K29: =IF(K$3<=2028,IF(K$3=2027,FwdPJM27,FwdPJM28)*Inputs!$B$53,IF(K$3=2029,0.5*FwdPJM29*Inputs!$B$53+0.5*$C$11*K$4,$C$11*K$4)) -> 55.189411 | L29: =IF(L$3<=2028,IF(L$3=2027,FwdPJM27,FwdPJM28)*Inputs!$B$53,IF(L$3=2029,0.5*FwdPJM29*Inputs!$B$53+0.5*$C$11*L$4,$C$11*L$4)) -> 56.293199 | M29: =IF(M$3<=2028,IF(M$3=2027,FwdPJM27,FwdPJM28)*Inputs!$B$53,IF(M$3=2029,0.5*FwdPJM29*Inputs!$B$53+0.5*$C$11*M$4,$C$11*M$4)) -> 57.419063 | N29: =IF(N$3<=2028,IF(N$3=2027,FwdPJM27,FwdPJM28)*Inputs!$B$53,IF(N$3=2029,0.5*FwdPJM29*Inputs!$B$53+0.5*$C$11*N$4,$C$11*N$4)) -> 58.567445 | ... AS29: =IF(AS$3<=2028,IF(AS$3=2027,FwdPJM27,FwdPJM28)*Inputs!$B$53,IF(AS$3=2029,0.5*FwdPJM29*Inputs!$B$53+0.5*$C$11*AS$4,$C$11*AS$4)) -> 108.20856
A30: CAP|MISO | B30: MISO capacity, nominal $/MW-day | G30: =IF(G$3<=2028,OtherCapBase,OtherCap)*G$4 -> 112.2 | H30: =IF(H$3<=2028,OtherCapBase,OtherCap)*H$4 -> 114.444 | I30: =IF(I$3<=2028,OtherCapBase,OtherCap)*I$4 -> 116.73288 | J30: =IF(J$3<=2028,OtherCapBase,OtherCap)*J$4 -> 119.06754 | K30: =IF(K$3<=2028,OtherCapBase,OtherCap)*K$4 -> 121.44889 | L30: =IF(L$3<=2028,OtherCapBase,OtherCap)*L$4 -> 123.87787 | M30: =IF(M$3<=2028,OtherCapBase,OtherCap)*M$4 -> 126.35542 | N30: =IF(N$3<=2028,OtherCapBase,OtherCap)*N$4 -> 128.88253 | ... AS30: =IF(AS$3<=2028,OtherCapBase,OtherCap)*AS$4 -> 238.12192
A31: GAS|NY | B31: NY gas, nominal $/MMBtu | G31: =(G$5+Inputs!$C$54)*G$4 -> 3.978 | H31: =(H$5+Inputs!$C$54)*H$4 -> 4.05756 | I31: =(I$5+Inputs!$C$54)*I$4 -> 4.244832 | J31: =(J$5+Inputs!$C$54)*J$4 -> 4.3297286 | K31: =(K$5+Inputs!$C$54)*K$4 -> 4.4163232 | L31: =(L$5+Inputs!$C$54)*L$4 -> 4.5046497 | M31: =(M$5+Inputs!$C$54)*M$4 -> 4.5947427 | N31: =(N$5+Inputs!$C$54)*N$4 -> 4.6866375 | ... AS31: =(AS$5+Inputs!$C$54)*AS$4 -> 8.6589791
A32: ATC|NY | B32: NY ATC power, nominal $/MWh | G32: =IF(G$3<=2028,IF(G$3=2027,FwdPJM27,FwdPJM28)*Inputs!$B$54,IF(G$3=2029,0.5*FwdPJM29*Inputs!$B$54+0.5*$C$12*G$4,$C$12*G$4)) -> 64.8 | H32: =IF(H$3<=2028,IF(H$3=2027,FwdPJM27,FwdPJM28)*Inputs!$B$54,IF(H$3=2029,0.5*FwdPJM29*Inputs!$B$54+0.5*$C$12*H$4,$C$12*H$4)) -> 65.7 | I32: =IF(I$3<=2028,IF(I$3=2027,FwdPJM27,FwdPJM28)*Inputs!$B$54,IF(I$3=2029,0.5*FwdPJM29*Inputs!$B$54+0.5*$C$12*I$4,$C$12*I$4)) -> 60.260063 | J32: =IF(J$3<=2028,IF(J$3=2027,FwdPJM27,FwdPJM28)*Inputs!$B$54,IF(J$3=2029,0.5*FwdPJM29*Inputs!$B$54+0.5*$C$12*J$4,$C$12*J$4)) -> 58.670529 | K32: =IF(K$3<=2028,IF(K$3=2027,FwdPJM27,FwdPJM28)*Inputs!$B$54,IF(K$3=2029,0.5*FwdPJM29*Inputs!$B$54+0.5*$C$12*K$4,$C$12*K$4)) -> 59.84394 | L32: =IF(L$3<=2028,IF(L$3=2027,FwdPJM27,FwdPJM28)*Inputs!$B$54,IF(L$3=2029,0.5*FwdPJM29*Inputs!$B$54+0.5*$C$12*L$4,$C$12*L$4)) -> 61.040819 | M32: =IF(M$3<=2028,IF(M$3=2027,FwdPJM27,FwdPJM28)*Inputs!$B$54,IF(M$3=2029,0.5*FwdPJM29*Inputs!$B$54+0.5*$C$12*M$4,$C$12*M$4)) -> 62.261635 | N32: =IF(N$3<=2028,IF(N$3=2027,FwdPJM27,FwdPJM28)*Inputs!$B$54,IF(N$3=2029,0.5*FwdPJM29*Inputs!$B$54+0.5*$C$12*N$4,$C$12*N$4)) -> 63.506868 | ... AS32: =IF(AS$3<=2028,IF(AS$3=2027,FwdPJM27,FwdPJM28)*Inputs!$B$54,IF(AS$3=2029,0.5*FwdPJM29*Inputs!$B$54+0.5*$C$12*AS$4,$C$12*AS$4)) -> 117.33458
A33: CAP|NY | B33: NY capacity, nominal $/MW-day | G33: =IF(G$3<=2028,OtherCapBase,OtherCap)*G$4 -> 112.2 | H33: =IF(H$3<=2028,OtherCapBase,OtherCap)*H$4 -> 114.444 | I33: =IF(I$3<=2028,OtherCapBase,OtherCap)*I$4 -> 116.73288 | J33: =IF(J$3<=2028,OtherCapBase,OtherCap)*J$4 -> 119.06754 | K33: =IF(K$3<=2028,OtherCapBase,OtherCap)*K$4 -> 121.44889 | L33: =IF(L$3<=2028,OtherCapBase,OtherCap)*L$4 -> 123.87787 | M33: =IF(M$3<=2028,OtherCapBase,OtherCap)*M$4 -> 126.35542 | N33: =IF(N$3<=2028,OtherCapBase,OtherCap)*N$4 -> 128.88253 | ... AS33: =IF(AS$3<=2028,OtherCapBase,OtherCap)*AS$4 -> 238.12192
A34: GAS|NE | B34: NE gas, nominal $/MMBtu | G34: =(G$5+Inputs!$C$55)*G$4 -> 5.406 | H34: =(H$5+Inputs!$C$55)*H$4 -> 5.51412 | I34: =(I$5+Inputs!$C$55)*I$4 -> 5.7305232 | J34: =(J$5+Inputs!$C$55)*J$4 -> 5.8451337 | K34: =(K$5+Inputs!$C$55)*K$4 -> 5.9620363 | L34: =(L$5+Inputs!$C$55)*L$4 -> 6.0812771 | M34: =(M$5+Inputs!$C$55)*M$4 -> 6.2029026 | N34: =(N$5+Inputs!$C$55)*N$4 -> 6.3269607 | ... AS34: =(AS$5+Inputs!$C$55)*AS$4 -> 11.689622
A35: ATC|NE | B35: NE ATC power, nominal $/MWh | G35: =IF(G$3<=2028,IF(G$3=2027,FwdPJM27,FwdPJM28)*Inputs!$B$55,IF(G$3=2029,0.5*FwdPJM29*Inputs!$B$55+0.5*$C$13*G$4,$C$13*G$4)) -> 77.76 | H35: =IF(H$3<=2028,IF(H$3=2027,FwdPJM27,FwdPJM28)*Inputs!$B$55,IF(H$3=2029,0.5*FwdPJM29*Inputs!$B$55+0.5*$C$13*H$4,$C$13*H$4)) -> 78.84 | I35: =IF(I$3<=2028,IF(I$3=2027,FwdPJM27,FwdPJM28)*Inputs!$B$55,IF(I$3=2029,0.5*FwdPJM29*Inputs!$B$55+0.5*$C$13*I$4,$C$13*I$4)) -> 72.312076 | J35: =IF(J$3<=2028,IF(J$3=2027,FwdPJM27,FwdPJM28)*Inputs!$B$55,IF(J$3=2029,0.5*FwdPJM29*Inputs!$B$55+0.5*$C$13*J$4,$C$13*J$4)) -> 70.404635 | K35: =IF(K$3<=2028,IF(K$3=2027,FwdPJM27,FwdPJM28)*Inputs!$B$55,IF(K$3=2029,0.5*FwdPJM29*Inputs!$B$55+0.5*$C$13*K$4,$C$13*K$4)) -> 71.812728 | L35: =IF(L$3<=2028,IF(L$3=2027,FwdPJM27,FwdPJM28)*Inputs!$B$55,IF(L$3=2029,0.5*FwdPJM29*Inputs!$B$55+0.5*$C$13*L$4,$C$13*L$4)) -> 73.248982 | M35: =IF(M$3<=2028,IF(M$3=2027,FwdPJM27,FwdPJM28)*Inputs!$B$55,IF(M$3=2029,0.5*FwdPJM29*Inputs!$B$55+0.5*$C$13*M$4,$C$13*M$4)) -> 74.713962 | N35: =IF(N$3<=2028,IF(N$3=2027,FwdPJM27,FwdPJM28)*Inputs!$B$55,IF(N$3=2029,0.5*FwdPJM29*Inputs!$B$55+0.5*$C$13*N$4,$C$13*N$4)) -> 76.208241 | ... AS35: =IF(AS$3<=2028,IF(AS$3=2027,FwdPJM27,FwdPJM28)*Inputs!$B$55,IF(AS$3=2029,0.5*FwdPJM29*Inputs!$B$55+0.5*$C$13*AS$4,$C$13*AS$4)) -> 140.80149
A36: CAP|NE | B36: NE capacity, nominal $/MW-day | G36: =IF(G$3<=2028,OtherCapBase,OtherCap)*G$4 -> 112.2 | H36: =IF(H$3<=2028,OtherCapBase,OtherCap)*H$4 -> 114.444 | I36: =IF(I$3<=2028,OtherCapBase,OtherCap)*I$4 -> 116.73288 | J36: =IF(J$3<=2028,OtherCapBase,OtherCap)*J$4 -> 119.06754 | K36: =IF(K$3<=2028,OtherCapBase,OtherCap)*K$4 -> 121.44889 | L36: =IF(L$3<=2028,OtherCapBase,OtherCap)*L$4 -> 123.87787 | M36: =IF(M$3<=2028,OtherCapBase,OtherCap)*M$4 -> 126.35542 | N36: =IF(N$3<=2028,OtherCapBase,OtherCap)*N$4 -> 128.88253 | ... AS36: =IF(AS$3<=2028,OtherCapBase,OtherCap)*AS$4 -> 238.12192
A37: GAS|WEST | B37: WEST gas, nominal $/MMBtu | G37: =(G$5+Inputs!$C$56)*G$4 -> 4.59 | H37: =(H$5+Inputs!$C$56)*H$4 -> 4.6818 | I37: =(I$5+Inputs!$C$56)*I$4 -> 4.8815568 | J37: =(J$5+Inputs!$C$56)*J$4 -> 4.9791879 | K37: =(K$5+Inputs!$C$56)*K$4 -> 5.0787717 | L37: =(L$5+Inputs!$C$56)*L$4 -> 5.1803471 | M37: =(M$5+Inputs!$C$56)*M$4 -> 5.2839541 | N37: =(N$5+Inputs!$C$56)*N$4 -> 5.3896332 | ... AS37: =(AS$5+Inputs!$C$56)*AS$4 -> 9.9578259
A38: ATC|WEST | B38: WEST ATC power, nominal $/MWh | G38: =IF(G$3<=2028,IF(G$3=2027,FwdPJM27,FwdPJM28)*Inputs!$B$56,IF(G$3=2029,0.5*FwdPJM29*Inputs!$B$56+0.5*$C$14*G$4,$C$14*G$4)) -> 66.24 | H38: =IF(H$3<=2028,IF(H$3=2027,FwdPJM27,FwdPJM28)*Inputs!$B$56,IF(H$3=2029,0.5*FwdPJM29*Inputs!$B$56+0.5*$C$14*H$4,$C$14*H$4)) -> 67.16 | I38: =IF(I$3<=2028,IF(I$3=2027,FwdPJM27,FwdPJM28)*Inputs!$B$56,IF(I$3=2029,0.5*FwdPJM29*Inputs!$B$56+0.5*$C$14*I$4,$C$14*I$4)) -> 61.599176 | J38: =IF(J$3<=2028,IF(J$3=2027,FwdPJM27,FwdPJM28)*Inputs!$B$56,IF(J$3=2029,0.5*FwdPJM29*Inputs!$B$56+0.5*$C$14*J$4,$C$14*J$4)) -> 59.974319 | K38: =IF(K$3<=2028,IF(K$3=2027,FwdPJM27,FwdPJM28)*Inputs!$B$56,IF(K$3=2029,0.5*FwdPJM29*Inputs!$B$56+0.5*$C$14*K$4,$C$14*K$4)) -> 61.173805 | L38: =IF(L$3<=2028,IF(L$3=2027,FwdPJM27,FwdPJM28)*Inputs!$B$56,IF(L$3=2029,0.5*FwdPJM29*Inputs!$B$56+0.5*$C$14*L$4,$C$14*L$4)) -> 62.397281 | M38: =IF(M$3<=2028,IF(M$3=2027,FwdPJM27,FwdPJM28)*Inputs!$B$56,IF(M$3=2029,0.5*FwdPJM29*Inputs!$B$56+0.5*$C$14*M$4,$C$14*M$4)) -> 63.645227 | N38: =IF(N$3<=2028,IF(N$3=2027,FwdPJM27,FwdPJM28)*Inputs!$B$56,IF(N$3=2029,0.5*FwdPJM29*Inputs!$B$56+0.5*$C$14*N$4,$C$14*N$4)) -> 64.918131 | ... AS38: =IF(AS$3<=2028,IF(AS$3=2027,FwdPJM27,FwdPJM28)*Inputs!$B$56,IF(AS$3=2029,0.5*FwdPJM29*Inputs!$B$56+0.5*$C$14*AS$4,$C$14*AS$4)) -> 119.94201
A39: CAP|WEST | B39: WEST capacity, nominal $/MW-day | G39: =IF(G$3<=2028,WestCapBase,WestCap)*G$4 -> 224.4 | H39: =IF(H$3<=2028,WestCapBase,WestCap)*H$4 -> 228.888 | I39: =IF(I$3<=2028,WestCapBase,WestCap)*I$4 -> 233.46576 | J39: =IF(J$3<=2028,WestCapBase,WestCap)*J$4 -> 238.13508 | K39: =IF(K$3<=2028,WestCapBase,WestCap)*K$4 -> 242.89778 | L39: =IF(L$3<=2028,WestCapBase,WestCap)*L$4 -> 247.75573 | M39: =IF(M$3<=2028,WestCapBase,WestCap)*M$4 -> 252.71085 | N39: =IF(N$3<=2028,WestCapBase,WestCap)*N$4 -> 257.76506 | ... AS39: =IF(AS$3<=2028,WestCapBase,WestCap)*AS$4 -> 476.24385
A40: GAS|ERCOT | B40: ERCOT gas, nominal $/MMBtu | G40: =(G$5+Inputs!$C$57)*G$4 -> 3.825 | H40: =(H$5+Inputs!$C$57)*H$4 -> 3.9015 | I40: =(I$5+Inputs!$C$57)*I$4 -> 4.0856508 | J40: =(J$5+Inputs!$C$57)*J$4 -> 4.1673638 | K40: =(K$5+Inputs!$C$57)*K$4 -> 4.2507111 | L40: =(L$5+Inputs!$C$57)*L$4 -> 4.3357253 | M40: =(M$5+Inputs!$C$57)*M$4 -> 4.4224398 | N40: =(N$5+Inputs!$C$57)*N$4 -> 4.5108886 | ... AS40: =(AS$5+Inputs!$C$57)*AS$4 -> 8.3342674
A41: ATC|ERCOT | B41: ERCOT ATC power, nominal $/MWh | G41: =IF(G$3<=2028,IF(G$3=2027,FwdERC27,FwdERC28)*1,IF(G$3=2029,0.5*FwdERC29*1+0.5*$C$15*G$4,$C$15*G$4)) -> 49 | H41: =IF(H$3<=2028,IF(H$3=2027,FwdERC27,FwdERC28)*1,IF(H$3=2029,0.5*FwdERC29*1+0.5*$C$15*H$4,$C$15*H$4)) -> 51 | I41: =IF(I$3<=2028,IF(I$3=2027,FwdERC27,FwdERC28)*1,IF(I$3=2029,0.5*FwdERC29*1+0.5*$C$15*I$4,$C$15*I$4)) -> 52.55673 | J41: =IF(J$3<=2028,IF(J$3=2027,FwdERC27,FwdERC28)*1,IF(J$3=2029,0.5*FwdERC29*1+0.5*$C$15*J$4,$C$15*J$4)) -> 54.17573 | K41: =IF(K$3<=2028,IF(K$3=2027,FwdERC27,FwdERC28)*1,IF(K$3=2029,0.5*FwdERC29*1+0.5*$C$15*K$4,$C$15*K$4)) -> 55.259244 | L41: =IF(L$3<=2028,IF(L$3=2027,FwdERC27,FwdERC28)*1,IF(L$3=2029,0.5*FwdERC29*1+0.5*$C$15*L$4,$C$15*L$4)) -> 56.364429 | M41: =IF(M$3<=2028,IF(M$3=2027,FwdERC27,FwdERC28)*1,IF(M$3=2029,0.5*FwdERC29*1+0.5*$C$15*M$4,$C$15*M$4)) -> 57.491718 | N41: =IF(N$3<=2028,IF(N$3=2027,FwdERC27,FwdERC28)*1,IF(N$3=2029,0.5*FwdERC29*1+0.5*$C$15*N$4,$C$15*N$4)) -> 58.641552 | ... AS41: =IF(AS$3<=2028,IF(AS$3=2027,FwdERC27,FwdERC28)*1,IF(AS$3=2029,0.5*FwdERC29*1+0.5*$C$15*AS$4,$C$15*AS$4)) -> 108.34548
A42: CAP|ERCOT | B42: ERCOT capacity, nominal $/MW-day | G42: =0 -> 0 | H42: =0 -> 0 | I42: =0 -> 0 | J42: =0 -> 0 | K42: =0 -> 0 | L42: =0 -> 0 | M42: =0 -> 0 | N42: =0 -> 0 | ... AS42: =0 -> 0

Sheet CEG_Assets
A1: Asset | B1: Tech | C1: Hub | D1: MW | E1: Start year | F1: End year | G1: Avg in-service year (COD) | H1: Method (Cashflow / $/kW) | I1: Capacity factor | J1: Capture (x ATC) | K1: Heat rate | L1: Fuel price override (2026$/MMBtu) | M1: Variable O&M ($/MWh) | N1: Fuel ($/MWh) | O1: O&M ($/MWh) | P1: Capex ($/MWh) | Q1: Per-MWh cost escalator | R1: Fixed O&M ($/kW-yr) | S1: Sust. capex ($/kW-yr) | T1: Capacity accreditation | U1: ZEC ($/MWh) | V1: ZEC last year | W1: 45U eligible | X1: Dispatch check | Y1: Mothball floor | Z1: Contract MW | AA1: Contract start | AB1: Contract end | AC1: Contract ramp (yrs) | AD1: PPA price ($/MWh, nominal flat) | AE1: Merchant discount rate | AF1: Contract discount rate | AG1: One-off capex ($mm) | AH1: One-off capex year | AI1: $/kW value (if $/kW method) | AJ1: Replacement cost ($/kW) | AK1: Remaining-life override | AL1: Remaining-life fraction | AM1: Depreciated replacement cost ($mm) | AN1: ATC row | AO1: Gas row | AP1: Cap row | AQ1: Asset NAV ($mm) | AR1: NAV $/kW
A2: Nuclear - PJM East (Limerick, Peach Bottom 50%, Calvert Cliffs, Salem 42.6%) | B2: nuclear | C2: PJMW | D2: 6430 | E2: 2027 | F2: 2055 | G2: 1979 | H2: Cashflow | I2: =Inputs!$B$61 -> 0.935 | J2: =Inputs!$F$50 -> 0.99 | K2: =Inputs!$D$61 -> 0 | M2: =Inputs!$F$61 -> 0 | N2: =Inputs!$G$61 -> 5.5 | O2: =Inputs!$H$61 -> 22.3 | P2: =Inputs!$I$61 -> 7.7 | Q2: =Inputs!$J$61 -> 0.025 | R2: =Inputs!$K$61 -> 0 | S2: =Inputs!$L$61 -> 0 | T2: =Inputs!$M$61 -> 0.95 | U2: 0 | V2: 2026 | W2: =Inputs!$R$61 -> 1 | X2: =Inputs!$P$61 -> 0 | Y2: =Inputs!$Q$61 -> 0 | Z2: 0 | AA2: 2026 | AB2: 2026 | AC2: 1 | AD2: 0 | AE2: =Inputs!$N$61 -> 0.08 | AF2: =Inputs!$O$61 -> 0.0675 | AG2: 0 | AH2: 2026 | AJ2: =NucRC -> 4500 | AL2: =IF(ISNUMBER(AK2),AK2,MAX(0,MIN(1,(F2+1-ValDate)/(F2+1-G2)))) -> 0.37987013 | AM2: =D2*AJ2*AL2/1000 -> 10991.542 | AN2: =MATCH("ATC|"&C2,Prices!$A:$A,0) -> 20 | AO2: =MATCH("GAS|"&C2,Prices!$A:$A,0) -> 19 | AP2: =MATCH("CAP|"&C2,Prices!$A:$A,0) -> 21 | AQ2: =CEG_Model!C61+CEG_Model!C62+CEG_Model!C63 -> 20063.905 | AR2: =IF(D2=0,0,AQ2/D2*1000) -> 3120.3584
A3: Nuclear - PJM ComEd (Byron, Braidwood, LaSalle, Dresden, Quad Cities 75%) | B3: nuclear | C3: NIHUB | D3: 10300 | E3: 2027 | F3: 2055 | G3: 1980 | H3: Cashflow | I3: =Inputs!$B$61 -> 0.935 | J3: =Inputs!$F$52 -> 0.99 | K3: =Inputs!$D$61 -> 0 | M3: =Inputs!$F$61 -> 0 | N3: =Inputs!$G$61 -> 5.5 | O3: =Inputs!$H$61 -> 22.3 | P3: =Inputs!$I$61 -> 7.7 | Q3: =Inputs!$J$61 -> 0.025 | R3: =Inputs!$K$61 -> 0 | S3: =Inputs!$L$61 -> 0 | T3: =Inputs!$M$61 -> 0.95 | U3: 0 | V3: 2026 | W3: =Inputs!$R$61 -> 1 | X3: =Inputs!$P$61 -> 0 | Y3: =Inputs!$Q$61 -> 0 | Z3: 920 | AA3: 2027 | AB3: 2046 | AC3: 1 | AD3: 85 | AE3: =Inputs!$N$61 -> 0.08 | AF3: =Inputs!$O$61 -> 0.0675 | AG3: 0 | AH3: 2026 | AJ3: =NucRC -> 4500 | AL3: =IF(ISNUMBER(AK3),AK3,MAX(0,MIN(1,(F3+1-ValDate)/(F3+1-G3)))) -> 0.38486842 | AM3: =D3*AJ3*AL3/1000 -> 17838.651 | AN3: =MATCH("ATC|"&C3,Prices!$A:$A,0) -> 26 | AO3: =MATCH("GAS|"&C3,Prices!$A:$A,0) -> 25 | AP3: =MATCH("CAP|"&C3,Prices!$A:$A,0) -> 27 | AQ3: =CEG_Model!C91+CEG_Model!C92+CEG_Model!C93 -> 24343.611 | AR3: =IF(D3=0,0,AQ3/D3*1000) -> 2363.4574
A4: Nuclear - Clinton (MISO) - Meta 20-yr PPA | B4: nuclear | C4: MISO | D4: 1080 | E4: 2027 | F4: 2055 | G4: 1987 | H4: Cashflow | I4: =Inputs!$B$61 -> 0.935 | J4: =Inputs!$F$53 -> 0.99 | K4: =Inputs!$D$61 -> 0 | M4: =Inputs!$F$61 -> 0 | N4: =Inputs!$G$61 -> 5.5 | O4: =Inputs!$H$61 -> 22.3 | P4: =Inputs!$I$61 -> 7.7 | Q4: =Inputs!$J$61 -> 0.025 | R4: =Inputs!$K$61 -> 0 | S4: =Inputs!$L$61 -> 0 | T4: =Inputs!$M$61 -> 0.95 | U4: 0 | V4: 2026 | W4: =Inputs!$R$61 -> 1 | X4: =Inputs!$P$61 -> 0 | Y4: =Inputs!$Q$61 -> 0 | Z4: 1080 | AA4: 2027 | AB4: 2046 | AC4: 1 | AD4: 80 | AE4: =Inputs!$N$61 -> 0.08 | AF4: =Inputs!$O$61 -> 0.0675 | AG4: 0 | AH4: 2026 | AJ4: =NucRC -> 4500 | AL4: =IF(ISNUMBER(AK4),AK4,MAX(0,MIN(1,(F4+1-ValDate)/(F4+1-G4)))) -> 0.42391304 | AM4: =D4*AJ4*AL4/1000 -> 2060.2174 | AN4: =MATCH("ATC|"&C4,Prices!$A:$A,0) -> 29 | AO4: =MATCH("GAS|"&C4,Prices!$A:$A,0) -> 28 | AP4: =MATCH("CAP|"&C4,Prices!$A:$A,0) -> 30 | AQ4: =CEG_Model!C121+CEG_Model!C122+CEG_Model!C123 -> 3012.4773 | AR4: =IF(D4=0,0,AQ4/D4*1000) -> 2789.3308
A5: Nuclear - New York (Nine Mile Pt, Ginna, FitzPatrick) | B5: nuclear | C5: NY | D5: 3000 | E5: 2027 | F5: 2055 | G5: 1974 | H5: Cashflow | I5: =Inputs!$B$61 -> 0.935 | J5: =Inputs!$F$54 -> 0.99 | K5: =Inputs!$D$61 -> 0 | M5: =Inputs!$F$61 -> 0 | N5: =Inputs!$G$61 -> 5.5 | O5: =Inputs!$H$61 -> 22.3 | P5: =Inputs!$I$61 -> 7.7 | Q5: =Inputs!$J$61 -> 0.025 | R5: =Inputs!$K$61 -> 0 | S5: =Inputs!$L$61 -> 0 | T5: =Inputs!$M$61 -> 0.95 | U5: 18 | V5: 2029 | W5: =Inputs!$R$61 -> 1 | X5: =Inputs!$P$61 -> 0 | Y5: =Inputs!$Q$61 -> 0 | Z5: 0 | AA5: 2026 | AB5: 2026 | AC5: 1 | AD5: 0 | AE5: =Inputs!$N$61 -> 0.08 | AF5: =Inputs!$O$61 -> 0.0675 | AG5: 0 | AH5: 2026 | AJ5: =NucRC -> 4500 | AL5: =IF(ISNUMBER(AK5),AK5,MAX(0,MIN(1,(F5+1-ValDate)/(F5+1-G5)))) -> 0.35670732 | AM5: =D5*AJ5*AL5/1000 -> 4815.5488 | AN5: =MATCH("ATC|"&C5,Prices!$A:$A,0) -> 32 | AO5: =MATCH("GAS|"&C5,Prices!$A:$A,0) -> 31 | AP5: =MATCH("CAP|"&C5,Prices!$A:$A,0) -> 33 | AQ5: =CEG_Model!C151+CEG_Model!C152+CEG_Model!C153 -> 7040.1687 | AR5: =IF(D5=0,0,AQ5/D5*1000) -> 2346.7229
A6: Nuclear - South Texas Project 44% (ERCOT) | B6: nuclear | C6: ERCOT | D6: 1165 | E6: 2027 | F6: 2055 | G6: 1988 | H6: Cashflow | I6: =Inputs!$B$61 -> 0.935 | J6: =Inputs!$F$57 -> 0.95 | K6: =Inputs!$D$61 -> 0 | M6: =Inputs!$F$61 -> 0 | N6: =Inputs!$G$61 -> 5.5 | O6: =Inputs!$H$61 -> 22.3 | P6: =Inputs!$I$61 -> 7.7 | Q6: =Inputs!$J$61 -> 0.025 | R6: =Inputs!$K$61 -> 0 | S6: =Inputs!$L$61 -> 0 | T6: =Inputs!$M$61 -> 0.95 | U6: 0 | V6: 2026 | W6: =Inputs!$R$61 -> 1 | X6: =Inputs!$P$61 -> 0 | Y6: =Inputs!$Q$61 -> 0 | Z6: 0 | AA6: 2026 | AB6: 2026 | AC6: 1 | AD6: 0 | AE6: =Inputs!$N$61 -> 0.08 | AF6: =Inputs!$O$61 -> 0.0675 | AG6: 0 | AH6: 2026 | AJ6: =NucRC -> 4500 | AL6: =IF(ISNUMBER(AK6),AK6,MAX(0,MIN(1,(F6+1-ValDate)/(F6+1-G6)))) -> 0.43014706 | AM6: =D6*AJ6*AL6/1000 -> 2255.046 | AN6: =MATCH("ATC|"&C6,Prices!$A:$A,0) -> 41 | AO6: =MATCH("GAS|"&C6,Prices!$A:$A,0) -> 40 | AP6: =MATCH("CAP|"&C6,Prices!$A:$A,0) -> 42 | AQ6: =CEG_Model!C181+CEG_Model!C182+CEG_Model!C183 -> 1049.5306 | AR6: =IF(D6=0,0,AQ6/D6*1000) -> 900.8846
A7: Nuclear - Crane restart (TMI-1) - Microsoft 20-yr PPA | B7: nuclear | C7: PJMW | D7: 835 | E7: 2028 | F7: 2054 | G7: 1974 | H7: Cashflow | I7: =Inputs!$B$61 -> 0.935 | J7: =Inputs!$F$50 -> 0.99 | K7: =Inputs!$D$61 -> 0 | M7: =Inputs!$F$61 -> 0 | N7: =Inputs!$G$61 -> 5.5 | O7: =Inputs!$H$61 -> 22.3 | P7: =Inputs!$I$61 -> 7.7 | Q7: =Inputs!$J$61 -> 0.025 | R7: =Inputs!$K$61 -> 0 | S7: =Inputs!$L$61 -> 0 | T7: =Inputs!$M$61 -> 0.95 | U7: 0 | V7: 2026 | W7: =Inputs!$R$61 -> 1 | X7: =Inputs!$P$61 -> 0 | Y7: =Inputs!$Q$61 -> 0 | Z7: 835 | AA7: 2028 | AB7: 2047 | AC7: 1 | AD7: 100 | AE7: =Inputs!$N$61 -> 0.08 | AF7: =Inputs!$O$61 -> 0.0675 | AG7: 500 | AH7: 2027 | AJ7: =NucRC -> 4500 | AL7: =IF(ISNUMBER(AK7),AK7,MAX(0,MIN(1,(F7+1-ValDate)/(F7+1-G7)))) -> 0.34876543 | AM7: =D7*AJ7*AL7/1000 -> 1310.4861 | AN7: =MATCH("ATC|"&C7,Prices!$A:$A,0) -> 20 | AO7: =MATCH("GAS|"&C7,Prices!$A:$A,0) -> 19 | AP7: =MATCH("CAP|"&C7,Prices!$A:$A,0) -> 21 | AQ7: =CEG_Model!C211+CEG_Model!C212+CEG_Model!C213 -> 2982.9966 | AR7: =IF(D7=0,0,AQ7/D7*1000) -> 3572.451
A8: Hydro - Conowingo + Muddy Run pumped storage (PJM) | B8: hydro | C8: PJMW | D8: 1642 | E8: 2027 | F8: 2055 | H8: Cashflow | I8: =Inputs!$B$65 -> 0.2 | J8: =Inputs!$C$65 -> 1.3 | K8: =Inputs!$D$65 -> 0 | M8: =Inputs!$F$65 -> 0 | N8: =Inputs!$G$65 -> 0 | O8: =Inputs!$H$65 -> 0 | P8: =Inputs!$I$65 -> 0 | Q8: =Inputs!$J$65 -> 0 | R8: =Inputs!$K$65 -> 40 | S8: =Inputs!$L$65 -> 0 | T8: =Inputs!$M$65 -> 0.7 | U8: 0 | V8: 2026 | W8: =Inputs!$R$65 -> 0 | X8: =Inputs!$P$65 -> 0 | Y8: =Inputs!$Q$65 -> 0 | Z8: 0 | AA8: 2026 | AB8: 2026 | AC8: 1 | AD8: 0 | AE8: =Inputs!$N$65 -> 0.08 | AF8: =Inputs!$O$65 -> 0.08 | AG8: 0 | AH8: 2026 | AJ8: =Inputs!$S$65 -> 3500 | AK8: 0.5 | AL8: =IF(ISNUMBER(AK8),AK8,MAX(0,MIN(1,(F8+1-ValDate)/(F8+1-G8)))) -> 0.5 | AM8: =D8*AJ8*AL8/1000 -> 2873.5 | AN8: =MATCH("ATC|"&C8,Prices!$A:$A,0) -> 20 | AO8: =MATCH("GAS|"&C8,Prices!$A:$A,0) -> 19 | AP8: =MATCH("CAP|"&C8,Prices!$A:$A,0) -> 21 | AQ8: =CEG_Model!C241+CEG_Model!C242+CEG_Model!C243 -> 3003.5869 | AR8: =IF(D8=0,0,AQ8/D8*1000) -> 1829.2247
A9: Wind & solar (legacy CEG, ~1.9 GW) | B9: renewable | C9: PJMW | D9: 1900 | E9: 2027 | F9: 2026 | H9: $/kW | I9: 0 | J9: 0 | K9: 0 | M9: 0 | N9: 0 | O9: 0 | P9: 0 | Q9: 0 | R9: 0 | S9: 0 | T9: 0 | U9: 0 | V9: 2026 | W9: 0 | X9: 0 | Y9: 0 | Z9: 0 | AA9: 2026 | AB9: 2026 | AC9: 1 | AD9: 0 | AE9: 0.08 | AF9: 0.08 | AG9: 0 | AH9: 2026 | AI9: 450 | AJ9: =Inputs!$S$67 -> 1600 | AK9: 0.35 | AL9: =IF(ISNUMBER(AK9),AK9,MAX(0,MIN(1,(F9+1-ValDate)/(F9+1-G9)))) -> 0.35 | AM9: =D9*AJ9*AL9/1000 -> 1064 | AN9: =MATCH("ATC|"&C9,Prices!$A:$A,0) -> 20 | AO9: =MATCH("GAS|"&C9,Prices!$A:$A,0) -> 19 | AP9: =MATCH("CAP|"&C9,Prices!$A:$A,0) -> 21 | AQ9: =CEG_Model!C271+CEG_Model!C272+CEG_Model!C273 -> 855 | AR9: =IF(D9=0,0,AQ9/D9*1000) -> 450
A10: Gas - ERCOT CCGT (Colorado Bend II, Wolf Hollow II, etc.) | B10: ccgt | C10: ERCOT | D10: 2300 | E10: 2027 | F10: 2050 | G10: 2017 | H10: Cashflow | I10: =Inputs!$D$57 -> 0.55 | J10: =Inputs!$E$57 -> 1.2 | K10: =Inputs!$D$62 -> 7.2 | M10: =Inputs!$F$62 -> 3.5 | N10: =Inputs!$G$62 -> 0 | O10: =Inputs!$H$62 -> 0 | P10: =Inputs!$I$62 -> 0 | Q10: =Inputs!$J$62 -> 0 | R10: =Inputs!$K$62 -> 32 | S10: =Inputs!$L$62 -> 12 | T10: =Inputs!$M$62 -> 0.78 | U10: 0 | V10: 2026 | W10: =Inputs!$R$62 -> 0 | X10: =Inputs!$P$62 -> 1 | Y10: =Inputs!$Q$62 -> 1 | Z10: 0 | AA10: 2026 | AB10: 2026 | AC10: 1 | AD10: 0 | AE10: =Inputs!$N$62 -> 0.095 | AF10: =Inputs!$O$62 -> 0.095 | AG10: 0 | AH10: 2026 | AJ10: =Inputs!$S$62 -> 2350 | AL10: =IF(ISNUMBER(AK10),AK10,MAX(0,MIN(1,(F10+1-ValDate)/(F10+1-G10)))) -> 0.71323529 | AM10: =D10*AJ10*AL10/1000 -> 3855.0368 | AN10: =MATCH("ATC|"&C10,Prices!$A:$A,0) -> 41 | AO10: =MATCH("GAS|"&C10,Prices!$A:$A,0) -> 40 | AP10: =MATCH("CAP|"&C10,Prices!$A:$A,0) -> 42 | AQ10: =CEG_Model!C301+CEG_Model!C302+CEG_Model!C303 -> 1746.9661 | AR10: =IF(D10=0,0,AQ10/D10*1000) -> 759.55047
A11: Gas/oil - ERCOT peakers & steam (legacy CEG) | B11: peaker | C11: ERCOT | D11: 1277 | E11: 2027 | F11: 2038 | G11: 1990 | H11: Cashflow | I11: =Inputs!$B$63 -> 0.06 | J11: =ScarcityERC -> 2.5 | K11: =Inputs!$D$63 -> 10.5 | M11: =Inputs!$F$63 -> 5 | N11: =Inputs!$G$63 -> 0 | O11: =Inputs!$H$63 -> 0 | P11: =Inputs!$I$63 -> 0 | Q11: =Inputs!$J$63 -> 0 | R11: =Inputs!$K$63 -> 18 | S11: =Inputs!$L$63 -> 5 | T11: =Inputs!$M$63 -> 0.6 | U11: 0 | V11: 2026 | W11: =Inputs!$R$63 -> 0 | X11: =Inputs!$P$63 -> 1 | Y11: =Inputs!$Q$63 -> 1 | Z11: 0 | AA11: 2026 | AB11: 2026 | AC11: 1 | AD11: 0 | AE11: =Inputs!$N$63 -> 0.1 | AF11: =Inputs!$O$63 -> 0.1 | AG11: 0 | AH11: 2026 | AJ11: =Inputs!$S$63 -> 1970 | AL11: =IF(ISNUMBER(AK11),AK11,MAX(0,MIN(1,(F11+1-ValDate)/(F11+1-G11)))) -> 0.25 | AM11: =D11*AJ11*AL11/1000 -> 628.9225 | AN11: =MATCH("ATC|"&C11,Prices!$A:$A,0) -> 41 | AO11: =MATCH("GAS|"&C11,Prices!$A:$A,0) -> 40 | AP11: =MATCH("CAP|"&C11,Prices!$A:$A,0) -> 42 | AQ11: =CEG_Model!C331+CEG_Model!C332+CEG_Model!C333 -> 133.67387 | AR11: =IF(D11=0,0,AQ11/D11*1000) -> 104.67805
A12: Gas/oil - PJM/NE/other peakers & oil (legacy CEG) | B12: peaker | C12: PJMW | D12: 2582 | E12: 2027 | F12: 2038 | G12: 1995 | H12: Cashflow | I12: =Inputs!$B$63 -> 0.06 | J12: =Scarcity -> 2.5 | K12: =Inputs!$D$63 -> 10.5 | M12: =Inputs!$F$63 -> 5 | N12: =Inputs!$G$63 -> 0 | O12: =Inputs!$H$63 -> 0 | P12: =Inputs!$I$63 -> 0 | Q12: =Inputs!$J$63 -> 0 | R12: =Inputs!$K$63 -> 18 | S12: =Inputs!$L$63 -> 5 | T12: =Inputs!$M$63 -> 0.6 | U12: 0 | V12: 2026 | W12: =Inputs!$R$63 -> 0 | X12: =Inputs!$P$63 -> 1 | Y12: =Inputs!$Q$63 -> 1 | Z12: 0 | AA12: 2026 | AB12: 2026 | AC12: 1 | AD12: 0 | AE12: =Inputs!$N$63 -> 0.1 | AF12: =Inputs!$O$63 -> 0.1 | AG12: 0 | AH12: 2026 | AJ12: =Inputs!$S$63 -> 1970 | AL12: =IF(ISNUMBER(AK12),AK12,MAX(0,MIN(1,(F12+1-ValDate)/(F12+1-G12)))) -> 0.27840909 | AM12: =D12*AJ12*AL12/1000 -> 1416.139 | AN12: =MATCH("ATC|"&C12,Prices!$A:$A,0) -> 20 | AO12: =MATCH("GAS|"&C12,Prices!$A:$A,0) -> 19 | AP12: =MATCH("CAP|"&C12,Prices!$A:$A,0) -> 21 | AQ12: =CEG_Model!C361+CEG_Model!C362+CEG_Model!C363 -> 1464.8758 | AR12: =IF(D12=0,0,AQ12/D12*1000) -> 567.34152
A13: Calpine - ERCOT CCGT (Deer Park, Freestone, Channel, Baytown, etc.) | B13: ccgt | C13: ERCOT | D13: 7000 | E13: 2027 | F13: 2045 | G13: 2002 | H13: Cashflow | I13: =Inputs!$D$57 -> 0.55 | J13: =Inputs!$E$57 -> 1.2 | K13: =Inputs!$D$62 -> 7.2 | M13: =Inputs!$F$62 -> 3.5 | N13: =Inputs!$G$62 -> 0 | O13: =Inputs!$H$62 -> 0 | P13: =Inputs!$I$62 -> 0 | Q13: =Inputs!$J$62 -> 0 | R13: =Inputs!$K$62 -> 32 | S13: =Inputs!$L$62 -> 12 | T13: =Inputs!$M$62 -> 0.78 | U13: 0 | V13: 2026 | W13: =Inputs!$R$62 -> 0 | X13: =Inputs!$P$62 -> 1 | Y13: =Inputs!$Q$62 -> 1 | Z13: 0 | AA13: 2026 | AB13: 2026 | AC13: 1 | AD13: 0 | AE13: =Inputs!$N$62 -> 0.095 | AF13: =Inputs!$O$62 -> 0.095 | AG13: 0 | AH13: 2026 | AJ13: =Inputs!$S$62 -> 2350 | AL13: =IF(ISNUMBER(AK13),AK13,MAX(0,MIN(1,(F13+1-ValDate)/(F13+1-G13)))) -> 0.4375 | AM13: =D13*AJ13*AL13/1000 -> 7196.875 | AN13: =MATCH("ATC|"&C13,Prices!$A:$A,0) -> 41 | AO13: =MATCH("GAS|"&C13,Prices!$A:$A,0) -> 40 | AP13: =MATCH("CAP|"&C13,Prices!$A:$A,0) -> 42 | AQ13: =CEG_Model!C391+CEG_Model!C392+CEG_Model!C393 -> 4805.91 | AR13: =IF(D13=0,0,AQ13/D13*1000) -> 686.55857
A14: Calpine - ERCOT peakers/cogen | B14: peaker | C14: ERCOT | D14: 400 | E14: 2027 | F14: 2040 | G14: 2000 | H14: Cashflow | I14: =Inputs!$B$63 -> 0.06 | J14: =ScarcityERC -> 2.5 | K14: =Inputs!$D$63 -> 10.5 | M14: =Inputs!$F$63 -> 5 | N14: =Inputs!$G$63 -> 0 | O14: =Inputs!$H$63 -> 0 | P14: =Inputs!$I$63 -> 0 | Q14: =Inputs!$J$63 -> 0 | R14: =Inputs!$K$63 -> 18 | S14: =Inputs!$L$63 -> 5 | T14: =Inputs!$M$63 -> 0.6 | U14: 0 | V14: 2026 | W14: =Inputs!$R$63 -> 0 | X14: =Inputs!$P$63 -> 1 | Y14: =Inputs!$Q$63 -> 1 | Z14: 0 | AA14: 2026 | AB14: 2026 | AC14: 1 | AD14: 0 | AE14: =Inputs!$N$63 -> 0.1 | AF14: =Inputs!$O$63 -> 0.1 | AG14: 0 | AH14: 2026 | AJ14: =Inputs!$S$63 -> 1970 | AL14: =IF(ISNUMBER(AK14),AK14,MAX(0,MIN(1,(F14+1-ValDate)/(F14+1-G14)))) -> 0.34756098 | AM14: =D14*AJ14*AL14/1000 -> 273.87805 | AN14: =MATCH("ATC|"&C14,Prices!$A:$A,0) -> 41 | AO14: =MATCH("GAS|"&C14,Prices!$A:$A,0) -> 40 | AP14: =MATCH("CAP|"&C14,Prices!$A:$A,0) -> 42 | AQ14: =CEG_Model!C421+CEG_Model!C422+CEG_Model!C423 -> 45.950107 | AR14: =IF(D14=0,0,AQ14/D14*1000) -> 114.87527
A15: Calpine - West CCGT (CAISO) | B15: ccgt | C15: WEST | D15: 5000 | E15: 2027 | F15: 2045 | G15: 2003 | H15: Cashflow | I15: =Inputs!$D$56 -> 0.45 | J15: =Inputs!$E$56 -> 1.15 | K15: =Inputs!$D$62 -> 7.2 | M15: =Inputs!$F$62 -> 3.5 | N15: =Inputs!$G$62 -> 0 | O15: =Inputs!$H$62 -> 0 | P15: =Inputs!$I$62 -> 0 | Q15: =Inputs!$J$62 -> 0 | R15: =Inputs!$K$62 -> 32 | S15: =Inputs!$L$62 -> 12 | T15: =Inputs!$M$62 -> 0.78 | U15: 0 | V15: 2026 | W15: =Inputs!$R$62 -> 0 | X15: =Inputs!$P$62 -> 1 | Y15: =Inputs!$Q$62 -> 1 | Z15: 0 | AA15: 2026 | AB15: 2026 | AC15: 1 | AD15: 0 | AE15: =Inputs!$N$62 -> 0.095 | AF15: =Inputs!$O$62 -> 0.095 | AG15: 0 | AH15: 2026 | AJ15: =Inputs!$S$62 -> 2350 | AL15: =IF(ISNUMBER(AK15),AK15,MAX(0,MIN(1,(F15+1-ValDate)/(F15+1-G15)))) -> 0.44767442 | AM15: =D15*AJ15*AL15/1000 -> 5260.1744 | AN15: =MATCH("ATC|"&C15,Prices!$A:$A,0) -> 38 | AO15: =MATCH("GAS|"&C15,Prices!$A:$A,0) -> 37 | AP15: =MATCH("CAP|"&C15,Prices!$A:$A,0) -> 39 | AQ15: =CEG_Model!C451+CEG_Model!C452+CEG_Model!C453 -> 5189.6616 | AR15: =IF(D15=0,0,AQ15/D15*1000) -> 1037.9323
A16: Calpine - West peakers | B16: peaker | C16: WEST | D16: 800 | E16: 2027 | F16: 2040 | G16: 2002 | H16: Cashflow | I16: =Inputs!$B$63 -> 0.06 | J16: =Scarcity -> 2.5 | K16: =Inputs!$D$63 -> 10.5 | M16: =Inputs!$F$63 -> 5 | N16: =Inputs!$G$63 -> 0 | O16: =Inputs!$H$63 -> 0 | P16: =Inputs!$I$63 -> 0 | Q16: =Inputs!$J$63 -> 0 | R16: =Inputs!$K$63 -> 18 | S16: =Inputs!$L$63 -> 5 | T16: =Inputs!$M$63 -> 0.6 | U16: 0 | V16: 2026 | W16: =Inputs!$R$63 -> 0 | X16: =Inputs!$P$63 -> 1 | Y16: =Inputs!$Q$63 -> 1 | Z16: 0 | AA16: 2026 | AB16: 2026 | AC16: 1 | AD16: 0 | AE16: =Inputs!$N$63 -> 0.1 | AF16: =Inputs!$O$63 -> 0.1 | AG16: 0 | AH16: 2026 | AJ16: =Inputs!$S$63 -> 1970 | AL16: =IF(ISNUMBER(AK16),AK16,MAX(0,MIN(1,(F16+1-ValDate)/(F16+1-G16)))) -> 0.36538462 | AM16: =D16*AJ16*AL16/1000 -> 575.84615 | AN16: =MATCH("ATC|"&C16,Prices!$A:$A,0) -> 38 | AO16: =MATCH("GAS|"&C16,Prices!$A:$A,0) -> 37 | AP16: =MATCH("CAP|"&C16,Prices!$A:$A,0) -> 39 | AQ16: =CEG_Model!C481+CEG_Model!C482+CEG_Model!C483 -> 389.37341 | AR16: =IF(D16=0,0,AQ16/D16*1000) -> 486.71676
A17: Calpine - The Geysers geothermal | B17: geothermal | C17: WEST | D17: 750 | E17: 2027 | F17: 2055 | G17: 1985 | H17: Cashflow | I17: =Inputs!$B$66 -> 0.85 | J17: =Inputs!$C$66 -> 1.1 | K17: =Inputs!$D$66 -> 0 | M17: =Inputs!$F$66 -> 0 | N17: =Inputs!$G$66 -> 0 | O17: =Inputs!$H$66 -> 38 | P17: =Inputs!$I$66 -> 0 | Q17: =Inputs!$J$66 -> 0.025 | R17: =Inputs!$K$66 -> 0 | S17: =Inputs!$L$66 -> 0 | T17: =Inputs!$M$66 -> 0.9 | U17: 0 | V17: 2026 | W17: =Inputs!$R$66 -> 0 | X17: =Inputs!$P$66 -> 0 | Y17: =Inputs!$Q$66 -> 0 | Z17: 750 | AA17: 2027 | AB17: 2035 | AC17: 1 | AD17: 85 | AE17: =Inputs!$N$66 -> 0.075 | AF17: =Inputs!$O$66 -> 0.075 | AG17: 0 | AH17: 2026 | AJ17: =Inputs!$S$66 -> 5500 | AL17: =IF(ISNUMBER(AK17),AK17,MAX(0,MIN(1,(F17+1-ValDate)/(F17+1-G17)))) -> 0.41197183 | AM17: =D17*AJ17*AL17/1000 -> 1699.3838 | AN17: =MATCH("ATC|"&C17,Prices!$A:$A,0) -> 38 | AO17: =MATCH("GAS|"&C17,Prices!$A:$A,0) -> 37 | AP17: =MATCH("CAP|"&C17,Prices!$A:$A,0) -> 39 | AQ17: =CEG_Model!C511+CEG_Model!C512+CEG_Model!C513 -> 2229.0568 | AR17: =IF(D17=0,0,AQ17/D17*1000) -> 2972.0758
A18: Calpine - East CCGT (NE/NY/PJM residual/SE) | B18: ccgt | C18: NE | D18: 2900 | E18: 2027 | F18: 2045 | G18: 2003 | H18: Cashflow | I18: =Inputs!$D$55 -> 0.45 | J18: =Inputs!$E$55 -> 1.05 | K18: =Inputs!$D$62 -> 7.2 | M18: =Inputs!$F$62 -> 3.5 | N18: =Inputs!$G$62 -> 0 | O18: =Inputs!$H$62 -> 0 | P18: =Inputs!$I$62 -> 0 | Q18: =Inputs!$J$62 -> 0 | R18: =Inputs!$K$62 -> 32 | S18: =Inputs!$L$62 -> 12 | T18: =Inputs!$M$62 -> 0.78 | U18: 0 | V18: 2026 | W18: =Inputs!$R$62 -> 0 | X18: =Inputs!$P$62 -> 1 | Y18: =Inputs!$Q$62 -> 1 | Z18: 0 | AA18: 2026 | AB18: 2026 | AC18: 1 | AD18: 0 | AE18: =Inputs!$N$62 -> 0.095 | AF18: =Inputs!$O$62 -> 0.095 | AG18: 0 | AH18: 2026 | AJ18: =Inputs!$S$62 -> 2350 | AL18: =IF(ISNUMBER(AK18),AK18,MAX(0,MIN(1,(F18+1-ValDate)/(F18+1-G18)))) -> 0.44767442 | AM18: =D18*AJ18*AL18/1000 -> 3050.9012 | AN18: =MATCH("ATC|"&C18,Prices!$A:$A,0) -> 35 | AO18: =MATCH("GAS|"&C18,Prices!$A:$A,0) -> 34 | AP18: =MATCH("CAP|"&C18,Prices!$A:$A,0) -> 36 | AQ18: =CEG_Model!C541+CEG_Model!C542+CEG_Model!C543 -> 2164.9878 | AR18: =IF(D18=0,0,AQ18/D18*1000) -> 746.54751
A19: RISEC (609 MW CCGT, ISO-NE) - pending, $715mm | B19: ccgt | C19: NE | D19: 609 | E19: 2027 | F19: 2050 | G19: 2002 | H19: Cashflow | I19: =Inputs!$D$55 -> 0.45 | J19: =Inputs!$E$55 -> 1.05 | K19: =Inputs!$D$62 -> 7.2 | M19: =Inputs!$F$62 -> 3.5 | N19: =Inputs!$G$62 -> 0 | O19: =Inputs!$H$62 -> 0 | P19: =Inputs!$I$62 -> 0 | Q19: =Inputs!$J$62 -> 0 | R19: =Inputs!$K$62 -> 32 | S19: =Inputs!$L$62 -> 12 | T19: =Inputs!$M$62 -> 0.78 | U19: 0 | V19: 2026 | W19: =Inputs!$R$62 -> 0 | X19: =Inputs!$P$62 -> 1 | Y19: =Inputs!$Q$62 -> 1 | Z19: 0 | AA19: 2026 | AB19: 2026 | AC19: 1 | AD19: 0 | AE19: =Inputs!$N$62 -> 0.095 | AF19: =Inputs!$O$62 -> 0.095 | AG19: 0 | AH19: 2026 | AJ19: =Inputs!$S$62 -> 2350 | AL19: =IF(ISNUMBER(AK19),AK19,MAX(0,MIN(1,(F19+1-ValDate)/(F19+1-G19)))) -> 0.49489796 | AM19: =D19*AJ19*AL19/1000 -> 708.27321 | AN19: =MATCH("ATC|"&C19,Prices!$A:$A,0) -> 35 | AO19: =MATCH("GAS|"&C19,Prices!$A:$A,0) -> 34 | AP19: =MATCH("CAP|"&C19,Prices!$A:$A,0) -> 36 | AQ19: =CEG_Model!C571+CEG_Model!C572+CEG_Model!C573 -> 497.21486 | AR19: =IF(D19=0,0,AQ19/D19*1000) -> 816.44475
A20: Total | D20: =SUM(D2:D19) -> 49970 | AM20: =SUM(AM2:AM19) -> 67874.422 | AQ20: =SUM(AQ2:AQ19) -> 81018.946

Sheet CEG_Model
A1: CEG - annual asset cash flows and consolidated FCF ($mm, nominal). Formulas only.
A3: Line | B3: Key | C3: PV / total | D3: PV to horizon | E3: Value at horizon | G3: 2027 | H3: 2028 | I3: 2029 | J3: 2030 | K3: 2031 | L3: 2032 | M3: 2033 | N3: 2034 | O3: 2035 | P3: 2036 | Q3: 2037 | R3: 2038 | S3: 2039 | T3: 2040 | U3: 2041 | V3: 2042 | W3: 2043 | X3: 2044 | Y3: 2045 | Z3: 2046 | AA3: 2047 | AB3: 2048 | AC3: 2049 | AD3: 2050 | AE3: 2051 | AF3: 2052 | AG3: 2053 | AH3: 2054 | AI3: 2055 | AJ3: 2056 | AK3: 2057 | AL3: 2058 | AM3: 2059 | AN3: 2060 | AO3: 2061 | AP3: 2062 | AQ3: 2063 | AR3: 2064 | AS3: 2065
A4: Inflation index | G4: =Prices!G$4 -> 1.02 | H4: =Prices!H$4 -> 1.0404 | I4: =Prices!I$4 -> 1.061208 | J4: =Prices!J$4 -> 1.0824322 | K4: =Prices!K$4 -> 1.1040808 | L4: =Prices!L$4 -> 1.1261624 | M4: =Prices!M$4 -> 1.1486857 | N4: =Prices!N$4 -> 1.1716594 | ... AS4: =Prices!AS$4 -> 2.1647448
A5: CONSOLIDATED
A6: Merchant energy revenue | B6: c_energy | C6: =SUM(G6:AS6) -> 514082.27 | G6: =SUMIF($B$35:$B$574,"energy",G$35:G$574) -> 16386.008 | H6: =SUMIF($B$35:$B$574,"energy",H$35:H$574) -> 16699.404 | I6: =SUMIF($B$35:$B$574,"energy",I$35:I$574) -> 15692.584 | J6: =SUMIF($B$35:$B$574,"energy",J$35:J$574) -> 15474.106 | K6: =SUMIF($B$35:$B$574,"energy",K$35:K$574) -> 15783.588 | L6: =SUMIF($B$35:$B$574,"energy",L$35:L$574) -> 16099.26 | M6: =SUMIF($B$35:$B$574,"energy",M$35:M$574) -> 16421.245 | N6: =SUMIF($B$35:$B$574,"energy",N$35:N$574) -> 16749.67 | ... AS6: =SUMIF($B$35:$B$574,"energy",AS$35:AS$574) -> 0
A7: Capacity revenue | B7: c_capacity | C7: =SUM(G7:AS7) -> 76134.872 | G7: =SUMIF($B$35:$B$574,"capacity",G$35:G$574) -> 2732.4341 | H7: =SUMIF($B$35:$B$574,"capacity",H$35:H$574) -> 2723.8784 | I7: =SUMIF($B$35:$B$574,"capacity",I$35:I$574) -> 2407.8232 | J7: =SUMIF($B$35:$B$574,"capacity",J$35:J$574) -> 2233.5634 | K7: =SUMIF($B$35:$B$574,"capacity",K$35:K$574) -> 2278.2347 | L7: =SUMIF($B$35:$B$574,"capacity",L$35:L$574) -> 2323.7994 | M7: =SUMIF($B$35:$B$574,"capacity",M$35:M$574) -> 2370.2754 | N7: =SUMIF($B$35:$B$574,"capacity",N$35:N$574) -> 2417.6809 | ... AS7: =SUMIF($B$35:$B$574,"capacity",AS$35:AS$574) -> 0
A8: Long-term PPA revenue | B8: c_ppa | C8: =SUM(G8:AS8) -> 44913.9 | G8: =SUMIF($B$35:$B$574,"ppa",G$35:G$574) -> 1822.8553 | H8: =SUMIF($B$35:$B$574,"ppa",H$35:H$574) -> 2506.7704 | I8: =SUMIF($B$35:$B$574,"ppa",I$35:I$574) -> 2506.7704 | J8: =SUMIF($B$35:$B$574,"ppa",J$35:J$574) -> 2506.7704 | K8: =SUMIF($B$35:$B$574,"ppa",K$35:K$574) -> 2506.7704 | L8: =SUMIF($B$35:$B$574,"ppa",L$35:L$574) -> 2506.7704 | M8: =SUMIF($B$35:$B$574,"ppa",M$35:M$574) -> 2506.7704 | N8: =SUMIF($B$35:$B$574,"ppa",N$35:N$574) -> 2506.7704 | ... AS8: =SUMIF($B$35:$B$574,"ppa",AS$35:AS$574) -> 0
A9: ZEC revenue | B9: c_zec | C9: =SUM(G9:AS9) -> 1326.8772 | G9: =SUMIF($B$35:$B$574,"zec",G$35:G$574) -> 442.2924 | H9: =SUMIF($B$35:$B$574,"zec",H$35:H$574) -> 442.2924 | I9: =SUMIF($B$35:$B$574,"zec",I$35:I$574) -> 442.2924 | J9: =SUMIF($B$35:$B$574,"zec",J$35:J$574) -> 0 | K9: =SUMIF($B$35:$B$574,"zec",K$35:K$574) -> 0 | L9: =SUMIF($B$35:$B$574,"zec",L$35:L$574) -> 0 | M9: =SUMIF($B$35:$B$574,"zec",M$35:M$574) -> 0 | N9: =SUMIF($B$35:$B$574,"zec",N$35:N$574) -> 0 | ... AS9: =SUMIF($B$35:$B$574,"zec",AS$35:AS$574) -> 0
A10: TOTAL REVENUE | B10: c_rev | C10: =SUM(G10:AS10) -> 636457.92 | G10: =SUMIF($B$35:$B$574,"revenue",G$35:G$574) -> 21383.59 | H10: =SUMIF($B$35:$B$574,"revenue",H$35:H$574) -> 22372.346 | I10: =SUMIF($B$35:$B$574,"revenue",I$35:I$574) -> 21049.47 | J10: =SUMIF($B$35:$B$574,"revenue",J$35:J$574) -> 20214.44 | K10: =SUMIF($B$35:$B$574,"revenue",K$35:K$574) -> 20568.593 | L10: =SUMIF($B$35:$B$574,"revenue",L$35:L$574) -> 20929.83 | M10: =SUMIF($B$35:$B$574,"revenue",M$35:M$574) -> 21298.291 | N10: =SUMIF($B$35:$B$574,"revenue",N$35:N$574) -> 21674.121 | ... AS10: =SUMIF($B$35:$B$574,"revenue",AS$35:AS$574) -> 0
A11: Fuel & variable cost | B11: c_fuel | C11: =SUM(G11:AS11) -> 116402.58 | G11: =SUMIF($B$35:$B$574,"fuelvar",G$35:G$574) -> 4020.158 | H11: =SUMIF($B$35:$B$574,"fuelvar",H$35:H$574) -> 4145.1541 | I11: =SUMIF($B$35:$B$574,"fuelvar",I$35:I$574) -> 4296.2827 | J11: =SUMIF($B$35:$B$574,"fuelvar",J$35:J$574) -> 4387.7412 | K11: =SUMIF($B$35:$B$574,"fuelvar",K$35:K$574) -> 4481.1671 | L11: =SUMIF($B$35:$B$574,"fuelvar",L$35:L$574) -> 4576.6034 | M11: =SUMIF($B$35:$B$574,"fuelvar",M$35:M$574) -> 4674.0937 | N11: =SUMIF($B$35:$B$574,"fuelvar",N$35:N$574) -> 4773.6827 | ... AS11: =SUMIF($B$35:$B$574,"fuelvar",AS$35:AS$574) -> 0
A12: GROSS MARGIN | B12: c_gm | C12: =SUM(G12:AS12) -> 520055.34 | G12: =SUMIF($B$35:$B$574,"gm",G$35:G$574) -> 17363.432 | H12: =SUMIF($B$35:$B$574,"gm",H$35:H$574) -> 18227.192 | I12: =SUMIF($B$35:$B$574,"gm",I$35:I$574) -> 16753.187 | J12: =SUMIF($B$35:$B$574,"gm",J$35:J$574) -> 15826.699 | K12: =SUMIF($B$35:$B$574,"gm",K$35:K$574) -> 16087.426 | L12: =SUMIF($B$35:$B$574,"gm",L$35:L$574) -> 16353.226 | M12: =SUMIF($B$35:$B$574,"gm",M$35:M$574) -> 16624.197 | N12: =SUMIF($B$35:$B$574,"gm",N$35:N$574) -> 16900.438 | ... AS12: =SUMIF($B$35:$B$574,"gm",AS$35:AS$574) -> 0
A13: Gross margin % | B13: c_gmpct | G13: =IF(G10=0,0,G12/G10) -> 0.81199798 | H13: =IF(H10=0,0,H12/H10) -> 0.81471973 | I13: =IF(I10=0,0,I12/I10) -> 0.79589592 | J13: =IF(J10=0,0,J12/J10) -> 0.78294025 | K13: =IF(K10=0,0,K12/K10) -> 0.78213546 | L13: =IF(L10=0,0,L12/L10) -> 0.78133585 | M13: =IF(M10=0,0,M12/M10) -> 0.78054137 | N13: =IF(N10=0,0,N12/N10) -> 0.77975196 | ... AS13: =IF(AS10=0,0,AS12/AS10) -> 0
A14: Fixed O&M | B14: c_fom | C14: =SUM(G14:AS14) -> 205277.37 | G14: =SUMIF($B$35:$B$574,"fom",G$35:G$574) -> 5072.7645 | H14: =SUMIF($B$35:$B$574,"fom",H$35:H$574) -> 5356.1119 | I14: =SUMIF($B$35:$B$574,"fom",I$35:I$574) -> 5486.2347 | J14: =SUMIF($B$35:$B$574,"fom",J$35:J$574) -> 5619.5351 | K14: =SUMIF($B$35:$B$574,"fom",K$35:K$574) -> 5756.0908 | L14: =SUMIF($B$35:$B$574,"fom",L$35:L$574) -> 5895.9818 | M14: =SUMIF($B$35:$B$574,"fom",M$35:M$574) -> 6039.2898 | N14: =SUMIF($B$35:$B$574,"fom",N$35:N$574) -> 6186.0987 | ... AS14: =SUMIF($B$35:$B$574,"fom",AS$35:AS$574) -> 0
A15: ASSET EBITDA | B15: c_ebitda | C15: =SUM(G15:AS15) -> 314777.97 | G15: =SUMIF($B$35:$B$574,"ebitda",G$35:G$574) -> 12290.667 | H15: =SUMIF($B$35:$B$574,"ebitda",H$35:H$574) -> 12871.08 | I15: =SUMIF($B$35:$B$574,"ebitda",I$35:I$574) -> 11266.953 | J15: =SUMIF($B$35:$B$574,"ebitda",J$35:J$574) -> 10207.163 | K15: =SUMIF($B$35:$B$574,"ebitda",K$35:K$574) -> 10331.335 | L15: =SUMIF($B$35:$B$574,"ebitda",L$35:L$574) -> 10457.244 | M15: =SUMIF($B$35:$B$574,"ebitda",M$35:M$574) -> 10584.907 | N15: =SUMIF($B$35:$B$574,"ebitda",N$35:N$574) -> 10714.34 | ... AS15: =SUMIF($B$35:$B$574,"ebitda",AS$35:AS$574) -> 0
A16: EBITDA margin % | B16: c_ebitdapct | G16: =IF(G10=0,0,G15/G10) -> 0.574771 | H16: =IF(H10=0,0,H15/H10) -> 0.57531203 | I16: =IF(I10=0,0,I15/I10) -> 0.53526063 | J16: =IF(J10=0,0,J15/J10) -> 0.50494417 | K16: =IF(K10=0,0,K15/K10) -> 0.50228691 | L16: =IF(L10=0,0,L15/L10) -> 0.49963352 | M16: =IF(M10=0,0,M15/M10) -> 0.49698388 | N16: =IF(N10=0,0,N15/N10) -> 0.49433791 | ... AS16: =IF(AS10=0,0,AS15/AS10) -> 0
A17: Capex (sustaining + one-off) | B17: c_capex | C17: =SUM(G17:AS17) -> 67667.398 | G17: =SUMIF($B$35:$B$574,"capex",G$35:G$574) -> 2164.3418 | H17: =SUMIF($B$35:$B$574,"capex",H$35:H$574) -> 1760.0589 | I17: =SUMIF($B$35:$B$574,"capex",I$35:I$574) -> 1802.817 | J17: =SUMIF($B$35:$B$574,"capex",J$35:J$574) -> 1846.6193 | K17: =SUMIF($B$35:$B$574,"capex",K$35:K$574) -> 1891.4913 | L17: =SUMIF($B$35:$B$574,"capex",L$35:L$574) -> 1937.4592 | M17: =SUMIF($B$35:$B$574,"capex",M$35:M$574) -> 1984.5499 | N17: =SUMIF($B$35:$B$574,"capex",N$35:N$574) -> 2032.7909 | ... AS17: =SUMIF($B$35:$B$574,"capex",AS$35:AS$574) -> 0
A18: Asset pre-tax cash flow (after mothball floor) | B18: c_pretax | C18: =SUM(G18:AS18) -> 247110.57 | G18: =SUMIF($B$35:$B$574,"pretax",G$35:G$574) -> 10126.325 | H18: =SUMIF($B$35:$B$574,"pretax",H$35:H$574) -> 11111.021 | I18: =SUMIF($B$35:$B$574,"pretax",I$35:I$574) -> 9464.1356 | J18: =SUMIF($B$35:$B$574,"pretax",J$35:J$574) -> 8360.5442 | K18: =SUMIF($B$35:$B$574,"pretax",K$35:K$574) -> 8439.8439 | L18: =SUMIF($B$35:$B$574,"pretax",L$35:L$574) -> 8519.7853 | M18: =SUMIF($B$35:$B$574,"pretax",M$35:M$574) -> 8600.3574 | N18: =SUMIF($B$35:$B$574,"pretax",N$35:N$574) -> 8681.5488 | ... AS18: =SUMIF($B$35:$B$574,"pretax",AS$35:AS$574) -> 0
A19: 45U credit | B19: c_ptc | C19: =SUM(G19:AS19) -> 0 | G19: =SUMIF($B$35:$B$574,"ptc",G$35:G$574) -> 0 | H19: =SUMIF($B$35:$B$574,"ptc",H$35:H$574) -> 0 | I19: =SUMIF($B$35:$B$574,"ptc",I$35:I$574) -> 0 | J19: =SUMIF($B$35:$B$574,"ptc",J$35:J$574) -> 0 | K19: =SUMIF($B$35:$B$574,"ptc",K$35:K$574) -> 0 | L19: =SUMIF($B$35:$B$574,"ptc",L$35:L$574) -> 0 | M19: =SUMIF($B$35:$B$574,"ptc",M$35:M$574) -> 0 | N19: =SUMIF($B$35:$B$574,"ptc",N$35:N$574) -> 0 | ... AS19: =SUMIF($B$35:$B$574,"ptc",AS$35:AS$574) -> 0
A20: Renewables cash (value x yield) | B20: c_ren | C20: =SUM(G20:AS20) -> 3001.05 | G20: =SUMIF($B$35:$B$574,"fixedval",$C$35:$C$574)*CEG_RenYield -> 76.95 | H20: =SUMIF($B$35:$B$574,"fixedval",$C$35:$C$574)*CEG_RenYield -> 76.95 | I20: =SUMIF($B$35:$B$574,"fixedval",$C$35:$C$574)*CEG_RenYield -> 76.95 | J20: =SUMIF($B$35:$B$574,"fixedval",$C$35:$C$574)*CEG_RenYield -> 76.95 | K20: =SUMIF($B$35:$B$574,"fixedval",$C$35:$C$574)*CEG_RenYield -> 76.95 | L20: =SUMIF($B$35:$B$574,"fixedval",$C$35:$C$574)*CEG_RenYield -> 76.95 | M20: =SUMIF($B$35:$B$574,"fixedval",$C$35:$C$574)*CEG_RenYield -> 76.95 | N20: =SUMIF($B$35:$B$574,"fixedval",$C$35:$C$574)*CEG_RenYield -> 76.95 | ... AS20: =SUMIF($B$35:$B$574,"fixedval",$C$35:$C$574)*CEG_RenYield -> 76.95
A21: ASSET CASH MARGIN | B21: c_assetcash | C21: =SUM(G21:AS21) -> 250111.62 | G21: =G18+G19+G20 -> 10203.275 | H21: =H18+H19+H20 -> 11187.971 | I21: =I18+I19+I20 -> 9541.0856 | J21: =J18+J19+J20 -> 8437.4942 | K21: =K18+K19+K20 -> 8516.7939 | L21: =L18+L19+L20 -> 8596.7353 | M21: =M18+M19+M20 -> 8677.3074 | N21: =N18+N19+N20 -> 8758.4988 | ... AS21: =AS18+AS19+AS20 -> 76.95
A22: + Retail/platform EBITDA | B22: c_plat | C22: =SUM(G22:AS22) -> 59401.983 | G22: =CEG_PlatEBITDA*G$4 -> 1020 | H22: =CEG_PlatEBITDA*H$4 -> 1040.4 | I22: =CEG_PlatEBITDA*I$4 -> 1061.208 | J22: =CEG_PlatEBITDA*J$4 -> 1082.4322 | K22: =CEG_PlatEBITDA*K$4 -> 1104.0808 | L22: =CEG_PlatEBITDA*L$4 -> 1126.1624 | M22: =CEG_PlatEBITDA*M$4 -> 1148.6857 | N22: =CEG_PlatEBITDA*N$4 -> 1171.6594 | ... AS22: =CEG_PlatEBITDA*AS$4 -> 2164.7448
A23: - Corporate overhead | B23: c_oh | C23: =SUM(G23:AS23) -> 26730.892 | G23: =CEG_OH*G$4 -> 459 | H23: =CEG_OH*H$4 -> 468.18 | I23: =CEG_OH*I$4 -> 477.5436 | J23: =CEG_OH*J$4 -> 487.09447 | K23: =CEG_OH*K$4 -> 496.83636 | L23: =CEG_OH*L$4 -> 506.77309 | M23: =CEG_OH*M$4 -> 516.90855 | N23: =CEG_OH*N$4 -> 527.24672 | ... AS23: =CEG_OH*AS$4 -> 974.13515
A24: - Interest | B24: c_int | C24: =SUM(G24:AS24) -> 28437.786 | G24: =CEG_NetDebt*1000*CEG_CoD -> 729.174 | H24: =CEG_NetDebt*1000*CEG_CoD -> 729.174 | I24: =CEG_NetDebt*1000*CEG_CoD -> 729.174 | J24: =CEG_NetDebt*1000*CEG_CoD -> 729.174 | K24: =CEG_NetDebt*1000*CEG_CoD -> 729.174 | L24: =CEG_NetDebt*1000*CEG_CoD -> 729.174 | M24: =CEG_NetDebt*1000*CEG_CoD -> 729.174 | N24: =CEG_NetDebt*1000*CEG_CoD -> 729.174 | ... AS24: =CEG_NetDebt*1000*CEG_CoD -> 729.174
A25: Taxable income | B25: c_taxable | C25: =SUM(G25:AS25) -> 254344.93 | G25: =G21-G19+G22-G23-G24 -> 10035.101 | H25: =H21-H19+H22-H23-H24 -> 11031.017 | I25: =I21-I19+I22-I23-I24 -> 9395.576 | J25: =J21-J19+J22-J23-J24 -> 8303.6579 | K25: =K21-K19+K22-K23-K24 -> 8394.8644 | L25: =L21-L19+L22-L23-L24 -> 8486.9506 | M25: =M21-M19+M22-M23-M24 -> 8579.9105 | N25: =N21-N19+N22-N23-N24 -> 8673.7375 | ... AS25: =AS21-AS19+AS22-AS23-AS24 -> 538.38562
A26: - Cash tax | B26: c_tax | C26: =SUM(G26:AS26) -> 50868.986 | G26: =TaxRate*MAX(0,G25) -> 2007.0202 | H26: =TaxRate*MAX(0,H25) -> 2206.2034 | I26: =TaxRate*MAX(0,I25) -> 1879.1152 | J26: =TaxRate*MAX(0,J25) -> 1660.7316 | K26: =TaxRate*MAX(0,K25) -> 1678.9729 | L26: =TaxRate*MAX(0,L25) -> 1697.3901 | M26: =TaxRate*MAX(0,M25) -> 1715.9821 | N26: =TaxRate*MAX(0,N25) -> 1734.7475 | ... AS26: =TaxRate*MAX(0,AS25) -> 107.67712
A27: - Preferred dividends | B27: c_pref | C27: =SUM(G27:AS27) -> 0 | G27: =CEG_Pref*1000*CEG_PrefRate -> 0 | H27: =CEG_Pref*1000*CEG_PrefRate -> 0 | I27: =CEG_Pref*1000*CEG_PrefRate -> 0 | J27: =CEG_Pref*1000*CEG_PrefRate -> 0 | K27: =CEG_Pref*1000*CEG_PrefRate -> 0 | L27: =CEG_Pref*1000*CEG_PrefRate -> 0 | M27: =CEG_Pref*1000*CEG_PrefRate -> 0 | N27: =CEG_Pref*1000*CEG_PrefRate -> 0 | ... AS27: =CEG_Pref*1000*CEG_PrefRate -> 0
A28: EQUITY FCF (before haircut) | B28: c_fcf | C28: =SUM(G28:AS28) -> 203475.94 | G28: =G21+G22-G23-G24-G26-G27 -> 8028.081 | H28: =H21+H22-H23-H24-H26-H27 -> 8824.8134 | I28: =I21+I22-I23-I24-I26-I27 -> 7516.4608 | J28: =J21+J22-J23-J24-J26-J27 -> 6642.9263 | K28: =K21+K22-K23-K24-K26-K27 -> 6715.8915 | L28: =L21+L22-L23-L24-L26-L27 -> 6789.5605 | M28: =M21+M22-M23-M24-M26-M27 -> 6863.9284 | N28: =N21+N22-N23-N24-N26-N27 -> 6938.99 | ... AS28: =AS21+AS22-AS23-AS24-AS26-AS27 -> 430.7085
A29: EQUITY FCF (after haircut) | B29: c_fcfadj | C29: =SUM(G29:AS29) -> 203475.94 | G29: =G28*(1-IF(G$3<=Horizon,CEG_Haircut,0)) -> 8028.081 | H29: =H28*(1-IF(H$3<=Horizon,CEG_Haircut,0)) -> 8824.8134 | I29: =I28*(1-IF(I$3<=Horizon,CEG_Haircut,0)) -> 7516.4608 | J29: =J28*(1-IF(J$3<=Horizon,CEG_Haircut,0)) -> 6642.9263 | K29: =K28*(1-IF(K$3<=Horizon,CEG_Haircut,0)) -> 6715.8915 | L29: =L28*(1-IF(L$3<=Horizon,CEG_Haircut,0)) -> 6789.5605 | M29: =M28*(1-IF(M$3<=Horizon,CEG_Haircut,0)) -> 6863.9284 | N29: =N28*(1-IF(N$3<=Horizon,CEG_Haircut,0)) -> 6938.99 | ... AS29: =AS28*(1-IF(AS$3<=Horizon,CEG_Haircut,0)) -> 430.7085
A30: Overhead PV (NAV, after tax) | B30: c_ohpv | C30: =SUM(G30:AS30) -> 4862.064 | G30: =IF(G$3<=2026+OHYears,CEG_OH*G$4*(1-TaxRate)*(1+OHDisc)^-(G$3+0.5-ValDate),0) -> 345.40639 | H30: =IF(H$3<=2026+OHYears,CEG_OH*H$4*(1-TaxRate)*(1+OHDisc)^-(H$3+0.5-ValDate),0) -> 324.71384 | I30: =IF(I$3<=2026+OHYears,CEG_OH*I$4*(1-TaxRate)*(1+OHDisc)^-(I$3+0.5-ValDate),0) -> 305.26094 | J30: =IF(J$3<=2026+OHYears,CEG_OH*J$4*(1-TaxRate)*(1+OHDisc)^-(J$3+0.5-ValDate),0) -> 286.97342 | K30: =IF(K$3<=2026+OHYears,CEG_OH*K$4*(1-TaxRate)*(1+OHDisc)^-(K$3+0.5-ValDate),0) -> 269.78146 | L30: =IF(L$3<=2026+OHYears,CEG_OH*L$4*(1-TaxRate)*(1+OHDisc)^-(L$3+0.5-ValDate),0) -> 253.61944 | M30: =IF(M$3<=2026+OHYears,CEG_OH*M$4*(1-TaxRate)*(1+OHDisc)^-(M$3+0.5-ValDate),0) -> 238.42565 | N30: =IF(N$3<=2026+OHYears,CEG_OH*N$4*(1-TaxRate)*(1+OHDisc)^-(N$3+0.5-ValDate),0) -> 224.14208 | ... AS30: =IF(AS$3<=2026+OHYears,CEG_OH*AS$4*(1-TaxRate)*(1+OHDisc)^-(AS$3+0.5-ValDate),0) -> 0
A31: Overhead PV at horizon (after tax) | B31: c_ohfwd | C31: =SUM(G31:AS31) -> 5371.2924 | G31: =IF(AND(G$3>Horizon,G$3<=Horizon+OHYears),CEG_OH*G$4*(1-TaxRate)*(1+OHDisc)^-(G$3+0.5-(Horizon+1)),0) -> 0 | H31: =IF(AND(H$3>Horizon,H$3<=Horizon+OHYears),CEG_OH*H$4*(1-TaxRate)*(1+OHDisc)^-(H$3+0.5-(Horizon+1)),0) -> 0 | I31: =IF(AND(I$3>Horizon,I$3<=Horizon+OHYears),CEG_OH*I$4*(1-TaxRate)*(1+OHDisc)^-(I$3+0.5-(Horizon+1)),0) -> 0 | J31: =IF(AND(J$3>Horizon,J$3<=Horizon+OHYears),CEG_OH*J$4*(1-TaxRate)*(1+OHDisc)^-(J$3+0.5-(Horizon+1)),0) -> 0 | K31: =IF(AND(K$3>Horizon,K$3<=Horizon+OHYears),CEG_OH*K$4*(1-TaxRate)*(1+OHDisc)^-(K$3+0.5-(Horizon+1)),0) -> 381.58254 | L31: =IF(AND(L$3>Horizon,L$3<=Horizon+OHYears),CEG_OH*L$4*(1-TaxRate)*(1+OHDisc)^-(L$3+0.5-(Horizon+1)),0) -> 358.72275 | M31: =IF(AND(M$3>Horizon,M$3<=Horizon+OHYears),CEG_OH*M$4*(1-TaxRate)*(1+OHDisc)^-(M$3+0.5-(Horizon+1)),0) -> 337.23245 | N31: =IF(AND(N$3>Horizon,N$3<=Horizon+OHYears),CEG_OH*N$4*(1-TaxRate)*(1+OHDisc)^-(N$3+0.5-(Horizon+1)),0) -> 317.02958 | ... AS31: =IF(AND(AS$3>Horizon,AS$3<=Horizon+OHYears),CEG_OH*AS$4*(1-TaxRate)*(1+OHDisc)^-(AS$3+0.5-(Horizon+1)),0) -> 0
A32: Equity discount factor | B32: c_dfeq | G32: =(1+EquityDisc)^-(G$3+0.5-ValDate) -> 0.93741118 | H32: =(1+EquityDisc)^-(H$3+0.5-ValDate) -> 0.86001025 | I32: =(1+EquityDisc)^-(I$3+0.5-ValDate) -> 0.78900023 | J32: =(1+EquityDisc)^-(J$3+0.5-ValDate) -> 0.72385342 | K32: =(1+EquityDisc)^-(K$3+0.5-ValDate) -> 0.66408571 | L32: =(1+EquityDisc)^-(L$3+0.5-ValDate) -> 0.60925294 | M32: =(1+EquityDisc)^-(M$3+0.5-ValDate) -> 0.55894766 | N32: =(1+EquityDisc)^-(N$3+0.5-ValDate) -> 0.51279601 | ... AS32: =(1+EquityDisc)^-(AS$3+0.5-ValDate) -> 0.035458732
A35: =CEG_Assets!$A$2 -> Nuclear - PJM East (Limerick, Peach Bottom 50%, Calvert Cliffs, Salem 42.6%)
A36: Operating (1/0) | B36: op | G36: =IF(AND(G$3>=CEG_Assets!$E$2,G$3<=CEG_Assets!$F$2,CEG_Assets!$H$2="Cashflow"),1,0) -> 1 | H36: =IF(AND(H$3>=CEG_Assets!$E$2,H$3<=CEG_Assets!$F$2,CEG_Assets!$H$2="Cashflow"),1,0) -> 1 | I36: =IF(AND(I$3>=CEG_Assets!$E$2,I$3<=CEG_Assets!$F$2,CEG_Assets!$H$2="Cashflow"),1,0) -> 1 | J36: =IF(AND(J$3>=CEG_Assets!$E$2,J$3<=CEG_Assets!$F$2,CEG_Assets!$H$2="Cashflow"),1,0) -> 1 | K36: =IF(AND(K$3>=CEG_Assets!$E$2,K$3<=CEG_Assets!$F$2,CEG_Assets!$H$2="Cashflow"),1,0) -> 1 | L36: =IF(AND(L$3>=CEG_Assets!$E$2,L$3<=CEG_Assets!$F$2,CEG_Assets!$H$2="Cashflow"),1,0) -> 1 | M36: =IF(AND(M$3>=CEG_Assets!$E$2,M$3<=CEG_Assets!$F$2,CEG_Assets!$H$2="Cashflow"),1,0) -> 1 | N36: =IF(AND(N$3>=CEG_Assets!$E$2,N$3<=CEG_Assets!$F$2,CEG_Assets!$H$2="Cashflow"),1,0) -> 1 | ... AS36: =IF(AND(AS$3>=CEG_Assets!$E$2,AS$3<=CEG_Assets!$F$2,CEG_Assets!$H$2="Cashflow"),1,0) -> 0
A37: Contracted MW | B37: cmw | G37: =IF(AND(G$3>=CEG_Assets!$AA$2,G$3<=CEG_Assets!$AB$2),MIN(CEG_Assets!$D$2,CEG_Assets!$Z$2*MIN(1,(G$3-CEG_Assets!$AA$2+1)/MAX(1,CEG_Assets!$AC$2))),0)*G36 -> 0 | H37: =IF(AND(H$3>=CEG_Assets!$AA$2,H$3<=CEG_Assets!$AB$2),MIN(CEG_Assets!$D$2,CEG_Assets!$Z$2*MIN(1,(H$3-CEG_Assets!$AA$2+1)/MAX(1,CEG_Assets!$AC$2))),0)*H36 -> 0 | I37: =IF(AND(I$3>=CEG_Assets!$AA$2,I$3<=CEG_Assets!$AB$2),MIN(CEG_Assets!$D$2,CEG_Assets!$Z$2*MIN(1,(I$3-CEG_Assets!$AA$2+1)/MAX(1,CEG_Assets!$AC$2))),0)*I36 -> 0 | J37: =IF(AND(J$3>=CEG_Assets!$AA$2,J$3<=CEG_Assets!$AB$2),MIN(CEG_Assets!$D$2,CEG_Assets!$Z$2*MIN(1,(J$3-CEG_Assets!$AA$2+1)/MAX(1,CEG_Assets!$AC$2))),0)*J36 -> 0 | K37: =IF(AND(K$3>=CEG_Assets!$AA$2,K$3<=CEG_Assets!$AB$2),MIN(CEG_Assets!$D$2,CEG_Assets!$Z$2*MIN(1,(K$3-CEG_Assets!$AA$2+1)/MAX(1,CEG_Assets!$AC$2))),0)*K36 -> 0 | L37: =IF(AND(L$3>=CEG_Assets!$AA$2,L$3<=CEG_Assets!$AB$2),MIN(CEG_Assets!$D$2,CEG_Assets!$Z$2*MIN(1,(L$3-CEG_Assets!$AA$2+1)/MAX(1,CEG_Assets!$AC$2))),0)*L36 -> 0 | M37: =IF(AND(M$3>=CEG_Assets!$AA$2,M$3<=CEG_Assets!$AB$2),MIN(CEG_Assets!$D$2,CEG_Assets!$Z$2*MIN(1,(M$3-CEG_Assets!$AA$2+1)/MAX(1,CEG_Assets!$AC$2))),0)*M36 -> 0 | N37: =IF(AND(N$3>=CEG_Assets!$AA$2,N$3<=CEG_Assets!$AB$2),MIN(CEG_Assets!$D$2,CEG_Assets!$Z$2*MIN(1,(N$3-CEG_Assets!$AA$2+1)/MAX(1,CEG_Assets!$AC$2))),0)*N36 -> 0 | ... AS37: =IF(AND(AS$3>=CEG_Assets!$AA$2,AS$3<=CEG_Assets!$AB$2),MIN(CEG_Assets!$D$2,CEG_Assets!$Z$2*MIN(1,(AS$3-CEG_Assets!$AA$2+1)/MAX(1,CEG_Assets!$AC$2))),0)*AS36 -> 0
A38: Merchant generation (MWh) | B38: gen_m | G38: =(CEG_Assets!$D$2-G37)*8760*CEG_Assets!$I$2*G36 -> 52665558 | H38: =(CEG_Assets!$D$2-H37)*8760*CEG_Assets!$I$2*H36 -> 52665558 | I38: =(CEG_Assets!$D$2-I37)*8760*CEG_Assets!$I$2*I36 -> 52665558 | J38: =(CEG_Assets!$D$2-J37)*8760*CEG_Assets!$I$2*J36 -> 52665558 | K38: =(CEG_Assets!$D$2-K37)*8760*CEG_Assets!$I$2*K36 -> 52665558 | L38: =(CEG_Assets!$D$2-L37)*8760*CEG_Assets!$I$2*L36 -> 52665558 | M38: =(CEG_Assets!$D$2-M37)*8760*CEG_Assets!$I$2*M36 -> 52665558 | N38: =(CEG_Assets!$D$2-N37)*8760*CEG_Assets!$I$2*N36 -> 52665558 | ... AS38: =(CEG_Assets!$D$2-AS37)*8760*CEG_Assets!$I$2*AS36 -> 0
A39: Contracted generation (MWh) | B39: gen_c | G39: =G37*8760*CEG_Assets!$I$2*G36 -> 0 | H39: =H37*8760*CEG_Assets!$I$2*H36 -> 0 | I39: =I37*8760*CEG_Assets!$I$2*I36 -> 0 | J39: =J37*8760*CEG_Assets!$I$2*J36 -> 0 | K39: =K37*8760*CEG_Assets!$I$2*K36 -> 0 | L39: =L37*8760*CEG_Assets!$I$2*L36 -> 0 | M39: =M37*8760*CEG_Assets!$I$2*M36 -> 0 | N39: =N37*8760*CEG_Assets!$I$2*N36 -> 0 | ... AS39: =AS37*8760*CEG_Assets!$I$2*AS36 -> 0
A40: Fuel price, delivered ($/MMBtu) | B40: fuelp | G40: =IF(ISNUMBER(CEG_Assets!$L$2),CEG_Assets!$L$2*G$4,INDEX(Prices!G:G,CEG_Assets!$AO$2)+FuelAdder*G$4) -> 3.927 | H40: =IF(ISNUMBER(CEG_Assets!$L$2),CEG_Assets!$L$2*H$4,INDEX(Prices!H:H,CEG_Assets!$AO$2)+FuelAdder*H$4) -> 4.00554 | I40: =IF(ISNUMBER(CEG_Assets!$L$2),CEG_Assets!$L$2*I$4,INDEX(Prices!I:I,CEG_Assets!$AO$2)+FuelAdder*I$4) -> 4.1917716 | J40: =IF(ISNUMBER(CEG_Assets!$L$2),CEG_Assets!$L$2*J$4,INDEX(Prices!J:J,CEG_Assets!$AO$2)+FuelAdder*J$4) -> 4.275607 | K40: =IF(ISNUMBER(CEG_Assets!$L$2),CEG_Assets!$L$2*K$4,INDEX(Prices!K:K,CEG_Assets!$AO$2)+FuelAdder*K$4) -> 4.3611192 | L40: =IF(ISNUMBER(CEG_Assets!$L$2),CEG_Assets!$L$2*L$4,INDEX(Prices!L:L,CEG_Assets!$AO$2)+FuelAdder*L$4) -> 4.4483416 | M40: =IF(ISNUMBER(CEG_Assets!$L$2),CEG_Assets!$L$2*M$4,INDEX(Prices!M:M,CEG_Assets!$AO$2)+FuelAdder*M$4) -> 4.5373084 | N40: =IF(ISNUMBER(CEG_Assets!$L$2),CEG_Assets!$L$2*N$4,INDEX(Prices!N:N,CEG_Assets!$AO$2)+FuelAdder*N$4) -> 4.6280546 | O40: =IF(ISNUMBER(CEG_Assets!$L$2),CEG_Assets!$L$2*O$4,INDEX(Prices!O:O,CEG_Assets!$AO$2)+FuelAdder*O$4) -> 4.7206156 | P40: =IF(ISNUMBER(CEG_Assets!$L$2),CEG_Assets!$L$2*P$4,INDEX(Prices!P:P,CEG_Assets!$AO$2)+FuelAdder*P$4) -> 4.815028 | Q40: =IF(ISNUMBER(CEG_Assets!$L$2),CEG_Assets!$L$2*Q$4,INDEX(Prices!Q:Q,CEG_Assets!$AO$2)+FuelAdder*Q$4) -> 4.9113285 | R40: =IF(ISNUMBER(CEG_Assets!$L$2),CEG_Assets!$L$2*R$4,INDEX(Prices!R:R,CEG_Assets!$AO$2)+FuelAdder*R$4) -> 5.0095551 | S40: =IF(ISNUMBER(CEG_Assets!$L$2),CEG_Assets!$L$2*S$4,INDEX(Prices!S:S,CEG_Assets!$AO$2)+FuelAdder*S$4) -> 5.1097462 | T40: =IF(ISNUMBER(CEG_Assets!$L$2),CEG_Assets!$L$2*T$4,INDEX(Prices!T:T,CEG_Assets!$AO$2)+FuelAdder*T$4) -> 5.2119411 | U40: =IF(ISNUMBER(CEG_Assets!$L$2),CEG_Assets!$L$2*U$4,INDEX(Prices!U:U,CEG_Assets!$AO$2)+FuelAdder*U$4) -> 5.3161799 | V40: =IF(ISNUMBER(CEG_Assets!$L$2),CEG_Assets!$L$2*V$4,INDEX(Prices!V:V,CEG_Assets!$AO$2)+FuelAdder*V$4) -> 5.4225035 | W40: =IF(ISNUMBER(CEG_Assets!$L$2),CEG_Assets!$L$2*W$4,INDEX(Prices!W:W,CEG_Assets!$AO$2)+FuelAdder*W$4) -> 5.5309536 | X40: =IF(ISNUMBER(CEG_Assets!$L$2),CEG_Assets!$L$2*X$4,INDEX(Prices!X:X,CEG_Assets!$AO$2)+FuelAdder*X$4) -> 5.6415727 | Y40: =IF(ISNUMBER(CEG_Assets!$L$2),CEG_Assets!$L$2*Y$4,INDEX(Prices!Y:Y,CEG_Assets!$AO$2)+FuelAdder*Y$4) -> 5.7544041 | Z40: =IF(ISNUMBER(CEG_Assets!$L$2),CEG_Assets!$L$2*Z$4,INDEX(Prices!Z:Z,CEG_Assets!$AO$2)+FuelAdder*Z$4) -> 5.8694922 | AA40: =IF(ISNUMBER(CEG_Assets!$L$2),CEG_Assets!$L$2*AA$4,INDEX(Prices!AA:AA,CEG_Assets!$AO$2)+FuelAdder*AA$4) -> 5.9868821 | AB40: =IF(ISNUMBER(CEG_Assets!$L$2),CEG_Assets!$L$2*AB$4,INDEX(Prices!AB:AB,CEG_Assets!$AO$2)+FuelAdder*AB$4) -> 6.1066197 | AC40: =IF(ISNUMBER(CEG_Assets!$L$2),CEG_Assets!$L$2*AC$4,INDEX(Prices!AC:AC,CEG_Assets!$AO$2)+FuelAdder*AC$4) -> 6.2287521 | AD40: =IF(ISNUMBER(CEG_Assets!$L$2),CEG_Assets!$L$2*AD$4,INDEX(Prices!AD:AD,CEG_Assets!$AO$2)+FuelAdder*AD$4) -> 6.3533271 | AE40: =IF(ISNUMBER(CEG_Assets!$L$2),CEG_Assets!$L$2*AE$4,INDEX(Prices!AE:AE,CEG_Assets!$AO$2)+FuelAdder*AE$4) -> 6.4803937 | AF40: =IF(ISNUMBER(CEG_Assets!$L$2),CEG_Assets!$L$2*AF$4,INDEX(Prices!AF:AF,CEG_Assets!$AO$2)+FuelAdder*AF$4) -> 6.6100016 | AG40: =IF(ISNUMBER(CEG_Assets!$L$2),CEG_Assets!$L$2*AG$4,INDEX(Prices!AG:AG,CEG_Assets!$AO$2)+FuelAdder*AG$4) -> 6.7422016 | AH40: =IF(ISNUMBER(CEG_Assets!$L$2),CEG_Assets!$L$2*AH$4,INDEX(Prices!AH:AH,CEG_Assets!$AO$2)+FuelAdder*AH$4) -> 6.8770456 | AI40: =IF(ISNUMBER(CEG_Assets!$L$2),CEG_Assets!$L$2*AI$4,INDEX(Prices!AI:AI,CEG_Assets!$AO$2)+FuelAdder*AI$4) -> 7.0145865 | AJ40: =IF(ISNUMBER(CEG_Assets!$L$2),CEG_Assets!$L$2*AJ$4,INDEX(Prices!AJ:AJ,CEG_Assets!$AO$2)+FuelAdder*AJ$4) -> 7.1548783 | AK40: =IF(ISNUMBER(CEG_Assets!$L$2),CEG_Assets!$L$2*AK$4,INDEX(Prices!AK:AK,CEG_Assets!$AO$2)+FuelAdder*AK$4) -> 7.2979758 | AL40: =IF(ISNUMBER(CEG_Assets!$L$2),CEG_Assets!$L$2*AL$4,INDEX(Prices!AL:AL,CEG_Assets!$AO$2)+FuelAdder*AL$4) -> 7.4439353 | AM40: =IF(ISNUMBER(CEG_Assets!$L$2),CEG_Assets!$L$2*AM$4,INDEX(Prices!AM:AM,CEG_Assets!$AO$2)+FuelAdder*AM$4) -> 7.592814 | AN40: =IF(ISNUMBER(CEG_Assets!$L$2),CEG_Assets!$L$2*AN$4,INDEX(Prices!AN:AN,CEG_Assets!$AO$2)+FuelAdder*AN$4) -> 7.7446703 | AO40: =IF(ISNUMBER(CEG_Assets!$L$2),CEG_Assets!$L$2*AO$4,INDEX(Prices!AO:AO,CEG_Assets!$AO$2)+FuelAdder*AO$4) -> 7.8995637 | AP40: =IF(ISNUMBER(CEG_Assets!$L$2),CEG_Assets!$L$2*AP$4,INDEX(Prices!AP:AP,CEG_Assets!$AO$2)+FuelAdder*AP$4) -> 8.057555 | AQ40: =IF(ISNUMBER(CEG_Assets!$L$2),CEG_Assets!$L$2*AQ$4,INDEX(Prices!AQ:AQ,CEG_Assets!$AO$2)+FuelAdder*AQ$4) -> 8.2187061 | AR40: =IF(ISNUMBER(CEG_Assets!$L$2),CEG_Assets!$L$2*AR$4,INDEX(Prices!AR:AR,CEG_Assets!$AO$2)+FuelAdder*AR$4) -> 8.3830802 | AS40: =IF(ISNUMBER(CEG_Assets!$L$2),CEG_Assets!$L$2*AS$4,INDEX(Prices!AS:AS,CEG_Assets!$AO$2)+FuelAdder*AS$4) -> 8.5507418
A41: Spread vs fuel ($/MWh) | B41: spark | G41: =INDEX(Prices!G:G,CEG_Assets!$AN$2)*CEG_Assets!$J$2-CEG_Assets!$K$2*G40-CEG_Assets!$M$2*G$4 -> 71.28 | H41: =INDEX(Prices!H:H,CEG_Assets!$AN$2)*CEG_Assets!$J$2-CEG_Assets!$K$2*H40-CEG_Assets!$M$2*H$4 -> 72.27 | I41: =INDEX(Prices!I:I,CEG_Assets!$AN$2)*CEG_Assets!$J$2-CEG_Assets!$K$2*I40-CEG_Assets!$M$2*I$4 -> 66.28607 | J41: =INDEX(Prices!J:J,CEG_Assets!$AN$2)*CEG_Assets!$J$2-CEG_Assets!$K$2*J40-CEG_Assets!$M$2*J$4 -> 64.537582 | K41: =INDEX(Prices!K:K,CEG_Assets!$AN$2)*CEG_Assets!$J$2-CEG_Assets!$K$2*K40-CEG_Assets!$M$2*K$4 -> 65.828334 | L41: =INDEX(Prices!L:L,CEG_Assets!$AN$2)*CEG_Assets!$J$2-CEG_Assets!$K$2*L40-CEG_Assets!$M$2*L$4 -> 67.1449 | M41: =INDEX(Prices!M:M,CEG_Assets!$AN$2)*CEG_Assets!$J$2-CEG_Assets!$K$2*M40-CEG_Assets!$M$2*M$4 -> 68.487798 | N41: =INDEX(Prices!N:N,CEG_Assets!$AN$2)*CEG_Assets!$J$2-CEG_Assets!$K$2*N40-CEG_Assets!$M$2*N$4 -> 69.857554 | O41: =INDEX(Prices!O:O,CEG_Assets!$AN$2)*CEG_Assets!$J$2-CEG_Assets!$K$2*O40-CEG_Assets!$M$2*O$4 -> 71.254705 | P41: =INDEX(Prices!P:P,CEG_Assets!$AN$2)*CEG_Assets!$J$2-CEG_Assets!$K$2*P40-CEG_Assets!$M$2*P$4 -> 72.6798 | Q41: =INDEX(Prices!Q:Q,CEG_Assets!$AN$2)*CEG_Assets!$J$2-CEG_Assets!$K$2*Q40-CEG_Assets!$M$2*Q$4 -> 74.133396 | R41: =INDEX(Prices!R:R,CEG_Assets!$AN$2)*CEG_Assets!$J$2-CEG_Assets!$K$2*R40-CEG_Assets!$M$2*R$4 -> 75.616063 | S41: =INDEX(Prices!S:S,CEG_Assets!$AN$2)*CEG_Assets!$J$2-CEG_Assets!$K$2*S40-CEG_Assets!$M$2*S$4 -> 77.128385 | T41: =INDEX(Prices!T:T,CEG_Assets!$AN$2)*CEG_Assets!$J$2-CEG_Assets!$K$2*T40-CEG_Assets!$M$2*T$4 -> 78.670952 | U41: =INDEX(Prices!U:U,CEG_Assets!$AN$2)*CEG_Assets!$J$2-CEG_Assets!$K$2*U40-CEG_Assets!$M$2*U$4 -> 80.244371 | V41: =INDEX(Prices!V:V,CEG_Assets!$AN$2)*CEG_Assets!$J$2-CEG_Assets!$K$2*V40-CEG_Assets!$M$2*V$4 -> 81.849259 | W41: =INDEX(Prices!W:W,CEG_Assets!$AN$2)*CEG_Assets!$J$2-CEG_Assets!$K$2*W40-CEG_Assets!$M$2*W$4 -> 83.486244 | X41: =INDEX(Prices!X:X,CEG_Assets!$AN$2)*CEG_Assets!$J$2-CEG_Assets!$K$2*X40-CEG_Assets!$M$2*X$4 -> 85.155969 | Y41: =INDEX(Prices!Y:Y,CEG_Assets!$AN$2)*CEG_Assets!$J$2-CEG_Assets!$K$2*Y40-CEG_Assets!$M$2*Y$4 -> 86.859088 | Z41: =INDEX(Prices!Z:Z,CEG_Assets!$AN$2)*CEG_Assets!$J$2-CEG_Assets!$K$2*Z40-CEG_Assets!$M$2*Z$4 -> 88.59627 | AA41: =INDEX(Prices!AA:AA,CEG_Assets!$AN$2)*CEG_Assets!$J$2-CEG_Assets!$K$2*AA40-CEG_Assets!$M$2*AA$4 -> 90.368196 | AB41: =INDEX(Prices!AB:AB,CEG_Assets!$AN$2)*CEG_Assets!$J$2-CEG_Assets!$K$2*AB40-CEG_Assets!$M$2*AB$4 -> 92.175559 | AC41: =INDEX(Prices!AC:AC,CEG_Assets!$AN$2)*CEG_Assets!$J$2-CEG_Assets!$K$2*AC40-CEG_Assets!$M$2*AC$4 -> 94.019071 | AD41: =INDEX(Prices!AD:AD,CEG_Assets!$AN$2)*CEG_Assets!$J$2-CEG_Assets!$K$2*AD40-CEG_Assets!$M$2*AD$4 -> 95.899452 | AE41: =INDEX(Prices!AE:AE,CEG_Assets!$AN$2)*CEG_Assets!$J$2-CEG_Assets!$K$2*AE40-CEG_Assets!$M$2*AE$4 -> 97.817441 | AF41: =INDEX(Prices!AF:AF,CEG_Assets!$AN$2)*CEG_Assets!$J$2-CEG_Assets!$K$2*AF40-CEG_Assets!$M$2*AF$4 -> 99.77379 | AG41: =INDEX(Prices!AG:AG,CEG_Assets!$AN$2)*CEG_Assets!$J$2-CEG_Assets!$K$2*AG40-CEG_Assets!$M$2*AG$4 -> 101.76927 | AH41: =INDEX(Prices!AH:AH,CEG_Assets!$AN$2)*CEG_Assets!$J$2-CEG_Assets!$K$2*AH40-CEG_Assets!$M$2*AH$4 -> 103.80465 | AI41: =INDEX(Prices!AI:AI,CEG_Assets!$AN$2)*CEG_Assets!$J$2-CEG_Assets!$K$2*AI40-CEG_Assets!$M$2*AI$4 -> 105.88074 | AJ41: =INDEX(Prices!AJ:AJ,CEG_Assets!$AN$2)*CEG_Assets!$J$2-CEG_Assets!$K$2*AJ40-CEG_Assets!$M$2*AJ$4 -> 107.99836 | AK41: =INDEX(Prices!AK:AK,CEG_Assets!$AN$2)*CEG_Assets!$J$2-CEG_Assets!$K$2*AK40-CEG_Assets!$M$2*AK$4 -> 110.15833 | AL41: =INDEX(Prices!AL:AL,CEG_Assets!$AN$2)*CEG_Assets!$J$2-CEG_Assets!$K$2*AL40-CEG_Assets!$M$2*AL$4 -> 112.36149 | AM41: =INDEX(Prices!AM:AM,CEG_Assets!$AN$2)*CEG_Assets!$J$2-CEG_Assets!$K$2*AM40-CEG_Assets!$M$2*AM$4 -> 114.60872 | AN41: =INDEX(Prices!AN:AN,CEG_Assets!$AN$2)*CEG_Assets!$J$2-CEG_Assets!$K$2*AN40-CEG_Assets!$M$2*AN$4 -> 116.9009 | AO41: =INDEX(Prices!AO:AO,CEG_Assets!$AN$2)*CEG_Assets!$J$2-CEG_Assets!$K$2*AO40-CEG_Assets!$M$2*AO$4 -> 119.23891 | AP41: =INDEX(Prices!AP:AP,CEG_Assets!$AN$2)*CEG_Assets!$J$2-CEG_Assets!$K$2*AP40-CEG_Assets!$M$2*AP$4 -> 121.62369 | AQ41: =INDEX(Prices!AQ:AQ,CEG_Assets!$AN$2)*CEG_Assets!$J$2-CEG_Assets!$K$2*AQ40-CEG_Assets!$M$2*AQ$4 -> 124.05617 | AR41: =INDEX(Prices!AR:AR,CEG_Assets!$AN$2)*CEG_Assets!$J$2-CEG_Assets!$K$2*AR40-CEG_Assets!$M$2*AR$4 -> 126.53729 | AS41: =INDEX(Prices!AS:AS,CEG_Assets!$AN$2)*CEG_Assets!$J$2-CEG_Assets!$K$2*AS40-CEG_Assets!$M$2*AS$4 -> 129.06804
A42: Runs (1/0) | B42: run | G42: =IF(CEG_Assets!$X$2=1,IF(G41>0,1,0),1) -> 1 | H42: =IF(CEG_Assets!$X$2=1,IF(H41>0,1,0),1) -> 1 | I42: =IF(CEG_Assets!$X$2=1,IF(I41>0,1,0),1) -> 1 | J42: =IF(CEG_Assets!$X$2=1,IF(J41>0,1,0),1) -> 1 | K42: =IF(CEG_Assets!$X$2=1,IF(K41>0,1,0),1) -> 1 | L42: =IF(CEG_Assets!$X$2=1,IF(L41>0,1,0),1) -> 1 | M42: =IF(CEG_Assets!$X$2=1,IF(M41>0,1,0),1) -> 1 | N42: =IF(CEG_Assets!$X$2=1,IF(N41>0,1,0),1) -> 1 | ... AS42: =IF(CEG_Assets!$X$2=1,IF(AS41>0,1,0),1) -> 1
A43: Merchant energy revenue ($mm) | B43: energy | C43: =SUM(G43:AS43) -> 125495.44 | G43: =G38*INDEX(Prices!G:G,CEG_Assets!$AN$2)*CEG_Assets!$J$2*G42/1000000*(1+CEG_RevAdj) -> 3754.001 | H43: =H38*INDEX(Prices!H:H,CEG_Assets!$AN$2)*CEG_Assets!$J$2*H42/1000000*(1+CEG_RevAdj) -> 3806.1399 | I43: =I38*INDEX(Prices!I:I,CEG_Assets!$AN$2)*CEG_Assets!$J$2*I42/1000000*(1+CEG_RevAdj) -> 3490.9928 | J43: =J38*INDEX(Prices!J:J,CEG_Assets!$AN$2)*CEG_Assets!$J$2*J42/1000000*(1+CEG_RevAdj) -> 3398.9078 | K43: =K38*INDEX(Prices!K:K,CEG_Assets!$AN$2)*CEG_Assets!$J$2*K42/1000000*(1+CEG_RevAdj) -> 3466.8859 | L43: =L38*INDEX(Prices!L:L,CEG_Assets!$AN$2)*CEG_Assets!$J$2*L42/1000000*(1+CEG_RevAdj) -> 3536.2236 | M43: =M38*INDEX(Prices!M:M,CEG_Assets!$AN$2)*CEG_Assets!$J$2*M42/1000000*(1+CEG_RevAdj) -> 3606.9481 | N43: =N38*INDEX(Prices!N:N,CEG_Assets!$AN$2)*CEG_Assets!$J$2*N42/1000000*(1+CEG_RevAdj) -> 3679.0871 | O43: =O38*INDEX(Prices!O:O,CEG_Assets!$AN$2)*CEG_Assets!$J$2*O42/1000000*(1+CEG_RevAdj) -> 3752.6688 | P43: =P38*INDEX(Prices!P:P,CEG_Assets!$AN$2)*CEG_Assets!$J$2*P42/1000000*(1+CEG_RevAdj) -> 3827.7222 | Q43: =Q38*INDEX(Prices!Q:Q,CEG_Assets!$AN$2)*CEG_Assets!$J$2*Q42/1000000*(1+CEG_RevAdj) -> 3904.2766 | R43: =R38*INDEX(Prices!R:R,CEG_Assets!$AN$2)*CEG_Assets!$J$2*R42/1000000*(1+CEG_RevAdj) -> 3982.3622 | S43: =S38*INDEX(Prices!S:S,CEG_Assets!$AN$2)*CEG_Assets!$J$2*S42/1000000*(1+CEG_RevAdj) -> 4062.0094 | T43: =T38*INDEX(Prices!T:T,CEG_Assets!$AN$2)*CEG_Assets!$J$2*T42/1000000*(1+CEG_RevAdj) -> 4143.2496 | U43: =U38*INDEX(Prices!U:U,CEG_Assets!$AN$2)*CEG_Assets!$J$2*U42/1000000*(1+CEG_RevAdj) -> 4226.1146 | V43: =V38*INDEX(Prices!V:V,CEG_Assets!$AN$2)*CEG_Assets!$J$2*V42/1000000*(1+CEG_RevAdj) -> 4310.6369 | W43: =W38*INDEX(Prices!W:W,CEG_Assets!$AN$2)*CEG_Assets!$J$2*W42/1000000*(1+CEG_RevAdj) -> 4396.8496 | X43: =X38*INDEX(Prices!X:X,CEG_Assets!$AN$2)*CEG_Assets!$J$2*X42/1000000*(1+CEG_RevAdj) -> 4484.7866 | Y43: =Y38*INDEX(Prices!Y:Y,CEG_Assets!$AN$2)*CEG_Assets!$J$2*Y42/1000000*(1+CEG_RevAdj) -> 4574.4824 | Z43: =Z38*INDEX(Prices!Z:Z,CEG_Assets!$AN$2)*CEG_Assets!$J$2*Z42/1000000*(1+CEG_RevAdj) -> 4665.972 | AA43: =AA38*INDEX(Prices!AA:AA,CEG_Assets!$AN$2)*CEG_Assets!$J$2*AA42/1000000*(1+CEG_RevAdj) -> 4759.2914 | AB43: =AB38*INDEX(Prices!AB:AB,CEG_Assets!$AN$2)*CEG_Assets!$J$2*AB42/1000000*(1+CEG_RevAdj) -> 4854.4773 | AC43: =AC38*INDEX(Prices!AC:AC,CEG_Assets!$AN$2)*CEG_Assets!$J$2*AC42/1000000*(1+CEG_RevAdj) -> 4951.5668 | AD43: =AD38*INDEX(Prices!AD:AD,CEG_Assets!$AN$2)*CEG_Assets!$J$2*AD42/1000000*(1+CEG_RevAdj) -> 5050.5982 | AE43: =AE38*INDEX(Prices!AE:AE,CEG_Assets!$AN$2)*CEG_Assets!$J$2*AE42/1000000*(1+CEG_RevAdj) -> 5151.6101 | AF43: =AF38*INDEX(Prices!AF:AF,CEG_Assets!$AN$2)*CEG_Assets!$J$2*AF42/1000000*(1+CEG_RevAdj) -> 5254.6423 | AG43: =AG38*INDEX(Prices!AG:AG,CEG_Assets!$AN$2)*CEG_Assets!$J$2*AG42/1000000*(1+CEG_RevAdj) -> 5359.7352 | AH43: =AH38*INDEX(Prices!AH:AH,CEG_Assets!$AN$2)*CEG_Assets!$J$2*AH42/1000000*(1+CEG_RevAdj) -> 5466.9299 | AI43: =AI38*INDEX(Prices!AI:AI,CEG_Assets!$AN$2)*CEG_Assets!$J$2*AI42/1000000*(1+CEG_RevAdj) -> 5576.2685 | AJ43: =AJ38*INDEX(Prices!AJ:AJ,CEG_Assets!$AN$2)*CEG_Assets!$J$2*AJ42/1000000*(1+CEG_RevAdj) -> 0 | AK43: =AK38*INDEX(Prices!AK:AK,CEG_Assets!$AN$2)*CEG_Assets!$J$2*AK42/1000000*(1+CEG_RevAdj) -> 0 | AL43: =AL38*INDEX(Prices!AL:AL,CEG_Assets!$AN$2)*CEG_Assets!$J$2*AL42/1000000*(1+CEG_RevAdj) -> 0 | AM43: =AM38*INDEX(Prices!AM:AM,CEG_Assets!$AN$2)*CEG_Assets!$J$2*AM42/1000000*(1+CEG_RevAdj) -> 0 | AN43: =AN38*INDEX(Prices!AN:AN,CEG_Assets!$AN$2)*CEG_Assets!$J$2*AN42/1000000*(1+CEG_RevAdj) -> 0 | AO43: =AO38*INDEX(Prices!AO:AO,CEG_Assets!$AN$2)*CEG_Assets!$J$2*AO42/1000000*(1+CEG_RevAdj) -> 0 | AP43: =AP38*INDEX(Prices!AP:AP,CEG_Assets!$AN$2)*CEG_Assets!$J$2*AP42/1000000*(1+CEG_RevAdj) -> 0 | AQ43: =AQ38*INDEX(Prices!AQ:AQ,CEG_Assets!$AN$2)*CEG_Assets!$J$2*AQ42/1000000*(1+CEG_RevAdj) -> 0 | AR43: =AR38*INDEX(Prices!AR:AR,CEG_Assets!$AN$2)*CEG_Assets!$J$2*AR42/1000000*(1+CEG_RevAdj) -> 0 | AS43: =AS38*INDEX(Prices!AS:AS,CEG_Assets!$AN$2)*CEG_Assets!$J$2*AS42/1000000*(1+CEG_RevAdj) -> 0
A44: Capacity revenue ($mm) | B44: capacity | C44: =SUM(G44:AS44) -> 20781.375 | G44: =(CEG_Assets!$D$2-G37)*INDEX(Prices!G:G,CEG_Assets!$AP$2)*365*CEG_Assets!$T$2*G36/1000000*(1+CEG_RevAdj) -> 739.46997 | H44: =(CEG_Assets!$D$2-H37)*INDEX(Prices!H:H,CEG_Assets!$AP$2)*365*CEG_Assets!$T$2*H36/1000000*(1+CEG_RevAdj) -> 732.46901 | I44: =(CEG_Assets!$D$2-I37)*INDEX(Prices!I:I,CEG_Assets!$AP$2)*365*CEG_Assets!$T$2*I36/1000000*(1+CEG_RevAdj) -> 619.37333 | J44: =(CEG_Assets!$D$2-J37)*INDEX(Prices!J:J,CEG_Assets!$AP$2)*365*CEG_Assets!$T$2*J36/1000000*(1+CEG_RevAdj) -> 555.08049 | K44: =(CEG_Assets!$D$2-K37)*INDEX(Prices!K:K,CEG_Assets!$AP$2)*365*CEG_Assets!$T$2*K36/1000000*(1+CEG_RevAdj) -> 566.1821 | L44: =(CEG_Assets!$D$2-L37)*INDEX(Prices!L:L,CEG_Assets!$AP$2)*365*CEG_Assets!$T$2*L36/1000000*(1+CEG_RevAdj) -> 577.50575 | M44: =(CEG_Assets!$D$2-M37)*INDEX(Prices!M:M,CEG_Assets!$AP$2)*365*CEG_Assets!$T$2*M36/1000000*(1+CEG_RevAdj) -> 589.05586 | N44: =(CEG_Assets!$D$2-N37)*INDEX(Prices!N:N,CEG_Assets!$AP$2)*365*CEG_Assets!$T$2*N36/1000000*(1+CEG_RevAdj) -> 600.83698 | O44: =(CEG_Assets!$D$2-O37)*INDEX(Prices!O:O,CEG_Assets!$AP$2)*365*CEG_Assets!$T$2*O36/1000000*(1+CEG_RevAdj) -> 612.85372 | P44: =(CEG_Assets!$D$2-P37)*INDEX(Prices!P:P,CEG_Assets!$AP$2)*365*CEG_Assets!$T$2*P36/1000000*(1+CEG_RevAdj) -> 625.11079 | Q44: =(CEG_Assets!$D$2-Q37)*INDEX(Prices!Q:Q,CEG_Assets!$AP$2)*365*CEG_Assets!$T$2*Q36/1000000*(1+CEG_RevAdj) -> 637.61301 | R44: =(CEG_Assets!$D$2-R37)*INDEX(Prices!R:R,CEG_Assets!$AP$2)*365*CEG_Assets!$T$2*R36/1000000*(1+CEG_RevAdj) -> 650.36527 | S44: =(CEG_Assets!$D$2-S37)*INDEX(Prices!S:S,CEG_Assets!$AP$2)*365*CEG_Assets!$T$2*S36/1000000*(1+CEG_RevAdj) -> 663.37257 | T44: =(CEG_Assets!$D$2-T37)*INDEX(Prices!T:T,CEG_Assets!$AP$2)*365*CEG_Assets!$T$2*T36/1000000*(1+CEG_RevAdj) -> 676.64002 | U44: =(CEG_Assets!$D$2-U37)*INDEX(Prices!U:U,CEG_Assets!$AP$2)*365*CEG_Assets!$T$2*U36/1000000*(1+CEG_RevAdj) -> 690.17282 | V44: =(CEG_Assets!$D$2-V37)*INDEX(Prices!V:V,CEG_Assets!$AP$2)*365*CEG_Assets!$T$2*V36/1000000*(1+CEG_RevAdj) -> 703.97628 | W44: =(CEG_Assets!$D$2-W37)*INDEX(Prices!W:W,CEG_Assets!$AP$2)*365*CEG_Assets!$T$2*W36/1000000*(1+CEG_RevAdj) -> 718.05581 | X44: =(CEG_Assets!$D$2-X37)*INDEX(Prices!X:X,CEG_Assets!$AP$2)*365*CEG_Assets!$T$2*X36/1000000*(1+CEG_RevAdj) -> 732.41692 | Y44: =(CEG_Assets!$D$2-Y37)*INDEX(Prices!Y:Y,CEG_Assets!$AP$2)*365*CEG_Assets!$T$2*Y36/1000000*(1+CEG_RevAdj) -> 747.06526 | Z44: =(CEG_Assets!$D$2-Z37)*INDEX(Prices!Z:Z,CEG_Assets!$AP$2)*365*CEG_Assets!$T$2*Z36/1000000*(1+CEG_RevAdj) -> 762.00657 | AA44: =(CEG_Assets!$D$2-AA37)*INDEX(Prices!AA:AA,CEG_Assets!$AP$2)*365*CEG_Assets!$T$2*AA36/1000000*(1+CEG_RevAdj) -> 777.2467 | AB44: =(CEG_Assets!$D$2-AB37)*INDEX(Prices!AB:AB,CEG_Assets!$AP$2)*365*CEG_Assets!$T$2*AB36/1000000*(1+CEG_RevAdj) -> 792.79163 | AC44: =(CEG_Assets!$D$2-AC37)*INDEX(Prices!AC:AC,CEG_Assets!$AP$2)*365*CEG_Assets!$T$2*AC36/1000000*(1+CEG_RevAdj) -> 808.64746 | AD44: =(CEG_Assets!$D$2-AD37)*INDEX(Prices!AD:AD,CEG_Assets!$AP$2)*365*CEG_Assets!$T$2*AD36/1000000*(1+CEG_RevAdj) -> 824.82041 | AE44: =(CEG_Assets!$D$2-AE37)*INDEX(Prices!AE:AE,CEG_Assets!$AP$2)*365*CEG_Assets!$T$2*AE36/1000000*(1+CEG_RevAdj) -> 841.31682 | AF44: =(CEG_Assets!$D$2-AF37)*INDEX(Prices!AF:AF,CEG_Assets!$AP$2)*365*CEG_Assets!$T$2*AF36/1000000*(1+CEG_RevAdj) -> 858.14316 | AG44: =(CEG_Assets!$D$2-AG37)*INDEX(Prices!AG:AG,CEG_Assets!$AP$2)*365*CEG_Assets!$T$2*AG36/1000000*(1+CEG_RevAdj) -> 875.30602 | AH44: =(CEG_Assets!$D$2-AH37)*INDEX(Prices!AH:AH,CEG_Assets!$AP$2)*365*CEG_Assets!$T$2*AH36/1000000*(1+CEG_RevAdj) -> 892.81214 | AI44: =(CEG_Assets!$D$2-AI37)*INDEX(Prices!AI:AI,CEG_Assets!$AP$2)*365*CEG_Assets!$T$2*AI36/1000000*(1+CEG_RevAdj) -> 910.66839 | AJ44: =(CEG_Assets!$D$2-AJ37)*INDEX(Prices!AJ:AJ,CEG_Assets!$AP$2)*365*CEG_Assets!$T$2*AJ36/1000000*(1+CEG_RevAdj) -> 0 | AK44: =(CEG_Assets!$D$2-AK37)*INDEX(Prices!AK:AK,CEG_Assets!$AP$2)*365*CEG_Assets!$T$2*AK36/1000000*(1+CEG_RevAdj) -> 0 | AL44: =(CEG_Assets!$D$2-AL37)*INDEX(Prices!AL:AL,CEG_Assets!$AP$2)*365*CEG_Assets!$T$2*AL36/1000000*(1+CEG_RevAdj) -> 0 | AM44: =(CEG_Assets!$D$2-AM37)*INDEX(Prices!AM:AM,CEG_Assets!$AP$2)*365*CEG_Assets!$T$2*AM36/1000000*(1+CEG_RevAdj) -> 0 | AN44: =(CEG_Assets!$D$2-AN37)*INDEX(Prices!AN:AN,CEG_Assets!$AP$2)*365*CEG_Assets!$T$2*AN36/1000000*(1+CEG_RevAdj) -> 0 | AO44: =(CEG_Assets!$D$2-AO37)*INDEX(Prices!AO:AO,CEG_Assets!$AP$2)*365*CEG_Assets!$T$2*AO36/1000000*(1+CEG_RevAdj) -> 0 | AP44: =(CEG_Assets!$D$2-AP37)*INDEX(Prices!AP:AP,CEG_Assets!$AP$2)*365*CEG_Assets!$T$2*AP36/1000000*(1+CEG_RevAdj) -> 0 | AQ44: =(CEG_Assets!$D$2-AQ37)*INDEX(Prices!AQ:AQ,CEG_Assets!$AP$2)*365*CEG_Assets!$T$2*AQ36/1000000*(1+CEG_RevAdj) -> 0 | AR44: =(CEG_Assets!$D$2-AR37)*INDEX(Prices!AR:AR,CEG_Assets!$AP$2)*365*CEG_Assets!$T$2*AR36/1000000*(1+CEG_RevAdj) -> 0 | AS44: =(CEG_Assets!$D$2-AS37)*INDEX(Prices!AS:AS,CEG_Assets!$AP$2)*365*CEG_Assets!$T$2*AS36/1000000*(1+CEG_RevAdj) -> 0
A45: Long-term PPA revenue ($mm) | B45: ppa | C45: =SUM(G45:AS45) -> 0 | G45: =G39*(CEG_Assets!$AD$2+CEG_PPAAdj)/1000000*(1+CEG_RevAdj) -> 0 | H45: =H39*(CEG_Assets!$AD$2+CEG_PPAAdj)/1000000*(1+CEG_RevAdj) -> 0 | I45: =I39*(CEG_Assets!$AD$2+CEG_PPAAdj)/1000000*(1+CEG_RevAdj) -> 0 | J45: =J39*(CEG_Assets!$AD$2+CEG_PPAAdj)/1000000*(1+CEG_RevAdj) -> 0 | K45: =K39*(CEG_Assets!$AD$2+CEG_PPAAdj)/1000000*(1+CEG_RevAdj) -> 0 | L45: =L39*(CEG_Assets!$AD$2+CEG_PPAAdj)/1000000*(1+CEG_RevAdj) -> 0 | M45: =M39*(CEG_Assets!$AD$2+CEG_PPAAdj)/1000000*(1+CEG_RevAdj) -> 0 | N45: =N39*(CEG_Assets!$AD$2+CEG_PPAAdj)/1000000*(1+CEG_RevAdj) -> 0 | ... AS45: =AS39*(CEG_Assets!$AD$2+CEG_PPAAdj)/1000000*(1+CEG_RevAdj) -> 0
A46: ZEC revenue ($mm) | B46: zec | C46: =SUM(G46:AS46) -> 0 | G46: =IF(G$3<=CEG_Assets!$V$2,G38*CEG_Assets!$U$2,0)/1000000*(1+CEG_RevAdj) -> 0 | H46: =IF(H$3<=CEG_Assets!$V$2,H38*CEG_Assets!$U$2,0)/1000000*(1+CEG_RevAdj) -> 0 | I46: =IF(I$3<=CEG_Assets!$V$2,I38*CEG_Assets!$U$2,0)/1000000*(1+CEG_RevAdj) -> 0 | J46: =IF(J$3<=CEG_Assets!$V$2,J38*CEG_Assets!$U$2,0)/1000000*(1+CEG_RevAdj) -> 0 | K46: =IF(K$3<=CEG_Assets!$V$2,K38*CEG_Assets!$U$2,0)/1000000*(1+CEG_RevAdj) -> 0 | L46: =IF(L$3<=CEG_Assets!$V$2,L38*CEG_Assets!$U$2,0)/1000000*(1+CEG_RevAdj) -> 0 | M46: =IF(M$3<=CEG_Assets!$V$2,M38*CEG_Assets!$U$2,0)/1000000*(1+CEG_RevAdj) -> 0 | N46: =IF(N$3<=CEG_Assets!$V$2,N38*CEG_Assets!$U$2,0)/1000000*(1+CEG_RevAdj) -> 0 | ... AS46: =IF(AS$3<=CEG_Assets!$V$2,AS38*CEG_Assets!$U$2,0)/1000000*(1+CEG_RevAdj) -> 0
A47: Total revenue ($mm) | B47: revenue | C47: =SUM(G47:AS47) -> 146276.81 | G47: =G43+G44+G45+G46 -> 4493.4709 | H47: =H43+H44+H45+H46 -> 4538.6089 | I47: =I43+I44+I45+I46 -> 4110.3662 | J47: =J43+J44+J45+J46 -> 3953.9883 | K47: =K43+K44+K45+K46 -> 4033.068 | L47: =L43+L44+L45+L46 -> 4113.7294 | M47: =M43+M44+M45+M46 -> 4196.004 | N47: =N43+N44+N45+N46 -> 4279.9241 | ... AS47: =AS43+AS44+AS45+AS46 -> 0
A48: Fuel & variable cost ($mm) | B48: fuelvar | C48: =SUM(G48:AS48) -> 12427.221 | G48: =((CEG_Assets!$K$2*G40+CEG_Assets!$M$2*G$4)*G38*G42+CEG_Assets!$N$2*(1+CEG_Assets!$Q$2)^(G$3-2026)*(G38+G39))/1000000*(1+CEG_FuelAdj) -> 296.90208 | H48: =((CEG_Assets!$K$2*H40+CEG_Assets!$M$2*H$4)*H38*H42+CEG_Assets!$N$2*(1+CEG_Assets!$Q$2)^(H$3-2026)*(H38+H39))/1000000*(1+CEG_FuelAdj) -> 304.32464 | I48: =((CEG_Assets!$K$2*I40+CEG_Assets!$M$2*I$4)*I38*I42+CEG_Assets!$N$2*(1+CEG_Assets!$Q$2)^(I$3-2026)*(I38+I39))/1000000*(1+CEG_FuelAdj) -> 311.93275 | J48: =((CEG_Assets!$K$2*J40+CEG_Assets!$M$2*J$4)*J38*J42+CEG_Assets!$N$2*(1+CEG_Assets!$Q$2)^(J$3-2026)*(J38+J39))/1000000*(1+CEG_FuelAdj) -> 319.73107 | K48: =((CEG_Assets!$K$2*K40+CEG_Assets!$M$2*K$4)*K38*K42+CEG_Assets!$N$2*(1+CEG_Assets!$Q$2)^(K$3-2026)*(K38+K39))/1000000*(1+CEG_FuelAdj) -> 327.72435 | L48: =((CEG_Assets!$K$2*L40+CEG_Assets!$M$2*L$4)*L38*L42+CEG_Assets!$N$2*(1+CEG_Assets!$Q$2)^(L$3-2026)*(L38+L39))/1000000*(1+CEG_FuelAdj) -> 335.91746 | M48: =((CEG_Assets!$K$2*M40+CEG_Assets!$M$2*M$4)*M38*M42+CEG_Assets!$N$2*(1+CEG_Assets!$Q$2)^(M$3-2026)*(M38+M39))/1000000*(1+CEG_FuelAdj) -> 344.31539 | N48: =((CEG_Assets!$K$2*N40+CEG_Assets!$M$2*N$4)*N38*N42+CEG_Assets!$N$2*(1+CEG_Assets!$Q$2)^(N$3-2026)*(N38+N39))/1000000*(1+CEG_FuelAdj) -> 352.92328 | ... AS48: =((CEG_Assets!$K$2*AS40+CEG_Assets!$M$2*AS$4)*AS38*AS42+CEG_Assets!$N$2*(1+CEG_Assets!$Q$2)^(AS$3-2026)*(AS38+AS39))/1000000*(1+CEG_FuelAdj) -> 0
A49: Gross margin ($mm) | B49: gm | C49: =SUM(G49:AS49) -> 133849.59 | G49: =G47-G48 -> 4196.5689 | H49: =H47-H48 -> 4234.2843 | I49: =I47-I48 -> 3798.4334 | J49: =J47-J48 -> 3634.2572 | K49: =K47-K48 -> 3705.3437 | L49: =L47-L48 -> 3777.8119 | M49: =M47-M48 -> 3851.6886 | N49: =N47-N48 -> 3927.0008 | ... AS49: =AS47-AS48 -> 0
A50: Fixed O&M ($mm) | B50: fom | C50: =SUM(G50:AS50) -> 50386.734 | G50: =(CEG_Assets!$R$2*CEG_Assets!$D$2*1000*G$4*G36+CEG_Assets!$O$2*(1+CEG_Assets!$Q$2)^(G$3-2026)*(G38+G39))/1000000*(1+CEG_OMAdj) -> 1203.803 | H50: =(CEG_Assets!$R$2*CEG_Assets!$D$2*1000*H$4*H36+CEG_Assets!$O$2*(1+CEG_Assets!$Q$2)^(H$3-2026)*(H38+H39))/1000000*(1+CEG_OMAdj) -> 1233.8981 | I50: =(CEG_Assets!$R$2*CEG_Assets!$D$2*1000*I$4*I36+CEG_Assets!$O$2*(1+CEG_Assets!$Q$2)^(I$3-2026)*(I38+I39))/1000000*(1+CEG_OMAdj) -> 1264.7455 | J50: =(CEG_Assets!$R$2*CEG_Assets!$D$2*1000*J$4*J36+CEG_Assets!$O$2*(1+CEG_Assets!$Q$2)^(J$3-2026)*(J38+J39))/1000000*(1+CEG_OMAdj) -> 1296.3642 | K50: =(CEG_Assets!$R$2*CEG_Assets!$D$2*1000*K$4*K36+CEG_Assets!$O$2*(1+CEG_Assets!$Q$2)^(K$3-2026)*(K38+K39))/1000000*(1+CEG_OMAdj) -> 1328.7733 | L50: =(CEG_Assets!$R$2*CEG_Assets!$D$2*1000*L$4*L36+CEG_Assets!$O$2*(1+CEG_Assets!$Q$2)^(L$3-2026)*(L38+L39))/1000000*(1+CEG_OMAdj) -> 1361.9926 | M50: =(CEG_Assets!$R$2*CEG_Assets!$D$2*1000*M$4*M36+CEG_Assets!$O$2*(1+CEG_Assets!$Q$2)^(M$3-2026)*(M38+M39))/1000000*(1+CEG_OMAdj) -> 1396.0424 | N50: =(CEG_Assets!$R$2*CEG_Assets!$D$2*1000*N$4*N36+CEG_Assets!$O$2*(1+CEG_Assets!$Q$2)^(N$3-2026)*(N38+N39))/1000000*(1+CEG_OMAdj) -> 1430.9435 | ... AS50: =(CEG_Assets!$R$2*CEG_Assets!$D$2*1000*AS$4*AS36+CEG_Assets!$O$2*(1+CEG_Assets!$Q$2)^(AS$3-2026)*(AS38+AS39))/1000000*(1+CEG_OMAdj) -> 0
A51: Asset EBITDA ($mm) | B51: ebitda | C51: =SUM(G51:AS51) -> 83462.857 | G51: =G49-G50 -> 2992.7659 | H51: =H49-H50 -> 3000.3862 | I51: =I49-I50 -> 2533.6879 | J51: =J49-J50 -> 2337.893 | K51: =K49-K50 -> 2376.5704 | L51: =L49-L50 -> 2415.8193 | M51: =M49-M50 -> 2455.6462 | N51: =N49-N50 -> 2496.0573 | ... AS51: =AS49-AS50 -> 0
A52: Capex - sustaining + one-off ($mm) | B52: capex | C52: =SUM(G52:AS52) -> 17398.11 | G52: =((CEG_Assets!$S$2*CEG_Assets!$D$2*1000*G$4*G36+CEG_Assets!$P$2*(1+CEG_Assets!$Q$2)^(G$3-2026)*(G38+G39))/1000000+IF(G$3=CEG_Assets!$AH$2,CEG_Assets!$AG$2,0))*(1+CEG_CapexAdj) -> 415.66292 | H52: =((CEG_Assets!$S$2*CEG_Assets!$D$2*1000*H$4*H36+CEG_Assets!$P$2*(1+CEG_Assets!$Q$2)^(H$3-2026)*(H38+H39))/1000000+IF(H$3=CEG_Assets!$AH$2,CEG_Assets!$AG$2,0))*(1+CEG_CapexAdj) -> 426.05449 | I52: =((CEG_Assets!$S$2*CEG_Assets!$D$2*1000*I$4*I36+CEG_Assets!$P$2*(1+CEG_Assets!$Q$2)^(I$3-2026)*(I38+I39))/1000000+IF(I$3=CEG_Assets!$AH$2,CEG_Assets!$AG$2,0))*(1+CEG_CapexAdj) -> 436.70585 | J52: =((CEG_Assets!$S$2*CEG_Assets!$D$2*1000*J$4*J36+CEG_Assets!$P$2*(1+CEG_Assets!$Q$2)^(J$3-2026)*(J38+J39))/1000000+IF(J$3=CEG_Assets!$AH$2,CEG_Assets!$AG$2,0))*(1+CEG_CapexAdj) -> 447.6235 | K52: =((CEG_Assets!$S$2*CEG_Assets!$D$2*1000*K$4*K36+CEG_Assets!$P$2*(1+CEG_Assets!$Q$2)^(K$3-2026)*(K38+K39))/1000000+IF(K$3=CEG_Assets!$AH$2,CEG_Assets!$AG$2,0))*(1+CEG_CapexAdj) -> 458.81409 | L52: =((CEG_Assets!$S$2*CEG_Assets!$D$2*1000*L$4*L36+CEG_Assets!$P$2*(1+CEG_Assets!$Q$2)^(L$3-2026)*(L38+L39))/1000000+IF(L$3=CEG_Assets!$AH$2,CEG_Assets!$AG$2,0))*(1+CEG_CapexAdj) -> 470.28444 | M52: =((CEG_Assets!$S$2*CEG_Assets!$D$2*1000*M$4*M36+CEG_Assets!$P$2*(1+CEG_Assets!$Q$2)^(M$3-2026)*(M38+M39))/1000000+IF(M$3=CEG_Assets!$AH$2,CEG_Assets!$AG$2,0))*(1+CEG_CapexAdj) -> 482.04155 | N52: =((CEG_Assets!$S$2*CEG_Assets!$D$2*1000*N$4*N36+CEG_Assets!$P$2*(1+CEG_Assets!$Q$2)^(N$3-2026)*(N38+N39))/1000000+IF(N$3=CEG_Assets!$AH$2,CEG_Assets!$AG$2,0))*(1+CEG_CapexAdj) -> 494.09259 | ... AS52: =((CEG_Assets!$S$2*CEG_Assets!$D$2*1000*AS$4*AS36+CEG_Assets!$P$2*(1+CEG_Assets!$Q$2)^(AS$3-2026)*(AS38+AS39))/1000000+IF(AS$3=CEG_Assets!$AH$2,CEG_Assets!$AG$2,0))*(1+CEG_CapexAdj) -> 0
A53: Pre-tax cash flow ($mm) | B53: pretax | C53: =SUM(G53:AS53) -> 66064.747 | G53: =IF(CEG_Assets!$Y$2=1,MAX(0,G51-G52),G51-G52) -> 2577.1029 | H53: =IF(CEG_Assets!$Y$2=1,MAX(0,H51-H52),H51-H52) -> 2574.3317 | I53: =IF(CEG_Assets!$Y$2=1,MAX(0,I51-I52),I51-I52) -> 2096.9821 | J53: =IF(CEG_Assets!$Y$2=1,MAX(0,J51-J52),J51-J52) -> 1890.2695 | K53: =IF(CEG_Assets!$Y$2=1,MAX(0,K51-K52),K51-K52) -> 1917.7563 | L53: =IF(CEG_Assets!$Y$2=1,MAX(0,L51-L52),L51-L52) -> 1945.5349 | M53: =IF(CEG_Assets!$Y$2=1,MAX(0,M51-M52),M51-M52) -> 1973.6046 | N53: =IF(CEG_Assets!$Y$2=1,MAX(0,N51-N52),N51-N52) -> 2001.9647 | ... AS53: =IF(CEG_Assets!$Y$2=1,MAX(0,AS51-AS52),AS51-AS52) -> 0
A54: 45U credit - untaxed ($mm) | B54: ptc | C54: =SUM(G54:AS54) -> 0 | G54: =IF(AND(CEG_Assets!$W$2=1,G$3<=PTCLast,G38>0),G38*MAX(0,PTCCredit*(1+Infl)^(G$3-PTCBase)-0.8*MAX(0,(G43+G44+G46)*1000000/MAX(1,G38)-PTCThresh*(1+Infl)^(G$3-PTCBase)))/1000000,0) -> 0 | H54: =IF(AND(CEG_Assets!$W$2=1,H$3<=PTCLast,H38>0),H38*MAX(0,PTCCredit*(1+Infl)^(H$3-PTCBase)-0.8*MAX(0,(H43+H44+H46)*1000000/MAX(1,H38)-PTCThresh*(1+Infl)^(H$3-PTCBase)))/1000000,0) -> 0 | I54: =IF(AND(CEG_Assets!$W$2=1,I$3<=PTCLast,I38>0),I38*MAX(0,PTCCredit*(1+Infl)^(I$3-PTCBase)-0.8*MAX(0,(I43+I44+I46)*1000000/MAX(1,I38)-PTCThresh*(1+Infl)^(I$3-PTCBase)))/1000000,0) -> 0 | J54: =IF(AND(CEG_Assets!$W$2=1,J$3<=PTCLast,J38>0),J38*MAX(0,PTCCredit*(1+Infl)^(J$3-PTCBase)-0.8*MAX(0,(J43+J44+J46)*1000000/MAX(1,J38)-PTCThresh*(1+Infl)^(J$3-PTCBase)))/1000000,0) -> 0 | K54: =IF(AND(CEG_Assets!$W$2=1,K$3<=PTCLast,K38>0),K38*MAX(0,PTCCredit*(1+Infl)^(K$3-PTCBase)-0.8*MAX(0,(K43+K44+K46)*1000000/MAX(1,K38)-PTCThresh*(1+Infl)^(K$3-PTCBase)))/1000000,0) -> 0 | L54: =IF(AND(CEG_Assets!$W$2=1,L$3<=PTCLast,L38>0),L38*MAX(0,PTCCredit*(1+Infl)^(L$3-PTCBase)-0.8*MAX(0,(L43+L44+L46)*1000000/MAX(1,L38)-PTCThresh*(1+Infl)^(L$3-PTCBase)))/1000000,0) -> 0 | M54: =IF(AND(CEG_Assets!$W$2=1,M$3<=PTCLast,M38>0),M38*MAX(0,PTCCredit*(1+Infl)^(M$3-PTCBase)-0.8*MAX(0,(M43+M44+M46)*1000000/MAX(1,M38)-PTCThresh*(1+Infl)^(M$3-PTCBase)))/1000000,0) -> 0 | N54: =IF(AND(CEG_Assets!$W$2=1,N$3<=PTCLast,N38>0),N38*MAX(0,PTCCredit*(1+Infl)^(N$3-PTCBase)-0.8*MAX(0,(N43+N44+N46)*1000000/MAX(1,N38)-PTCThresh*(1+Infl)^(N$3-PTCBase)))/1000000,0) -> 0 | ... AS54: =IF(AND(CEG_Assets!$W$2=1,AS$3<=PTCLast,AS38>0),AS38*MAX(0,PTCCredit*(1+Infl)^(AS$3-PTCBase)-0.8*MAX(0,(AS43+AS44+AS46)*1000000/MAX(1,AS38)-PTCThresh*(1+Infl)^(AS$3-PTCBase)))/1000000,0) -> 0
A55: of which contracted pre-tax ($mm) | B55: con_cf | G55: =G45-G39*(CEG_Assets!$N$2*(1+CEG_FuelAdj)+CEG_Assets!$O$2*(1+CEG_OMAdj)+CEG_Assets!$P$2*(1+CEG_CapexAdj))*(1+CEG_Assets!$Q$2)^(G$3-2026)/1000000 -> 0 | H55: =H45-H39*(CEG_Assets!$N$2*(1+CEG_FuelAdj)+CEG_Assets!$O$2*(1+CEG_OMAdj)+CEG_Assets!$P$2*(1+CEG_CapexAdj))*(1+CEG_Assets!$Q$2)^(H$3-2026)/1000000 -> 0 | I55: =I45-I39*(CEG_Assets!$N$2*(1+CEG_FuelAdj)+CEG_Assets!$O$2*(1+CEG_OMAdj)+CEG_Assets!$P$2*(1+CEG_CapexAdj))*(1+CEG_Assets!$Q$2)^(I$3-2026)/1000000 -> 0 | J55: =J45-J39*(CEG_Assets!$N$2*(1+CEG_FuelAdj)+CEG_Assets!$O$2*(1+CEG_OMAdj)+CEG_Assets!$P$2*(1+CEG_CapexAdj))*(1+CEG_Assets!$Q$2)^(J$3-2026)/1000000 -> 0 | K55: =K45-K39*(CEG_Assets!$N$2*(1+CEG_FuelAdj)+CEG_Assets!$O$2*(1+CEG_OMAdj)+CEG_Assets!$P$2*(1+CEG_CapexAdj))*(1+CEG_Assets!$Q$2)^(K$3-2026)/1000000 -> 0 | L55: =L45-L39*(CEG_Assets!$N$2*(1+CEG_FuelAdj)+CEG_Assets!$O$2*(1+CEG_OMAdj)+CEG_Assets!$P$2*(1+CEG_CapexAdj))*(1+CEG_Assets!$Q$2)^(L$3-2026)/1000000 -> 0 | M55: =M45-M39*(CEG_Assets!$N$2*(1+CEG_FuelAdj)+CEG_Assets!$O$2*(1+CEG_OMAdj)+CEG_Assets!$P$2*(1+CEG_CapexAdj))*(1+CEG_Assets!$Q$2)^(M$3-2026)/1000000 -> 0 | N55: =N45-N39*(CEG_Assets!$N$2*(1+CEG_FuelAdj)+CEG_Assets!$O$2*(1+CEG_OMAdj)+CEG_Assets!$P$2*(1+CEG_CapexAdj))*(1+CEG_Assets!$Q$2)^(N$3-2026)/1000000 -> 0 | ... AS55: =AS45-AS39*(CEG_Assets!$N$2*(1+CEG_FuelAdj)+CEG_Assets!$O$2*(1+CEG_OMAdj)+CEG_Assets!$P$2*(1+CEG_CapexAdj))*(1+CEG_Assets!$Q$2)^(AS$3-2026)/1000000 -> 0
A56: of which merchant pre-tax ($mm) | B56: merch_cf | G56: =G53-G55 -> 2577.1029 | H56: =H53-H55 -> 2574.3317 | I56: =I53-I55 -> 2096.9821 | J56: =J53-J55 -> 1890.2695 | K56: =K53-K55 -> 1917.7563 | L56: =L53-L55 -> 1945.5349 | M56: =M53-M55 -> 1973.6046 | N56: =N53-N55 -> 2001.9647 | ... AS56: =AS53-AS55 -> 0
A57: After-tax merchant CF incl. 45U ($mm) | B57: at_m | G57: =G56*(1-TaxRate)+G54 -> 2061.6824 | H57: =H56*(1-TaxRate)+H54 -> 2059.4654 | I57: =I56*(1-TaxRate)+I54 -> 1677.5856 | J57: =J56*(1-TaxRate)+J54 -> 1512.2156 | K57: =K56*(1-TaxRate)+K54 -> 1534.2051 | L57: =L56*(1-TaxRate)+L54 -> 1556.4279 | M57: =M56*(1-TaxRate)+M54 -> 1578.8837 | N57: =N56*(1-TaxRate)+N54 -> 1601.5718 | ... AS57: =AS56*(1-TaxRate)+AS54 -> 0
A58: After-tax contracted CF ($mm) | B58: at_c | G58: =G55*(1-TaxRate) -> 0 | H58: =H55*(1-TaxRate) -> 0 | I58: =I55*(1-TaxRate) -> 0 | J58: =J55*(1-TaxRate) -> 0 | K58: =K55*(1-TaxRate) -> 0 | L58: =L55*(1-TaxRate) -> 0 | M58: =M55*(1-TaxRate) -> 0 | N58: =N55*(1-TaxRate) -> 0 | ... AS58: =AS55*(1-TaxRate) -> 0
A59: Discount factor - merchant | B59: df_m | G59: =(1+CEG_Assets!$AE$2)^-(G$3+0.5-ValDate) -> 0.94391347 | H59: =(1+CEG_Assets!$AE$2)^-(H$3+0.5-ValDate) -> 0.87399395 | I59: =(1+CEG_Assets!$AE$2)^-(I$3+0.5-ValDate) -> 0.80925366 | J59: =(1+CEG_Assets!$AE$2)^-(J$3+0.5-ValDate) -> 0.74930894 | K59: =(1+CEG_Assets!$AE$2)^-(K$3+0.5-ValDate) -> 0.69380458 | L59: =(1+CEG_Assets!$AE$2)^-(L$3+0.5-ValDate) -> 0.64241165 | M59: =(1+CEG_Assets!$AE$2)^-(M$3+0.5-ValDate) -> 0.5948256 | N59: =(1+CEG_Assets!$AE$2)^-(N$3+0.5-ValDate) -> 0.55076444 | ... AS59: =(1+CEG_Assets!$AE$2)^-(AS$3+0.5-ValDate) -> 0.050679168
A60: Discount factor - contracted | B60: df_c | G60: =(1+CEG_Assets!$AF$2)^-(G$3+0.5-ValDate) -> 0.95219103 | H60: =(1+CEG_Assets!$AF$2)^-(H$3+0.5-ValDate) -> 0.89198223 | I60: =(1+CEG_Assets!$AF$2)^-(I$3+0.5-ValDate) -> 0.83558055 | J60: =(1+CEG_Assets!$AF$2)^-(J$3+0.5-ValDate) -> 0.78274524 | K60: =(1+CEG_Assets!$AF$2)^-(K$3+0.5-ValDate) -> 0.73325081 | L60: =(1+CEG_Assets!$AF$2)^-(L$3+0.5-ValDate) -> 0.68688601 | M60: =(1+CEG_Assets!$AF$2)^-(M$3+0.5-ValDate) -> 0.64345293 | N60: =(1+CEG_Assets!$AF$2)^-(N$3+0.5-ValDate) -> 0.60276621 | ... AS60: =(1+CEG_Assets!$AF$2)^-(AS$3+0.5-ValDate) -> 0.079569111
A61: PV merchant ($mm) | B61: pv_m | C61: =SUM(G61:AS61) -> 20063.905 | D61: =SUMIF($G$3:$AS$3,"<="&Horizon,G61:AS61) -> 6236.719 | E61: =(C61-D61)*(1+CEG_Assets!$AE$2)^(Horizon+1-ValDate) -> 19177.18 | G61: =G57*G59 -> 1946.0497 | H61: =H57*H59 -> 1799.9603 | I61: =I57*I59 -> 1357.5923 | J61: =J57*J59 -> 1133.1167 | K61: =K57*K59 -> 1064.4385 | L61: =L57*L59 -> 999.86743 | M61: =M57*M59 -> 939.16045 | N61: =N57*N59 -> 882.08879 | ... AS61: =AS57*AS59 -> 0
A62: PV contracted ($mm) | B62: pv_c | C62: =SUM(G62:AS62) -> 0 | D62: =SUMIF($G$3:$AS$3,"<="&Horizon,G62:AS62) -> 0 | E62: =(C62-D62)*(1+CEG_Assets!$AF$2)^(Horizon+1-ValDate) -> 0 | G62: =G58*G60 -> 0 | H62: =H58*H60 -> 0 | I62: =I58*I60 -> 0 | J62: =J58*J60 -> 0 | K62: =K58*K60 -> 0 | L62: =L58*L60 -> 0 | M62: =M58*M60 -> 0 | N62: =N58*N60 -> 0 | ... AS62: =AS58*AS60 -> 0
A63: $/kW-method value ($mm) | B63: fixedval | C63: =IF(CEG_Assets!$H$2="$/kW",CEG_Assets!$D$2*CEG_Assets!$AI$2*(1+0.4*(PJMWLR/PJMWLRBase-1))/1000,0) -> 0 | E63: =C63 -> 0 | G63: =0 -> 0 | H63: =0 -> 0 | I63: =0 -> 0 | J63: =0 -> 0 | K63: =0 -> 0 | L63: =0 -> 0 | M63: =0 -> 0 | N63: =0 -> 0 | ... AS63: =0 -> 0
A65: =CEG_Assets!$A$3 -> Nuclear - PJM ComEd (Byron, Braidwood, LaSalle, Dresden, Quad Cities 75%)
A66: Operating (1/0) | B66: op | G66: =IF(AND(G$3>=CEG_Assets!$E$3,G$3<=CEG_Assets!$F$3,CEG_Assets!$H$3="Cashflow"),1,0) -> 1 | H66: =IF(AND(H$3>=CEG_Assets!$E$3,H$3<=CEG_Assets!$F$3,CEG_Assets!$H$3="Cashflow"),1,0) -> 1 | I66: =IF(AND(I$3>=CEG_Assets!$E$3,I$3<=CEG_Assets!$F$3,CEG_Assets!$H$3="Cashflow"),1,0) -> 1 | J66: =IF(AND(J$3>=CEG_Assets!$E$3,J$3<=CEG_Assets!$F$3,CEG_Assets!$H$3="Cashflow"),1,0) -> 1 | K66: =IF(AND(K$3>=CEG_Assets!$E$3,K$3<=CEG_Assets!$F$3,CEG_Assets!$H$3="Cashflow"),1,0) -> 1 | L66: =IF(AND(L$3>=CEG_Assets!$E$3,L$3<=CEG_Assets!$F$3,CEG_Assets!$H$3="Cashflow"),1,0) -> 1 | M66: =IF(AND(M$3>=CEG_Assets!$E$3,M$3<=CEG_Assets!$F$3,CEG_Assets!$H$3="Cashflow"),1,0) -> 1 | N66: =IF(AND(N$3>=CEG_Assets!$E$3,N$3<=CEG_Assets!$F$3,CEG_Assets!$H$3="Cashflow"),1,0) -> 1 | ... AS66: =IF(AND(AS$3>=CEG_Assets!$E$3,AS$3<=CEG_Assets!$F$3,CEG_Assets!$H$3="Cashflow"),1,0) -> 0
A67: Contracted MW | B67: cmw | G67: =IF(AND(G$3>=CEG_Assets!$AA$3,G$3<=CEG_Assets!$AB$3),MIN(CEG_Assets!$D$3,CEG_Assets!$Z$3*MIN(1,(G$3-CEG_Assets!$AA$3+1)/MAX(1,CEG_Assets!$AC$3))),0)*G66 -> 920 | H67: =IF(AND(H$3>=CEG_Assets!$AA$3,H$3<=CEG_Assets!$AB$3),MIN(CEG_Assets!$D$3,CEG_Assets!$Z$3*MIN(1,(H$3-CEG_Assets!$AA$3+1)/MAX(1,CEG_Assets!$AC$3))),0)*H66 -> 920 | I67: =IF(AND(I$3>=CEG_Assets!$AA$3,I$3<=CEG_Assets!$AB$3),MIN(CEG_Assets!$D$3,CEG_Assets!$Z$3*MIN(1,(I$3-CEG_Assets!$AA$3+1)/MAX(1,CEG_Assets!$AC$3))),0)*I66 -> 920 | J67: =IF(AND(J$3>=CEG_Assets!$AA$3,J$3<=CEG_Assets!$AB$3),MIN(CEG_Assets!$D$3,CEG_Assets!$Z$3*MIN(1,(J$3-CEG_Assets!$AA$3+1)/MAX(1,CEG_Assets!$AC$3))),0)*J66 -> 920 | K67: =IF(AND(K$3>=CEG_Assets!$AA$3,K$3<=CEG_Assets!$AB$3),MIN(CEG_Assets!$D$3,CEG_Assets!$Z$3*MIN(1,(K$3-CEG_Assets!$AA$3+1)/MAX(1,CEG_Assets!$AC$3))),0)*K66 -> 920 | L67: =IF(AND(L$3>=CEG_Assets!$AA$3,L$3<=CEG_Assets!$AB$3),MIN(CEG_Assets!$D$3,CEG_Assets!$Z$3*MIN(1,(L$3-CEG_Assets!$AA$3+1)/MAX(1,CEG_Assets!$AC$3))),0)*L66 -> 920 | M67: =IF(AND(M$3>=CEG_Assets!$AA$3,M$3<=CEG_Assets!$AB$3),MIN(CEG_Assets!$D$3,CEG_Assets!$Z$3*MIN(1,(M$3-CEG_Assets!$AA$3+1)/MAX(1,CEG_Assets!$AC$3))),0)*M66 -> 920 | N67: =IF(AND(N$3>=CEG_Assets!$AA$3,N$3<=CEG_Assets!$AB$3),MIN(CEG_Assets!$D$3,CEG_Assets!$Z$3*MIN(1,(N$3-CEG_Assets!$AA$3+1)/MAX(1,CEG_Assets!$AC$3))),0)*N66 -> 920 | ... AS67: =IF(AND(AS$3>=CEG_Assets!$AA$3,AS$3<=CEG_Assets!$AB$3),MIN(CEG_Assets!$D$3,CEG_Assets!$Z$3*MIN(1,(AS$3-CEG_Assets!$AA$3+1)/MAX(1,CEG_Assets!$AC$3))),0)*AS66 -> 0
A68: Merchant generation (MWh) | B68: gen_m | G68: =(CEG_Assets!$D$3-G67)*8760*CEG_Assets!$I$3*G66 -> 76827828 | H68: =(CEG_Assets!$D$3-H67)*8760*CEG_Assets!$I$3*H66 -> 76827828 | I68: =(CEG_Assets!$D$3-I67)*8760*CEG_Assets!$I$3*I66 -> 76827828 | J68: =(CEG_Assets!$D$3-J67)*8760*CEG_Assets!$I$3*J66 -> 76827828 | K68: =(CEG_Assets!$D$3-K67)*8760*CEG_Assets!$I$3*K66 -> 76827828 | L68: =(CEG_Assets!$D$3-L67)*8760*CEG_Assets!$I$3*L66 -> 76827828 | M68: =(CEG_Assets!$D$3-M67)*8760*CEG_Assets!$I$3*M66 -> 76827828 | N68: =(CEG_Assets!$D$3-N67)*8760*CEG_Assets!$I$3*N66 -> 76827828 | ... AS68: =(CEG_Assets!$D$3-AS67)*8760*CEG_Assets!$I$3*AS66 -> 0
A69: Contracted generation (MWh) | B69: gen_c | G69: =G67*8760*CEG_Assets!$I$3*G66 -> 7535352 | H69: =H67*8760*CEG_Assets!$I$3*H66 -> 7535352 | I69: =I67*8760*CEG_Assets!$I$3*I66 -> 7535352 | J69: =J67*8760*CEG_Assets!$I$3*J66 -> 7535352 | K69: =K67*8760*CEG_Assets!$I$3*K66 -> 7535352 | L69: =L67*8760*CEG_Assets!$I$3*L66 -> 7535352 | M69: =M67*8760*CEG_Assets!$I$3*M66 -> 7535352 | N69: =N67*8760*CEG_Assets!$I$3*N66 -> 7535352 | ... AS69: =AS67*8760*CEG_Assets!$I$3*AS66 -> 0
A70: Fuel price, delivered ($/MMBtu) | B70: fuelp | G70: =IF(ISNUMBER(CEG_Assets!$L$3),CEG_Assets!$L$3*G$4,INDEX(Prices!G:G,CEG_Assets!$AO$3)+FuelAdder*G$4) -> 4.029 | H70: =IF(ISNUMBER(CEG_Assets!$L$3),CEG_Assets!$L$3*H$4,INDEX(Prices!H:H,CEG_Assets!$AO$3)+FuelAdder*H$4) -> 4.10958 | I70: =IF(ISNUMBER(CEG_Assets!$L$3),CEG_Assets!$L$3*I$4,INDEX(Prices!I:I,CEG_Assets!$AO$3)+FuelAdder*I$4) -> 4.2978924 | J70: =IF(ISNUMBER(CEG_Assets!$L$3),CEG_Assets!$L$3*J$4,INDEX(Prices!J:J,CEG_Assets!$AO$3)+FuelAdder*J$4) -> 4.3838502 | K70: =IF(ISNUMBER(CEG_Assets!$L$3),CEG_Assets!$L$3*K$4,INDEX(Prices!K:K,CEG_Assets!$AO$3)+FuelAdder*K$4) -> 4.4715273 | L70: =IF(ISNUMBER(CEG_Assets!$L$3),CEG_Assets!$L$3*L$4,INDEX(Prices!L:L,CEG_Assets!$AO$3)+FuelAdder*L$4) -> 4.5609578 | M70: =IF(ISNUMBER(CEG_Assets!$L$3),CEG_Assets!$L$3*M$4,INDEX(Prices!M:M,CEG_Assets!$AO$3)+FuelAdder*M$4) -> 4.652177 | N70: =IF(ISNUMBER(CEG_Assets!$L$3),CEG_Assets!$L$3*N$4,INDEX(Prices!N:N,CEG_Assets!$AO$3)+FuelAdder*N$4) -> 4.7452205 | O70: =IF(ISNUMBER(CEG_Assets!$L$3),CEG_Assets!$L$3*O$4,INDEX(Prices!O:O,CEG_Assets!$AO$3)+FuelAdder*O$4) -> 4.8401249 | P70: =IF(ISNUMBER(CEG_Assets!$L$3),CEG_Assets!$L$3*P$4,INDEX(Prices!P:P,CEG_Assets!$AO$3)+FuelAdder*P$4) -> 4.9369274 | Q70: =IF(ISNUMBER(CEG_Assets!$L$3),CEG_Assets!$L$3*Q$4,INDEX(Prices!Q:Q,CEG_Assets!$AO$3)+FuelAdder*Q$4) -> 5.0356659 | R70: =IF(ISNUMBER(CEG_Assets!$L$3),CEG_Assets!$L$3*R$4,INDEX(Prices!R:R,CEG_Assets!$AO$3)+FuelAdder*R$4) -> 5.1363793 | S70: =IF(ISNUMBER(CEG_Assets!$L$3),CEG_Assets!$L$3*S$4,INDEX(Prices!S:S,CEG_Assets!$AO$3)+FuelAdder*S$4) -> 5.2391069 | T70: =IF(ISNUMBER(CEG_Assets!$L$3),CEG_Assets!$L$3*T$4,INDEX(Prices!T:T,CEG_Assets!$AO$3)+FuelAdder*T$4) -> 5.343889 | U70: =IF(ISNUMBER(CEG_Assets!$L$3),CEG_Assets!$L$3*U$4,INDEX(Prices!U:U,CEG_Assets!$AO$3)+FuelAdder*U$4) -> 5.4507668 | V70: =IF(ISNUMBER(CEG_Assets!$L$3),CEG_Assets!$L$3*V$4,INDEX(Prices!V:V,CEG_Assets!$AO$3)+FuelAdder*V$4) -> 5.5597821 | W70: =IF(ISNUMBER(CEG_Assets!$L$3),CEG_Assets!$L$3*W$4,INDEX(Prices!W:W,CEG_Assets!$AO$3)+FuelAdder*W$4) -> 5.6709777 | X70: =IF(ISNUMBER(CEG_Assets!$L$3),CEG_Assets!$L$3*X$4,INDEX(Prices!X:X,CEG_Assets!$AO$3)+FuelAdder*X$4) -> 5.7843973 | Y70: =IF(ISNUMBER(CEG_Assets!$L$3),CEG_Assets!$L$3*Y$4,INDEX(Prices!Y:Y,CEG_Assets!$AO$3)+FuelAdder*Y$4) -> 5.9000852 | Z70: =IF(ISNUMBER(CEG_Assets!$L$3),CEG_Assets!$L$3*Z$4,INDEX(Prices!Z:Z,CEG_Assets!$AO$3)+FuelAdder*Z$4) -> 6.018087 | AA70: =IF(ISNUMBER(CEG_Assets!$L$3),CEG_Assets!$L$3*AA$4,INDEX(Prices!AA:AA,CEG_Assets!$AO$3)+FuelAdder*AA$4) -> 6.1384487 | AB70: =IF(ISNUMBER(CEG_Assets!$L$3),CEG_Assets!$L$3*AB$4,INDEX(Prices!AB:AB,CEG_Assets!$AO$3)+FuelAdder*AB$4) -> 6.2612177 | AC70: =IF(ISNUMBER(CEG_Assets!$L$3),CEG_Assets!$L$3*AC$4,INDEX(Prices!AC:AC,CEG_Assets!$AO$3)+FuelAdder*AC$4) -> 6.386442 | AD70: =IF(ISNUMBER(CEG_Assets!$L$3),CEG_Assets!$L$3*AD$4,INDEX(Prices!AD:AD,CEG_Assets!$AO$3)+FuelAdder*AD$4) -> 6.5141709 | AE70: =IF(ISNUMBER(CEG_Assets!$L$3),CEG_Assets!$L$3*AE$4,INDEX(Prices!AE:AE,CEG_Assets!$AO$3)+FuelAdder*AE$4) -> 6.6444543 | AF70: =IF(ISNUMBER(CEG_Assets!$L$3),CEG_Assets!$L$3*AF$4,INDEX(Prices!AF:AF,CEG_Assets!$AO$3)+FuelAdder*AF$4) -> 6.7773434 | AG70: =IF(ISNUMBER(CEG_Assets!$L$3),CEG_Assets!$L$3*AG$4,INDEX(Prices!AG:AG,CEG_Assets!$AO$3)+FuelAdder*AG$4) -> 6.9128902 | AH70: =IF(ISNUMBER(CEG_Assets!$L$3),CEG_Assets!$L$3*AH$4,INDEX(Prices!AH:AH,CEG_Assets!$AO$3)+FuelAdder*AH$4) -> 7.051148 | AI70: =IF(ISNUMBER(CEG_Assets!$L$3),CEG_Assets!$L$3*AI$4,INDEX(Prices!AI:AI,CEG_Assets!$AO$3)+FuelAdder*AI$4) -> 7.192171 | AJ70: =IF(ISNUMBER(CEG_Assets!$L$3),CEG_Assets!$L$3*AJ$4,INDEX(Prices!AJ:AJ,CEG_Assets!$AO$3)+FuelAdder*AJ$4) -> 7.3360144 | AK70: =IF(ISNUMBER(CEG_Assets!$L$3),CEG_Assets!$L$3*AK$4,INDEX(Prices!AK:AK,CEG_Assets!$AO$3)+FuelAdder*AK$4) -> 7.4827347 | AL70: =IF(ISNUMBER(CEG_Assets!$L$3),CEG_Assets!$L$3*AL$4,INDEX(Prices!AL:AL,CEG_Assets!$AO$3)+FuelAdder*AL$4) -> 7.6323894 | AM70: =IF(ISNUMBER(CEG_Assets!$L$3),CEG_Assets!$L$3*AM$4,INDEX(Prices!AM:AM,CEG_Assets!$AO$3)+FuelAdder*AM$4) -> 7.7850372 | AN70: =IF(ISNUMBER(CEG_Assets!$L$3),CEG_Assets!$L$3*AN$4,INDEX(Prices!AN:AN,CEG_Assets!$AO$3)+FuelAdder*AN$4) -> 7.9407379 | AO70: =IF(ISNUMBER(CEG_Assets!$L$3),CEG_Assets!$L$3*AO$4,INDEX(Prices!AO:AO,CEG_Assets!$AO$3)+FuelAdder*AO$4) -> 8.0995527 | AP70: =IF(ISNUMBER(CEG_Assets!$L$3),CEG_Assets!$L$3*AP$4,INDEX(Prices!AP:AP,CEG_Assets!$AO$3)+FuelAdder*AP$4) -> 8.2615437 | AQ70: =IF(ISNUMBER(CEG_Assets!$L$3),CEG_Assets!$L$3*AQ$4,INDEX(Prices!AQ:AQ,CEG_Assets!$AO$3)+FuelAdder*AQ$4) -> 8.4267746 | AR70: =IF(ISNUMBER(CEG_Assets!$L$3),CEG_Assets!$L$3*AR$4,INDEX(Prices!AR:AR,CEG_Assets!$AO$3)+FuelAdder*AR$4) -> 8.5953101 | AS70: =IF(ISNUMBER(CEG_Assets!$L$3),CEG_Assets!$L$3*AS$4,INDEX(Prices!AS:AS,CEG_Assets!$AO$3)+FuelAdder*AS$4) -> 8.7672163
A71: Spread vs fuel ($/MWh) | B71: spark | G71: =INDEX(Prices!G:G,CEG_Assets!$AN$3)*CEG_Assets!$J$3-CEG_Assets!$K$3*G70-CEG_Assets!$M$3*G$4 -> 60.588 | H71: =INDEX(Prices!H:H,CEG_Assets!$AN$3)*CEG_Assets!$J$3-CEG_Assets!$K$3*H70-CEG_Assets!$M$3*H$4 -> 61.4295 | I71: =INDEX(Prices!I:I,CEG_Assets!$AN$3)*CEG_Assets!$J$3-CEG_Assets!$K$3*I70-CEG_Assets!$M$3*I$4 -> 56.343159 | J71: =INDEX(Prices!J:J,CEG_Assets!$AN$3)*CEG_Assets!$J$3-CEG_Assets!$K$3*J70-CEG_Assets!$M$3*J$4 -> 54.856945 | K71: =INDEX(Prices!K:K,CEG_Assets!$AN$3)*CEG_Assets!$J$3-CEG_Assets!$K$3*K70-CEG_Assets!$M$3*K$4 -> 55.954084 | L71: =INDEX(Prices!L:L,CEG_Assets!$AN$3)*CEG_Assets!$J$3-CEG_Assets!$K$3*L70-CEG_Assets!$M$3*L$4 -> 57.073165 | M71: =INDEX(Prices!M:M,CEG_Assets!$AN$3)*CEG_Assets!$J$3-CEG_Assets!$K$3*M70-CEG_Assets!$M$3*M$4 -> 58.214629 | N71: =INDEX(Prices!N:N,CEG_Assets!$AN$3)*CEG_Assets!$J$3-CEG_Assets!$K$3*N70-CEG_Assets!$M$3*N$4 -> 59.378921 | O71: =INDEX(Prices!O:O,CEG_Assets!$AN$3)*CEG_Assets!$J$3-CEG_Assets!$K$3*O70-CEG_Assets!$M$3*O$4 -> 60.5665 | P71: =INDEX(Prices!P:P,CEG_Assets!$AN$3)*CEG_Assets!$J$3-CEG_Assets!$K$3*P70-CEG_Assets!$M$3*P$4 -> 61.77783 | Q71: =INDEX(Prices!Q:Q,CEG_Assets!$AN$3)*CEG_Assets!$J$3-CEG_Assets!$K$3*Q70-CEG_Assets!$M$3*Q$4 -> 63.013386 | R71: =INDEX(Prices!R:R,CEG_Assets!$AN$3)*CEG_Assets!$J$3-CEG_Assets!$K$3*R70-CEG_Assets!$M$3*R$4 -> 64.273654 | S71: =INDEX(Prices!S:S,CEG_Assets!$AN$3)*CEG_Assets!$J$3-CEG_Assets!$K$3*S70-CEG_Assets!$M$3*S$4 -> 65.559127 | T71: =INDEX(Prices!T:T,CEG_Assets!$AN$3)*CEG_Assets!$J$3-CEG_Assets!$K$3*T70-CEG_Assets!$M$3*T$4 -> 66.87031 | U71: =INDEX(Prices!U:U,CEG_Assets!$AN$3)*CEG_Assets!$J$3-CEG_Assets!$K$3*U70-CEG_Assets!$M$3*U$4 -> 68.207716 | V71: =INDEX(Prices!V:V,CEG_Assets!$AN$3)*CEG_Assets!$J$3-CEG_Assets!$K$3*V70-CEG_Assets!$M$3*V$4 -> 69.57187 | W71: =INDEX(Prices!W:W,CEG_Assets!$AN$3)*CEG_Assets!$J$3-CEG_Assets!$K$3*W70-CEG_Assets!$M$3*W$4 -> 70.963307 | X71: =INDEX(Prices!X:X,CEG_Assets!$AN$3)*CEG_Assets!$J$3-CEG_Assets!$K$3*X70-CEG_Assets!$M$3*X$4 -> 72.382574 | Y71: =INDEX(Prices!Y:Y,CEG_Assets!$AN$3)*CEG_Assets!$J$3-CEG_Assets!$K$3*Y70-CEG_Assets!$M$3*Y$4 -> 73.830225 | Z71: =INDEX(Prices!Z:Z,CEG_Assets!$AN$3)*CEG_Assets!$J$3-CEG_Assets!$K$3*Z70-CEG_Assets!$M$3*Z$4 -> 75.30683 | AA71: =INDEX(Prices!AA:AA,CEG_Assets!$AN$3)*CEG_Assets!$J$3-CEG_Assets!$K$3*AA70-CEG_Assets!$M$3*AA$4 -> 76.812966 | AB71: =INDEX(Prices!AB:AB,CEG_Assets!$AN$3)*CEG_Assets!$J$3-CEG_Assets!$K$3*AB70-CEG_Assets!$M$3*AB$4 -> 78.349226 | AC71: =INDEX(Prices!AC:AC,CEG_Assets!$AN$3)*CEG_Assets!$J$3-CEG_Assets!$K$3*AC70-CEG_Assets!$M$3*AC$4 -> 79.91621 | AD71: =INDEX(Prices!AD:AD,CEG_Assets!$AN$3)*CEG_Assets!$J$3-CEG_Assets!$K$3*AD70-CEG_Assets!$M$3*AD$4 -> 81.514534 | AE71: =INDEX(Prices!AE:AE,CEG_Assets!$AN$3)*CEG_Assets!$J$3-CEG_Assets!$K$3*AE70-CEG_Assets!$M$3*AE$4 -> 83.144825 | AF71: =INDEX(Prices!AF:AF,CEG_Assets!$AN$3)*CEG_Assets!$J$3-CEG_Assets!$K$3*AF70-CEG_Assets!$M$3*AF$4 -> 84.807721 | AG71: =INDEX(Prices!AG:AG,CEG_Assets!$AN$3)*CEG_Assets!$J$3-CEG_Assets!$K$3*AG70-CEG_Assets!$M$3*AG$4 -> 86.503876 | AH71: =INDEX(Prices!AH:AH,CEG_Assets!$AN$3)*CEG_Assets!$J$3-CEG_Assets!$K$3*AH70-CEG_Assets!$M$3*AH$4 -> 88.233953 | AI71: =INDEX(Prices!AI:AI,CEG_Assets!$AN$3)*CEG_Assets!$J$3-CEG_Assets!$K$3*AI70-CEG_Assets!$M$3*AI$4 -> 89.998632 | AJ71: =INDEX(Prices!AJ:AJ,CEG_Assets!$AN$3)*CEG_Assets!$J$3-CEG_Assets!$K$3*AJ70-CEG_Assets!$M$3*AJ$4 -> 91.798605 | AK71: =INDEX(Prices!AK:AK,CEG_Assets!$AN$3)*CEG_Assets!$J$3-CEG_Assets!$K$3*AK70-CEG_Assets!$M$3*AK$4 -> 93.634577 | AL71: =INDEX(Prices!AL:AL,CEG_Assets!$AN$3)*CEG_Assets!$J$3-CEG_Assets!$K$3*AL70-CEG_Assets!$M$3*AL$4 -> 95.507269 | AM71: =INDEX(Prices!AM:AM,CEG_Assets!$AN$3)*CEG_Assets!$J$3-CEG_Assets!$K$3*AM70-CEG_Assets!$M$3*AM$4 -> 97.417414 | AN71: =INDEX(Prices!AN:AN,CEG_Assets!$AN$3)*CEG_Assets!$J$3-CEG_Assets!$K$3*AN70-CEG_Assets!$M$3*AN$4 -> 99.365762 | AO71: =INDEX(Prices!AO:AO,CEG_Assets!$AN$3)*CEG_Assets!$J$3-CEG_Assets!$K$3*AO70-CEG_Assets!$M$3*AO$4 -> 101.35308 | AP71: =INDEX(Prices!AP:AP,CEG_Assets!$AN$3)*CEG_Assets!$J$3-CEG_Assets!$K$3*AP70-CEG_Assets!$M$3*AP$4 -> 103.38014 | AQ71: =INDEX(Prices!AQ:AQ,CEG_Assets!$AN$3)*CEG_Assets!$J$3-CEG_Assets!$K$3*AQ70-CEG_Assets!$M$3*AQ$4 -> 105.44774 | AR71: =INDEX(Prices!AR:AR,CEG_Assets!$AN$3)*CEG_Assets!$J$3-CEG_Assets!$K$3*AR70-CEG_Assets!$M$3*AR$4 -> 107.5567 | AS71: =INDEX(Prices!AS:AS,CEG_Assets!$AN$3)*CEG_Assets!$J$3-CEG_Assets!$K$3*AS70-CEG_Assets!$M$3*AS$4 -> 109.70783
A72: Runs (1/0) | B72: run | G72: =IF(CEG_Assets!$X$3=1,IF(G71>0,1,0),1) -> 1 | H72: =IF(CEG_Assets!$X$3=1,IF(H71>0,1,0),1) -> 1 | I72: =IF(CEG_Assets!$X$3=1,IF(I71>0,1,0),1) -> 1 | J72: =IF(CEG_Assets!$X$3=1,IF(J71>0,1,0),1) -> 1 | K72: =IF(CEG_Assets!$X$3=1,IF(K71>0,1,0),1) -> 1 | L72: =IF(CEG_Assets!$X$3=1,IF(L71>0,1,0),1) -> 1 | M72: =IF(CEG_Assets!$X$3=1,IF(M71>0,1,0),1) -> 1 | N72: =IF(CEG_Assets!$X$3=1,IF(N71>0,1,0),1) -> 1 | ... AS72: =IF(CEG_Assets!$X$3=1,IF(AS71>0,1,0),1) -> 1
A73: Merchant energy revenue ($mm) | B73: energy | C73: =SUM(G73:AS73) -> 161256.54 | G73: =G68*INDEX(Prices!G:G,CEG_Assets!$AN$3)*CEG_Assets!$J$3*G72/1000000*(1+CEG_RevAdj) -> 4654.8444 | H73: =H68*INDEX(Prices!H:H,CEG_Assets!$AN$3)*CEG_Assets!$J$3*H72/1000000*(1+CEG_RevAdj) -> 4719.4951 | I73: =I68*INDEX(Prices!I:I,CEG_Assets!$AN$3)*CEG_Assets!$J$3*I72/1000000*(1+CEG_RevAdj) -> 4328.7225 | J73: =J68*INDEX(Prices!J:J,CEG_Assets!$AN$3)*CEG_Assets!$J$3*J72/1000000*(1+CEG_RevAdj) -> 4214.5399 | K73: =K68*INDEX(Prices!K:K,CEG_Assets!$AN$3)*CEG_Assets!$J$3*K72/1000000*(1+CEG_RevAdj) -> 4298.8307 | L73: =L68*INDEX(Prices!L:L,CEG_Assets!$AN$3)*CEG_Assets!$J$3*L72/1000000*(1+CEG_RevAdj) -> 4384.8073 | M73: =M68*INDEX(Prices!M:M,CEG_Assets!$AN$3)*CEG_Assets!$J$3*M72/1000000*(1+CEG_RevAdj) -> 4472.5035 | N73: =N68*INDEX(Prices!N:N,CEG_Assets!$AN$3)*CEG_Assets!$J$3*N72/1000000*(1+CEG_RevAdj) -> 4561.9535 | O73: =O68*INDEX(Prices!O:O,CEG_Assets!$AN$3)*CEG_Assets!$J$3*O72/1000000*(1+CEG_RevAdj) -> 4653.1926 | P73: =P68*INDEX(Prices!P:P,CEG_Assets!$AN$3)*CEG_Assets!$J$3*P72/1000000*(1+CEG_RevAdj) -> 4746.2565 | Q73: =Q68*INDEX(Prices!Q:Q,CEG_Assets!$AN$3)*CEG_Assets!$J$3*Q72/1000000*(1+CEG_RevAdj) -> 4841.1816 | R73: =R68*INDEX(Prices!R:R,CEG_Assets!$AN$3)*CEG_Assets!$J$3*R72/1000000*(1+CEG_RevAdj) -> 4938.0052 | S73: =S68*INDEX(Prices!S:S,CEG_Assets!$AN$3)*CEG_Assets!$J$3*S72/1000000*(1+CEG_RevAdj) -> 5036.7653 | T73: =T68*INDEX(Prices!T:T,CEG_Assets!$AN$3)*CEG_Assets!$J$3*T72/1000000*(1+CEG_RevAdj) -> 5137.5006 | U73: =U68*INDEX(Prices!U:U,CEG_Assets!$AN$3)*CEG_Assets!$J$3*U72/1000000*(1+CEG_RevAdj) -> 5240.2507 | V73: =V68*INDEX(Prices!V:V,CEG_Assets!$AN$3)*CEG_Assets!$J$3*V72/1000000*(1+CEG_RevAdj) -> 5345.0557 | W73: =W68*INDEX(Prices!W:W,CEG_Assets!$AN$3)*CEG_Assets!$J$3*W72/1000000*(1+CEG_RevAdj) -> 5451.9568 | X73: =X68*INDEX(Prices!X:X,CEG_Assets!$AN$3)*CEG_Assets!$J$3*X72/1000000*(1+CEG_RevAdj) -> 5560.9959 | Y73: =Y68*INDEX(Prices!Y:Y,CEG_Assets!$AN$3)*CEG_Assets!$J$3*Y72/1000000*(1+CEG_RevAdj) -> 5672.2158 | Z73: =Z68*INDEX(Prices!Z:Z,CEG_Assets!$AN$3)*CEG_Assets!$J$3*Z72/1000000*(1+CEG_RevAdj) -> 5785.6602 | AA73: =AA68*INDEX(Prices!AA:AA,CEG_Assets!$AN$3)*CEG_Assets!$J$3*AA72/1000000*(1+CEG_RevAdj) -> 6480.1861 | AB73: =AB68*INDEX(Prices!AB:AB,CEG_Assets!$AN$3)*CEG_Assets!$J$3*AB72/1000000*(1+CEG_RevAdj) -> 6609.7898 | AC73: =AC68*INDEX(Prices!AC:AC,CEG_Assets!$AN$3)*CEG_Assets!$J$3*AC72/1000000*(1+CEG_RevAdj) -> 6741.9856 | AD73: =AD68*INDEX(Prices!AD:AD,CEG_Assets!$AN$3)*CEG_Assets!$J$3*AD72/1000000*(1+CEG_RevAdj) -> 6876.8253 | AE73: =AE68*INDEX(Prices!AE:AE,CEG_Assets!$AN$3)*CEG_Assets!$J$3*AE72/1000000*(1+CEG_RevAdj) -> 7014.3618 | AF73: =AF68*INDEX(Prices!AF:AF,CEG_Assets!$AN$3)*CEG_Assets!$J$3*AF72/1000000*(1+CEG_RevAdj) -> 7154.6491 | AG73: =AG68*INDEX(Prices!AG:AG,CEG_Assets!$AN$3)*CEG_Assets!$J$3*AG72/1000000*(1+CEG_RevAdj) -> 7297.742 | AH73: =AH68*INDEX(Prices!AH:AH,CEG_Assets!$AN$3)*CEG_Assets!$J$3*AH72/1000000*(1+CEG_RevAdj) -> 7443.6969 | AI73: =AI68*INDEX(Prices!AI:AI,CEG_Assets!$AN$3)*CEG_Assets!$J$3*AI72/1000000*(1+CEG_RevAdj) -> 7592.5708 | AJ73: =AJ68*INDEX(Prices!AJ:AJ,CEG_Assets!$AN$3)*CEG_Assets!$J$3*AJ72/1000000*(1+CEG_RevAdj) -> 0 | AK73: =AK68*INDEX(Prices!AK:AK,CEG_Assets!$AN$3)*CEG_Assets!$J$3*AK72/1000000*(1+CEG_RevAdj) -> 0 | AL73: =AL68*INDEX(Prices!AL:AL,CEG_Assets!$AN$3)*CEG_Assets!$J$3*AL72/1000000*(1+CEG_RevAdj) -> 0 | AM73: =AM68*INDEX(Prices!AM:AM,CEG_Assets!$AN$3)*CEG_Assets!$J$3*AM72/1000000*(1+CEG_RevAdj) -> 0 | AN73: =AN68*INDEX(Prices!AN:AN,CEG_Assets!$AN$3)*CEG_Assets!$J$3*AN72/1000000*(1+CEG_RevAdj) -> 0 | AO73: =AO68*INDEX(Prices!AO:AO,CEG_Assets!$AN$3)*CEG_Assets!$J$3*AO72/1000000*(1+CEG_RevAdj) -> 0 | AP73: =AP68*INDEX(Prices!AP:AP,CEG_Assets!$AN$3)*CEG_Assets!$J$3*AP72/1000000*(1+CEG_RevAdj) -> 0 | AQ73: =AQ68*INDEX(Prices!AQ:AQ,CEG_Assets!$AN$3)*CEG_Assets!$J$3*AQ72/1000000*(1+CEG_RevAdj) -> 0 | AR73: =AR68*INDEX(Prices!AR:AR,CEG_Assets!$AN$3)*CEG_Assets!$J$3*AR72/1000000*(1+CEG_RevAdj) -> 0 | AS73: =AS68*INDEX(Prices!AS:AS,CEG_Assets!$AN$3)*CEG_Assets!$J$3*AS72/1000000*(1+CEG_RevAdj) -> 0
A74: Capacity revenue ($mm) | B74: capacity | C74: =SUM(G74:AS74) -> 31400.391 | G74: =(CEG_Assets!$D$3-G67)*INDEX(Prices!G:G,CEG_Assets!$AP$3)*365*CEG_Assets!$T$3*G66/1000000*(1+CEG_RevAdj) -> 1078.7291 | H74: =(CEG_Assets!$D$3-H67)*INDEX(Prices!H:H,CEG_Assets!$AP$3)*365*CEG_Assets!$T$3*H66/1000000*(1+CEG_RevAdj) -> 1068.5162 | I74: =(CEG_Assets!$D$3-I67)*INDEX(Prices!I:I,CEG_Assets!$AP$3)*365*CEG_Assets!$T$3*I66/1000000*(1+CEG_RevAdj) -> 903.53373 | J74: =(CEG_Assets!$D$3-J67)*INDEX(Prices!J:J,CEG_Assets!$AP$3)*365*CEG_Assets!$T$3*J66/1000000*(1+CEG_RevAdj) -> 809.74417 | K74: =(CEG_Assets!$D$3-K67)*INDEX(Prices!K:K,CEG_Assets!$AP$3)*365*CEG_Assets!$T$3*K66/1000000*(1+CEG_RevAdj) -> 825.93906 | L74: =(CEG_Assets!$D$3-L67)*INDEX(Prices!L:L,CEG_Assets!$AP$3)*365*CEG_Assets!$T$3*L66/1000000*(1+CEG_RevAdj) -> 842.45784 | M74: =(CEG_Assets!$D$3-M67)*INDEX(Prices!M:M,CEG_Assets!$AP$3)*365*CEG_Assets!$T$3*M66/1000000*(1+CEG_RevAdj) -> 859.30699 | N74: =(CEG_Assets!$D$3-N67)*INDEX(Prices!N:N,CEG_Assets!$AP$3)*365*CEG_Assets!$T$3*N66/1000000*(1+CEG_RevAdj) -> 876.49313 | O74: =(CEG_Assets!$D$3-O67)*INDEX(Prices!O:O,CEG_Assets!$AP$3)*365*CEG_Assets!$T$3*O66/1000000*(1+CEG_RevAdj) -> 894.023 | P74: =(CEG_Assets!$D$3-P67)*INDEX(Prices!P:P,CEG_Assets!$AP$3)*365*CEG_Assets!$T$3*P66/1000000*(1+CEG_RevAdj) -> 911.90346 | Q74: =(CEG_Assets!$D$3-Q67)*INDEX(Prices!Q:Q,CEG_Assets!$AP$3)*365*CEG_Assets!$T$3*Q66/1000000*(1+CEG_RevAdj) -> 930.14153 | R74: =(CEG_Assets!$D$3-R67)*INDEX(Prices!R:R,CEG_Assets!$AP$3)*365*CEG_Assets!$T$3*R66/1000000*(1+CEG_RevAdj) -> 948.74436 | S74: =(CEG_Assets!$D$3-S67)*INDEX(Prices!S:S,CEG_Assets!$AP$3)*365*CEG_Assets!$T$3*S66/1000000*(1+CEG_RevAdj) -> 967.71924 | T74: =(CEG_Assets!$D$3-T67)*INDEX(Prices!T:T,CEG_Assets!$AP$3)*365*CEG_Assets!$T$3*T66/1000000*(1+CEG_RevAdj) -> 987.07363 | U74: =(CEG_Assets!$D$3-U67)*INDEX(Prices!U:U,CEG_Assets!$AP$3)*365*CEG_Assets!$T$3*U66/1000000*(1+CEG_RevAdj) -> 1006.8151 | V74: =(CEG_Assets!$D$3-V67)*INDEX(Prices!V:V,CEG_Assets!$AP$3)*365*CEG_Assets!$T$3*V66/1000000*(1+CEG_RevAdj) -> 1026.9514 | W74: =(CEG_Assets!$D$3-W67)*INDEX(Prices!W:W,CEG_Assets!$AP$3)*365*CEG_Assets!$T$3*W66/1000000*(1+CEG_RevAdj) -> 1047.4904 | X74: =(CEG_Assets!$D$3-X67)*INDEX(Prices!X:X,CEG_Assets!$AP$3)*365*CEG_Assets!$T$3*X66/1000000*(1+CEG_RevAdj) -> 1068.4402 | Y74: =(CEG_Assets!$D$3-Y67)*INDEX(Prices!Y:Y,CEG_Assets!$AP$3)*365*CEG_Assets!$T$3*Y66/1000000*(1+CEG_RevAdj) -> 1089.809 | Z74: =(CEG_Assets!$D$3-Z67)*INDEX(Prices!Z:Z,CEG_Assets!$AP$3)*365*CEG_Assets!$T$3*Z66/1000000*(1+CEG_RevAdj) -> 1111.6052 | AA74: =(CEG_Assets!$D$3-AA67)*INDEX(Prices!AA:AA,CEG_Assets!$AP$3)*365*CEG_Assets!$T$3*AA66/1000000*(1+CEG_RevAdj) -> 1245.0453 | AB74: =(CEG_Assets!$D$3-AB67)*INDEX(Prices!AB:AB,CEG_Assets!$AP$3)*365*CEG_Assets!$T$3*AB66/1000000*(1+CEG_RevAdj) -> 1269.9462 | AC74: =(CEG_Assets!$D$3-AC67)*INDEX(Prices!AC:AC,CEG_Assets!$AP$3)*365*CEG_Assets!$T$3*AC66/1000000*(1+CEG_RevAdj) -> 1295.3451 | AD74: =(CEG_Assets!$D$3-AD67)*INDEX(Prices!AD:AD,CEG_Assets!$AP$3)*365*CEG_Assets!$T$3*AD66/1000000*(1+CEG_RevAdj) -> 1321.252 | AE74: =(CEG_Assets!$D$3-AE67)*INDEX(Prices!AE:AE,CEG_Assets!$AP$3)*365*CEG_Assets!$T$3*AE66/1000000*(1+CEG_RevAdj) -> 1347.677 | AF74: =(CEG_Assets!$D$3-AF67)*INDEX(Prices!AF:AF,CEG_Assets!$AP$3)*365*CEG_Assets!$T$3*AF66/1000000*(1+CEG_RevAdj) -> 1374.6306 | AG74: =(CEG_Assets!$D$3-AG67)*INDEX(Prices!AG:AG,CEG_Assets!$AP$3)*365*CEG_Assets!$T$3*AG66/1000000*(1+CEG_RevAdj) -> 1402.1232 | AH74: =(CEG_Assets!$D$3-AH67)*INDEX(Prices!AH:AH,CEG_Assets!$AP$3)*365*CEG_Assets!$T$3*AH66/1000000*(1+CEG_RevAdj) -> 1430.1656 | AI74: =(CEG_Assets!$D$3-AI67)*INDEX(Prices!AI:AI,CEG_Assets!$AP$3)*365*CEG_Assets!$T$3*AI66/1000000*(1+CEG_RevAdj) -> 1458.769 | AJ74: =(CEG_Assets!$D$3-AJ67)*INDEX(Prices!AJ:AJ,CEG_Assets!$AP$3)*365*CEG_Assets!$T$3*AJ66/1000000*(1+CEG_RevAdj) -> 0 | AK74: =(CEG_Assets!$D$3-AK67)*INDEX(Prices!AK:AK,CEG_Assets!$AP$3)*365*CEG_Assets!$T$3*AK66/1000000*(1+CEG_RevAdj) -> 0 | AL74: =(CEG_Assets!$D$3-AL67)*INDEX(Prices!AL:AL,CEG_Assets!$AP$3)*365*CEG_Assets!$T$3*AL66/1000000*(1+CEG_RevAdj) -> 0 | AM74: =(CEG_Assets!$D$3-AM67)*INDEX(Prices!AM:AM,CEG_Assets!$AP$3)*365*CEG_Assets!$T$3*AM66/1000000*(1+CEG_RevAdj) -> 0 | AN74: =(CEG_Assets!$D$3-AN67)*INDEX(Prices!AN:AN,CEG_Assets!$AP$3)*365*CEG_Assets!$T$3*AN66/1000000*(1+CEG_RevAdj) -> 0 | AO74: =(CEG_Assets!$D$3-AO67)*INDEX(Prices!AO:AO,CEG_Assets!$AP$3)*365*CEG_Assets!$T$3*AO66/1000000*(1+CEG_RevAdj) -> 0 | AP74: =(CEG_Assets!$D$3-AP67)*INDEX(Prices!AP:AP,CEG_Assets!$AP$3)*365*CEG_Assets!$T$3*AP66/1000000*(1+CEG_RevAdj) -> 0 | AQ74: =(CEG_Assets!$D$3-AQ67)*INDEX(Prices!AQ:AQ,CEG_Assets!$AP$3)*365*CEG_Assets!$T$3*AQ66/1000000*(1+CEG_RevAdj) -> 0 | AR74: =(CEG_Assets!$D$3-AR67)*INDEX(Prices!AR:AR,CEG_Assets!$AP$3)*365*CEG_Assets!$T$3*AR66/1000000*(1+CEG_RevAdj) -> 0 | AS74: =(CEG_Assets!$D$3-AS67)*INDEX(Prices!AS:AS,CEG_Assets!$AP$3)*365*CEG_Assets!$T$3*AS66/1000000*(1+CEG_RevAdj) -> 0
A75: Long-term PPA revenue ($mm) | B75: ppa | C75: =SUM(G75:AS75) -> 12810.098 | G75: =G69*(CEG_Assets!$AD$3+CEG_PPAAdj)/1000000*(1+CEG_RevAdj) -> 640.50492 | H75: =H69*(CEG_Assets!$AD$3+CEG_PPAAdj)/1000000*(1+CEG_RevAdj) -> 640.50492 | I75: =I69*(CEG_Assets!$AD$3+CEG_PPAAdj)/1000000*(1+CEG_RevAdj) -> 640.50492 | J75: =J69*(CEG_Assets!$AD$3+CEG_PPAAdj)/1000000*(1+CEG_RevAdj) -> 640.50492 | K75: =K69*(CEG_Assets!$AD$3+CEG_PPAAdj)/1000000*(1+CEG_RevAdj) -> 640.50492 | L75: =L69*(CEG_Assets!$AD$3+CEG_PPAAdj)/1000000*(1+CEG_RevAdj) -> 640.50492 | M75: =M69*(CEG_Assets!$AD$3+CEG_PPAAdj)/1000000*(1+CEG_RevAdj) -> 640.50492 | N75: =N69*(CEG_Assets!$AD$3+CEG_PPAAdj)/1000000*(1+CEG_RevAdj) -> 640.50492 | ... AS75: =AS69*(CEG_Assets!$AD$3+CEG_PPAAdj)/1000000*(1+CEG_RevAdj) -> 0
A76: ZEC revenue ($mm) | B76: zec | C76: =SUM(G76:AS76) -> 0 | G76: =IF(G$3<=CEG_Assets!$V$3,G68*CEG_Assets!$U$3,0)/1000000*(1+CEG_RevAdj) -> 0 | H76: =IF(H$3<=CEG_Assets!$V$3,H68*CEG_Assets!$U$3,0)/1000000*(1+CEG_RevAdj) -> 0 | I76: =IF(I$3<=CEG_Assets!$V$3,I68*CEG_Assets!$U$3,0)/1000000*(1+CEG_RevAdj) -> 0 | J76: =IF(J$3<=CEG_Assets!$V$3,J68*CEG_Assets!$U$3,0)/1000000*(1+CEG_RevAdj) -> 0 | K76: =IF(K$3<=CEG_Assets!$V$3,K68*CEG_Assets!$U$3,0)/1000000*(1+CEG_RevAdj) -> 0 | L76: =IF(L$3<=CEG_Assets!$V$3,L68*CEG_Assets!$U$3,0)/1000000*(1+CEG_RevAdj) -> 0 | M76: =IF(M$3<=CEG_Assets!$V$3,M68*CEG_Assets!$U$3,0)/1000000*(1+CEG_RevAdj) -> 0 | N76: =IF(N$3<=CEG_Assets!$V$3,N68*CEG_Assets!$U$3,0)/1000000*(1+CEG_RevAdj) -> 0 | ... AS76: =IF(AS$3<=CEG_Assets!$V$3,AS68*CEG_Assets!$U$3,0)/1000000*(1+CEG_RevAdj) -> 0
A77: Total revenue ($mm) | B77: revenue | C77: =SUM(G77:AS77) -> 205467.03 | G77: =G73+G74+G75+G76 -> 6374.0785 | H77: =H73+H74+H75+H76 -> 6428.5162 | I77: =I73+I74+I75+I76 -> 5872.7612 | J77: =J73+J74+J75+J76 -> 5664.789 | K77: =K73+K74+K75+K76 -> 5765.2747 | L77: =L73+L74+L75+L76 -> 5867.7701 | M77: =M73+M74+M75+M76 -> 5972.3154 | N77: =N73+N74+N75+N76 -> 6078.9516 | ... AS77: =AS73+AS74+AS75+AS76 -> 0
A78: Fuel & variable cost ($mm) | B78: fuelvar | C78: =SUM(G78:AS78) -> 19906.747 | G78: =((CEG_Assets!$K$3*G70+CEG_Assets!$M$3*G$4)*G68*G72+CEG_Assets!$N$3*(1+CEG_Assets!$Q$3)^(G$3-2026)*(G68+G69))/1000000*(1+CEG_FuelAdj) -> 475.59743 | H78: =((CEG_Assets!$K$3*H70+CEG_Assets!$M$3*H$4)*H68*H72+CEG_Assets!$N$3*(1+CEG_Assets!$Q$3)^(H$3-2026)*(H68+H69))/1000000*(1+CEG_FuelAdj) -> 487.48736 | I78: =((CEG_Assets!$K$3*I70+CEG_Assets!$M$3*I$4)*I68*I72+CEG_Assets!$N$3*(1+CEG_Assets!$Q$3)^(I$3-2026)*(I68+I69))/1000000*(1+CEG_FuelAdj) -> 499.67455 | J78: =((CEG_Assets!$K$3*J70+CEG_Assets!$M$3*J$4)*J68*J72+CEG_Assets!$N$3*(1+CEG_Assets!$Q$3)^(J$3-2026)*(J68+J69))/1000000*(1+CEG_FuelAdj) -> 512.16641 | K78: =((CEG_Assets!$K$3*K70+CEG_Assets!$M$3*K$4)*K68*K72+CEG_Assets!$N$3*(1+CEG_Assets!$Q$3)^(K$3-2026)*(K68+K69))/1000000*(1+CEG_FuelAdj) -> 524.97057 | L78: =((CEG_Assets!$K$3*L70+CEG_Assets!$M$3*L$4)*L68*L72+CEG_Assets!$N$3*(1+CEG_Assets!$Q$3)^(L$3-2026)*(L68+L69))/1000000*(1+CEG_FuelAdj) -> 538.09484 | M78: =((CEG_Assets!$K$3*M70+CEG_Assets!$M$3*M$4)*M68*M72+CEG_Assets!$N$3*(1+CEG_Assets!$Q$3)^(M$3-2026)*(M68+M69))/1000000*(1+CEG_FuelAdj) -> 551.54721 | N78: =((CEG_Assets!$K$3*N70+CEG_Assets!$M$3*N$4)*N68*N72+CEG_Assets!$N$3*(1+CEG_Assets!$Q$3)^(N$3-2026)*(N68+N69))/1000000*(1+CEG_FuelAdj) -> 565.33589 | ... AS78: =((CEG_Assets!$K$3*AS70+CEG_Assets!$M$3*AS$4)*AS68*AS72+CEG_Assets!$N$3*(1+CEG_Assets!$Q$3)^(AS$3-2026)*(AS68+AS69))/1000000*(1+CEG_FuelAdj) -> 0
A79: Gross margin ($mm) | B79: gm | C79: =SUM(G79:AS79) -> 185560.28 | G79: =G77-G78 -> 5898.4811 | H79: =H77-H78 -> 5941.0288 | I79: =I77-I78 -> 5373.0866 | J79: =J77-J78 -> 5152.6226 | K79: =K77-K78 -> 5240.3041 | L79: =L77-L78 -> 5329.6753 | M79: =M77-M78 -> 5420.7682 | N79: =N77-N78 -> 5513.6157 | ... AS79: =AS77-AS78 -> 0
A80: Fixed O&M ($mm) | B80: fom | C80: =SUM(G80:AS80) -> 80712.809 | G80: =(CEG_Assets!$R$3*CEG_Assets!$D$3*1000*G$4*G66+CEG_Assets!$O$3*(1+CEG_Assets!$Q$3)^(G$3-2026)*(G68+G69))/1000000*(1+CEG_OMAdj) -> 1928.3314 | H80: =(CEG_Assets!$R$3*CEG_Assets!$D$3*1000*H$4*H66+CEG_Assets!$O$3*(1+CEG_Assets!$Q$3)^(H$3-2026)*(H68+H69))/1000000*(1+CEG_OMAdj) -> 1976.5397 | I80: =(CEG_Assets!$R$3*CEG_Assets!$D$3*1000*I$4*I66+CEG_Assets!$O$3*(1+CEG_Assets!$Q$3)^(I$3-2026)*(I68+I69))/1000000*(1+CEG_OMAdj) -> 2025.9532 | J80: =(CEG_Assets!$R$3*CEG_Assets!$D$3*1000*J$4*J66+CEG_Assets!$O$3*(1+CEG_Assets!$Q$3)^(J$3-2026)*(J68+J69))/1000000*(1+CEG_OMAdj) -> 2076.602 | K80: =(CEG_Assets!$R$3*CEG_Assets!$D$3*1000*K$4*K66+CEG_Assets!$O$3*(1+CEG_Assets!$Q$3)^(K$3-2026)*(K68+K69))/1000000*(1+CEG_OMAdj) -> 2128.517 | L80: =(CEG_Assets!$R$3*CEG_Assets!$D$3*1000*L$4*L66+CEG_Assets!$O$3*(1+CEG_Assets!$Q$3)^(L$3-2026)*(L68+L69))/1000000*(1+CEG_OMAdj) -> 2181.73 | M80: =(CEG_Assets!$R$3*CEG_Assets!$D$3*1000*M$4*M66+CEG_Assets!$O$3*(1+CEG_Assets!$Q$3)^(M$3-2026)*(M68+M69))/1000000*(1+CEG_OMAdj) -> 2236.2732 | N80: =(CEG_Assets!$R$3*CEG_Assets!$D$3*1000*N$4*N66+CEG_Assets!$O$3*(1+CEG_Assets!$Q$3)^(N$3-2026)*(N68+N69))/1000000*(1+CEG_OMAdj) -> 2292.18 | ... AS80: =(CEG_Assets!$R$3*CEG_Assets!$D$3*1000*AS$4*AS66+CEG_Assets!$O$3*(1+CEG_Assets!$Q$3)^(AS$3-2026)*(AS68+AS69))/1000000*(1+CEG_OMAdj) -> 0
A81: Asset EBITDA ($mm) | B81: ebitda | C81: =SUM(G81:AS81) -> 104847.48 | G81: =G79-G80 -> 3970.1497 | H81: =H79-H80 -> 3964.4892 | I81: =I79-I80 -> 3347.1335 | J81: =J79-J80 -> 3076.0206 | K81: =K79-K80 -> 3111.7871 | L81: =L79-L80 -> 3147.9453 | M81: =M79-M80 -> 3184.495 | N81: =N79-N80 -> 3221.4357 | ... AS81: =AS79-AS80 -> 0
A82: Capex - sustaining + one-off ($mm) | B82: capex | C82: =SUM(G82:AS82) -> 27869.445 | G82: =((CEG_Assets!$S$3*CEG_Assets!$D$3*1000*G$4*G66+CEG_Assets!$P$3*(1+CEG_Assets!$Q$3)^(G$3-2026)*(G68+G69))/1000000+IF(G$3=CEG_Assets!$AH$3,CEG_Assets!$AG$3,0))*(1+CEG_CapexAdj) -> 665.8364 | H82: =((CEG_Assets!$S$3*CEG_Assets!$D$3*1000*H$4*H66+CEG_Assets!$P$3*(1+CEG_Assets!$Q$3)^(H$3-2026)*(H68+H69))/1000000+IF(H$3=CEG_Assets!$AH$3,CEG_Assets!$AG$3,0))*(1+CEG_CapexAdj) -> 682.48231 | I82: =((CEG_Assets!$S$3*CEG_Assets!$D$3*1000*I$4*I66+CEG_Assets!$P$3*(1+CEG_Assets!$Q$3)^(I$3-2026)*(I68+I69))/1000000+IF(I$3=CEG_Assets!$AH$3,CEG_Assets!$AG$3,0))*(1+CEG_CapexAdj) -> 699.54437 | J82: =((CEG_Assets!$S$3*CEG_Assets!$D$3*1000*J$4*J66+CEG_Assets!$P$3*(1+CEG_Assets!$Q$3)^(J$3-2026)*(J68+J69))/1000000+IF(J$3=CEG_Assets!$AH$3,CEG_Assets!$AG$3,0))*(1+CEG_CapexAdj) -> 717.03297 | K82: =((CEG_Assets!$S$3*CEG_Assets!$D$3*1000*K$4*K66+CEG_Assets!$P$3*(1+CEG_Assets!$Q$3)^(K$3-2026)*(K68+K69))/1000000+IF(K$3=CEG_Assets!$AH$3,CEG_Assets!$AG$3,0))*(1+CEG_CapexAdj) -> 734.9588 | L82: =((CEG_Assets!$S$3*CEG_Assets!$D$3*1000*L$4*L66+CEG_Assets!$P$3*(1+CEG_Assets!$Q$3)^(L$3-2026)*(L68+L69))/1000000+IF(L$3=CEG_Assets!$AH$3,CEG_Assets!$AG$3,0))*(1+CEG_CapexAdj) -> 753.33277 | M82: =((CEG_Assets!$S$3*CEG_Assets!$D$3*1000*M$4*M66+CEG_Assets!$P$3*(1+CEG_Assets!$Q$3)^(M$3-2026)*(M68+M69))/1000000+IF(M$3=CEG_Assets!$AH$3,CEG_Assets!$AG$3,0))*(1+CEG_CapexAdj) -> 772.16609 | N82: =((CEG_Assets!$S$3*CEG_Assets!$D$3*1000*N$4*N66+CEG_Assets!$P$3*(1+CEG_Assets!$Q$3)^(N$3-2026)*(N68+N69))/1000000+IF(N$3=CEG_Assets!$AH$3,CEG_Assets!$AG$3,0))*(1+CEG_CapexAdj) -> 791.47024 | ... AS82: =((CEG_Assets!$S$3*CEG_Assets!$D$3*1000*AS$4*AS66+CEG_Assets!$P$3*(1+CEG_Assets!$Q$3)^(AS$3-2026)*(AS68+AS69))/1000000+IF(AS$3=CEG_Assets!$AH$3,CEG_Assets!$AG$3,0))*(1+CEG_CapexAdj) -> 0
A83: Pre-tax cash flow ($mm) | B83: pretax | C83: =SUM(G83:AS83) -> 76978.03 | G83: =IF(CEG_Assets!$Y$3=1,MAX(0,G81-G82),G81-G82) -> 3304.3133 | H83: =IF(CEG_Assets!$Y$3=1,MAX(0,H81-H82),H81-H82) -> 3282.0069 | I83: =IF(CEG_Assets!$Y$3=1,MAX(0,I81-I82),I81-I82) -> 2647.5891 | J83: =IF(CEG_Assets!$Y$3=1,MAX(0,J81-J82),J81-J82) -> 2358.9876 | K83: =IF(CEG_Assets!$Y$3=1,MAX(0,K81-K82),K81-K82) -> 2376.8283 | L83: =IF(CEG_Assets!$Y$3=1,MAX(0,L81-L82),L81-L82) -> 2394.6125 | M83: =IF(CEG_Assets!$Y$3=1,MAX(0,M81-M82),M81-M82) -> 2412.3289 | N83: =IF(CEG_Assets!$Y$3=1,MAX(0,N81-N82),N81-N82) -> 2429.9654 | ... AS83: =IF(CEG_Assets!$Y$3=1,MAX(0,AS81-AS82),AS81-AS82) -> 0
A84: 45U credit - untaxed ($mm) | B84: ptc | C84: =SUM(G84:AS84) -> 0 | G84: =IF(AND(CEG_Assets!$W$3=1,G$3<=PTCLast,G68>0),G68*MAX(0,PTCCredit*(1+Infl)^(G$3-PTCBase)-0.8*MAX(0,(G73+G74+G76)*1000000/MAX(1,G68)-PTCThresh*(1+Infl)^(G$3-PTCBase)))/1000000,0) -> 0 | H84: =IF(AND(CEG_Assets!$W$3=1,H$3<=PTCLast,H68>0),H68*MAX(0,PTCCredit*(1+Infl)^(H$3-PTCBase)-0.8*MAX(0,(H73+H74+H76)*1000000/MAX(1,H68)-PTCThresh*(1+Infl)^(H$3-PTCBase)))/1000000,0) -> 0 | I84: =IF(AND(CEG_Assets!$W$3=1,I$3<=PTCLast,I68>0),I68*MAX(0,PTCCredit*(1+Infl)^(I$3-PTCBase)-0.8*MAX(0,(I73+I74+I76)*1000000/MAX(1,I68)-PTCThresh*(1+Infl)^(I$3-PTCBase)))/1000000,0) -> 0 | J84: =IF(AND(CEG_Assets!$W$3=1,J$3<=PTCLast,J68>0),J68*MAX(0,PTCCredit*(1+Infl)^(J$3-PTCBase)-0.8*MAX(0,(J73+J74+J76)*1000000/MAX(1,J68)-PTCThresh*(1+Infl)^(J$3-PTCBase)))/1000000,0) -> 0 | K84: =IF(AND(CEG_Assets!$W$3=1,K$3<=PTCLast,K68>0),K68*MAX(0,PTCCredit*(1+Infl)^(K$3-PTCBase)-0.8*MAX(0,(K73+K74+K76)*1000000/MAX(1,K68)-PTCThresh*(1+Infl)^(K$3-PTCBase)))/1000000,0) -> 0 | L84: =IF(AND(CEG_Assets!$W$3=1,L$3<=PTCLast,L68>0),L68*MAX(0,PTCCredit*(1+Infl)^(L$3-PTCBase)-0.8*MAX(0,(L73+L74+L76)*1000000/MAX(1,L68)-PTCThresh*(1+Infl)^(L$3-PTCBase)))/1000000,0) -> 0 | M84: =IF(AND(CEG_Assets!$W$3=1,M$3<=PTCLast,M68>0),M68*MAX(0,PTCCredit*(1+Infl)^(M$3-PTCBase)-0.8*MAX(0,(M73+M74+M76)*1000000/MAX(1,M68)-PTCThresh*(1+Infl)^(M$3-PTCBase)))/1000000,0) -> 0 | N84: =IF(AND(CEG_Assets!$W$3=1,N$3<=PTCLast,N68>0),N68*MAX(0,PTCCredit*(1+Infl)^(N$3-PTCBase)-0.8*MAX(0,(N73+N74+N76)*1000000/MAX(1,N68)-PTCThresh*(1+Infl)^(N$3-PTCBase)))/1000000,0) -> 0 | ... AS84: =IF(AND(CEG_Assets!$W$3=1,AS$3<=PTCLast,AS68>0),AS68*MAX(0,PTCCredit*(1+Infl)^(AS$3-PTCBase)-0.8*MAX(0,(AS73+AS74+AS76)*1000000/MAX(1,AS68)-PTCThresh*(1+Infl)^(AS$3-PTCBase)))/1000000,0) -> 0
A85: of which contracted pre-tax ($mm) | B85: con_cf | G85: =G75-G69*(CEG_Assets!$N$3*(1+CEG_FuelAdj)+CEG_Assets!$O$3*(1+CEG_OMAdj)+CEG_Assets!$P$3*(1+CEG_CapexAdj))*(1+CEG_Assets!$Q$3)^(G$3-2026)/1000000 -> 366.3123 | H85: =H75-H69*(CEG_Assets!$N$3*(1+CEG_FuelAdj)+CEG_Assets!$O$3*(1+CEG_OMAdj)+CEG_Assets!$P$3*(1+CEG_CapexAdj))*(1+CEG_Assets!$Q$3)^(H$3-2026)/1000000 -> 359.45748 | I85: =I75-I69*(CEG_Assets!$N$3*(1+CEG_FuelAdj)+CEG_Assets!$O$3*(1+CEG_OMAdj)+CEG_Assets!$P$3*(1+CEG_CapexAdj))*(1+CEG_Assets!$Q$3)^(I$3-2026)/1000000 -> 352.4313 | J85: =J75-J69*(CEG_Assets!$N$3*(1+CEG_FuelAdj)+CEG_Assets!$O$3*(1+CEG_OMAdj)+CEG_Assets!$P$3*(1+CEG_CapexAdj))*(1+CEG_Assets!$Q$3)^(J$3-2026)/1000000 -> 345.22946 | K85: =K75-K69*(CEG_Assets!$N$3*(1+CEG_FuelAdj)+CEG_Assets!$O$3*(1+CEG_OMAdj)+CEG_Assets!$P$3*(1+CEG_CapexAdj))*(1+CEG_Assets!$Q$3)^(K$3-2026)/1000000 -> 337.84757 | L85: =L75-L69*(CEG_Assets!$N$3*(1+CEG_FuelAdj)+CEG_Assets!$O$3*(1+CEG_OMAdj)+CEG_Assets!$P$3*(1+CEG_CapexAdj))*(1+CEG_Assets!$Q$3)^(L$3-2026)/1000000 -> 330.28114 | M85: =M75-M69*(CEG_Assets!$N$3*(1+CEG_FuelAdj)+CEG_Assets!$O$3*(1+CEG_OMAdj)+CEG_Assets!$P$3*(1+CEG_CapexAdj))*(1+CEG_Assets!$Q$3)^(M$3-2026)/1000000 -> 322.52554 | N85: =N75-N69*(CEG_Assets!$N$3*(1+CEG_FuelAdj)+CEG_Assets!$O$3*(1+CEG_OMAdj)+CEG_Assets!$P$3*(1+CEG_CapexAdj))*(1+CEG_Assets!$Q$3)^(N$3-2026)/1000000 -> 314.57606 | ... AS85: =AS75-AS69*(CEG_Assets!$N$3*(1+CEG_FuelAdj)+CEG_Assets!$O$3*(1+CEG_OMAdj)+CEG_Assets!$P$3*(1+CEG_CapexAdj))*(1+CEG_Assets!$Q$3)^(AS$3-2026)/1000000 -> 0
A86: of which merchant pre-tax ($mm) | B86: merch_cf | G86: =G83-G85 -> 2938.001 | H86: =H83-H85 -> 2922.5494 | I86: =I83-I85 -> 2295.1578 | J86: =J83-J85 -> 2013.7582 | K86: =K83-K85 -> 2038.9807 | L86: =L83-L85 -> 2064.3314 | M86: =M83-M85 -> 2089.8033 | N86: =N83-N85 -> 2115.3894 | ... AS86: =AS83-AS85 -> 0
A87: After-tax merchant CF incl. 45U ($mm) | B87: at_m | G87: =G86*(1-TaxRate)+G84 -> 2350.4008 | H87: =H86*(1-TaxRate)+H84 -> 2338.0395 | I87: =I86*(1-TaxRate)+I84 -> 1836.1263 | J87: =J86*(1-TaxRate)+J84 -> 1611.0065 | K87: =K86*(1-TaxRate)+K84 -> 1631.1846 | L87: =L86*(1-TaxRate)+L84 -> 1651.4651 | M87: =M86*(1-TaxRate)+M84 -> 1671.8427 | N87: =N86*(1-TaxRate)+N84 -> 1692.3115 | ... AS87: =AS86*(1-TaxRate)+AS84 -> 0
A88: After-tax contracted CF ($mm) | B88: at_c | G88: =G85*(1-TaxRate) -> 293.04984 | H88: =H85*(1-TaxRate) -> 287.56599 | I88: =I85*(1-TaxRate) -> 281.94504 | J88: =J85*(1-TaxRate) -> 276.18357 | K88: =K85*(1-TaxRate) -> 270.27806 | L88: =L85*(1-TaxRate) -> 264.22491 | M88: =M85*(1-TaxRate) -> 258.02043 | N88: =N85*(1-TaxRate) -> 251.66085 | ... AS88: =AS85*(1-TaxRate) -> 0
A89: Discount factor - merchant | B89: df_m | G89: =(1+CEG_Assets!$AE$3)^-(G$3+0.5-ValDate) -> 0.94391347 | H89: =(1+CEG_Assets!$AE$3)^-(H$3+0.5-ValDate) -> 0.87399395 | I89: =(1+CEG_Assets!$AE$3)^-(I$3+0.5-ValDate) -> 0.80925366 | J89: =(1+CEG_Assets!$AE$3)^-(J$3+0.5-ValDate) -> 0.74930894 | K89: =(1+CEG_Assets!$AE$3)^-(K$3+0.5-ValDate) -> 0.69380458 | L89: =(1+CEG_Assets!$AE$3)^-(L$3+0.5-ValDate) -> 0.64241165 | M89: =(1+CEG_Assets!$AE$3)^-(M$3+0.5-ValDate) -> 0.5948256 | N89: =(1+CEG_Assets!$AE$3)^-(N$3+0.5-ValDate) -> 0.55076444 | ... AS89: =(1+CEG_Assets!$AE$3)^-(AS$3+0.5-ValDate) -> 0.050679168
A90: Discount factor - contracted | B90: df_c | G90: =(1+CEG_Assets!$AF$3)^-(G$3+0.5-ValDate) -> 0.95219103 | H90: =(1+CEG_Assets!$AF$3)^-(H$3+0.5-ValDate) -> 0.89198223 | I90: =(1+CEG_Assets!$AF$3)^-(I$3+0.5-ValDate) -> 0.83558055 | J90: =(1+CEG_Assets!$AF$3)^-(J$3+0.5-ValDate) -> 0.78274524 | K90: =(1+CEG_Assets!$AF$3)^-(K$3+0.5-ValDate) -> 0.73325081 | L90: =(1+CEG_Assets!$AF$3)^-(L$3+0.5-ValDate) -> 0.68688601 | M90: =(1+CEG_Assets!$AF$3)^-(M$3+0.5-ValDate) -> 0.64345293 | N90: =(1+CEG_Assets!$AF$3)^-(N$3+0.5-ValDate) -> 0.60276621 | ... AS90: =(1+CEG_Assets!$AF$3)^-(AS$3+0.5-ValDate) -> 0.079569111
A91: PV merchant ($mm) | B91: pv_m | C91: =SUM(G91:AS91) -> 21635.29 | D91: =SUMIF($G$3:$AS$3,"<="&Horizon,G91:AS91) -> 6955.0408 | E91: =(C91-D91)*(1+CEG_Assets!$AE$3)^(Horizon+1-ValDate) -> 20360.31 | G91: =G87*G89 -> 2218.575 | H91: =H87*H89 -> 2043.4324 | I91: =I87*I89 -> 1485.8919 | J91: =J87*J89 -> 1207.1416 | K91: =K87*K89 -> 1131.7233 | L91: =L87*L89 -> 1060.9204 | M91: =M87*M89 -> 994.45482 | N91: =N87*N89 -> 932.065 | ... AS91: =AS87*AS89 -> 0
A92: PV contracted ($mm) | B92: pv_c | C92: =SUM(G92:AS92) -> 2708.3213 | D92: =SUMIF($G$3:$AS$3,"<="&Horizon,G92:AS92) -> 987.31234 | E92: =(C92-D92)*(1+CEG_Assets!$AF$3)^(Horizon+1-ValDate) -> 2271.6773 | G92: =G88*G90 -> 279.03943 | H92: =H88*H90 -> 256.50375 | I92: =I88*I90 -> 235.58779 | J92: =J88*J90 -> 216.18137 | K92: =K88*K90 -> 198.1816 | L92: =L88*L90 -> 181.49239 | M92: =M88*M90 -> 166.024 | N92: =N88*N90 -> 151.69266 | ... AS92: =AS88*AS90 -> 0
A93: $/kW-method value ($mm) | B93: fixedval | C93: =IF(CEG_Assets!$H$3="$/kW",CEG_Assets!$D$3*CEG_Assets!$AI$3*(1+0.4*(PJMWLR/PJMWLRBase-1))/1000,0) -> 0 | E93: =C93 -> 0 | G93: =0 -> 0 | H93: =0 -> 0 | I93: =0 -> 0 | J93: =0 -> 0 | K93: =0 -> 0 | L93: =0 -> 0 | M93: =0 -> 0 | N93: =0 -> 0 | ... AS93: =0 -> 0
A95: =CEG_Assets!$A$4 -> Nuclear - Clinton (MISO) - Meta 20-yr PPA
A96: Operating (1/0) | B96: op | G96: =IF(AND(G$3>=CEG_Assets!$E$4,G$3<=CEG_Assets!$F$4,CEG_Assets!$H$4="Cashflow"),1,0) -> 1 | H96: =IF(AND(H$3>=CEG_Assets!$E$4,H$3<=CEG_Assets!$F$4,CEG_Assets!$H$4="Cashflow"),1,0) -> 1 | I96: =IF(AND(I$3>=CEG_Assets!$E$4,I$3<=CEG_Assets!$F$4,CEG_Assets!$H$4="Cashflow"),1,0) -> 1 | J96: =IF(AND(J$3>=CEG_Assets!$E$4,J$3<=CEG_Assets!$F$4,CEG_Assets!$H$4="Cashflow"),1,0) -> 1 | K96: =IF(AND(K$3>=CEG_Assets!$E$4,K$3<=CEG_Assets!$F$4,CEG_Assets!$H$4="Cashflow"),1,0) -> 1 | L96: =IF(AND(L$3>=CEG_Assets!$E$4,L$3<=CEG_Assets!$F$4,CEG_Assets!$H$4="Cashflow"),1,0) -> 1 | M96: =IF(AND(M$3>=CEG_Assets!$E$4,M$3<=CEG_Assets!$F$4,CEG_Assets!$H$4="Cashflow"),1,0) -> 1 | N96: =IF(AND(N$3>=CEG_Assets!$E$4,N$3<=CEG_Assets!$F$4,CEG_Assets!$H$4="Cashflow"),1,0) -> 1 | ... AS96: =IF(AND(AS$3>=CEG_Assets!$E$4,AS$3<=CEG_Assets!$F$4,CEG_Assets!$H$4="Cashflow"),1,0) -> 0
A97: Contracted MW | B97: cmw | G97: =IF(AND(G$3>=CEG_Assets!$AA$4,G$3<=CEG_Assets!$AB$4),MIN(CEG_Assets!$D$4,CEG_Assets!$Z$4*MIN(1,(G$3-CEG_Assets!$AA$4+1)/MAX(1,CEG_Assets!$AC$4))),0)*G96 -> 1080 | H97: =IF(AND(H$3>=CEG_Assets!$AA$4,H$3<=CEG_Assets!$AB$4),MIN(CEG_Assets!$D$4,CEG_Assets!$Z$4*MIN(1,(H$3-CEG_Assets!$AA$4+1)/MAX(1,CEG_Assets!$AC$4))),0)*H96 -> 1080 | I97: =IF(AND(I$3>=CEG_Assets!$AA$4,I$3<=CEG_Assets!$AB$4),MIN(CEG_Assets!$D$4,CEG_Assets!$Z$4*MIN(1,(I$3-CEG_Assets!$AA$4+1)/MAX(1,CEG_Assets!$AC$4))),0)*I96 -> 1080 | J97: =IF(AND(J$3>=CEG_Assets!$AA$4,J$3<=CEG_Assets!$AB$4),MIN(CEG_Assets!$D$4,CEG_Assets!$Z$4*MIN(1,(J$3-CEG_Assets!$AA$4+1)/MAX(1,CEG_Assets!$AC$4))),0)*J96 -> 1080 | K97: =IF(AND(K$3>=CEG_Assets!$AA$4,K$3<=CEG_Assets!$AB$4),MIN(CEG_Assets!$D$4,CEG_Assets!$Z$4*MIN(1,(K$3-CEG_Assets!$AA$4+1)/MAX(1,CEG_Assets!$AC$4))),0)*K96 -> 1080 | L97: =IF(AND(L$3>=CEG_Assets!$AA$4,L$3<=CEG_Assets!$AB$4),MIN(CEG_Assets!$D$4,CEG_Assets!$Z$4*MIN(1,(L$3-CEG_Assets!$AA$4+1)/MAX(1,CEG_Assets!$AC$4))),0)*L96 -> 1080 | M97: =IF(AND(M$3>=CEG_Assets!$AA$4,M$3<=CEG_Assets!$AB$4),MIN(CEG_Assets!$D$4,CEG_Assets!$Z$4*MIN(1,(M$3-CEG_Assets!$AA$4+1)/MAX(1,CEG_Assets!$AC$4))),0)*M96 -> 1080 | N97: =IF(AND(N$3>=CEG_Assets!$AA$4,N$3<=CEG_Assets!$AB$4),MIN(CEG_Assets!$D$4,CEG_Assets!$Z$4*MIN(1,(N$3-CEG_Assets!$AA$4+1)/MAX(1,CEG_Assets!$AC$4))),0)*N96 -> 1080 | ... AS97: =IF(AND(AS$3>=CEG_Assets!$AA$4,AS$3<=CEG_Assets!$AB$4),MIN(CEG_Assets!$D$4,CEG_Assets!$Z$4*MIN(1,(AS$3-CEG_Assets!$AA$4+1)/MAX(1,CEG_Assets!$AC$4))),0)*AS96 -> 0
A98: Merchant generation (MWh) | B98: gen_m | G98: =(CEG_Assets!$D$4-G97)*8760*CEG_Assets!$I$4*G96 -> 0 | H98: =(CEG_Assets!$D$4-H97)*8760*CEG_Assets!$I$4*H96 -> 0 | I98: =(CEG_Assets!$D$4-I97)*8760*CEG_Assets!$I$4*I96 -> 0 | J98: =(CEG_Assets!$D$4-J97)*8760*CEG_Assets!$I$4*J96 -> 0 | K98: =(CEG_Assets!$D$4-K97)*8760*CEG_Assets!$I$4*K96 -> 0 | L98: =(CEG_Assets!$D$4-L97)*8760*CEG_Assets!$I$4*L96 -> 0 | M98: =(CEG_Assets!$D$4-M97)*8760*CEG_Assets!$I$4*M96 -> 0 | N98: =(CEG_Assets!$D$4-N97)*8760*CEG_Assets!$I$4*N96 -> 0 | ... AS98: =(CEG_Assets!$D$4-AS97)*8760*CEG_Assets!$I$4*AS96 -> 0
A99: Contracted generation (MWh) | B99: gen_c | G99: =G97*8760*CEG_Assets!$I$4*G96 -> 8845848 | H99: =H97*8760*CEG_Assets!$I$4*H96 -> 8845848 | I99: =I97*8760*CEG_Assets!$I$4*I96 -> 8845848 | J99: =J97*8760*CEG_Assets!$I$4*J96 -> 8845848 | K99: =K97*8760*CEG_Assets!$I$4*K96 -> 8845848 | L99: =L97*8760*CEG_Assets!$I$4*L96 -> 8845848 | M99: =M97*8760*CEG_Assets!$I$4*M96 -> 8845848 | N99: =N97*8760*CEG_Assets!$I$4*N96 -> 8845848 | ... AS99: =AS97*8760*CEG_Assets!$I$4*AS96 -> 0
A100: Fuel price, delivered ($/MMBtu) | B100: fuelp | G100: =IF(ISNUMBER(CEG_Assets!$L$4),CEG_Assets!$L$4*G$4,INDEX(Prices!G:G,CEG_Assets!$AO$4)+FuelAdder*G$4) -> 4.08 | H100: =IF(ISNUMBER(CEG_Assets!$L$4),CEG_Assets!$L$4*H$4,INDEX(Prices!H:H,CEG_Assets!$AO$4)+FuelAdder*H$4) -> 4.1616 | I100: =IF(ISNUMBER(CEG_Assets!$L$4),CEG_Assets!$L$4*I$4,INDEX(Prices!I:I,CEG_Assets!$AO$4)+FuelAdder*I$4) -> 4.3509528 | J100: =IF(ISNUMBER(CEG_Assets!$L$4),CEG_Assets!$L$4*J$4,INDEX(Prices!J:J,CEG_Assets!$AO$4)+FuelAdder*J$4) -> 4.4379719 | K100: =IF(ISNUMBER(CEG_Assets!$L$4),CEG_Assets!$L$4*K$4,INDEX(Prices!K:K,CEG_Assets!$AO$4)+FuelAdder*K$4) -> 4.5267313 | L100: =IF(ISNUMBER(CEG_Assets!$L$4),CEG_Assets!$L$4*L$4,INDEX(Prices!L:L,CEG_Assets!$AO$4)+FuelAdder*L$4) -> 4.6172659 | M100: =IF(ISNUMBER(CEG_Assets!$L$4),CEG_Assets!$L$4*M$4,INDEX(Prices!M:M,CEG_Assets!$AO$4)+FuelAdder*M$4) -> 4.7096112 | N100: =IF(ISNUMBER(CEG_Assets!$L$4),CEG_Assets!$L$4*N$4,INDEX(Prices!N:N,CEG_Assets!$AO$4)+FuelAdder*N$4) -> 4.8038035 | O100: =IF(ISNUMBER(CEG_Assets!$L$4),CEG_Assets!$L$4*O$4,INDEX(Prices!O:O,CEG_Assets!$AO$4)+FuelAdder*O$4) -> 4.8998795 | P100: =IF(ISNUMBER(CEG_Assets!$L$4),CEG_Assets!$L$4*P$4,INDEX(Prices!P:P,CEG_Assets!$AO$4)+FuelAdder*P$4) -> 4.9978771 | Q100: =IF(ISNUMBER(CEG_Assets!$L$4),CEG_Assets!$L$4*Q$4,INDEX(Prices!Q:Q,CEG_Assets!$AO$4)+FuelAdder*Q$4) -> 5.0978347 | R100: =IF(ISNUMBER(CEG_Assets!$L$4),CEG_Assets!$L$4*R$4,INDEX(Prices!R:R,CEG_Assets!$AO$4)+FuelAdder*R$4) -> 5.1997914 | S100: =IF(ISNUMBER(CEG_Assets!$L$4),CEG_Assets!$L$4*S$4,INDEX(Prices!S:S,CEG_Assets!$AO$4)+FuelAdder*S$4) -> 5.3037872 | T100: =IF(ISNUMBER(CEG_Assets!$L$4),CEG_Assets!$L$4*T$4,INDEX(Prices!T:T,CEG_Assets!$AO$4)+FuelAdder*T$4) -> 5.4098629 | U100: =IF(ISNUMBER(CEG_Assets!$L$4),CEG_Assets!$L$4*U$4,INDEX(Prices!U:U,CEG_Assets!$AO$4)+FuelAdder*U$4) -> 5.5180602 | V100: =IF(ISNUMBER(CEG_Assets!$L$4),CEG_Assets!$L$4*V$4,INDEX(Prices!V:V,CEG_Assets!$AO$4)+FuelAdder*V$4) -> 5.6284214 | W100: =IF(ISNUMBER(CEG_Assets!$L$4),CEG_Assets!$L$4*W$4,INDEX(Prices!W:W,CEG_Assets!$AO$4)+FuelAdder*W$4) -> 5.7409898 | X100: =IF(ISNUMBER(CEG_Assets!$L$4),CEG_Assets!$L$4*X$4,INDEX(Prices!X:X,CEG_Assets!$AO$4)+FuelAdder*X$4) -> 5.8558096 | Y100: =IF(ISNUMBER(CEG_Assets!$L$4),CEG_Assets!$L$4*Y$4,INDEX(Prices!Y:Y,CEG_Assets!$AO$4)+FuelAdder*Y$4) -> 5.9729258 | Z100: =IF(ISNUMBER(CEG_Assets!$L$4),CEG_Assets!$L$4*Z$4,INDEX(Prices!Z:Z,CEG_Assets!$AO$4)+FuelAdder*Z$4) -> 6.0923843 | AA100: =IF(ISNUMBER(CEG_Assets!$L$4),CEG_Assets!$L$4*AA$4,INDEX(Prices!AA:AA,CEG_Assets!$AO$4)+FuelAdder*AA$4) -> 6.214232 | AB100: =IF(ISNUMBER(CEG_Assets!$L$4),CEG_Assets!$L$4*AB$4,INDEX(Prices!AB:AB,CEG_Assets!$AO$4)+FuelAdder*AB$4) -> 6.3385167 | AC100: =IF(ISNUMBER(CEG_Assets!$L$4),CEG_Assets!$L$4*AC$4,INDEX(Prices!AC:AC,CEG_Assets!$AO$4)+FuelAdder*AC$4) -> 6.465287 | AD100: =IF(ISNUMBER(CEG_Assets!$L$4),CEG_Assets!$L$4*AD$4,INDEX(Prices!AD:AD,CEG_Assets!$AO$4)+FuelAdder*AD$4) -> 6.5945927 | AE100: =IF(ISNUMBER(CEG_Assets!$L$4),CEG_Assets!$L$4*AE$4,INDEX(Prices!AE:AE,CEG_Assets!$AO$4)+FuelAdder*AE$4) -> 6.7264846 | AF100: =IF(ISNUMBER(CEG_Assets!$L$4),CEG_Assets!$L$4*AF$4,INDEX(Prices!AF:AF,CEG_Assets!$AO$4)+FuelAdder*AF$4) -> 6.8610143 | AG100: =IF(ISNUMBER(CEG_Assets!$L$4),CEG_Assets!$L$4*AG$4,INDEX(Prices!AG:AG,CEG_Assets!$AO$4)+FuelAdder*AG$4) -> 6.9982346 | AH100: =IF(ISNUMBER(CEG_Assets!$L$4),CEG_Assets!$L$4*AH$4,INDEX(Prices!AH:AH,CEG_Assets!$AO$4)+FuelAdder*AH$4) -> 7.1381992 | AI100: =IF(ISNUMBER(CEG_Assets!$L$4),CEG_Assets!$L$4*AI$4,INDEX(Prices!AI:AI,CEG_Assets!$AO$4)+FuelAdder*AI$4) -> 7.2809632 | AJ100: =IF(ISNUMBER(CEG_Assets!$L$4),CEG_Assets!$L$4*AJ$4,INDEX(Prices!AJ:AJ,CEG_Assets!$AO$4)+FuelAdder*AJ$4) -> 7.4265825 | AK100: =IF(ISNUMBER(CEG_Assets!$L$4),CEG_Assets!$L$4*AK$4,INDEX(Prices!AK:AK,CEG_Assets!$AO$4)+FuelAdder*AK$4) -> 7.5751141 | AL100: =IF(ISNUMBER(CEG_Assets!$L$4),CEG_Assets!$L$4*AL$4,INDEX(Prices!AL:AL,CEG_Assets!$AO$4)+FuelAdder*AL$4) -> 7.7266164 | AM100: =IF(ISNUMBER(CEG_Assets!$L$4),CEG_Assets!$L$4*AM$4,INDEX(Prices!AM:AM,CEG_Assets!$AO$4)+FuelAdder*AM$4) -> 7.8811488 | AN100: =IF(ISNUMBER(CEG_Assets!$L$4),CEG_Assets!$L$4*AN$4,INDEX(Prices!AN:AN,CEG_Assets!$AO$4)+FuelAdder*AN$4) -> 8.0387717 | AO100: =IF(ISNUMBER(CEG_Assets!$L$4),CEG_Assets!$L$4*AO$4,INDEX(Prices!AO:AO,CEG_Assets!$AO$4)+FuelAdder*AO$4) -> 8.1995472 | AP100: =IF(ISNUMBER(CEG_Assets!$L$4),CEG_Assets!$L$4*AP$4,INDEX(Prices!AP:AP,CEG_Assets!$AO$4)+FuelAdder*AP$4) -> 8.3635381 | AQ100: =IF(ISNUMBER(CEG_Assets!$L$4),CEG_Assets!$L$4*AQ$4,INDEX(Prices!AQ:AQ,CEG_Assets!$AO$4)+FuelAdder*AQ$4) -> 8.5308089 | AR100: =IF(ISNUMBER(CEG_Assets!$L$4),CEG_Assets!$L$4*AR$4,INDEX(Prices!AR:AR,CEG_Assets!$AO$4)+FuelAdder*AR$4) -> 8.701425 | AS100: =IF(ISNUMBER(CEG_Assets!$L$4),CEG_Assets!$L$4*AS$4,INDEX(Prices!AS:AS,CEG_Assets!$AO$4)+FuelAdder*AS$4) -> 8.8754535
A101: Spread vs fuel ($/MWh) | B101: spark | G101: =INDEX(Prices!G:G,CEG_Assets!$AN$4)*CEG_Assets!$J$4-CEG_Assets!$K$4*G100-CEG_Assets!$M$4*G$4 -> 59.1624 | H101: =INDEX(Prices!H:H,CEG_Assets!$AN$4)*CEG_Assets!$J$4-CEG_Assets!$K$4*H100-CEG_Assets!$M$4*H$4 -> 59.9841 | I101: =INDEX(Prices!I:I,CEG_Assets!$AN$4)*CEG_Assets!$J$4-CEG_Assets!$K$4*I100-CEG_Assets!$M$4*I$4 -> 55.017438 | J101: =INDEX(Prices!J:J,CEG_Assets!$AN$4)*CEG_Assets!$J$4-CEG_Assets!$K$4*J100-CEG_Assets!$M$4*J$4 -> 53.566193 | K101: =INDEX(Prices!K:K,CEG_Assets!$AN$4)*CEG_Assets!$J$4-CEG_Assets!$K$4*K100-CEG_Assets!$M$4*K$4 -> 54.637517 | L101: =INDEX(Prices!L:L,CEG_Assets!$AN$4)*CEG_Assets!$J$4-CEG_Assets!$K$4*L100-CEG_Assets!$M$4*L$4 -> 55.730267 | M101: =INDEX(Prices!M:M,CEG_Assets!$AN$4)*CEG_Assets!$J$4-CEG_Assets!$K$4*M100-CEG_Assets!$M$4*M$4 -> 56.844873 | N101: =INDEX(Prices!N:N,CEG_Assets!$AN$4)*CEG_Assets!$J$4-CEG_Assets!$K$4*N100-CEG_Assets!$M$4*N$4 -> 57.98177 | O101: =INDEX(Prices!O:O,CEG_Assets!$AN$4)*CEG_Assets!$J$4-CEG_Assets!$K$4*O100-CEG_Assets!$M$4*O$4 -> 59.141406 | P101: =INDEX(Prices!P:P,CEG_Assets!$AN$4)*CEG_Assets!$J$4-CEG_Assets!$K$4*P100-CEG_Assets!$M$4*P$4 -> 60.324234 | Q101: =INDEX(Prices!Q:Q,CEG_Assets!$AN$4)*CEG_Assets!$J$4-CEG_Assets!$K$4*Q100-CEG_Assets!$M$4*Q$4 -> 61.530718 | R101: =INDEX(Prices!R:R,CEG_Assets!$AN$4)*CEG_Assets!$J$4-CEG_Assets!$K$4*R100-CEG_Assets!$M$4*R$4 -> 62.761333 | S101: =INDEX(Prices!S:S,CEG_Assets!$AN$4)*CEG_Assets!$J$4-CEG_Assets!$K$4*S100-CEG_Assets!$M$4*S$4 -> 64.016559 | T101: =INDEX(Prices!T:T,CEG_Assets!$AN$4)*CEG_Assets!$J$4-CEG_Assets!$K$4*T100-CEG_Assets!$M$4*T$4 -> 65.296891 | U101: =INDEX(Prices!U:U,CEG_Assets!$AN$4)*CEG_Assets!$J$4-CEG_Assets!$K$4*U100-CEG_Assets!$M$4*U$4 -> 66.602828 | V101: =INDEX(Prices!V:V,CEG_Assets!$AN$4)*CEG_Assets!$J$4-CEG_Assets!$K$4*V100-CEG_Assets!$M$4*V$4 -> 67.934885 | W101: =INDEX(Prices!W:W,CEG_Assets!$AN$4)*CEG_Assets!$J$4-CEG_Assets!$K$4*W100-CEG_Assets!$M$4*W$4 -> 69.293583 | X101: =INDEX(Prices!X:X,CEG_Assets!$AN$4)*CEG_Assets!$J$4-CEG_Assets!$K$4*X100-CEG_Assets!$M$4*X$4 -> 70.679454 | Y101: =INDEX(Prices!Y:Y,CEG_Assets!$AN$4)*CEG_Assets!$J$4-CEG_Assets!$K$4*Y100-CEG_Assets!$M$4*Y$4 -> 72.093043 | Z101: =INDEX(Prices!Z:Z,CEG_Assets!$AN$4)*CEG_Assets!$J$4-CEG_Assets!$K$4*Z100-CEG_Assets!$M$4*Z$4 -> 73.534904 | AA101: =INDEX(Prices!AA:AA,CEG_Assets!$AN$4)*CEG_Assets!$J$4-CEG_Assets!$K$4*AA100-CEG_Assets!$M$4*AA$4 -> 75.005602 | AB101: =INDEX(Prices!AB:AB,CEG_Assets!$AN$4)*CEG_Assets!$J$4-CEG_Assets!$K$4*AB100-CEG_Assets!$M$4*AB$4 -> 76.505714 | AC101: =INDEX(Prices!AC:AC,CEG_Assets!$AN$4)*CEG_Assets!$J$4-CEG_Assets!$K$4*AC100-CEG_Assets!$M$4*AC$4 -> 78.035829 | AD101: =INDEX(Prices!AD:AD,CEG_Assets!$AN$4)*CEG_Assets!$J$4-CEG_Assets!$K$4*AD100-CEG_Assets!$M$4*AD$4 -> 79.596545 | AE101: =INDEX(Prices!AE:AE,CEG_Assets!$AN$4)*CEG_Assets!$J$4-CEG_Assets!$K$4*AE100-CEG_Assets!$M$4*AE$4 -> 81.188476 | AF101: =INDEX(Prices!AF:AF,CEG_Assets!$AN$4)*CEG_Assets!$J$4-CEG_Assets!$K$4*AF100-CEG_Assets!$M$4*AF$4 -> 82.812246 | AG101: =INDEX(Prices!AG:AG,CEG_Assets!$AN$4)*CEG_Assets!$J$4-CEG_Assets!$K$4*AG100-CEG_Assets!$M$4*AG$4 -> 84.468491 | AH101: =INDEX(Prices!AH:AH,CEG_Assets!$AN$4)*CEG_Assets!$J$4-CEG_Assets!$K$4*AH100-CEG_Assets!$M$4*AH$4 -> 86.15786 | AI101: =INDEX(Prices!AI:AI,CEG_Assets!$AN$4)*CEG_Assets!$J$4-CEG_Assets!$K$4*AI100-CEG_Assets!$M$4*AI$4 -> 87.881018 | AJ101: =INDEX(Prices!AJ:AJ,CEG_Assets!$AN$4)*CEG_Assets!$J$4-CEG_Assets!$K$4*AJ100-CEG_Assets!$M$4*AJ$4 -> 89.638638 | AK101: =INDEX(Prices!AK:AK,CEG_Assets!$AN$4)*CEG_Assets!$J$4-CEG_Assets!$K$4*AK100-CEG_Assets!$M$4*AK$4 -> 91.431411 | AL101: =INDEX(Prices!AL:AL,CEG_Assets!$AN$4)*CEG_Assets!$J$4-CEG_Assets!$K$4*AL100-CEG_Assets!$M$4*AL$4 -> 93.260039 | AM101: =INDEX(Prices!AM:AM,CEG_Assets!$AN$4)*CEG_Assets!$J$4-CEG_Assets!$K$4*AM100-CEG_Assets!$M$4*AM$4 -> 95.12524 | AN101: =INDEX(Prices!AN:AN,CEG_Assets!$AN$4)*CEG_Assets!$J$4-CEG_Assets!$K$4*AN100-CEG_Assets!$M$4*AN$4 -> 97.027744 | AO101: =INDEX(Prices!AO:AO,CEG_Assets!$AN$4)*CEG_Assets!$J$4-CEG_Assets!$K$4*AO100-CEG_Assets!$M$4*AO$4 -> 98.968299 | AP101: =INDEX(Prices!AP:AP,CEG_Assets!$AN$4)*CEG_Assets!$J$4-CEG_Assets!$K$4*AP100-CEG_Assets!$M$4*AP$4 -> 100.94767 | AQ101: =INDEX(Prices!AQ:AQ,CEG_Assets!$AN$4)*CEG_Assets!$J$4-CEG_Assets!$K$4*AQ100-CEG_Assets!$M$4*AQ$4 -> 102.96662 | AR101: =INDEX(Prices!AR:AR,CEG_Assets!$AN$4)*CEG_Assets!$J$4-CEG_Assets!$K$4*AR100-CEG_Assets!$M$4*AR$4 -> 105.02595 | AS101: =INDEX(Prices!AS:AS,CEG_Assets!$AN$4)*CEG_Assets!$J$4-CEG_Assets!$K$4*AS100-CEG_Assets!$M$4*AS$4 -> 107.12647
A102: Runs (1/0) | B102: run | G102: =IF(CEG_Assets!$X$4=1,IF(G101>0,1,0),1) -> 1 | H102: =IF(CEG_Assets!$X$4=1,IF(H101>0,1,0),1) -> 1 | I102: =IF(CEG_Assets!$X$4=1,IF(I101>0,1,0),1) -> 1 | J102: =IF(CEG_Assets!$X$4=1,IF(J101>0,1,0),1) -> 1 | K102: =IF(CEG_Assets!$X$4=1,IF(K101>0,1,0),1) -> 1 | L102: =IF(CEG_Assets!$X$4=1,IF(L101>0,1,0),1) -> 1 | M102: =IF(CEG_Assets!$X$4=1,IF(M101>0,1,0),1) -> 1 | N102: =IF(CEG_Assets!$X$4=1,IF(N101>0,1,0),1) -> 1 | ... AS102: =IF(CEG_Assets!$X$4=1,IF(AS101>0,1,0),1) -> 1
A103: Merchant energy revenue ($mm) | B103: energy | C103: =SUM(G103:AS103) -> 6472.0804 | G103: =G98*INDEX(Prices!G:G,CEG_Assets!$AN$4)*CEG_Assets!$J$4*G102/1000000*(1+CEG_RevAdj) -> 0 | H103: =H98*INDEX(Prices!H:H,CEG_Assets!$AN$4)*CEG_Assets!$J$4*H102/1000000*(1+CEG_RevAdj) -> 0 | I103: =I98*INDEX(Prices!I:I,CEG_Assets!$AN$4)*CEG_Assets!$J$4*I102/1000000*(1+CEG_RevAdj) -> 0 | J103: =J98*INDEX(Prices!J:J,CEG_Assets!$AN$4)*CEG_Assets!$J$4*J102/1000000*(1+CEG_RevAdj) -> 0 | K103: =K98*INDEX(Prices!K:K,CEG_Assets!$AN$4)*CEG_Assets!$J$4*K102/1000000*(1+CEG_RevAdj) -> 0 | L103: =L98*INDEX(Prices!L:L,CEG_Assets!$AN$4)*CEG_Assets!$J$4*L102/1000000*(1+CEG_RevAdj) -> 0 | M103: =M98*INDEX(Prices!M:M,CEG_Assets!$AN$4)*CEG_Assets!$J$4*M102/1000000*(1+CEG_RevAdj) -> 0 | N103: =N98*INDEX(Prices!N:N,CEG_Assets!$AN$4)*CEG_Assets!$J$4*N102/1000000*(1+CEG_RevAdj) -> 0 | O103: =O98*INDEX(Prices!O:O,CEG_Assets!$AN$4)*CEG_Assets!$J$4*O102/1000000*(1+CEG_RevAdj) -> 0 | P103: =P98*INDEX(Prices!P:P,CEG_Assets!$AN$4)*CEG_Assets!$J$4*P102/1000000*(1+CEG_RevAdj) -> 0 | Q103: =Q98*INDEX(Prices!Q:Q,CEG_Assets!$AN$4)*CEG_Assets!$J$4*Q102/1000000*(1+CEG_RevAdj) -> 0 | R103: =R98*INDEX(Prices!R:R,CEG_Assets!$AN$4)*CEG_Assets!$J$4*R102/1000000*(1+CEG_RevAdj) -> 0 | S103: =S98*INDEX(Prices!S:S,CEG_Assets!$AN$4)*CEG_Assets!$J$4*S102/1000000*(1+CEG_RevAdj) -> 0 | T103: =T98*INDEX(Prices!T:T,CEG_Assets!$AN$4)*CEG_Assets!$J$4*T102/1000000*(1+CEG_RevAdj) -> 0 | U103: =U98*INDEX(Prices!U:U,CEG_Assets!$AN$4)*CEG_Assets!$J$4*U102/1000000*(1+CEG_RevAdj) -> 0 | V103: =V98*INDEX(Prices!V:V,CEG_Assets!$AN$4)*CEG_Assets!$J$4*V102/1000000*(1+CEG_RevAdj) -> 0 | W103: =W98*INDEX(Prices!W:W,CEG_Assets!$AN$4)*CEG_Assets!$J$4*W102/1000000*(1+CEG_RevAdj) -> 0 | X103: =X98*INDEX(Prices!X:X,CEG_Assets!$AN$4)*CEG_Assets!$J$4*X102/1000000*(1+CEG_RevAdj) -> 0 | Y103: =Y98*INDEX(Prices!Y:Y,CEG_Assets!$AN$4)*CEG_Assets!$J$4*Y102/1000000*(1+CEG_RevAdj) -> 0 | Z103: =Z98*INDEX(Prices!Z:Z,CEG_Assets!$AN$4)*CEG_Assets!$J$4*Z102/1000000*(1+CEG_RevAdj) -> 0 | AA103: =AA98*INDEX(Prices!AA:AA,CEG_Assets!$AN$4)*CEG_Assets!$J$4*AA102/1000000*(1+CEG_RevAdj) -> 663.48816 | AB103: =AB98*INDEX(Prices!AB:AB,CEG_Assets!$AN$4)*CEG_Assets!$J$4*AB102/1000000*(1+CEG_RevAdj) -> 676.75792 | AC103: =AC98*INDEX(Prices!AC:AC,CEG_Assets!$AN$4)*CEG_Assets!$J$4*AC102/1000000*(1+CEG_RevAdj) -> 690.29308 | AD103: =AD98*INDEX(Prices!AD:AD,CEG_Assets!$AN$4)*CEG_Assets!$J$4*AD102/1000000*(1+CEG_RevAdj) -> 704.09894 | AE103: =AE98*INDEX(Prices!AE:AE,CEG_Assets!$AN$4)*CEG_Assets!$J$4*AE102/1000000*(1+CEG_RevAdj) -> 718.18092 | AF103: =AF98*INDEX(Prices!AF:AF,CEG_Assets!$AN$4)*CEG_Assets!$J$4*AF102/1000000*(1+CEG_RevAdj) -> 732.54454 | AG103: =AG98*INDEX(Prices!AG:AG,CEG_Assets!$AN$4)*CEG_Assets!$J$4*AG102/1000000*(1+CEG_RevAdj) -> 747.19543 | AH103: =AH98*INDEX(Prices!AH:AH,CEG_Assets!$AN$4)*CEG_Assets!$J$4*AH102/1000000*(1+CEG_RevAdj) -> 762.13934 | AI103: =AI98*INDEX(Prices!AI:AI,CEG_Assets!$AN$4)*CEG_Assets!$J$4*AI102/1000000*(1+CEG_RevAdj) -> 777.38212 | AJ103: =AJ98*INDEX(Prices!AJ:AJ,CEG_Assets!$AN$4)*CEG_Assets!$J$4*AJ102/1000000*(1+CEG_RevAdj) -> 0 | AK103: =AK98*INDEX(Prices!AK:AK,CEG_Assets!$AN$4)*CEG_Assets!$J$4*AK102/1000000*(1+CEG_RevAdj) -> 0 | AL103: =AL98*INDEX(Prices!AL:AL,CEG_Assets!$AN$4)*CEG_Assets!$J$4*AL102/1000000*(1+CEG_RevAdj) -> 0 | AM103: =AM98*INDEX(Prices!AM:AM,CEG_Assets!$AN$4)*CEG_Assets!$J$4*AM102/1000000*(1+CEG_RevAdj) -> 0 | AN103: =AN98*INDEX(Prices!AN:AN,CEG_Assets!$AN$4)*CEG_Assets!$J$4*AN102/1000000*(1+CEG_RevAdj) -> 0 | AO103: =AO98*INDEX(Prices!AO:AO,CEG_Assets!$AN$4)*CEG_Assets!$J$4*AO102/1000000*(1+CEG_RevAdj) -> 0 | AP103: =AP98*INDEX(Prices!AP:AP,CEG_Assets!$AN$4)*CEG_Assets!$J$4*AP102/1000000*(1+CEG_RevAdj) -> 0 | AQ103: =AQ98*INDEX(Prices!AQ:AQ,CEG_Assets!$AN$4)*CEG_Assets!$J$4*AQ102/1000000*(1+CEG_RevAdj) -> 0 | AR103: =AR98*INDEX(Prices!AR:AR,CEG_Assets!$AN$4)*CEG_Assets!$J$4*AR102/1000000*(1+CEG_RevAdj) -> 0 | AS103: =AS98*INDEX(Prices!AS:AS,CEG_Assets!$AN$4)*CEG_Assets!$J$4*AS102/1000000*(1+CEG_RevAdj) -> 0
A104: Capacity revenue ($mm) | B104: capacity | C104: =SUM(G104:AS104) -> 609.04201 | G104: =(CEG_Assets!$D$4-G97)*INDEX(Prices!G:G,CEG_Assets!$AP$4)*365*CEG_Assets!$T$4*G96/1000000*(1+CEG_RevAdj) -> 0 | H104: =(CEG_Assets!$D$4-H97)*INDEX(Prices!H:H,CEG_Assets!$AP$4)*365*CEG_Assets!$T$4*H96/1000000*(1+CEG_RevAdj) -> 0 | I104: =(CEG_Assets!$D$4-I97)*INDEX(Prices!I:I,CEG_Assets!$AP$4)*365*CEG_Assets!$T$4*I96/1000000*(1+CEG_RevAdj) -> 0 | J104: =(CEG_Assets!$D$4-J97)*INDEX(Prices!J:J,CEG_Assets!$AP$4)*365*CEG_Assets!$T$4*J96/1000000*(1+CEG_RevAdj) -> 0 | K104: =(CEG_Assets!$D$4-K97)*INDEX(Prices!K:K,CEG_Assets!$AP$4)*365*CEG_Assets!$T$4*K96/1000000*(1+CEG_RevAdj) -> 0 | L104: =(CEG_Assets!$D$4-L97)*INDEX(Prices!L:L,CEG_Assets!$AP$4)*365*CEG_Assets!$T$4*L96/1000000*(1+CEG_RevAdj) -> 0 | M104: =(CEG_Assets!$D$4-M97)*INDEX(Prices!M:M,CEG_Assets!$AP$4)*365*CEG_Assets!$T$4*M96/1000000*(1+CEG_RevAdj) -> 0 | N104: =(CEG_Assets!$D$4-N97)*INDEX(Prices!N:N,CEG_Assets!$AP$4)*365*CEG_Assets!$T$4*N96/1000000*(1+CEG_RevAdj) -> 0 | O104: =(CEG_Assets!$D$4-O97)*INDEX(Prices!O:O,CEG_Assets!$AP$4)*365*CEG_Assets!$T$4*O96/1000000*(1+CEG_RevAdj) -> 0 | P104: =(CEG_Assets!$D$4-P97)*INDEX(Prices!P:P,CEG_Assets!$AP$4)*365*CEG_Assets!$T$4*P96/1000000*(1+CEG_RevAdj) -> 0 | Q104: =(CEG_Assets!$D$4-Q97)*INDEX(Prices!Q:Q,CEG_Assets!$AP$4)*365*CEG_Assets!$T$4*Q96/1000000*(1+CEG_RevAdj) -> 0 | R104: =(CEG_Assets!$D$4-R97)*INDEX(Prices!R:R,CEG_Assets!$AP$4)*365*CEG_Assets!$T$4*R96/1000000*(1+CEG_RevAdj) -> 0 | S104: =(CEG_Assets!$D$4-S97)*INDEX(Prices!S:S,CEG_Assets!$AP$4)*365*CEG_Assets!$T$4*S96/1000000*(1+CEG_RevAdj) -> 0 | T104: =(CEG_Assets!$D$4-T97)*INDEX(Prices!T:T,CEG_Assets!$AP$4)*365*CEG_Assets!$T$4*T96/1000000*(1+CEG_RevAdj) -> 0 | U104: =(CEG_Assets!$D$4-U97)*INDEX(Prices!U:U,CEG_Assets!$AP$4)*365*CEG_Assets!$T$4*U96/1000000*(1+CEG_RevAdj) -> 0 | V104: =(CEG_Assets!$D$4-V97)*INDEX(Prices!V:V,CEG_Assets!$AP$4)*365*CEG_Assets!$T$4*V96/1000000*(1+CEG_RevAdj) -> 0 | W104: =(CEG_Assets!$D$4-W97)*INDEX(Prices!W:W,CEG_Assets!$AP$4)*365*CEG_Assets!$T$4*W96/1000000*(1+CEG_RevAdj) -> 0 | X104: =(CEG_Assets!$D$4-X97)*INDEX(Prices!X:X,CEG_Assets!$AP$4)*365*CEG_Assets!$T$4*X96/1000000*(1+CEG_RevAdj) -> 0 | Y104: =(CEG_Assets!$D$4-Y97)*INDEX(Prices!Y:Y,CEG_Assets!$AP$4)*365*CEG_Assets!$T$4*Y96/1000000*(1+CEG_RevAdj) -> 0 | Z104: =(CEG_Assets!$D$4-Z97)*INDEX(Prices!Z:Z,CEG_Assets!$AP$4)*365*CEG_Assets!$T$4*Z96/1000000*(1+CEG_RevAdj) -> 0 | AA104: =(CEG_Assets!$D$4-AA97)*INDEX(Prices!AA:AA,CEG_Assets!$AP$4)*365*CEG_Assets!$T$4*AA96/1000000*(1+CEG_RevAdj) -> 62.436208 | AB104: =(CEG_Assets!$D$4-AB97)*INDEX(Prices!AB:AB,CEG_Assets!$AP$4)*365*CEG_Assets!$T$4*AB96/1000000*(1+CEG_RevAdj) -> 63.684932 | AC104: =(CEG_Assets!$D$4-AC97)*INDEX(Prices!AC:AC,CEG_Assets!$AP$4)*365*CEG_Assets!$T$4*AC96/1000000*(1+CEG_RevAdj) -> 64.958631 | AD104: =(CEG_Assets!$D$4-AD97)*INDEX(Prices!AD:AD,CEG_Assets!$AP$4)*365*CEG_Assets!$T$4*AD96/1000000*(1+CEG_RevAdj) -> 66.257803 | AE104: =(CEG_Assets!$D$4-AE97)*INDEX(Prices!AE:AE,CEG_Assets!$AP$4)*365*CEG_Assets!$T$4*AE96/1000000*(1+CEG_RevAdj) -> 67.582959 | AF104: =(CEG_Assets!$D$4-AF97)*INDEX(Prices!AF:AF,CEG_Assets!$AP$4)*365*CEG_Assets!$T$4*AF96/1000000*(1+CEG_RevAdj) -> 68.934618 | AG104: =(CEG_Assets!$D$4-AG97)*INDEX(Prices!AG:AG,CEG_Assets!$AP$4)*365*CEG_Assets!$T$4*AG96/1000000*(1+CEG_RevAdj) -> 70.313311 | AH104: =(CEG_Assets!$D$4-AH97)*INDEX(Prices!AH:AH,CEG_Assets!$AP$4)*365*CEG_Assets!$T$4*AH96/1000000*(1+CEG_RevAdj) -> 71.719577 | AI104: =(CEG_Assets!$D$4-AI97)*INDEX(Prices!AI:AI,CEG_Assets!$AP$4)*365*CEG_Assets!$T$4*AI96/1000000*(1+CEG_RevAdj) -> 73.153969 | AJ104: =(CEG_Assets!$D$4-AJ97)*INDEX(Prices!AJ:AJ,CEG_Assets!$AP$4)*365*CEG_Assets!$T$4*AJ96/1000000*(1+CEG_RevAdj) -> 0 | AK104: =(CEG_Assets!$D$4-AK97)*INDEX(Prices!AK:AK,CEG_Assets!$AP$4)*365*CEG_Assets!$T$4*AK96/1000000*(1+CEG_RevAdj) -> 0 | AL104: =(CEG_Assets!$D$4-AL97)*INDEX(Prices!AL:AL,CEG_Assets!$AP$4)*365*CEG_Assets!$T$4*AL96/1000000*(1+CEG_RevAdj) -> 0 | AM104: =(CEG_Assets!$D$4-AM97)*INDEX(Prices!AM:AM,CEG_Assets!$AP$4)*365*CEG_Assets!$T$4*AM96/1000000*(1+CEG_RevAdj) -> 0 | AN104: =(CEG_Assets!$D$4-AN97)*INDEX(Prices!AN:AN,CEG_Assets!$AP$4)*365*CEG_Assets!$T$4*AN96/1000000*(1+CEG_RevAdj) -> 0 | AO104: =(CEG_Assets!$D$4-AO97)*INDEX(Prices!AO:AO,CEG_Assets!$AP$4)*365*CEG_Assets!$T$4*AO96/1000000*(1+CEG_RevAdj) -> 0 | AP104: =(CEG_Assets!$D$4-AP97)*INDEX(Prices!AP:AP,CEG_Assets!$AP$4)*365*CEG_Assets!$T$4*AP96/1000000*(1+CEG_RevAdj) -> 0 | AQ104: =(CEG_Assets!$D$4-AQ97)*INDEX(Prices!AQ:AQ,CEG_Assets!$AP$4)*365*CEG_Assets!$T$4*AQ96/1000000*(1+CEG_RevAdj) -> 0 | AR104: =(CEG_Assets!$D$4-AR97)*INDEX(Prices!AR:AR,CEG_Assets!$AP$4)*365*CEG_Assets!$T$4*AR96/1000000*(1+CEG_RevAdj) -> 0 | AS104: =(CEG_Assets!$D$4-AS97)*INDEX(Prices!AS:AS,CEG_Assets!$AP$4)*365*CEG_Assets!$T$4*AS96/1000000*(1+CEG_RevAdj) -> 0
A105: Long-term PPA revenue ($mm) | B105: ppa | C105: =SUM(G105:AS105) -> 14153.357 | G105: =G99*(CEG_Assets!$AD$4+CEG_PPAAdj)/1000000*(1+CEG_RevAdj) -> 707.66784 | H105: =H99*(CEG_Assets!$AD$4+CEG_PPAAdj)/1000000*(1+CEG_RevAdj) -> 707.66784 | I105: =I99*(CEG_Assets!$AD$4+CEG_PPAAdj)/1000000*(1+CEG_RevAdj) -> 707.66784 | J105: =J99*(CEG_Assets!$AD$4+CEG_PPAAdj)/1000000*(1+CEG_RevAdj) -> 707.66784 | K105: =K99*(CEG_Assets!$AD$4+CEG_PPAAdj)/1000000*(1+CEG_RevAdj) -> 707.66784 | L105: =L99*(CEG_Assets!$AD$4+CEG_PPAAdj)/1000000*(1+CEG_RevAdj) -> 707.66784 | M105: =M99*(CEG_Assets!$AD$4+CEG_PPAAdj)/1000000*(1+CEG_RevAdj) -> 707.66784 | N105: =N99*(CEG_Assets!$AD$4+CEG_PPAAdj)/1000000*(1+CEG_RevAdj) -> 707.66784 | ... AS105: =AS99*(CEG_Assets!$AD$4+CEG_PPAAdj)/1000000*(1+CEG_RevAdj) -> 0
...

Sheet VST_Assets
A1: Asset | B1: Tech | C1: Hub | D1: MW | E1: Start year | F1: End year | G1: Avg in-service year (COD) | H1: Method (Cashflow / $/kW) | I1: Capacity factor | J1: Capture (x ATC) | K1: Heat rate | L1: Fuel price override (2026$/MMBtu) | M1: Variable O&M ($/MWh) | N1: Fuel ($/MWh) | O1: O&M ($/MWh) | P1: Capex ($/MWh) | Q1: Per-MWh cost escalator | R1: Fixed O&M ($/kW-yr) | S1: Sust. capex ($/kW-yr) | T1: Capacity accreditation | U1: ZEC ($/MWh) | V1: ZEC last year | W1: 45U eligible | X1: Dispatch check | Y1: Mothball floor | Z1: Contract MW | AA1: Contract start | AB1: Contract end | AC1: Contract ramp (yrs) | AD1: PPA price ($/MWh, nominal flat) | AE1: Merchant discount rate | AF1: Contract discount rate | AG1: One-off capex ($mm) | AH1: One-off capex year | AI1: $/kW value (if $/kW method) | AJ1: Replacement cost ($/kW) | AK1: Remaining-life override | AL1: Remaining-life fraction | AM1: Depreciated replacement cost ($mm) | AN1: ATC row | AO1: Gas row | AP1: Cap row | AQ1: Asset NAV ($mm) | AR1: NAV $/kW
A2: Nuclear - Comanche Peak (ERCOT) - 1,200 MW 20-yr PPA | B2: nuclear | C2: ERCOT | D2: 2400 | E2: 2027 | F2: 2053 | G2: 1991 | H2: Cashflow | I2: =Inputs!$B$61 -> 0.935 | J2: =Inputs!$F$57 -> 0.95 | K2: =Inputs!$D$61 -> 0 | M2: =Inputs!$F$61 -> 0 | N2: =Inputs!$G$61 -> 5.5 | O2: =Inputs!$H$61 -> 22.3 | P2: =Inputs!$I$61 -> 7.7 | Q2: =Inputs!$J$61 -> 0.025 | R2: =Inputs!$K$61 -> 0 | S2: =Inputs!$L$61 -> 0 | T2: =Inputs!$M$61 -> 0.95 | U2: 0 | V2: 2026 | W2: =Inputs!$R$61 -> 1 | X2: =Inputs!$P$61 -> 0 | Y2: =Inputs!$Q$61 -> 0 | Z2: 1200 | AA2: 2028 | AB2: 2047 | AC2: 5 | AD2: 80 | AE2: =Inputs!$N$61 -> 0.08 | AF2: =Inputs!$O$61 -> 0.0675 | AG2: 0 | AH2: 2026 | AJ2: =NucRC -> 4500 | AL2: =IF(ISNUMBER(AK2),AK2,MAX(0,MIN(1,(F2+1-ValDate)/(F2+1-G2)))) -> 0.43253968 | AM2: =D2*AJ2*AL2/1000 -> 4671.4286 | AN2: =MATCH("ATC|"&C2,Prices!$A:$A,0) -> 41 | AO2: =MATCH("GAS|"&C2,Prices!$A:$A,0) -> 40 | AP2: =MATCH("CAP|"&C2,Prices!$A:$A,0) -> 42 | AQ2: =VST_Model!C61+VST_Model!C62+VST_Model!C63 -> 3638.7036 | AR2: =IF(D2=0,0,AQ2/D2*1000) -> 1516.1265
A3: Nuclear - Perry + Davis-Besse (PJM ATSI) - Meta 20-yr PPAs | B3: nuclear | C3: PJMA | D3: 2176 | E3: 2027 | F3: 2055 | G3: 1983 | H3: Cashflow | I3: =Inputs!$B$61 -> 0.935 | J3: =Inputs!$F$51 -> 0.99 | K3: =Inputs!$D$61 -> 0 | M3: =Inputs!$F$61 -> 0 | N3: =Inputs!$G$61 -> 5.5 | O3: =Inputs!$H$61 -> 22.3 | P3: =Inputs!$I$61 -> 7.7 | Q3: =Inputs!$J$61 -> 0.025 | R3: =Inputs!$K$61 -> 0 | S3: =Inputs!$L$61 -> 0 | T3: =Inputs!$M$61 -> 0.95 | U3: 0 | V3: 2026 | W3: =Inputs!$R$61 -> 1 | X3: =Inputs!$P$61 -> 0 | Y3: =Inputs!$Q$61 -> 0 | Z3: 2176 | AA3: 2027 | AB3: 2047 | AC3: 2 | AD3: 85 | AE3: =Inputs!$N$61 -> 0.08 | AF3: =Inputs!$O$61 -> 0.0675 | AG3: 0 | AH3: 2026 | AJ3: =NucRC -> 4500 | AL3: =IF(ISNUMBER(AK3),AK3,MAX(0,MIN(1,(F3+1-ValDate)/(F3+1-G3)))) -> 0.40068493 | AM3: =D3*AJ3*AL3/1000 -> 3923.5068 | AN3: =MATCH("ATC|"&C3,Prices!$A:$A,0) -> 23 | AO3: =MATCH("GAS|"&C3,Prices!$A:$A,0) -> 22 | AP3: =MATCH("CAP|"&C3,Prices!$A:$A,0) -> 24 | AQ3: =VST_Model!C91+VST_Model!C92+VST_Model!C93 -> 7232.4429 | AR3: =IF(D3=0,0,AQ3/D3*1000) -> 3323.733
A4: Nuclear - Beaver Valley (PJM) | B4: nuclear | C4: PJMW | D4: 1872 | E4: 2027 | F4: 2055 | G4: 1981 | H4: Cashflow | I4: =Inputs!$B$61 -> 0.935 | J4: =Inputs!$F$50 -> 0.99 | K4: =Inputs!$D$61 -> 0 | M4: =Inputs!$F$61 -> 0 | N4: =Inputs!$G$61 -> 5.5 | O4: =Inputs!$H$61 -> 22.3 | P4: =Inputs!$I$61 -> 7.7 | Q4: =Inputs!$J$61 -> 0.025 | R4: =Inputs!$K$61 -> 0 | S4: =Inputs!$L$61 -> 0 | T4: =Inputs!$M$61 -> 0.95 | U4: 0 | V4: 2026 | W4: =Inputs!$R$61 -> 1 | X4: =Inputs!$P$61 -> 0 | Y4: =Inputs!$Q$61 -> 0 | Z4: 0 | AA4: 2026 | AB4: 2026 | AC4: 1 | AD4: 0 | AE4: =Inputs!$N$61 -> 0.08 | AF4: =Inputs!$O$61 -> 0.0675 | AG4: 0 | AH4: 2026 | AJ4: =NucRC -> 4500 | AL4: =IF(ISNUMBER(AK4),AK4,MAX(0,MIN(1,(F4+1-ValDate)/(F4+1-G4)))) -> 0.39 | AM4: =D4*AJ4*AL4/1000 -> 3285.36 | AN4: =MATCH("ATC|"&C4,Prices!$A:$A,0) -> 20 | AO4: =MATCH("GAS|"&C4,Prices!$A:$A,0) -> 19 | AP4: =MATCH("CAP|"&C4,Prices!$A:$A,0) -> 21 | AQ4: =VST_Model!C121+VST_Model!C122+VST_Model!C123 -> 5841.311 | AR4: =IF(D4=0,0,AQ4/D4*1000) -> 3120.3584
A5: Gas - ERCOT CCGT | B5: ccgt | C5: ERCOT | D5: 9500 | E5: 2027 | F5: 2045 | G5: 2003 | H5: Cashflow | I5: =Inputs!$D$57 -> 0.55 | J5: =Inputs!$E$57 -> 1.2 | K5: =Inputs!$D$62 -> 7.2 | M5: =Inputs!$F$62 -> 3.5 | N5: =Inputs!$G$62 -> 0 | O5: =Inputs!$H$62 -> 0 | P5: =Inputs!$I$62 -> 0 | Q5: =Inputs!$J$62 -> 0 | R5: =Inputs!$K$62 -> 32 | S5: =Inputs!$L$62 -> 12 | T5: =Inputs!$M$62 -> 0.78 | U5: 0 | V5: 2026 | W5: =Inputs!$R$62 -> 0 | X5: =Inputs!$P$62 -> 1 | Y5: =Inputs!$Q$62 -> 1 | Z5: 0 | AA5: 2026 | AB5: 2026 | AC5: 1 | AD5: 0 | AE5: =Inputs!$N$62 -> 0.095 | AF5: =Inputs!$O$62 -> 0.095 | AG5: 0 | AH5: 2026 | AJ5: =Inputs!$S$62 -> 2350 | AL5: =IF(ISNUMBER(AK5),AK5,MAX(0,MIN(1,(F5+1-ValDate)/(F5+1-G5)))) -> 0.44767442 | AM5: =D5*AJ5*AL5/1000 -> 9994.3314 | AN5: =MATCH("ATC|"&C5,Prices!$A:$A,0) -> 41 | AO5: =MATCH("GAS|"&C5,Prices!$A:$A,0) -> 40 | AP5: =MATCH("CAP|"&C5,Prices!$A:$A,0) -> 42 | AQ5: =VST_Model!C151+VST_Model!C152+VST_Model!C153 -> 6522.3064 | AR5: =IF(D5=0,0,AQ5/D5*1000) -> 686.55857
A6: Gas - ERCOT peakers | B6: peaker | C6: ERCOT | D6: 2300 | E6: 2027 | F6: 2040 | G6: 2000 | H6: Cashflow | I6: =Inputs!$B$63 -> 0.06 | J6: =ScarcityERC -> 2.5 | K6: =Inputs!$D$63 -> 10.5 | M6: =Inputs!$F$63 -> 5 | N6: =Inputs!$G$63 -> 0 | O6: =Inputs!$H$63 -> 0 | P6: =Inputs!$I$63 -> 0 | Q6: =Inputs!$J$63 -> 0 | R6: =Inputs!$K$63 -> 18 | S6: =Inputs!$L$63 -> 5 | T6: =Inputs!$M$63 -> 0.6 | U6: 0 | V6: 2026 | W6: =Inputs!$R$63 -> 0 | X6: =Inputs!$P$63 -> 1 | Y6: =Inputs!$Q$63 -> 1 | Z6: 0 | AA6: 2026 | AB6: 2026 | AC6: 1 | AD6: 0 | AE6: =Inputs!$N$63 -> 0.1 | AF6: =Inputs!$O$63 -> 0.1 | AG6: 0 | AH6: 2026 | AJ6: =Inputs!$S$63 -> 1970 | AL6: =IF(ISNUMBER(AK6),AK6,MAX(0,MIN(1,(F6+1-ValDate)/(F6+1-G6)))) -> 0.34756098 | AM6: =D6*AJ6*AL6/1000 -> 1574.7988 | AN6: =MATCH("ATC|"&C6,Prices!$A:$A,0) -> 41 | AO6: =MATCH("GAS|"&C6,Prices!$A:$A,0) -> 40 | AP6: =MATCH("CAP|"&C6,Prices!$A:$A,0) -> 42 | AQ6: =VST_Model!C181+VST_Model!C182+VST_Model!C183 -> 264.21312 | AR6: =IF(D6=0,0,AQ6/D6*1000) -> 114.87527
A7: Gas - PJM CCGT (incl. Lotus) | B7: ccgt | C7: PJMW | D7: 8500 | E7: 2027 | F7: 2045 | G7: 2004 | H7: Cashflow | I7: =Inputs!$D$50 -> 0.5 | J7: =Inputs!$E$50 -> 1.02 | K7: =Inputs!$D$62 -> 7.2 | M7: =Inputs!$F$62 -> 3.5 | N7: =Inputs!$G$62 -> 0 | O7: =Inputs!$H$62 -> 0 | P7: =Inputs!$I$62 -> 0 | Q7: =Inputs!$J$62 -> 0 | R7: =Inputs!$K$62 -> 32 | S7: =Inputs!$L$62 -> 12 | T7: =Inputs!$M$62 -> 0.78 | U7: 0 | V7: 2026 | W7: =Inputs!$R$62 -> 0 | X7: =Inputs!$P$62 -> 1 | Y7: =Inputs!$Q$62 -> 1 | Z7: 0 | AA7: 2026 | AB7: 2026 | AC7: 1 | AD7: 0 | AE7: =Inputs!$N$62 -> 0.095 | AF7: =Inputs!$O$62 -> 0.095 | AG7: 0 | AH7: 2026 | AJ7: =Inputs!$S$62 -> 2350 | AL7: =IF(ISNUMBER(AK7),AK7,MAX(0,MIN(1,(F7+1-ValDate)/(F7+1-G7)))) -> 0.45833333 | AM7: =D7*AJ7*AL7/1000 -> 9155.2083 | AN7: =MATCH("ATC|"&C7,Prices!$A:$A,0) -> 20 | AO7: =MATCH("GAS|"&C7,Prices!$A:$A,0) -> 19 | AP7: =MATCH("CAP|"&C7,Prices!$A:$A,0) -> 21 | AQ7: =VST_Model!C211+VST_Model!C212+VST_Model!C213 -> 11603.085 | AR7: =IF(D7=0,0,AQ7/D7*1000) -> 1365.0688
A8: Gas - NY/NE CCGT | B8: ccgt | C8: NE | D8: 3167 | E8: 2027 | F8: 2045 | G8: 2002 | H8: Cashflow | I8: =Inputs!$D$55 -> 0.45 | J8: =Inputs!$E$55 -> 1.05 | K8: =Inputs!$D$62 -> 7.2 | M8: =Inputs!$F$62 -> 3.5 | N8: =Inputs!$G$62 -> 0 | O8: =Inputs!$H$62 -> 0 | P8: =Inputs!$I$62 -> 0 | Q8: =Inputs!$J$62 -> 0 | R8: =Inputs!$K$62 -> 32 | S8: =Inputs!$L$62 -> 12 | T8: =Inputs!$M$62 -> 0.78 | U8: 0 | V8: 2026 | W8: =Inputs!$R$62 -> 0 | X8: =Inputs!$P$62 -> 1 | Y8: =Inputs!$Q$62 -> 1 | Z8: 0 | AA8: 2026 | AB8: 2026 | AC8: 1 | AD8: 0 | AE8: =Inputs!$N$62 -> 0.095 | AF8: =Inputs!$O$62 -> 0.095 | AG8: 0 | AH8: 2026 | AJ8: =Inputs!$S$62 -> 2350 | AL8: =IF(ISNUMBER(AK8),AK8,MAX(0,MIN(1,(F8+1-ValDate)/(F8+1-G8)))) -> 0.4375 | AM8: =D8*AJ8*AL8/1000 -> 3256.0719 | AN8: =MATCH("ATC|"&C8,Prices!$A:$A,0) -> 35 | AO8: =MATCH("GAS|"&C8,Prices!$A:$A,0) -> 34 | AP8: =MATCH("CAP|"&C8,Prices!$A:$A,0) -> 36 | AQ8: =VST_Model!C241+VST_Model!C242+VST_Model!C243 -> 2364.316 | AR8: =IF(D8=0,0,AQ8/D8*1000) -> 746.54751
A9: Gas - West CCGT (CAISO) | B9: ccgt | C9: WEST | D9: 1000 | E9: 2027 | F9: 2040 | G9: 2002 | H9: Cashflow | I9: =Inputs!$D$56 -> 0.45 | J9: =Inputs!$E$56 -> 1.15 | K9: =Inputs!$D$62 -> 7.2 | M9: =Inputs!$F$62 -> 3.5 | N9: =Inputs!$G$62 -> 0 | O9: =Inputs!$H$62 -> 0 | P9: =Inputs!$I$62 -> 0 | Q9: =Inputs!$J$62 -> 0 | R9: =Inputs!$K$62 -> 32 | S9: =Inputs!$L$62 -> 12 | T9: =Inputs!$M$62 -> 0.78 | U9: 0 | V9: 2026 | W9: =Inputs!$R$62 -> 0 | X9: =Inputs!$P$62 -> 1 | Y9: =Inputs!$Q$62 -> 1 | Z9: 0 | AA9: 2026 | AB9: 2026 | AC9: 1 | AD9: 0 | AE9: =Inputs!$N$62 -> 0.095 | AF9: =Inputs!$O$62 -> 0.095 | AG9: 0 | AH9: 2026 | AJ9: =Inputs!$S$62 -> 2350 | AL9: =IF(ISNUMBER(AK9),AK9,MAX(0,MIN(1,(F9+1-ValDate)/(F9+1-G9)))) -> 0.36538462 | AM9: =D9*AJ9*AL9/1000 -> 858.65385 | AN9: =MATCH("ATC|"&C9,Prices!$A:$A,0) -> 38 | AO9: =MATCH("GAS|"&C9,Prices!$A:$A,0) -> 37 | AP9: =MATCH("CAP|"&C9,Prices!$A:$A,0) -> 39 | AQ9: =VST_Model!C271+VST_Model!C272+VST_Model!C273 -> 893.97867 | AR9: =IF(D9=0,0,AQ9/D9*1000) -> 893.97867
A10: Gas/oil - East peakers | B10: peaker | C10: PJMW | D10: 2709 | E10: 2027 | F10: 2038 | G10: 1998 | H10: Cashflow | I10: =Inputs!$B$63 -> 0.06 | J10: =Scarcity -> 2.5 | K10: =Inputs!$D$63 -> 10.5 | M10: =Inputs!$F$63 -> 5 | N10: =Inputs!$G$63 -> 0 | O10: =Inputs!$H$63 -> 0 | P10: =Inputs!$I$63 -> 0 | Q10: =Inputs!$J$63 -> 0 | R10: =Inputs!$K$63 -> 18 | S10: =Inputs!$L$63 -> 5 | T10: =Inputs!$M$63 -> 0.6 | U10: 0 | V10: 2026 | W10: =Inputs!$R$63 -> 0 | X10: =Inputs!$P$63 -> 1 | Y10: =Inputs!$Q$63 -> 1 | Z10: 0 | AA10: 2026 | AB10: 2026 | AC10: 1 | AD10: 0 | AE10: =Inputs!$N$63 -> 0.1 | AF10: =Inputs!$O$63 -> 0.1 | AG10: 0 | AH10: 2026 | AJ10: =Inputs!$S$63 -> 1970 | AL10: =IF(ISNUMBER(AK10),AK10,MAX(0,MIN(1,(F10+1-ValDate)/(F10+1-G10)))) -> 0.29878049 | AM10: =D10*AJ10*AL10/1000 -> 1594.5108 | AN10: =MATCH("ATC|"&C10,Prices!$A:$A,0) -> 20 | AO10: =MATCH("GAS|"&C10,Prices!$A:$A,0) -> 19 | AP10: =MATCH("CAP|"&C10,Prices!$A:$A,0) -> 21 | AQ10: =VST_Model!C301+VST_Model!C302+VST_Model!C303 -> 1536.9282 | AR10: =IF(D10=0,0,AQ10/D10*1000) -> 567.34152
A11: Coal - ERCOT (Martin Lake, Oak Grove, Coleto Creek) | B11: coal | C11: ERCOT | D11: 4500 | E11: 2027 | F11: 2035 | G11: 1980 | H11: Cashflow | I11: =Inputs!$B$64 -> 0.5 | J11: =Inputs!$C$64 -> 1.02 | K11: =Inputs!$D$64 -> 10.4 | L11: =Inputs!$E$64 -> 2.3 | M11: =Inputs!$F$64 -> 4.5 | N11: =Inputs!$G$64 -> 0 | O11: =Inputs!$H$64 -> 0 | P11: =Inputs!$I$64 -> 0 | Q11: =Inputs!$J$64 -> 0 | R11: =Inputs!$K$64 -> 50 | S11: =Inputs!$L$64 -> 15 | T11: =Inputs!$M$64 -> 0.83 | U11: 0 | V11: 2026 | W11: =Inputs!$R$64 -> 0 | X11: =Inputs!$P$64 -> 1 | Y11: =Inputs!$Q$64 -> 1 | Z11: 0 | AA11: 2026 | AB11: 2026 | AC11: 1 | AD11: 0 | AE11: =Inputs!$N$64 -> 0.12 | AF11: =Inputs!$O$64 -> 0.12 | AG11: 0 | AH11: 2026 | AJ11: =Inputs!$S$64 -> 2350 | AL11: =IF(ISNUMBER(AK11),AK11,MAX(0,MIN(1,(F11+1-ValDate)/(F11+1-G11)))) -> 0.16517857 | AM11: =D11*AJ11*AL11/1000 -> 1746.7634 | AN11: =MATCH("ATC|"&C11,Prices!$A:$A,0) -> 41 | AO11: =MATCH("GAS|"&C11,Prices!$A:$A,0) -> 40 | AP11: =MATCH("CAP|"&C11,Prices!$A:$A,0) -> 42 | AQ11: =VST_Model!C331+VST_Model!C332+VST_Model!C333 -> 682.51326 | AR11: =IF(D11=0,0,AQ11/D11*1000) -> 151.66961
A12: Coal - IL/OH (Baldwin, Kincaid, Newton, Miami Fort) - retiring ~2027 | B12: coal | C12: PJMW | D12: 4243 | E12: 2027 | F12: 2027 | G12: 1975 | H12: Cashflow | I12: =Inputs!$B$64 -> 0.5 | J12: =Inputs!$C$64 -> 1.02 | K12: =Inputs!$D$64 -> 10.4 | L12: =Inputs!$E$64 -> 2.3 | M12: =Inputs!$F$64 -> 4.5 | N12: =Inputs!$G$64 -> 0 | O12: =Inputs!$H$64 -> 0 | P12: =Inputs!$I$64 -> 0 | Q12: =Inputs!$J$64 -> 0 | R12: =Inputs!$K$64 -> 50 | S12: =Inputs!$L$64 -> 15 | T12: =Inputs!$M$64 -> 0.83 | U12: 0 | V12: 2026 | W12: =Inputs!$R$64 -> 0 | X12: =Inputs!$P$64 -> 1 | Y12: =Inputs!$Q$64 -> 1 | Z12: 0 | AA12: 2026 | AB12: 2026 | AC12: 1 | AD12: 0 | AE12: =Inputs!$N$64 -> 0.12 | AF12: =Inputs!$O$64 -> 0.12 | AG12: 0 | AH12: 2026 | AJ12: =Inputs!$S$64 -> 2350 | AL12: =IF(ISNUMBER(AK12),AK12,MAX(0,MIN(1,(F12+1-ValDate)/(F12+1-G12)))) -> 0.023584906 | AM12: =D12*AJ12*AL12/1000 -> 235.16627 | AN12: =MATCH("ATC|"&C12,Prices!$A:$A,0) -> 20 | AO12: =MATCH("GAS|"&C12,Prices!$A:$A,0) -> 19 | AP12: =MATCH("CAP|"&C12,Prices!$A:$A,0) -> 21 | AQ12: =VST_Model!C361+VST_Model!C362+VST_Model!C363 -> 713.58667 | AR12: =IF(D12=0,0,AQ12/D12*1000) -> 168.17975
A13: Solar & batteries (Vistra Zero) | B13: renewable | C13: ERCOT | D13: 1274 | E13: 2027 | F13: 2026 | H13: $/kW | I13: 0 | J13: 0 | K13: 0 | M13: 0 | N13: 0 | O13: 0 | P13: 0 | Q13: 0 | R13: 0 | S13: 0 | T13: 0 | U13: 0 | V13: 2026 | W13: 0 | X13: 0 | Y13: 0 | Z13: 0 | AA13: 2026 | AB13: 2026 | AC13: 1 | AD13: 0 | AE13: 0.08 | AF13: 0.08 | AG13: 0 | AH13: 2026 | AI13: 700 | AJ13: =Inputs!$S$67 -> 1600 | AK13: 0.55 | AL13: =IF(ISNUMBER(AK13),AK13,MAX(0,MIN(1,(F13+1-ValDate)/(F13+1-G13)))) -> 0.55 | AM13: =D13*AJ13*AL13/1000 -> 1121.12 | AN13: =MATCH("ATC|"&C13,Prices!$A:$A,0) -> 41 | AO13: =MATCH("GAS|"&C13,Prices!$A:$A,0) -> 40 | AP13: =MATCH("CAP|"&C13,Prices!$A:$A,0) -> 42 | AQ13: =VST_Model!C391+VST_Model!C392+VST_Model!C393 -> 891.8 | AR13: =IF(D13=0,0,AQ13/D13*1000) -> 700
A14: Cogentrix (pending) - modern CCGT, PJM | B14: ccgt | C14: PJMW | D14: 3850 | E14: 2027 | F14: 2050 | G14: 2012 | H14: Cashflow | I14: =Inputs!$D$50 -> 0.5 | J14: =Inputs!$E$50 -> 1.02 | K14: 6.9 | M14: =Inputs!$F$62 -> 3.5 | N14: =Inputs!$G$62 -> 0 | O14: =Inputs!$H$62 -> 0 | P14: =Inputs!$I$62 -> 0 | Q14: =Inputs!$J$62 -> 0 | R14: =Inputs!$K$62 -> 32 | S14: =Inputs!$L$62 -> 12 | T14: =Inputs!$M$62 -> 0.78 | U14: 0 | V14: 2026 | W14: =Inputs!$R$62 -> 0 | X14: =Inputs!$P$62 -> 1 | Y14: =Inputs!$Q$62 -> 1 | Z14: 0 | AA14: 2026 | AB14: 2026 | AC14: 1 | AD14: 0 | AE14: =Inputs!$N$62 -> 0.095 | AF14: =Inputs!$O$62 -> 0.095 | AG14: 0 | AH14: 2026 | AJ14: =Inputs!$S$62 -> 2350 | AL14: =IF(ISNUMBER(AK14),AK14,MAX(0,MIN(1,(F14+1-ValDate)/(F14+1-G14)))) -> 0.62179487 | AM14: =D14*AJ14*AL14/1000 -> 5625.6891 | AN14: =MATCH("ATC|"&C14,Prices!$A:$A,0) -> 20 | AO14: =MATCH("GAS|"&C14,Prices!$A:$A,0) -> 19 | AP14: =MATCH("CAP|"&C14,Prices!$A:$A,0) -> 21 | AQ14: =VST_Model!C421+VST_Model!C422+VST_Model!C423 -> 5937.3896 | AR14: =IF(D14=0,0,AQ14/D14*1000) -> 1542.1791
A15: Cogentrix (pending) - modern CCGT, NE | B15: ccgt | C15: NE | D15: 1650 | E15: 2027 | F15: 2050 | G15: 2012 | H15: Cashflow | I15: =Inputs!$D$55 -> 0.45 | J15: =Inputs!$E$55 -> 1.05 | K15: 6.9 | M15: =Inputs!$F$62 -> 3.5 | N15: =Inputs!$G$62 -> 0 | O15: =Inputs!$H$62 -> 0 | P15: =Inputs!$I$62 -> 0 | Q15: =Inputs!$J$62 -> 0 | R15: =Inputs!$K$62 -> 32 | S15: =Inputs!$L$62 -> 12 | T15: =Inputs!$M$62 -> 0.78 | U15: 0 | V15: 2026 | W15: =Inputs!$R$62 -> 0 | X15: =Inputs!$P$62 -> 1 | Y15: =Inputs!$Q$62 -> 1 | Z15: 0 | AA15: 2026 | AB15: 2026 | AC15: 1 | AD15: 0 | AE15: =Inputs!$N$62 -> 0.095 | AF15: =Inputs!$O$62 -> 0.095 | AG15: 0 | AH15: 2026 | AJ15: =Inputs!$S$62 -> 2350 | AL15: =IF(ISNUMBER(AK15),AK15,MAX(0,MIN(1,(F15+1-ValDate)/(F15+1-G15)))) -> 0.62179487 | AM15: =D15*AJ15*AL15/1000 -> 2411.0096 | AN15: =MATCH("ATC|"&C15,Prices!$A:$A,0) -> 35 | AO15: =MATCH("GAS|"&C15,Prices!$A:$A,0) -> 34 | AP15: =MATCH("CAP|"&C15,Prices!$A:$A,0) -> 36 | AQ15: =VST_Model!C451+VST_Model!C452+VST_Model!C453 -> 1448.0848 | AR15: =IF(D15=0,0,AQ15/D15*1000) -> 877.62716
A16: Total | D16: =SUM(D2:D15) -> 49141 | AM16: =SUM(AM2:AM15) -> 49453.619 | AQ16: =SUM(AQ2:AQ15) -> 49570.659

Sheet README
A1: CEG / VST asset-based NAV model - editable
A3: How to use
A4: 1. Change inputs on the 'Inputs' sheet (control panel at the top) and asset-level inputs on 'CEG_Assets' / 'VST_Assets'.
A5: 2. Everything else is formulas: price deck ('Prices'), annual asset cash flows ('CEG_Model' / 'VST_Model') and valuation ('Summary').
A6: 3. Read the new price target, NAV, FCF and replacement-cost value on 'Summary'.
A8: Colour legend
A9: Blue text = hard-coded input you can change
A10: Yellow fill = key lever (scenario, price/gas shifts, revenue/cost/margin adjustments, FCF haircut, price-target weights)
A11: Green text = link to another sheet (a default you can overwrite with your own number)
A12: Black text = formula - do not overwrite
A14: Main levers (Inputs sheet)
A15: Scenario (Low/Base/High/Extreme) - sets long-run heat rates, capacity prices and peaker scarcity.
... A29: Sources and caveats: see REPORT.md in the same folder. Plant-group MW splits, PPA prices and several liabilities are estimates.

Sheet VST_Model
A1: VST - annual asset cash flows and consolidated FCF ($mm, nominal). Formulas only.
A3: Line | B3: Key | C3: PV / total | D3: PV to horizon | E3: Value at horizon | G3: 2027 | H3: 2028 | I3: 2029 | J3: 2030 | K3: 2031 | L3: 2032 | M3: 2033 | N3: 2034 | O3: 2035 | P3: 2036 | Q3: 2037 | R3: 2038 | S3: 2039 | T3: 2040 | U3: 2041 | V3: 2042 | W3: 2043 | X3: 2044 | Y3: 2045 | Z3: 2046 | AA3: 2047 | AB3: 2048 | AC3: 2049 | AD3: 2050 | AE3: 2051 | AF3: 2052 | AG3: 2053 | AH3: 2054 | AI3: 2055 | AJ3: 2056 | AK3: 2057 | AL3: 2058 | AM3: 2059 | AN3: 2060 | AO3: 2061 | AP3: 2062 | AQ3: 2063 | AR3: 2064 | AS3: 2065
A4: Inflation index | G4: =Prices!G$4 -> 1.02 | H4: =Prices!H$4 -> 1.0404 | I4: =Prices!I$4 -> 1.061208 | J4: =Prices!J$4 -> 1.0824322 | K4: =Prices!K$4 -> 1.1040808 | L4: =Prices!L$4 -> 1.1261624 | M4: =Prices!M$4 -> 1.1486857 | N4: =Prices!N$4 -> 1.1716594 | ... AS4: =Prices!AS$4 -> 2.1647448
A5: CONSOLIDATED
A6: Merchant energy revenue | B6: c_energy | C6: =SUM(G6:AS6) -> 279358.77 | G6: =SUMIF($B$35:$B$454,"energy",G$35:G$454) -> 13893.036 | H6: =SUMIF($B$35:$B$454,"energy",H$35:H$454) -> 12109.885 | I6: =SUMIF($B$35:$B$454,"energy",I$35:I$454) -> 11557.281 | J6: =SUMIF($B$35:$B$454,"energy",J$35:J$454) -> 11430.723 | K6: =SUMIF($B$35:$B$454,"energy",K$35:K$454) -> 11556.143 | L6: =SUMIF($B$35:$B$454,"energy",L$35:L$454) -> 11682.008 | M6: =SUMIF($B$35:$B$454,"energy",M$35:M$454) -> 11915.648 | N6: =SUMIF($B$35:$B$454,"energy",N$35:N$454) -> 12153.961 | ... AS6: =SUMIF($B$35:$B$454,"energy",AS$35:AS$454) -> 0
A7: Capacity revenue | B7: c_capacity | C7: =SUM(G7:AS7) -> 37399.611 | G7: =SUMIF($B$35:$B$454,"capacity",G$35:G$454) -> 2347.384 | H7: =SUMIF($B$35:$B$454,"capacity",H$35:H$454) -> 1785.353 | I7: =SUMIF($B$35:$B$454,"capacity",I$35:I$454) -> 1548.4257 | J7: =SUMIF($B$35:$B$454,"capacity",J$35:J$454) -> 1415.7426 | K7: =SUMIF($B$35:$B$454,"capacity",K$35:K$454) -> 1444.0575 | L7: =SUMIF($B$35:$B$454,"capacity",L$35:L$454) -> 1472.9386 | M7: =SUMIF($B$35:$B$454,"capacity",M$35:M$454) -> 1502.3974 | N7: =SUMIF($B$35:$B$454,"capacity",N$35:N$454) -> 1532.4453 | ... AS7: =SUMIF($B$35:$B$454,"capacity",AS$35:AS$454) -> 0
