Workbook

Sheet README
A1: Intel (INTC) Valuation Model: scenario DCF built from the Sep 2026 product analysis
A2: Companion to research/intel-competitive-analysis-2026-09.md. Values in US$ billions unless stated; per-share values in US$.
A4: HOW TO USE
A5: 1. Edit blue cells only (inputs). Yellow-filled cells are key judgment calls or placeholders you should verify.
A6: 2. Black cells are formulas; green cells link to another sheet. Every sheet recalculates when inputs change.
A7: 3. Scenario drivers live on 'Inputs' (one row per scenario per driver). Bear/Base/Bull sheets are identical in structure.
A8: 4. 'Summary' shows each scenario, the probability-weighted value, and a reverse DCF (what today's price requires).
A9: 5. 'Sensitivity' has live WACC x terminal-growth grids, plus a tornado table computed by flexing single inputs.
A11: METHOD
A12: - Base year 2026E = Q1 + Q2 actuals + Q3 guidance midpoint + Q4 assumption, split by segment using the Q2 2026 mix.
A13: - 2027-2033 explicit forecast by segment: DCAI (server), CCPG (client), external foundry + packaging, other.
A14: - China layer: the China DOMESTIC share of DCAI+CCPG revenue (China-billed share x domestic fraction) erodes at a scenario-specific annual rate
... A35: - Not investment advice.

Sheet Summary
A1: Summary: scenario values vs market price (US$ bn unless stated)
A3: Metric | B3: Bear | C3: Base | D3: Bull | E3: Prob-weighted
A4: Scenario weight | B4: =Inputs!$B$79 | C4: =Inputs!$B$80 | D4: =Inputs!$B$81 | F4: Weights are my judgment (Inputs sheet); they must sum to 100%
A5: Value per share ($) | B5: =Bear!B43 | C5: =Base!B43 | D5: =Bull!B43 | E5: =SUMPRODUCT(B4:D4,B5:D5) | F5: Check weights sum:
A6: Upside / (downside) vs current price | B6: =Bear!B45 | C6: =Base!B45 | D6: =Bull!B45 | E6: =IF(Inputs!$B$4=0,0,E5/Inputs!$B$4-1) | F6: =IF(ABS(Inputs!$B$82-1)<0.0001,"OK","WEIGHTS DO NOT SUM TO 100%")
A7: Enterprise value | B7: =Bear!B37 | C7: =Base!B37 | D7: =Bull!B37
A8: Terminal value % of EV | B8: =Bear!B46 | C8: =Base!B46 | D8: =Bull!B46
A9: 2030 revenue | B9: =Bear!F14 | C9: =Base!F14 | D9: =Bull!F14
A10: 2033 revenue | B10: =Bear!I14 | C10: =Base!I14 | D10: =Bull!I14
A11: 2030 non-GAAP gross margin | B11: =Bear!F16 | C11: =Base!F16 | D11: =Bull!F16
A12: 2030 non-GAAP operating margin | B12: =Bear!F20 | C12: =Base!F20 | D12: =Bull!F20
A13: 2033 external foundry + packaging revenue | B13: =Bear!I9 | C13: =Base!I9 | D13: =Bull!I9
A14: 2033 revenue lost to China localization / trade | B14: =Bear!I13 | C14: =Base!I13 | D14: =Bull!I13
A15: 2030 unlevered FCF | B15: =Bear!F28 | C15: =Base!F28 | D15: =Bull!F28
A16: Cumulative FCF 2027-2033 | B16: =SUM(Bear!C28:I28) | C16: =SUM(Base!C28:I28) | D16: =SUM(Bull!C28:I28)
A18: MARKET SNAPSHOT
A19: Share price ($) | B19: =Inputs!$B$4
A20: Diluted shares (bn) | B20: =Inputs!$B$9
A21: Market cap | B21: =Inputs!$B$17
A22: Enterprise value at market | B22: =Inputs!$B$18
A23: WACC | B23: =Inputs!$B$62
A24: Terminal growth | B24: =Inputs!$B$63
A26: REVERSE DCF: WHAT DOES TODAY'S PRICE REQUIRE? (holding Base explicit-period cash flows)
A27: EV at market | B27: =Inputs!$B$18
A28: PV of Base explicit FCF 2027-2033 | B28: =Base!B34
A29: PV of terminal value required | B29: =B27-B28
A30: Required normalized 2034 FCF | B30: =B29/Base!I30*(Inputs!$B$62-Inputs!$B$63) | F30: FCF in 2034 that the Base explicit years plus the market price imply
A31: Base-case normalized 2034 FCF | B31: =Base!J28
A32: Required / Base terminal FCF | B32: =IF(B31=0,0,B30/B31)
A33: Base 2034 revenue | B33: =Base!J14
A34: Required 2034 FCF margin on Base revenue | B34: =IF(B33=0,0,B30/B33)
A35: Base 2034 FCF margin | B35: =Base!J29
A36: Reference: TSMC Q2-26 operating margin (not FCF margin) | B36: 0.603 | F36: Source: TSMC Q2 2026 results (60.3% op margin). Context only
A37: Market-implied perpetual FCF from today (EV x (WACC - g)) | B37: =Inputs!$B$18*(Inputs!$B$62-Inputs!$B$63)
A38: Base 2027 FCF, for comparison | B38: =Base!C28
A39: Required 2034 revenue if FCF margin = 20% | B39: =B30/0.20
A40: Required 2034 revenue if FCF margin = 25% | B40: =B30/0.25
A41: Required 2034 revenue if FCF margin = 30% | B41: =B30/0.30
A42: Bull-case 2034 revenue, for comparison | B42: =Bull!J14
A43: Bull-case 2034 FCF margin, for comparison | B43: =Bull!J29
A45: HOW TO READ THIS
A46: - 'If the scenario is true, the math says X.' None of the scenarios is a forecast I endorse. The weights express my judgment of plausibility from the product evidence.
A47: - The reverse DCF shows how much more (or less) terminal cash flow than my Base case the current price needs. A ratio well above 1.0x means the price embeds
A48: assumptions closer to the Bull case: a 14A anchor customer, packaging at scale, sustained CPU pricing and gross margins in the mid-50s.
A49: - Terminal value is a large share of EV in every scenario. Small changes in WACC or terminal growth move the answer a lot: see the Sensitivity sheet.

Sheet Sensitivity
A1: Sensitivity: value per share ($)
A3: Bear scenario: value/share vs WACC and terminal growth (live formulas)
A4: WACC (down) / terminal g (across) | B4: 0.02 | C4: 0.025 | D4: 0.03 | E4: 0.035 | F4: 0.04
A5: 0.085 | B5: =MAX(0,IF($A5<=B$4,0,(SUMPRODUCT(Bear!$C$28:$I$28,1/(1+$A5)^Bear!$C$4:$I$4)+(Bear!$I$24*(1+B$4)+Bear!$I$25*(1+B$4)*(1-Inputs!$B$64)-Inputs!$B$65*Bear!$I$14*B$4)/($A5-B$4)/(1+$A5)^Bear!$I$4+Inputs!$B$16+Inputs!$B$14-Inputs!$B$15)/Inputs!$B$9)) | C5: =MAX(0,IF($A5<=C$4,0,(SUMPRODUCT(Bear!$C$28:$I$28,1/(1+$A5)^Bear!$C$4:$I$4)+(Bear!$I$24*(1+C$4)+Bear!$I$25*(1+C$4)*(1-Inputs!$B$64)-Inputs!$B$65*Bear!$I$14*C$4)/($A5-C$4)/(1+$A5)^Bear!$I$4+Inputs!$B$16+Inputs!$B$14-Inputs!$B$15)/Inputs!$B$9)) | D5: =MAX(0,IF($A5<=D$4,0,(SUMPRODUCT(Bear!$C$28:$I$28,1/(1+$A5)^Bear!$C$4:$I$4)+(Bear!$I$24*(1+D$4)+Bear!$I$25*(1+D$4)*(1-Inputs!$B$64)-Inputs!$B$65*Bear!$I$14*D$4)/($A5-D$4)/(1+$A5)^Bear!$I$4+Inputs!$B$16+Inputs!$B$14-Inputs!$B$15)/Inputs!$B$9)) | E5: =MAX(0,IF($A5<=E$4,0,(SUMPRODUCT(Bear!$C$28:$I$28,1/(1+$A5)^Bear!$C$4:$I$4)+(Bear!$I$24*(1+E$4)+Bear!$I$25*(1+E$4)*(1-Inputs!$B$64)-Inputs!$B$65*Bear!$I$14*E$4)/($A5-E$4)/(1+$A5)^Bear!$I$4+Inputs!$B$16+Inputs!$B$14-Inputs!$B$15)/Inputs!$B$9)) | F5: =MAX(0,IF($A5<=F$4,0,(SUMPRODUCT(Bear!$C$28:$I$28,1/(1+$A5)^Bear!$C$4:$I$4)+(Bear!$I$24*(1+F$4)+Bear!$I$25*(1+F$4)*(1-Inputs!$B$64)-Inputs!$B$65*Bear!$I$14*F$4)/($A5-F$4)/(1+$A5)^Bear!$I$4+Inputs!$B$16+Inputs!$B$14-Inputs!$B$15)/Inputs!$B$9))
A6: 0.095 | B6: =MAX(0,IF($A6<=B$4,0,(SUMPRODUCT(Bear!$C$28:$I$28,1/(1+$A6)^Bear!$C$4:$I$4)+(Bear!$I$24*(1+B$4)+Bear!$I$25*(1+B$4)*(1-Inputs!$B$64)-Inputs!$B$65*Bear!$I$14*B$4)/($A6-B$4)/(1+$A6)^Bear!$I$4+Inputs!$B$16+Inputs!$B$14-Inputs!$B$15)/Inputs!$B$9)) | C6: =MAX(0,IF($A6<=C$4,0,(SUMPRODUCT(Bear!$C$28:$I$28,1/(1+$A6)^Bear!$C$4:$I$4)+(Bear!$I$24*(1+C$4)+Bear!$I$25*(1+C$4)*(1-Inputs!$B$64)-Inputs!$B$65*Bear!$I$14*C$4)/($A6-C$4)/(1+$A6)^Bear!$I$4+Inputs!$B$16+Inputs!$B$14-Inputs!$B$15)/Inputs!$B$9)) | D6: =MAX(0,IF($A6<=D$4,0,(SUMPRODUCT(Bear!$C$28:$I$28,1/(1+$A6)^Bear!$C$4:$I$4)+(Bear!$I$24*(1+D$4)+Bear!$I$25*(1+D$4)*(1-Inputs!$B$64)-Inputs!$B$65*Bear!$I$14*D$4)/($A6-D$4)/(1+$A6)^Bear!$I$4+Inputs!$B$16+Inputs!$B$14-Inputs!$B$15)/Inputs!$B$9)) | E6: =MAX(0,IF($A6<=E$4,0,(SUMPRODUCT(Bear!$C$28:$I$28,1/(1+$A6)^Bear!$C$4:$I$4)+(Bear!$I$24*(1+E$4)+Bear!$I$25*(1+E$4)*(1-Inputs!$B$64)-Inputs!$B$65*Bear!$I$14*E$4)/($A6-E$4)/(1+$A6)^Bear!$I$4+Inputs!$B$16+Inputs!$B$14-Inputs!$B$15)/Inputs!$B$9)) | F6: =MAX(0,IF($A6<=F$4,0,(SUMPRODUCT(Bear!$C$28:$I$28,1/(1+$A6)^Bear!$C$4:$I$4)+(Bear!$I$24*(1+F$4)+Bear!$I$25*(1+F$4)*(1-Inputs!$B$64)-Inputs!$B$65*Bear!$I$14*F$4)/($A6-F$4)/(1+$A6)^Bear!$I$4+Inputs!$B$16+Inputs!$B$14-Inputs!$B$15)/Inputs!$B$9))
A7: 0.105 | B7: =MAX(0,IF($A7<=B$4,0,(SUMPRODUCT(Bear!$C$28:$I$28,1/(1+$A7)^Bear!$C$4:$I$4)+(Bear!$I$24*(1+B$4)+Bear!$I$25*(1+B$4)*(1-Inputs!$B$64)-Inputs!$B$65*Bear!$I$14*B$4)/($A7-B$4)/(1+$A7)^Bear!$I$4+Inputs!$B$16+Inputs!$B$14-Inputs!$B$15)/Inputs!$B$9)) | C7: =MAX(0,IF($A7<=C$4,0,(SUMPRODUCT(Bear!$C$28:$I$28,1/(1+$A7)^Bear!$C$4:$I$4)+(Bear!$I$24*(1+C$4)+Bear!$I$25*(1+C$4)*(1-Inputs!$B$64)-Inputs!$B$65*Bear!$I$14*C$4)/($A7-C$4)/(1+$A7)^Bear!$I$4+Inputs!$B$16+Inputs!$B$14-Inputs!$B$15)/Inputs!$B$9)) | D7: =MAX(0,IF($A7<=D$4,0,(SUMPRODUCT(Bear!$C$28:$I$28,1/(1+$A7)^Bear!$C$4:$I$4)+(Bear!$I$24*(1+D$4)+Bear!$I$25*(1+D$4)*(1-Inputs!$B$64)-Inputs!$B$65*Bear!$I$14*D$4)/($A7-D$4)/(1+$A7)^Bear!$I$4+Inputs!$B$16+Inputs!$B$14-Inputs!$B$15)/Inputs!$B$9)) | E7: =MAX(0,IF($A7<=E$4,0,(SUMPRODUCT(Bear!$C$28:$I$28,1/(1+$A7)^Bear!$C$4:$I$4)+(Bear!$I$24*(1+E$4)+Bear!$I$25*(1+E$4)*(1-Inputs!$B$64)-Inputs!$B$65*Bear!$I$14*E$4)/($A7-E$4)/(1+$A7)^Bear!$I$4+Inputs!$B$16+Inputs!$B$14-Inputs!$B$15)/Inputs!$B$9)) | F7: =MAX(0,IF($A7<=F$4,0,(SUMPRODUCT(Bear!$C$28:$I$28,1/(1+$A7)^Bear!$C$4:$I$4)+(Bear!$I$24*(1+F$4)+Bear!$I$25*(1+F$4)*(1-Inputs!$B$64)-Inputs!$B$65*Bear!$I$14*F$4)/($A7-F$4)/(1+$A7)^Bear!$I$4+Inputs!$B$16+Inputs!$B$14-Inputs!$B$15)/Inputs!$B$9))
A8: 0.115 | B8: =MAX(0,IF($A8<=B$4,0,(SUMPRODUCT(Bear!$C$28:$I$28,1/(1+$A8)^Bear!$C$4:$I$4)+(Bear!$I$24*(1+B$4)+Bear!$I$25*(1+B$4)*(1-Inputs!$B$64)-Inputs!$B$65*Bear!$I$14*B$4)/($A8-B$4)/(1+$A8)^Bear!$I$4+Inputs!$B$16+Inputs!$B$14-Inputs!$B$15)/Inputs!$B$9)) | C8: =MAX(0,IF($A8<=C$4,0,(SUMPRODUCT(Bear!$C$28:$I$28,1/(1+$A8)^Bear!$C$4:$I$4)+(Bear!$I$24*(1+C$4)+Bear!$I$25*(1+C$4)*(1-Inputs!$B$64)-Inputs!$B$65*Bear!$I$14*C$4)/($A8-C$4)/(1+$A8)^Bear!$I$4+Inputs!$B$16+Inputs!$B$14-Inputs!$B$15)/Inputs!$B$9)) | D8: =MAX(0,IF($A8<=D$4,0,(SUMPRODUCT(Bear!$C$28:$I$28,1/(1+$A8)^Bear!$C$4:$I$4)+(Bear!$I$24*(1+D$4)+Bear!$I$25*(1+D$4)*(1-Inputs!$B$64)-Inputs!$B$65*Bear!$I$14*D$4)/($A8-D$4)/(1+$A8)^Bear!$I$4+Inputs!$B$16+Inputs!$B$14-Inputs!$B$15)/Inputs!$B$9)) | E8: =MAX(0,IF($A8<=E$4,0,(SUMPRODUCT(Bear!$C$28:$I$28,1/(1+$A8)^Bear!$C$4:$I$4)+(Bear!$I$24*(1+E$4)+Bear!$I$25*(1+E$4)*(1-Inputs!$B$64)-Inputs!$B$65*Bear!$I$14*E$4)/($A8-E$4)/(1+$A8)^Bear!$I$4+Inputs!$B$16+Inputs!$B$14-Inputs!$B$15)/Inputs!$B$9)) | F8: =MAX(0,IF($A8<=F$4,0,(SUMPRODUCT(Bear!$C$28:$I$28,1/(1+$A8)^Bear!$C$4:$I$4)+(Bear!$I$24*(1+F$4)+Bear!$I$25*(1+F$4)*(1-Inputs!$B$64)-Inputs!$B$65*Bear!$I$14*F$4)/($A8-F$4)/(1+$A8)^Bear!$I$4+Inputs!$B$16+Inputs!$B$14-Inputs!$B$15)/Inputs!$B$9))
A9: 0.125 | B9: =MAX(0,IF($A9<=B$4,0,(SUMPRODUCT(Bear!$C$28:$I$28,1/(1+$A9)^Bear!$C$4:$I$4)+(Bear!$I$24*(1+B$4)+Bear!$I$25*(1+B$4)*(1-Inputs!$B$64)-Inputs!$B$65*Bear!$I$14*B$4)/($A9-B$4)/(1+$A9)^Bear!$I$4+Inputs!$B$16+Inputs!$B$14-Inputs!$B$15)/Inputs!$B$9)) | C9: =MAX(0,IF($A9<=C$4,0,(SUMPRODUCT(Bear!$C$28:$I$28,1/(1+$A9)^Bear!$C$4:$I$4)+(Bear!$I$24*(1+C$4)+Bear!$I$25*(1+C$4)*(1-Inputs!$B$64)-Inputs!$B$65*Bear!$I$14*C$4)/($A9-C$4)/(1+$A9)^Bear!$I$4+Inputs!$B$16+Inputs!$B$14-Inputs!$B$15)/Inputs!$B$9)) | D9: =MAX(0,IF($A9<=D$4,0,(SUMPRODUCT(Bear!$C$28:$I$28,1/(1+$A9)^Bear!$C$4:$I$4)+(Bear!$I$24*(1+D$4)+Bear!$I$25*(1+D$4)*(1-Inputs!$B$64)-Inputs!$B$65*Bear!$I$14*D$4)/($A9-D$4)/(1+$A9)^Bear!$I$4+Inputs!$B$16+Inputs!$B$14-Inputs!$B$15)/Inputs!$B$9)) | E9: =MAX(0,IF($A9<=E$4,0,(SUMPRODUCT(Bear!$C$28:$I$28,1/(1+$A9)^Bear!$C$4:$I$4)+(Bear!$I$24*(1+E$4)+Bear!$I$25*(1+E$4)*(1-Inputs!$B$64)-Inputs!$B$65*Bear!$I$14*E$4)/($A9-E$4)/(1+$A9)^Bear!$I$4+Inputs!$B$16+Inputs!$B$14-Inputs!$B$15)/Inputs!$B$9)) | F9: =MAX(0,IF($A9<=F$4,0,(SUMPRODUCT(Bear!$C$28:$I$28,1/(1+$A9)^Bear!$C$4:$I$4)+(Bear!$I$24*(1+F$4)+Bear!$I$25*(1+F$4)*(1-Inputs!$B$64)-Inputs!$B$65*Bear!$I$14*F$4)/($A9-F$4)/(1+$A9)^Bear!$I$4+Inputs!$B$16+Inputs!$B$14-Inputs!$B$15)/Inputs!$B$9))
A11: Base scenario: value/share vs WACC and terminal growth (live formulas)
A12: WACC (down) / terminal g (across) | B12: 0.02 | C12: 0.025 | D12: 0.03 | E12: 0.035 | F12: 0.04
A13: 0.085 | B13: =MAX(0,IF($A13<=B$12,0,(SUMPRODUCT(Base!$C$28:$I$28,1/(1+$A13)^Base!$C$4:$I$4)+(Base!$I$24*(1+B$12)+Base!$I$25*(1+B$12)*(1-Inputs!$B$64)-Inputs!$B$65*Base!$I$14*B$12)/($A13-B$12)/(1+$A13)^Base!$I$4+Inputs!$B$16+Inputs!$B$14-Inputs!$B$15)/Inputs!$B$9)) | C13: =MAX(0,IF($A13<=C$12,0,(SUMPRODUCT(Base!$C$28:$I$28,1/(1+$A13)^Base!$C$4:$I$4)+(Base!$I$24*(1+C$12)+Base!$I$25*(1+C$12)*(1-Inputs!$B$64)-Inputs!$B$65*Base!$I$14*C$12)/($A13-C$12)/(1+$A13)^Base!$I$4+Inputs!$B$16+Inputs!$B$14-Inputs!$B$15)/Inputs!$B$9)) | D13: =MAX(0,IF($A13<=D$12,0,(SUMPRODUCT(Base!$C$28:$I$28,1/(1+$A13)^Base!$C$4:$I$4)+(Base!$I$24*(1+D$12)+Base!$I$25*(1+D$12)*(1-Inputs!$B$64)-Inputs!$B$65*Base!$I$14*D$12)/($A13-D$12)/(1+$A13)^Base!$I$4+Inputs!$B$16+Inputs!$B$14-Inputs!$B$15)/Inputs!$B$9)) | E13: =MAX(0,IF($A13<=E$12,0,(SUMPRODUCT(Base!$C$28:$I$28,1/(1+$A13)^Base!$C$4:$I$4)+(Base!$I$24*(1+E$12)+Base!$I$25*(1+E$12)*(1-Inputs!$B$64)-Inputs!$B$65*Base!$I$14*E$12)/($A13-E$12)/(1+$A13)^Base!$I$4+Inputs!$B$16+Inputs!$B$14-Inputs!$B$15)/Inputs!$B$9)) | F13: =MAX(0,IF($A13<=F$12,0,(SUMPRODUCT(Base!$C$28:$I$28,1/(1+$A13)^Base!$C$4:$I$4)+(Base!$I$24*(1+F$12)+Base!$I$25*(1+F$12)*(1-Inputs!$B$64)-Inputs!$B$65*Base!$I$14*F$12)/($A13-F$12)/(1+$A13)^Base!$I$4+Inputs!$B$16+Inputs!$B$14-Inputs!$B$15)/Inputs!$B$9))
A14: 0.095 | B14: =MAX(0,IF($A14<=B$12,0,(SUMPRODUCT(Base!$C$28:$I$28,1/(1+$A14)^Base!$C$4:$I$4)+(Base!$I$24*(1+B$12)+Base!$I$25*(1+B$12)*(1-Inputs!$B$64)-Inputs!$B$65*Base!$I$14*B$12)/($A14-B$12)/(1+$A14)^Base!$I$4+Inputs!$B$16+Inputs!$B$14-Inputs!$B$15)/Inputs!$B$9)) | C14: =MAX(0,IF($A14<=C$12,0,(SUMPRODUCT(Base!$C$28:$I$28,1/(1+$A14)^Base!$C$4:$I$4)+(Base!$I$24*(1+C$12)+Base!$I$25*(1+C$12)*(1-Inputs!$B$64)-Inputs!$B$65*Base!$I$14*C$12)/($A14-C$12)/(1+$A14)^Base!$I$4+Inputs!$B$16+Inputs!$B$14-Inputs!$B$15)/Inputs!$B$9)) | D14: =MAX(0,IF($A14<=D$12,0,(SUMPRODUCT(Base!$C$28:$I$28,1/(1+$A14)^Base!$C$4:$I$4)+(Base!$I$24*(1+D$12)+Base!$I$25*(1+D$12)*(1-Inputs!$B$64)-Inputs!$B$65*Base!$I$14*D$12)/($A14-D$12)/(1+$A14)^Base!$I$4+Inputs!$B$16+Inputs!$B$14-Inputs!$B$15)/Inputs!$B$9)) | E14: =MAX(0,IF($A14<=E$12,0,(SUMPRODUCT(Base!$C$28:$I$28,1/(1+$A14)^Base!$C$4:$I$4)+(Base!$I$24*(1+E$12)+Base!$I$25*(1+E$12)*(1-Inputs!$B$64)-Inputs!$B$65*Base!$I$14*E$12)/($A14-E$12)/(1+$A14)^Base!$I$4+Inputs!$B$16+Inputs!$B$14-Inputs!$B$15)/Inputs!$B$9)) | F14: =MAX(0,IF($A14<=F$12,0,(SUMPRODUCT(Base!$C$28:$I$28,1/(1+$A14)^Base!$C$4:$I$4)+(Base!$I$24*(1+F$12)+Base!$I$25*(1+F$12)*(1-Inputs!$B$64)-Inputs!$B$65*Base!$I$14*F$12)/($A14-F$12)/(1+$A14)^Base!$I$4+Inputs!$B$16+Inputs!$B$14-Inputs!$B$15)/Inputs!$B$9))
A15: 0.105 | B15: =MAX(0,IF($A15<=B$12,0,(SUMPRODUCT(Base!$C$28:$I$28,1/(1+$A15)^Base!$C$4:$I$4)+(Base!$I$24*(1+B$12)+Base!$I$25*(1+B$12)*(1-Inputs!$B$64)-Inputs!$B$65*Base!$I$14*B$12)/($A15-B$12)/(1+$A15)^Base!$I$4+Inputs!$B$16+Inputs!$B$14-Inputs!$B$15)/Inputs!$B$9)) | C15: =MAX(0,IF($A15<=C$12,0,(SUMPRODUCT(Base!$C$28:$I$28,1/(1+$A15)^Base!$C$4:$I$4)+(Base!$I$24*(1+C$12)+Base!$I$25*(1+C$12)*(1-Inputs!$B$64)-Inputs!$B$65*Base!$I$14*C$12)/($A15-C$12)/(1+$A15)^Base!$I$4+Inputs!$B$16+Inputs!$B$14-Inputs!$B$15)/Inputs!$B$9)) | D15: =MAX(0,IF($A15<=D$12,0,(SUMPRODUCT(Base!$C$28:$I$28,1/(1+$A15)^Base!$C$4:$I$4)+(Base!$I$24*(1+D$12)+Base!$I$25*(1+D$12)*(1-Inputs!$B$64)-Inputs!$B$65*Base!$I$14*D$12)/($A15-D$12)/(1+$A15)^Base!$I$4+Inputs!$B$16+Inputs!$B$14-Inputs!$B$15)/Inputs!$B$9)) | E15: =MAX(0,IF($A15<=E$12,0,(SUMPRODUCT(Base!$C$28:$I$28,1/(1+$A15)^Base!$C$4:$I$4)+(Base!$I$24*(1+E$12)+Base!$I$25*(1+E$12)*(1-Inputs!$B$64)-Inputs!$B$65*Base!$I$14*E$12)/($A15-E$12)/(1+$A15)^Base!$I$4+Inputs!$B$16+Inputs!$B$14-Inputs!$B$15)/Inputs!$B$9)) | F15: =MAX(0,IF($A15<=F$12,0,(SUMPRODUCT(Base!$C$28:$I$28,1/(1+$A15)^Base!$C$4:$I$4)+(Base!$I$24*(1+F$12)+Base!$I$25*(1+F$12)*(1-Inputs!$B$64)-Inputs!$B$65*Base!$I$14*F$12)/($A15-F$12)/(1+$A15)^Base!$I$4+Inputs!$B$16+Inputs!$B$14-Inputs!$B$15)/Inputs!$B$9))
A16: 0.115 | B16: =MAX(0,IF($A16<=B$12,0,(SUMPRODUCT(Base!$C$28:$I$28,1/(1+$A16)^Base!$C$4:$I$4)+(Base!$I$24*(1+B$12)+Base!$I$25*(1+B$12)*(1-Inputs!$B$64)-Inputs!$B$65*Base!$I$14*B$12)/($A16-B$12)/(1+$A16)^Base!$I$4+Inputs!$B$16+Inputs!$B$14-Inputs!$B$15)/Inputs!$B$9)) | C16: =MAX(0,IF($A16<=C$12,0,(SUMPRODUCT(Base!$C$28:$I$28,1/(1+$A16)^Base!$C$4:$I$4)+(Base!$I$24*(1+C$12)+Base!$I$25*(1+C$12)*(1-Inputs!$B$64)-Inputs!$B$65*Base!$I$14*C$12)/($A16-C$12)/(1+$A16)^Base!$I$4+Inputs!$B$16+Inputs!$B$14-Inputs!$B$15)/Inputs!$B$9)) | D16: =MAX(0,IF($A16<=D$12,0,(SUMPRODUCT(Base!$C$28:$I$28,1/(1+$A16)^Base!$C$4:$I$4)+(Base!$I$24*(1+D$12)+Base!$I$25*(1+D$12)*(1-Inputs!$B$64)-Inputs!$B$65*Base!$I$14*D$12)/($A16-D$12)/(1+$A16)^Base!$I$4+Inputs!$B$16+Inputs!$B$14-Inputs!$B$15)/Inputs!$B$9)) | E16: =MAX(0,IF($A16<=E$12,0,(SUMPRODUCT(Base!$C$28:$I$28,1/(1+$A16)^Base!$C$4:$I$4)+(Base!$I$24*(1+E$12)+Base!$I$25*(1+E$12)*(1-Inputs!$B$64)-Inputs!$B$65*Base!$I$14*E$12)/($A16-E$12)/(1+$A16)^Base!$I$4+Inputs!$B$16+Inputs!$B$14-Inputs!$B$15)/Inputs!$B$9)) | F16: =MAX(0,IF($A16<=F$12,0,(SUMPRODUCT(Base!$C$28:$I$28,1/(1+$A16)^Base!$C$4:$I$4)+(Base!$I$24*(1+F$12)+Base!$I$25*(1+F$12)*(1-Inputs!$B$64)-Inputs!$B$65*Base!$I$14*F$12)/($A16-F$12)/(1+$A16)^Base!$I$4+Inputs!$B$16+Inputs!$B$14-Inputs!$B$15)/Inputs!$B$9))
A17: 0.125 | B17: =MAX(0,IF($A17<=B$12,0,(SUMPRODUCT(Base!$C$28:$I$28,1/(1+$A17)^Base!$C$4:$I$4)+(Base!$I$24*(1+B$12)+Base!$I$25*(1+B$12)*(1-Inputs!$B$64)-Inputs!$B$65*Base!$I$14*B$12)/($A17-B$12)/(1+$A17)^Base!$I$4+Inputs!$B$16+Inputs!$B$14-Inputs!$B$15)/Inputs!$B$9)) | C17: =MAX(0,IF($A17<=C$12,0,(SUMPRODUCT(Base!$C$28:$I$28,1/(1+$A17)^Base!$C$4:$I$4)+(Base!$I$24*(1+C$12)+Base!$I$25*(1+C$12)*(1-Inputs!$B$64)-Inputs!$B$65*Base!$I$14*C$12)/($A17-C$12)/(1+$A17)^Base!$I$4+Inputs!$B$16+Inputs!$B$14-Inputs!$B$15)/Inputs!$B$9)) | D17: =MAX(0,IF($A17<=D$12,0,(SUMPRODUCT(Base!$C$28:$I$28,1/(1+$A17)^Base!$C$4:$I$4)+(Base!$I$24*(1+D$12)+Base!$I$25*(1+D$12)*(1-Inputs!$B$64)-Inputs!$B$65*Base!$I$14*D$12)/($A17-D$12)/(1+$A17)^Base!$I$4+Inputs!$B$16+Inputs!$B$14-Inputs!$B$15)/Inputs!$B$9)) | E17: =MAX(0,IF($A17<=E$12,0,(SUMPRODUCT(Base!$C$28:$I$28,1/(1+$A17)^Base!$C$4:$I$4)+(Base!$I$24*(1+E$12)+Base!$I$25*(1+E$12)*(1-Inputs!$B$64)-Inputs!$B$65*Base!$I$14*E$12)/($A17-E$12)/(1+$A17)^Base!$I$4+Inputs!$B$16+Inputs!$B$14-Inputs!$B$15)/Inputs!$B$9)) | F17: =MAX(0,IF($A17<=F$12,0,(SUMPRODUCT(Base!$C$28:$I$28,1/(1+$A17)^Base!$C$4:$I$4)+(Base!$I$24*(1+F$12)+Base!$I$25*(1+F$12)*(1-Inputs!$B$64)-Inputs!$B$65*Base!$I$14*F$12)/($A17-F$12)/(1+$A17)^Base!$I$4+Inputs!$B$16+Inputs!$B$14-Inputs!$B$15)/Inputs!$B$9))
A19: Bull scenario: value/share vs WACC and terminal growth (live formulas)
A20: WACC (down) / terminal g (across) | B20: 0.02 | C20: 0.025 | D20: 0.03 | E20: 0.035 | F20: 0.04
A21: 0.085 | B21: =MAX(0,IF($A21<=B$20,0,(SUMPRODUCT(Bull!$C$28:$I$28,1/(1+$A21)^Bull!$C$4:$I$4)+(Bull!$I$24*(1+B$20)+Bull!$I$25*(1+B$20)*(1-Inputs!$B$64)-Inputs!$B$65*Bull!$I$14*B$20)/($A21-B$20)/(1+$A21)^Bull!$I$4+Inputs!$B$16+Inputs!$B$14-Inputs!$B$15)/Inputs!$B$9)) | C21: =MAX(0,IF($A21<=C$20,0,(SUMPRODUCT(Bull!$C$28:$I$28,1/(1+$A21)^Bull!$C$4:$I$4)+(Bull!$I$24*(1+C$20)+Bull!$I$25*(1+C$20)*(1-Inputs!$B$64)-Inputs!$B$65*Bull!$I$14*C$20)/($A21-C$20)/(1+$A21)^Bull!$I$4+Inputs!$B$16+Inputs!$B$14-Inputs!$B$15)/Inputs!$B$9)) | D21: =MAX(0,IF($A21<=D$20,0,(SUMPRODUCT(Bull!$C$28:$I$28,1/(1+$A21)^Bull!$C$4:$I$4)+(Bull!$I$24*(1+D$20)+Bull!$I$25*(1+D$20)*(1-Inputs!$B$64)-Inputs!$B$65*Bull!$I$14*D$20)/($A21-D$20)/(1+$A21)^Bull!$I$4+Inputs!$B$16+Inputs!$B$14-Inputs!$B$15)/Inputs!$B$9)) | E21: =MAX(0,IF($A21<=E$20,0,(SUMPRODUCT(Bull!$C$28:$I$28,1/(1+$A21)^Bull!$C$4:$I$4)+(Bull!$I$24*(1+E$20)+Bull!$I$25*(1+E$20)*(1-Inputs!$B$64)-Inputs!$B$65*Bull!$I$14*E$20)/($A21-E$20)/(1+$A21)^Bull!$I$4+Inputs!$B$16+Inputs!$B$14-Inputs!$B$15)/Inputs!$B$9)) | F21: =MAX(0,IF($A21<=F$20,0,(SUMPRODUCT(Bull!$C$28:$I$28,1/(1+$A21)^Bull!$C$4:$I$4)+(Bull!$I$24*(1+F$20)+Bull!$I$25*(1+F$20)*(1-Inputs!$B$64)-Inputs!$B$65*Bull!$I$14*F$20)/($A21-F$20)/(1+$A21)^Bull!$I$4+Inputs!$B$16+Inputs!$B$14-Inputs!$B$15)/Inputs!$B$9))
A22: 0.095 | B22: =MAX(0,IF($A22<=B$20,0,(SUMPRODUCT(Bull!$C$28:$I$28,1/(1+$A22)^Bull!$C$4:$I$4)+(Bull!$I$24*(1+B$20)+Bull!$I$25*(1+B$20)*(1-Inputs!$B$64)-Inputs!$B$65*Bull!$I$14*B$20)/($A22-B$20)/(1+$A22)^Bull!$I$4+Inputs!$B$16+Inputs!$B$14-Inputs!$B$15)/Inputs!$B$9)) | C22: =MAX(0,IF($A22<=C$20,0,(SUMPRODUCT(Bull!$C$28:$I$28,1/(1+$A22)^Bull!$C$4:$I$4)+(Bull!$I$24*(1+C$20)+Bull!$I$25*(1+C$20)*(1-Inputs!$B$64)-Inputs!$B$65*Bull!$I$14*C$20)/($A22-C$20)/(1+$A22)^Bull!$I$4+Inputs!$B$16+Inputs!$B$14-Inputs!$B$15)/Inputs!$B$9)) | D22: =MAX(0,IF($A22<=D$20,0,(SUMPRODUCT(Bull!$C$28:$I$28,1/(1+$A22)^Bull!$C$4:$I$4)+(Bull!$I$24*(1+D$20)+Bull!$I$25*(1+D$20)*(1-Inputs!$B$64)-Inputs!$B$65*Bull!$I$14*D$20)/($A22-D$20)/(1+$A22)^Bull!$I$4+Inputs!$B$16+Inputs!$B$14-Inputs!$B$15)/Inputs!$B$9)) | E22: =MAX(0,IF($A22<=E$20,0,(SUMPRODUCT(Bull!$C$28:$I$28,1/(1+$A22)^Bull!$C$4:$I$4)+(Bull!$I$24*(1+E$20)+Bull!$I$25*(1+E$20)*(1-Inputs!$B$64)-Inputs!$B$65*Bull!$I$14*E$20)/($A22-E$20)/(1+$A22)^Bull!$I$4+Inputs!$B$16+Inputs!$B$14-Inputs!$B$15)/Inputs!$B$9)) | F22: =MAX(0,IF($A22<=F$20,0,(SUMPRODUCT(Bull!$C$28:$I$28,1/(1+$A22)^Bull!$C$4:$I$4)+(Bull!$I$24*(1+F$20)+Bull!$I$25*(1+F$20)*(1-Inputs!$B$64)-Inputs!$B$65*Bull!$I$14*F$20)/($A22-F$20)/(1+$A22)^Bull!$I$4+Inputs!$B$16+Inputs!$B$14-Inputs!$B$15)/Inputs!$B$9))
A23: 0.105 | B23: =MAX(0,IF($A23<=B$20,0,(SUMPRODUCT(Bull!$C$28:$I$28,1/(1+$A23)^Bull!$C$4:$I$4)+(Bull!$I$24*(1+B$20)+Bull!$I$25*(1+B$20)*(1-Inputs!$B$64)-Inputs!$B$65*Bull!$I$14*B$20)/($A23-B$20)/(1+$A23)^Bull!$I$4+Inputs!$B$16+Inputs!$B$14-Inputs!$B$15)/Inputs!$B$9)) | C23: =MAX(0,IF($A23<=C$20,0,(SUMPRODUCT(Bull!$C$28:$I$28,1/(1+$A23)^Bull!$C$4:$I$4)+(Bull!$I$24*(1+C$20)+Bull!$I$25*(1+C$20)*(1-Inputs!$B$64)-Inputs!$B$65*Bull!$I$14*C$20)/($A23-C$20)/(1+$A23)^Bull!$I$4+Inputs!$B$16+Inputs!$B$14-Inputs!$B$15)/Inputs!$B$9)) | D23: =MAX(0,IF($A23<=D$20,0,(SUMPRODUCT(Bull!$C$28:$I$28,1/(1+$A23)^Bull!$C$4:$I$4)+(Bull!$I$24*(1+D$20)+Bull!$I$25*(1+D$20)*(1-Inputs!$B$64)-Inputs!$B$65*Bull!$I$14*D$20)/($A23-D$20)/(1+$A23)^Bull!$I$4+Inputs!$B$16+Inputs!$B$14-Inputs!$B$15)/Inputs!$B$9)) | E23: =MAX(0,IF($A23<=E$20,0,(SUMPRODUCT(Bull!$C$28:$I$28,1/(1+$A23)^Bull!$C$4:$I$4)+(Bull!$I$24*(1+E$20)+Bull!$I$25*(1+E$20)*(1-Inputs!$B$64)-Inputs!$B$65*Bull!$I$14*E$20)/($A23-E$20)/(1+$A23)^Bull!$I$4+Inputs!$B$16+Inputs!$B$14-Inputs!$B$15)/Inputs!$B$9)) | F23: =MAX(0,IF($A23<=F$20,0,(SUMPRODUCT(Bull!$C$28:$I$28,1/(1+$A23)^Bull!$C$4:$I$4)+(Bull!$I$24*(1+F$20)+Bull!$I$25*(1+F$20)*(1-Inputs!$B$64)-Inputs!$B$65*Bull!$I$14*F$20)/($A23-F$20)/(1+$A23)^Bull!$I$4+Inputs!$B$16+Inputs!$B$14-Inputs!$B$15)/Inputs!$B$9))
A24: 0.115 | B24: =MAX(0,IF($A24<=B$20,0,(SUMPRODUCT(Bull!$C$28:$I$28,1/(1+$A24)^Bull!$C$4:$I$4)+(Bull!$I$24*(1+B$20)+Bull!$I$25*(1+B$20)*(1-Inputs!$B$64)-Inputs!$B$65*Bull!$I$14*B$20)/($A24-B$20)/(1+$A24)^Bull!$I$4+Inputs!$B$16+Inputs!$B$14-Inputs!$B$15)/Inputs!$B$9)) | C24: =MAX(0,IF($A24<=C$20,0,(SUMPRODUCT(Bull!$C$28:$I$28,1/(1+$A24)^Bull!$C$4:$I$4)+(Bull!$I$24*(1+C$20)+Bull!$I$25*(1+C$20)*(1-Inputs!$B$64)-Inputs!$B$65*Bull!$I$14*C$20)/($A24-C$20)/(1+$A24)^Bull!$I$4+Inputs!$B$16+Inputs!$B$14-Inputs!$B$15)/Inputs!$B$9)) | D24: =MAX(0,IF($A24<=D$20,0,(SUMPRODUCT(Bull!$C$28:$I$28,1/(1+$A24)^Bull!$C$4:$I$4)+(Bull!$I$24*(1+D$20)+Bull!$I$25*(1+D$20)*(1-Inputs!$B$64)-Inputs!$B$65*Bull!$I$14*D$20)/($A24-D$20)/(1+$A24)^Bull!$I$4+Inputs!$B$16+Inputs!$B$14-Inputs!$B$15)/Inputs!$B$9)) | E24: =MAX(0,IF($A24<=E$20,0,(SUMPRODUCT(Bull!$C$28:$I$28,1/(1+$A24)^Bull!$C$4:$I$4)+(Bull!$I$24*(1+E$20)+Bull!$I$25*(1+E$20)*(1-Inputs!$B$64)-Inputs!$B$65*Bull!$I$14*E$20)/($A24-E$20)/(1+$A24)^Bull!$I$4+Inputs!$B$16+Inputs!$B$14-Inputs!$B$15)/Inputs!$B$9)) | F24: =MAX(0,IF($A24<=F$20,0,(SUMPRODUCT(Bull!$C$28:$I$28,1/(1+$A24)^Bull!$C$4:$I$4)+(Bull!$I$24*(1+F$20)+Bull!$I$25*(1+F$20)*(1-Inputs!$B$64)-Inputs!$B$65*Bull!$I$14*F$20)/($A24-F$20)/(1+$A24)^Bull!$I$4+Inputs!$B$16+Inputs!$B$14-Inputs!$B$15)/Inputs!$B$9))
A25: 0.125 | B25: =MAX(0,IF($A25<=B$20,0,(SUMPRODUCT(Bull!$C$28:$I$28,1/(1+$A25)^Bull!$C$4:$I$4)+(Bull!$I$24*(1+B$20)+Bull!$I$25*(1+B$20)*(1-Inputs!$B$64)-Inputs!$B$65*Bull!$I$14*B$20)/($A25-B$20)/(1+$A25)^Bull!$I$4+Inputs!$B$16+Inputs!$B$14-Inputs!$B$15)/Inputs!$B$9)) | C25: =MAX(0,IF($A25<=C$20,0,(SUMPRODUCT(Bull!$C$28:$I$28,1/(1+$A25)^Bull!$C$4:$I$4)+(Bull!$I$24*(1+C$20)+Bull!$I$25*(1+C$20)*(1-Inputs!$B$64)-Inputs!$B$65*Bull!$I$14*C$20)/($A25-C$20)/(1+$A25)^Bull!$I$4+Inputs!$B$16+Inputs!$B$14-Inputs!$B$15)/Inputs!$B$9)) | D25: =MAX(0,IF($A25<=D$20,0,(SUMPRODUCT(Bull!$C$28:$I$28,1/(1+$A25)^Bull!$C$4:$I$4)+(Bull!$I$24*(1+D$20)+Bull!$I$25*(1+D$20)*(1-Inputs!$B$64)-Inputs!$B$65*Bull!$I$14*D$20)/($A25-D$20)/(1+$A25)^Bull!$I$4+Inputs!$B$16+Inputs!$B$14-Inputs!$B$15)/Inputs!$B$9)) | E25: =MAX(0,IF($A25<=E$20,0,(SUMPRODUCT(Bull!$C$28:$I$28,1/(1+$A25)^Bull!$C$4:$I$4)+(Bull!$I$24*(1+E$20)+Bull!$I$25*(1+E$20)*(1-Inputs!$B$64)-Inputs!$B$65*Bull!$I$14*E$20)/($A25-E$20)/(1+$A25)^Bull!$I$4+Inputs!$B$16+Inputs!$B$14-Inputs!$B$15)/Inputs!$B$9)) | F25: =MAX(0,IF($A25<=F$20,0,(SUMPRODUCT(Bull!$C$28:$I$28,1/(1+$A25)^Bull!$C$4:$I$4)+(Bull!$I$24*(1+F$20)+Bull!$I$25*(1+F$20)*(1-Inputs!$B$64)-Inputs!$B$65*Bull!$I$14*F$20)/($A25-F$20)/(1+$A25)^Bull!$I$4+Inputs!$B$16+Inputs!$B$14-Inputs!$B$15)/Inputs!$B$9))
A27: Current price ($) | B27: =Inputs!$B$4
A29: TORNADO (Base scenario): one input flexed at a time
A30: Input flexed (Base scenario, others held) | B30: Low case $/sh | C30: High case $/sh | D30: Base $/sh | E30: Swing $/sh
A31: Ext. foundry revenue x0.5 / x2.0 | B31: 16.94 | C31: 32.43 | D31: =Base!B43 | E31: =C31-B31
A32: China erosion 10 pts/yr faster / 5 pts/yr slower | B32: 19.98 | C32: 23.72 | D32: =Base!B43 | E32: =C32-B32
A33: DCAI growth -3 / +3 pts per yr | B33: 18.07 | C33: 26.82 | D33: =Base!B43 | E33: =C33-B33
A34: Gross margin -3 / +3 pts, all years | B34: 17.77 | C34: 26.43 | D34: =Base!B43 | E34: =C34-B34
A35: Capex x1.15 / x0.85 (2027+) | B35: 19.72 | C35: 24.48 | D35: =Base!B43 | E35: =C35-B35
A36: Tornado values are static: computed by setting each Inputs 'FLEX LEVER' and recalculating at the default inputs. Re-run them via the flex levers if you change base inputs. WACC and terminal-growth sensitivity: live grids above.

Sheet Inputs
A1: Inputs (US$ bn unless stated). Blue = input, black = formula, yellow = key judgment / placeholder to verify
A3: Item | B3: Value | J3: Source / note
A4: Share price ($) | B4: 123 | J4: Close 25 Sep 2026 per TradingKey (tradingkey.com). Update to current price.
A5: Q2 2026 non-GAAP net income attributable to Intel | B5: 2.2 | J5: Intel Q2 2026 earnings release (23 Jul 2026)
A6: Q2 2026 non-GAAP EPS ($) | B6: 0.42 | J6: Intel Q2 2026 earnings release (23 Jul 2026)
A7: Implied Q2 diluted shares (bn) | B7: =B5/B6 | J7: Derived = NI / EPS (rounding makes this approximate). VERIFY vs 10-Q.
A8: Shares issued in Aug 2026 offering incl. greenshoe (bn) | B8: 0.2421 | J8: 210,526,315 + 31,578,947 shares; Intel newsroom, 10-11 Aug 2026
A9: Diluted shares for valuation (bn) | B9: =B7+B8 | J9: Excludes any further escrowed government shares not in diluted count; verify.
A10: Cash & equivalents (27 Jun 2026) | B10: 12.874 | J10: Q2 2026 10-Q, via search extract
A11: Short-term investments (27 Jun 2026) | B11: 16.853 | J11: Q2 2026 10-Q, via search extract
A12: Net proceeds of Aug 2026 equity offering | B12: 22.62 | J12: Intel 8-K / newsroom, Aug 2026
A13: Total debt (27 Jun 2026) | B13: 48.549 | J13: Q2 2026 10-Q, via search extract
A14: Altera 49% stake (equity-method) | B14: =8.75*0.49 | J14: Placeholder: 49% x $8.75bn valuation from the 2025 Silver Lake deal. Verify carrying/fair value.
A15: Non-controlling interests (Mobileye minority, SCIP fab partners) | B15: 0 | J15: PLACEHOLDER = 0. Intel's Arizona/Ireland SCIP partners and Mobileye minority holders have material claims. Enter from 10-Q; this overstates value if left at 0.
A16: Net cash (debt) incl. offering | B16: =B10+B11+B12-B13 | J16: Formula
A17: Market capitalization | B17: =B4*B9 | J17: Formula
A18: Enterprise value at market | B18: =B17-B16-B14+B15 | J18: Market cap - net cash - Altera stake + NCI
A20: 2026E BASE YEAR BUILD
A21: Item | B21: Value
A22: Q1 2026 total revenue | B22: 13.6 | J22: Intel Q1 2026 results (23 Apr 2026)
A23: Q2 2026 total revenue | B23: 16.1 | J23: Intel Q2 2026 results
A24: Q3 2026 revenue guidance midpoint | B24: 16.3 | J24: Guidance $15.8-16.8bn (Q2 call)
A25: Q4 2026 revenue assumption | B25: =B24 | J25: ASSUMPTION: flat vs Q3 guide midpoint
A26: Q1 2026 DCAI revenue | B26: 5.1 | J26: Intel Q1 2026 results
A27: Q2 2026 DCAI revenue | B27: 6.3 | J27: Intel Q2 2026 results
A28: Q1 2026 CCPG (client) revenue | B28: 7.7 | J28: Intel Q1 2026 results
A29: Q2 2026 CCPG (client) revenue | B29: 8.9 | J29: Intel Q2 2026 results ($8.88bn)
A30: Q1 2026 external foundry revenue | B30: 0.25 | J30: PLACEHOLDER (not found); Q2 was $0.293bn
A31: Q2 2026 external foundry revenue | B31: 0.293 | J31: Intel Q2 2026 10-Q / DCD
A32: 2026E non-GAAP gross margin | B32: 0.41 | J32: Q2 41.8%, Q3 guide 42%; Q1 lower. Assumption.
A33: 2026E non-GAAP operating expenses | B33: 16.5 | J33: PLACEHOLDER near FY2025 target of $16.8bn; verify 2026 target
A34: 2026E stock-based compensation | B34: 2.5 | J34: PLACEHOLDER; verify from 10-Q cash-flow statement
A35: 2026E depreciation & amortization | B35: 11 | J35: PLACEHOLDER; verify from 10-Q cash-flow statement
A36: 2026E gross capex | B36: 20.5 | J36: Guided 'more than $20bn' (Q2 call)
A37: 2026E total revenue | B37: =$B$22+$B$23+$B$24+$B$25 | J37: Formula
A38: 2026E DCAI revenue | B38: =$B$26+$B$27+($B$24+$B$25)*$B$27/$B$23 | J38: H2 allocated at Q2 mix
A39: 2026E CCPG revenue | B39: =$B$28+$B$29+($B$24+$B$25)*$B$29/$B$23 | J39: H2 allocated at Q2 mix
A40: 2026E external foundry revenue | B40: =$B$30+$B$31+($B$24+$B$25)*$B$31/$B$23 | J40: H2 allocated at Q2 mix
A41: 2026E other revenue (Mobileye etc.) | B41: =$B$37-$B$38-$B$39-$B$40 | J41: Residual
A43: CHINA EXPOSURE
A44: Item | B44: Value
A45: FY2024 China (incl. HK) billed revenue | B45: 15.53 | J45: Intel FY2024 10-K geographic note (billing location); 29% of revenue
A46: FY2025 total revenue | B46: 52.9 | J46: Intel Q4/FY2025 results (22 Jan 2026)
A47: FY2025 US + Taiwan + Singapore + Other billed revenue | B47: =15.76+7.67+9.54+7.20 | J47: FY2025 10-K geographic note via search extract (US 15.76, Taiwan 7.67, Singapore 9.54, Other 7.20); VERIFY
A48: FY2025 China billed revenue (derived residual) | B48: =$B$46-$B$47 | J48: Derived = total - other regions. Not read directly from the 10-K; VERIFY
A49: China billed share of revenue (FY2025) | B49: =IF($B$46=0,0,$B$48/$B$46) | J49: Formula
A50: Share of China-billed revenue that is China DOMESTIC end-demand | B50: 0.5 | J50: JUDGMENT. Billing location includes PCs/servers assembled in China for export (Lenovo, ODMs), which domestic substitution does not hit. No source splits this; test 0.35-0.70
J51: China levers: xinchuang bans Intel/AMD in government PCs & servers (Mar 2024); Hygon+Zhaoxin ~15-20% of China server CPUs, Kunpeng 8-12% (2026 est.); Loongson 1M desktop CPUs; China customs treats WAFER-FAB location as origin -> US-fabbed chips (Intel) face retaliatory tariffs, TSMC-made rivals don't; US-China truce expires 10 Nov 2026.
A53: VALUATION PARAMETERS
A54: Item | B54: Value
A55: Risk-free rate | B55: 0.043 | J55: ASSUMPTION: ~10y UST; update
A56: Equity risk premium | B56: 0.05 | J56: ASSUMPTION
A57: Equity beta | B57: 1.3 | J57: ASSUMPTION: semis/turnaround risk
A58: Cost of equity | B58: =$B$55+$B$57*$B$56 | J58: CAPM
A59: Pre-tax cost of debt | B59: 0.055 | J59: ASSUMPTION
A60: Tax rate | B60: 0.15 | J60: ASSUMPTION: normalized cash tax; Intel has large NOLs near term
A61: Debt weight | B61: =$B$13/($B$13+$B$17) | J61: Market-value weights
A62: WACC | B62: =(1-$B$61)*$B$58+$B$61*$B$59*(1-$B$60) | J62: Formula
A63: Terminal FCF growth | B63: 0.03 | J63: ASSUMPTION
A64: Terminal capex / D&A ratio | B64: 1.15 | J64: ASSUMPTION: maintenance + modest growth capex in steady state
A65: Net working capital, % of revenue change | B65: 0.1 | J65: ASSUMPTION
A66: D&A catch-up toward prior-year capex (per year) | B66: 0.15 | J66: D&A(t) = D&A(t-1) + x * (capex(t-1) - D&A(t-1))
A67: Discount period offset (valuation date 30 Sep 2026) | B67: 0.25 | J67: End-2027 cash flow is 1.25 years out
A68: Other revenue growth (all scenarios) | B68: 0.05 | J68: ASSUMPTION
A70: FLEX LEVERS (for sensitivity; leave at defaults 0 / 0 / 1 / 1)
A71: Gross margin shift, all years, all scenarios (pts) | B71: 0 | J71: e.g. -0.03 = 3 pts lower
A72: DCAI growth shift per year (pts) | B72: 0 | J72: e.g. 0.03 = +3 pts/yr
A73: External foundry revenue multiplier | B73: 1 | J73: e.g. 0.5 = half
A74: Capex multiplier (2027+) | B74: 1 | J74: e.g. 1.15 = 15% more
A75: China domestic revenue change shift per year (pts) | B75: 0 | J75: e.g. -0.10 = 10 pts faster erosion every year
A77: SCENARIO WEIGHTS (judgment; must sum to 100%)
A78: Scenario | B78: Weight
A79: Bear | B79: 0.3 | J79: My judgment; edit
A80: Base | B80: 0.45 | J80: My judgment; edit
A81: Bull | B81: 0.25 | J81: My judgment; edit
A82: Check: sum of weights | B82: =$B$79+$B$80+$B$81 | J82: Must equal 100%
A84: SCENARIO DRIVERS (2027-2033). Hypothetical paths tied to product evidence; NOT forecasts I endorse
A85: DCAI revenue growth | B85: Scenario | C85: 2027 | D85: 2028 | E85: 2029 | F85: 2030 | G85: 2031 | H85: 2032 | I85: 2033
A86: DCAI revenue growth - Bear | B86: Bear | C86: -0.12 | D86: -0.03 | E86: 0 | F86: 0.02 | G86: 0.02 | H86: 0.02 | I86: 0.02
A87: DCAI revenue growth - Base | B87: Base | C87: 0.04 | D87: 0.05 | E87: 0.06 | F87: 0.06 | G87: 0.05 | H87: 0.04 | I87: 0.04
A88: DCAI revenue growth - Bull | B88: Bull | C88: 0.15 | D88: 0.12 | E88: 0.1 | F88: 0.08 | G88: 0.07 | H88: 0.06 | I88: 0.05
A89: Rationale: Bear: shortage ASP spike (+48% YoY in Q2-26) reverses as Venice ships Q4-26 and Diamond Rapids slips; Bull: DMR competitive + agentic CPU demand persists
A91: CCPG (client) revenue growth | B91: Scenario | C91: 2027 | D91: 2028 | E91: 2029 | F91: 2030 | G91: 2031 | H91: 2032 | I91: 2033
A92: CCPG (client) revenue growth - Bear | B92: Bear | C92: -0.08 | D92: -0.04 | E92: -0.03 | F92: -0.02 | G92: -0.02 | H92: -0.01 | I92: -0.01
A93: CCPG (client) revenue growth - Base | B93: Base | C93: -0.02 | D93: 0.01 | E93: 0.02 | F93: 0.02 | G93: 0.02 | H93: 0.02 | I93: 0.02
A94: CCPG (client) revenue growth - Bull | B94: Bull | C94: 0.04 | D94: 0.04 | E94: 0.03 | F94: 0.03 | G94: 0.03 | H94: 0.03 | I94: 0.03
A95: Rationale: Mercury: AMD client share 30.3% Q2-26 and rising; Arm WoA ~3%. Bull assumes Nova Lake + NVIDIA x86 RTX SoCs hold share
A97: External foundry + packaging revenue ($bn) | B97: Scenario | C97: 2027 | D97: 2028 | E97: 2029 | F97: 2030 | G97: 2031 | H97: 2032 | I97: 2033
A98: External foundry + packaging revenue ($bn) - Bear | B98: Bear | C98: 1.3 | D98: 1.6 | E98: 2 | F98: 2.5 | G98: 3 | H98: 3.5 | I98: 4
A99: External foundry + packaging revenue ($bn) - Base | B99: Base | C99: 1.8 | D99: 3.5 | E99: 6 | F99: 8.5 | G99: 11 | H99: 13 | I99: 15
A100: External foundry + packaging revenue ($bn) - Bull | B100: Bull | C100: 3 | D100: 7 | E100: 12 | F100: 18 | G100: 24 | H100: 29 | I100: 33
A101: Rationale: Today ~$1.2bn annualized, mostly Altera. Base = EMIB-T packaging + Apple 18A-P ramp. Bull = 14A anchor customer. All ABOVE Intel's historical base rate
A103: Non-GAAP gross margin | B103: Scenario | C103: 2027 | D103: 2028 | E103: 2029 | F103: 2030 | G103: 2031 | H103: 2032 | I103: 2033
A104: Non-GAAP gross margin - Bear | B104: Bear | C104: 0.39 | D104: 0.39 | E104: 0.4 | F104: 0.4 | G104: 0.4 | H104: 0.4 | I104: 0.4
A105: Non-GAAP gross margin - Base | B105: Base | C105: 0.43 | D105: 0.45 | E105: 0.47 | F105: 0.48 | G105: 0.49 | H105: 0.5 | I105: 0.5
A106: Non-GAAP gross margin - Bull | B106: Bull | C106: 0.46 | D106: 0.49 | E106: 0.52 | F106: 0.54 | G106: 0.55 | H106: 0.56 | I106: 0.57
A107: Rationale: Q2-26 41.8%. Compare TSMC 67.7% (Q2-26), Intel ~60% in the 2010s. Base requires 18A industry-standard yields in 2027 (CFO's own timeline)
A109: Non-GAAP opex growth | B109: Scenario | C109: 2027 | D109: 2028 | E109: 2029 | F109: 2030 | G109: 2031 | H109: 2032 | I109: 2033
A110: Non-GAAP opex growth - Bear | B110: Bear | C110: 0.01 | D110: 0.01 | E110: 0.01 | F110: 0.01 | G110: 0.01 | H110: 0.01 | I110: 0.01
A111: Non-GAAP opex growth - Base | B111: Base | C111: 0.03 | D111: 0.03 | E111: 0.03 | F111: 0.03 | G111: 0.03 | H111: 0.03 | I111: 0.03
...

Sheet Bear
A1: Bear scenario: US$ bn
A3: Line item | B3: 2026E | C3: 2027 | D3: 2028 | E3: 2029 | F3: 2030 | G3: 2031 | H3: 2032 | I3: 2033 | J3: Terminal
A4: Discount period (yrs from 30 Sep 2026) | C4: =Inputs!$B$67+1 | D4: =Inputs!$B$67+2 | E4: =Inputs!$B$67+3 | F4: =Inputs!$B$67+4 | G4: =Inputs!$B$67+5 | H4: =Inputs!$B$67+6 | I4: =Inputs!$B$67+7
A5: DCAI (server/data center) revenue | B5: =Inputs!$B$38 | C5: =B5*(1+C6) | D5: =C5*(1+D6) | E5: =D5*(1+E6) | F5: =E5*(1+F6) | G5: =F5*(1+G6) | H5: =G5*(1+H6) | I5: =H5*(1+I6)
A6: growth | C6: =Inputs!C86+Inputs!$B$72 | D6: =Inputs!D86+Inputs!$B$72 | E6: =Inputs!E86+Inputs!$B$72 | F6: =Inputs!F86+Inputs!$B$72 | G6: =Inputs!G86+Inputs!$B$72 | H6: =Inputs!H86+Inputs!$B$72 | I6: =Inputs!I86+Inputs!$B$72
A7: CCPG (client) revenue | B7: =Inputs!$B$39 | C7: =B7*(1+C8) | D7: =C7*(1+D8) | E7: =D7*(1+E8) | F7: =E7*(1+F8) | G7: =F7*(1+G8) | H7: =G7*(1+H8) | I7: =H7*(1+I8)
A8: growth | C8: =Inputs!C92 | D8: =Inputs!D92 | E8: =Inputs!E92 | F8: =Inputs!F92 | G8: =Inputs!G92 | H8: =Inputs!H92 | I8: =Inputs!I92
A9: External foundry + packaging revenue | B9: =Inputs!$B$40 | C9: =Inputs!C98*Inputs!$B$73 | D9: =Inputs!D98*Inputs!$B$73 | E9: =Inputs!E98*Inputs!$B$73 | F9: =Inputs!F98*Inputs!$B$73 | G9: =Inputs!G98*Inputs!$B$73 | H9: =Inputs!H98*Inputs!$B$73 | I9: =Inputs!I98*Inputs!$B$73
A10: Other revenue (Mobileye etc.) | B10: =Inputs!$B$41 | C10: =B10*(1+Inputs!$B$68) | D10: =C10*(1+Inputs!$B$68) | E10: =D10*(1+Inputs!$B$68) | F10: =E10*(1+Inputs!$B$68) | G10: =F10*(1+Inputs!$B$68) | H10: =G10*(1+Inputs!$B$68) | I10: =H10*(1+Inputs!$B$68)
A11: China domestic-demand revenue exposed (pre-erosion) | B11: =(B5+B7)*Inputs!$B$49*Inputs!$B$50 | C11: =(C5+C7)*Inputs!$B$49*Inputs!$B$50 | D11: =(D5+D7)*Inputs!$B$49*Inputs!$B$50 | E11: =(E5+E7)*Inputs!$B$49*Inputs!$B$50 | F11: =(F5+F7)*Inputs!$B$49*Inputs!$B$50 | G11: =(G5+G7)*Inputs!$B$49*Inputs!$B$50 | H11: =(H5+H7)*Inputs!$B$49*Inputs!$B$50 | I11: =(I5+I7)*Inputs!$B$49*Inputs!$B$50
A12: China erosion index (2026 = 1.00) | B12: 1 | C12: =MAX(0,B12*(1+Inputs!C116+Inputs!$B$75)) | D12: =MAX(0,C12*(1+Inputs!D116+Inputs!$B$75)) | E12: =MAX(0,D12*(1+Inputs!E116+Inputs!$B$75)) | F12: =MAX(0,E12*(1+Inputs!F116+Inputs!$B$75)) | G12: =MAX(0,F12*(1+Inputs!G116+Inputs!$B$75)) | H12: =MAX(0,G12*(1+Inputs!H116+Inputs!$B$75)) | I12: =MAX(0,H12*(1+Inputs!I116+Inputs!$B$75))
A13: Less: China localization / trade revenue loss | B13: =-B11*(1-B12) | C13: =-C11*(1-C12) | D13: =-D11*(1-D12) | E13: =-E11*(1-E12) | F13: =-F11*(1-F12) | G13: =-G11*(1-G12) | H13: =-H11*(1-H12) | I13: =-I11*(1-I12)
A14: Total revenue | B14: =SUM(B5,B7,B9,B10,B13) | C14: =SUM(C5,C7,C9,C10,C13) | D14: =SUM(D5,D7,D9,D10,D13) | E14: =SUM(E5,E7,E9,E10,E13) | F14: =SUM(F5,F7,F9,F10,F13) | G14: =SUM(G5,G7,G9,G10,G13) | H14: =SUM(H5,H7,H9,H10,H13) | I14: =SUM(I5,I7,I9,I10,I13) | J14: =I14*(1+Inputs!$B$63)
A15: growth | C15: =IF(B14=0,0,C14/B14-1) | D15: =IF(C14=0,0,D14/C14-1) | E15: =IF(D14=0,0,E14/D14-1) | F15: =IF(E14=0,0,F14/E14-1) | G15: =IF(F14=0,0,G14/F14-1) | H15: =IF(G14=0,0,H14/G14-1) | I15: =IF(H14=0,0,I14/H14-1)
A16: Non-GAAP gross margin | B16: =Inputs!$B$32+Inputs!$B$71 | C16: =Inputs!C104+Inputs!$B$71 | D16: =Inputs!D104+Inputs!$B$71 | E16: =Inputs!E104+Inputs!$B$71 | F16: =Inputs!F104+Inputs!$B$71 | G16: =Inputs!G104+Inputs!$B$71 | H16: =Inputs!H104+Inputs!$B$71 | I16: =Inputs!I104+Inputs!$B$71
A17: Gross profit | B17: =B14*B16 | C17: =C14*C16 | D17: =D14*D16 | E17: =E14*E16 | F17: =F14*F16 | G17: =G14*G16 | H17: =H14*H16 | I17: =I14*I16
A18: Non-GAAP opex | B18: =Inputs!$B$33 | C18: =B18*(1+Inputs!C110) | D18: =C18*(1+Inputs!D110) | E18: =D18*(1+Inputs!E110) | F18: =E18*(1+Inputs!F110) | G18: =F18*(1+Inputs!G110) | H18: =G18*(1+Inputs!H110) | I18: =H18*(1+Inputs!I110)
A19: Non-GAAP operating income | B19: =B17-B18 | C19: =C17-C18 | D19: =D17-D18 | E19: =E17-E18 | F19: =F17-F18 | G19: =G17-G18 | H19: =H17-H18 | I19: =I17-I18
A20: operating margin | B20: =IF(B14=0,0,B19/B14) | C20: =IF(C14=0,0,C19/C14) | D20: =IF(D14=0,0,D19/D14) | E20: =IF(E14=0,0,E19/E14) | F20: =IF(F14=0,0,F19/F14) | G20: =IF(G14=0,0,G19/G14) | H20: =IF(H14=0,0,H19/H14) | I20: =IF(I14=0,0,I19/I14)
A21: Stock-based compensation | B21: =Inputs!$B$34 | C21: =B21*(1+Inputs!C110) | D21: =C21*(1+Inputs!D110) | E21: =D21*(1+Inputs!E110) | F21: =E21*(1+Inputs!F110) | G21: =F21*(1+Inputs!G110) | H21: =G21*(1+Inputs!H110) | I21: =H21*(1+Inputs!I110)
A22: EBIT after SBC | C22: =C19-C21 | D22: =D19-D21 | E22: =E19-E21 | F22: =F19-F21 | G22: =G19-G21 | H22: =H19-H21 | I22: =I19-I21
A23: Taxes on EBIT | C23: =MAX(0,C22)*Inputs!$B$60 | D23: =MAX(0,D22)*Inputs!$B$60 | E23: =MAX(0,E22)*Inputs!$B$60 | F23: =MAX(0,F22)*Inputs!$B$60 | G23: =MAX(0,G22)*Inputs!$B$60 | H23: =MAX(0,H22)*Inputs!$B$60 | I23: =MAX(0,I22)*Inputs!$B$60
A24: NOPAT | C24: =C22-C23 | D24: =D22-D23 | E24: =E22-E23 | F24: =F22-F23 | G24: =G22-G23 | H24: =H22-H23 | I24: =I22-I23 | J24: =I24*(1+Inputs!$B$63)
A25: D&A | B25: =Inputs!$B$35 | C25: =B25+Inputs!$B$66*(B26-B25) | D25: =C25+Inputs!$B$66*(C26-C25) | E25: =D25+Inputs!$B$66*(D26-D25) | F25: =E25+Inputs!$B$66*(E26-E25) | G25: =F25+Inputs!$B$66*(F26-F25) | H25: =G25+Inputs!$B$66*(G26-G25) | I25: =H25+Inputs!$B$66*(H26-H25) | J25: =I25*(1+Inputs!$B$63)
A26: Capex | B26: =Inputs!$B$36 | C26: =Inputs!C122*Inputs!$B$74 | D26: =Inputs!D122*Inputs!$B$74 | E26: =Inputs!E122*Inputs!$B$74 | F26: =Inputs!F122*Inputs!$B$74 | G26: =Inputs!G122*Inputs!$B$74 | H26: =Inputs!H122*Inputs!$B$74 | I26: =Inputs!I122*Inputs!$B$74 | J26: =J25*Inputs!$B$64
A27: Change in net working capital | C27: =Inputs!$B$65*(C14-B14) | D27: =Inputs!$B$65*(D14-C14) | E27: =Inputs!$B$65*(E14-D14) | F27: =Inputs!$B$65*(F14-E14) | G27: =Inputs!$B$65*(G14-F14) | H27: =Inputs!$B$65*(H14-G14) | I27: =Inputs!$B$65*(I14-H14) | J27: =Inputs!$B$65*(J14-I14)
A28: Unlevered free cash flow | C28: =C24+C25-C26-C27 | D28: =D24+D25-D26-D27 | E28: =E24+E25-E26-E27 | F28: =F24+F25-F26-F27 | G28: =G24+G25-G26-G27 | H28: =H24+H25-H26-H27 | I28: =I24+I25-I26-I27 | J28: =J24+J25-J26-J27
A29: FCF margin | C29: =IF(C14=0,0,C28/C14) | D29: =IF(D14=0,0,D28/D14) | E29: =IF(E14=0,0,E28/E14) | F29: =IF(F14=0,0,F28/F14) | G29: =IF(G14=0,0,G28/G14) | H29: =IF(H14=0,0,H28/H14) | I29: =IF(I14=0,0,I28/I14) | J29: =IF(J14=0,0,J28/J14)
A30: Discount factor | C30: =1/(1+Inputs!$B$62)^C4 | D30: =1/(1+Inputs!$B$62)^D4 | E30: =1/(1+Inputs!$B$62)^E4 | F30: =1/(1+Inputs!$B$62)^F4 | G30: =1/(1+Inputs!$B$62)^G4 | H30: =1/(1+Inputs!$B$62)^H4 | I30: =1/(1+Inputs!$B$62)^I4
A31: PV of FCF | C31: =C28*C30 | D31: =D28*D30 | E31: =E28*E30 | F31: =F28*F30 | G31: =G28*G30 | H31: =H28*H30 | I31: =I28*I30
A33: VALUATION (value per share floored at $0: equity has limited liability)
A34: Sum of PV of explicit FCF (2027-2033) | B34: =SUM(C31:I31)
A35: Terminal value at end-2033 | B35: =IF(Inputs!$B$62<=Inputs!$B$63,0,J28/(Inputs!$B$62-Inputs!$B$63))
A36: PV of terminal value | B36: =B35*I30
A37: Enterprise value | B37: =B34+B36
A38: + Net cash (incl. Aug-26 raise) | B38: =Inputs!$B$16
A39: + Altera stake | B39: =Inputs!$B$14
A40: - Non-controlling interests | B40: =-Inputs!$B$15
A41: Equity value | B41: =B37+B38+B39+B40
A42: Diluted shares (bn) | B42: =Inputs!$B$9
A43: Value per share ($) | B43: =IF(B42=0,0,MAX(0,B41/B42))
A44: Current share price ($) | B44: =Inputs!$B$4
A45: Upside / (downside) vs price | B45: =IF(B44=0,0,B43/B44-1)
A46: Terminal value as % of EV | B46: =IF(B37=0,0,B36/B37)
A47: Implied P/E on 2027 NOPAT/share at value | B47: =IF(C24<=0,0,B43/(C24/B42))
A48: Market P/E on 2027 NOPAT/share | B48: =IF(C24<=0,0,B44/(C24/B42))

Sheet Base
A1: Base scenario: US$ bn
A3: Line item | B3: 2026E | C3: 2027 | D3: 2028 | E3: 2029 | F3: 2030 | G3: 2031 | H3: 2032 | I3: 2033 | J3: Terminal
A4: Discount period (yrs from 30 Sep 2026) | C4: =Inputs!$B$67+1 | D4: =Inputs!$B$67+2 | E4: =Inputs!$B$67+3 | F4: =Inputs!$B$67+4 | G4: =Inputs!$B$67+5 | H4: =Inputs!$B$67+6 | I4: =Inputs!$B$67+7
A5: DCAI (server/data center) revenue | B5: =Inputs!$B$38 | C5: =B5*(1+C6) | D5: =C5*(1+D6) | E5: =D5*(1+E6) | F5: =E5*(1+F6) | G5: =F5*(1+G6) | H5: =G5*(1+H6) | I5: =H5*(1+I6)
A6: growth | C6: =Inputs!C87+Inputs!$B$72 | D6: =Inputs!D87+Inputs!$B$72 | E6: =Inputs!E87+Inputs!$B$72 | F6: =Inputs!F87+Inputs!$B$72 | G6: =Inputs!G87+Inputs!$B$72 | H6: =Inputs!H87+Inputs!$B$72 | I6: =Inputs!I87+Inputs!$B$72
A7: CCPG (client) revenue | B7: =Inputs!$B$39 | C7: =B7*(1+C8) | D7: =C7*(1+D8) | E7: =D7*(1+E8) | F7: =E7*(1+F8) | G7: =F7*(1+G8) | H7: =G7*(1+H8) | I7: =H7*(1+I8)
A8: growth | C8: =Inputs!C93 | D8: =Inputs!D93 | E8: =Inputs!E93 | F8: =Inputs!F93 | G8: =Inputs!G93 | H8: =Inputs!H93 | I8: =Inputs!I93
A9: External foundry + packaging revenue | B9: =Inputs!$B$40 | C9: =Inputs!C99*Inputs!$B$73 | D9: =Inputs!D99*Inputs!$B$73 | E9: =Inputs!E99*Inputs!$B$73 | F9: =Inputs!F99*Inputs!$B$73 | G9: =Inputs!G99*Inputs!$B$73 | H9: =Inputs!H99*Inputs!$B$73 | I9: =Inputs!I99*Inputs!$B$73
A10: Other revenue (Mobileye etc.) | B10: =Inputs!$B$41 | C10: =B10*(1+Inputs!$B$68) | D10: =C10*(1+Inputs!$B$68) | E10: =D10*(1+Inputs!$B$68) | F10: =E10*(1+Inputs!$B$68) | G10: =F10*(1+Inputs!$B$68) | H10: =G10*(1+Inputs!$B$68) | I10: =H10*(1+Inputs!$B$68)
A11: China domestic-demand revenue exposed (pre-erosion) | B11: =(B5+B7)*Inputs!$B$49*Inputs!$B$50 | C11: =(C5+C7)*Inputs!$B$49*Inputs!$B$50 | D11: =(D5+D7)*Inputs!$B$49*Inputs!$B$50 | E11: =(E5+E7)*Inputs!$B$49*Inputs!$B$50 | F11: =(F5+F7)*Inputs!$B$49*Inputs!$B$50 | G11: =(G5+G7)*Inputs!$B$49*Inputs!$B$50 | H11: =(H5+H7)*Inputs!$B$49*Inputs!$B$50 | I11: =(I5+I7)*Inputs!$B$49*Inputs!$B$50
A12: China erosion index (2026 = 1.00) | B12: 1 | C12: =MAX(0,B12*(1+Inputs!C117+Inputs!$B$75)) | D12: =MAX(0,C12*(1+Inputs!D117+Inputs!$B$75)) | E12: =MAX(0,D12*(1+Inputs!E117+Inputs!$B$75)) | F12: =MAX(0,E12*(1+Inputs!F117+Inputs!$B$75)) | G12: =MAX(0,F12*(1+Inputs!G117+Inputs!$B$75)) | H12: =MAX(0,G12*(1+Inputs!H117+Inputs!$B$75)) | I12: =MAX(0,H12*(1+Inputs!I117+Inputs!$B$75))
A13: Less: China localization / trade revenue loss | B13: =-B11*(1-B12) | C13: =-C11*(1-C12) | D13: =-D11*(1-D12) | E13: =-E11*(1-E12) | F13: =-F11*(1-F12) | G13: =-G11*(1-G12) | H13: =-H11*(1-H12) | I13: =-I11*(1-I12)
A14: Total revenue | B14: =SUM(B5,B7,B9,B10,B13) | C14: =SUM(C5,C7,C9,C10,C13) | D14: =SUM(D5,D7,D9,D10,D13) | E14: =SUM(E5,E7,E9,E10,E13) | F14: =SUM(F5,F7,F9,F10,F13) | G14: =SUM(G5,G7,G9,G10,G13) | H14: =SUM(H5,H7,H9,H10,H13) | I14: =SUM(I5,I7,I9,I10,I13) | J14: =I14*(1+Inputs!$B$63)
A15: growth | C15: =IF(B14=0,0,C14/B14-1) | D15: =IF(C14=0,0,D14/C14-1) | E15: =IF(D14=0,0,E14/D14-1) | F15: =IF(E14=0,0,F14/E14-1) | G15: =IF(F14=0,0,G14/F14-1) | H15: =IF(G14=0,0,H14/G14-1) | I15: =IF(H14=0,0,I14/H14-1)
A16: Non-GAAP gross margin | B16: =Inputs!$B$32+Inputs!$B$71 | C16: =Inputs!C105+Inputs!$B$71 | D16: =Inputs!D105+Inputs!$B$71 | E16: =Inputs!E105+Inputs!$B$71 | F16: =Inputs!F105+Inputs!$B$71 | G16: =Inputs!G105+Inputs!$B$71 | H16: =Inputs!H105+Inputs!$B$71 | I16: =Inputs!I105+Inputs!$B$71
A17: Gross profit | B17: =B14*B16 | C17: =C14*C16 | D17: =D14*D16 | E17: =E14*E16 | F17: =F14*F16 | G17: =G14*G16 | H17: =H14*H16 | I17: =I14*I16
A18: Non-GAAP opex | B18: =Inputs!$B$33 | C18: =B18*(1+Inputs!C111) | D18: =C18*(1+Inputs!D111) | E18: =D18*(1+Inputs!E111) | F18: =E18*(1+Inputs!F111) | G18: =F18*(1+Inputs!G111) | H18: =G18*(1+Inputs!H111) | I18: =H18*(1+Inputs!I111)
A19: Non-GAAP operating income | B19: =B17-B18 | C19: =C17-C18 | D19: =D17-D18 | E19: =E17-E18 | F19: =F17-F18 | G19: =G17-G18 | H19: =H17-H18 | I19: =I17-I18
A20: operating margin | B20: =IF(B14=0,0,B19/B14) | C20: =IF(C14=0,0,C19/C14) | D20: =IF(D14=0,0,D19/D14) | E20: =IF(E14=0,0,E19/E14) | F20: =IF(F14=0,0,F19/F14) | G20: =IF(G14=0,0,G19/G14) | H20: =IF(H14=0,0,H19/H14) | I20: =IF(I14=0,0,I19/I14)
A21: Stock-based compensation | B21: =Inputs!$B$34 | C21: =B21*(1+Inputs!C111) | D21: =C21*(1+Inputs!D111) | E21: =D21*(1+Inputs!E111) | F21: =E21*(1+Inputs!F111) | G21: =F21*(1+Inputs!G111) | H21: =G21*(1+Inputs!H111) | I21: =H21*(1+Inputs!I111)
A22: EBIT after SBC | C22: =C19-C21 | D22: =D19-D21 | E22: =E19-E21 | F22: =F19-F21 | G22: =G19-G21 | H22: =H19-H21 | I22: =I19-I21
A23: Taxes on EBIT | C23: =MAX(0,C22)*Inputs!$B$60 | D23: =MAX(0,D22)*Inputs!$B$60 | E23: =MAX(0,E22)*Inputs!$B$60 | F23: =MAX(0,F22)*Inputs!$B$60 | G23: =MAX(0,G22)*Inputs!$B$60 | H23: =MAX(0,H22)*Inputs!$B$60 | I23: =MAX(0,I22)*Inputs!$B$60
A24: NOPAT | C24: =C22-C23 | D24: =D22-D23 | E24: =E22-E23 | F24: =F22-F23 | G24: =G22-G23 | H24: =H22-H23 | I24: =I22-I23 | J24: =I24*(1+Inputs!$B$63)
A25: D&A | B25: =Inputs!$B$35 | C25: =B25+Inputs!$B$66*(B26-B25) | D25: =C25+Inputs!$B$66*(C26-C25) | E25: =D25+Inputs!$B$66*(D26-D25) | F25: =E25+Inputs!$B$66*(E26-E25) | G25: =F25+Inputs!$B$66*(F26-F25) | H25: =G25+Inputs!$B$66*(G26-G25) | I25: =H25+Inputs!$B$66*(H26-H25) | J25: =I25*(1+Inputs!$B$63)
A26: Capex | B26: =Inputs!$B$36 | C26: =Inputs!C123*Inputs!$B$74 | D26: =Inputs!D123*Inputs!$B$74 | E26: =Inputs!E123*Inputs!$B$74 | F26: =Inputs!F123*Inputs!$B$74 | G26: =Inputs!G123*Inputs!$B$74 | H26: =Inputs!H123*Inputs!$B$74 | I26: =Inputs!I123*Inputs!$B$74 | J26: =J25*Inputs!$B$64
A27: Change in net working capital | C27: =Inputs!$B$65*(C14-B14) | D27: =Inputs!$B$65*(D14-C14) | E27: =Inputs!$B$65*(E14-D14) | F27: =Inputs!$B$65*(F14-E14) | G27: =Inputs!$B$65*(G14-F14) | H27: =Inputs!$B$65*(H14-G14) | I27: =Inputs!$B$65*(I14-H14) | J27: =Inputs!$B$65*(J14-I14)
A28: Unlevered free cash flow | C28: =C24+C25-C26-C27 | D28: =D24+D25-D26-D27 | E28: =E24+E25-E26-E27 | F28: =F24+F25-F26-F27 | G28: =G24+G25-G26-G27 | H28: =H24+H25-H26-H27 | I28: =I24+I25-I26-I27 | J28: =J24+J25-J26-J27
A29: FCF margin | C29: =IF(C14=0,0,C28/C14) | D29: =IF(D14=0,0,D28/D14) | E29: =IF(E14=0,0,E28/E14) | F29: =IF(F14=0,0,F28/F14) | G29: =IF(G14=0,0,G28/G14) | H29: =IF(H14=0,0,H28/H14) | I29: =IF(I14=0,0,I28/I14) | J29: =IF(J14=0,0,J28/J14)
A30: Discount factor | C30: =1/(1+Inputs!$B$62)^C4 | D30: =1/(1+Inputs!$B$62)^D4 | E30: =1/(1+Inputs!$B$62)^E4 | F30: =1/(1+Inputs!$B$62)^F4 | G30: =1/(1+Inputs!$B$62)^G4 | H30: =1/(1+Inputs!$B$62)^H4 | I30: =1/(1+Inputs!$B$62)^I4
A31: PV of FCF | C31: =C28*C30 | D31: =D28*D30 | E31: =E28*E30 | F31: =F28*F30 | G31: =G28*G30 | H31: =H28*H30 | I31: =I28*I30
A33: VALUATION (value per share floored at $0: equity has limited liability)
A34: Sum of PV of explicit FCF (2027-2033) | B34: =SUM(C31:I31)
A35: Terminal value at end-2033 | B35: =IF(Inputs!$B$62<=Inputs!$B$63,0,J28/(Inputs!$B$62-Inputs!$B$63))
A36: PV of terminal value | B36: =B35*I30
A37: Enterprise value | B37: =B34+B36
A38: + Net cash (incl. Aug-26 raise) | B38: =Inputs!$B$16
A39: + Altera stake | B39: =Inputs!$B$14
A40: - Non-controlling interests | B40: =-Inputs!$B$15
A41: Equity value | B41: =B37+B38+B39+B40
A42: Diluted shares (bn) | B42: =Inputs!$B$9
A43: Value per share ($) | B43: =IF(B42=0,0,MAX(0,B41/B42))
A44: Current share price ($) | B44: =Inputs!$B$4
A45: Upside / (downside) vs price | B45: =IF(B44=0,0,B43/B44-1)
A46: Terminal value as % of EV | B46: =IF(B37=0,0,B36/B37)
A47: Implied P/E on 2027 NOPAT/share at value | B47: =IF(C24<=0,0,B43/(C24/B42))
A48: Market P/E on 2027 NOPAT/share | B48: =IF(C24<=0,0,B44/(C24/B42))

Sheet Bull
A1: Bull scenario: US$ bn
A3: Line item | B3: 2026E | C3: 2027 | D3: 2028 | E3: 2029 | F3: 2030 | G3: 2031 | H3: 2032 | I3: 2033 | J3: Terminal
A4: Discount period (yrs from 30 Sep 2026) | C4: =Inputs!$B$67+1 | D4: =Inputs!$B$67+2 | E4: =Inputs!$B$67+3 | F4: =Inputs!$B$67+4 | G4: =Inputs!$B$67+5 | H4: =Inputs!$B$67+6 | I4: =Inputs!$B$67+7
A5: DCAI (server/data center) revenue | B5: =Inputs!$B$38 | C5: =B5*(1+C6) | D5: =C5*(1+D6) | E5: =D5*(1+E6) | F5: =E5*(1+F6) | G5: =F5*(1+G6) | H5: =G5*(1+H6) | I5: =H5*(1+I6)
A6: growth | C6: =Inputs!C88+Inputs!$B$72 | D6: =Inputs!D88+Inputs!$B$72 | E6: =Inputs!E88+Inputs!$B$72 | F6: =Inputs!F88+Inputs!$B$72 | G6: =Inputs!G88+Inputs!$B$72 | H6: =Inputs!H88+Inputs!$B$72 | I6: =Inputs!I88+Inputs!$B$72
A7: CCPG (client) revenue | B7: =Inputs!$B$39 | C7: =B7*(1+C8) | D7: =C7*(1+D8) | E7: =D7*(1+E8) | F7: =E7*(1+F8) | G7: =F7*(1+G8) | H7: =G7*(1+H8) | I7: =H7*(1+I8)
A8: growth | C8: =Inputs!C94 | D8: =Inputs!D94 | E8: =Inputs!E94 | F8: =Inputs!F94 | G8: =Inputs!G94 | H8: =Inputs!H94 | I8: =Inputs!I94
A9: External foundry + packaging revenue | B9: =Inputs!$B$40 | C9: =Inputs!C100*Inputs!$B$73 | D9: =Inputs!D100*Inputs!$B$73 | E9: =Inputs!E100*Inputs!$B$73 | F9: =Inputs!F100*Inputs!$B$73 | G9: =Inputs!G100*Inputs!$B$73 | H9: =Inputs!H100*Inputs!$B$73 | I9: =Inputs!I100*Inputs!$B$73
A10: Other revenue (Mobileye etc.) | B10: =Inputs!$B$41 | C10: =B10*(1+Inputs!$B$68) | D10: =C10*(1+Inputs!$B$68) | E10: =D10*(1+Inputs!$B$68) | F10: =E10*(1+Inputs!$B$68) | G10: =F10*(1+Inputs!$B$68) | H10: =G10*(1+Inputs!$B$68) | I10: =H10*(1+Inputs!$B$68)
A11: China domestic-demand revenue exposed (pre-erosion) | B11: =(B5+B7)*Inputs!$B$49*Inputs!$B$50 | C11: =(C5+C7)*Inputs!$B$49*Inputs!$B$50 | D11: =(D5+D7)*Inputs!$B$49*Inputs!$B$50 | E11: =(E5+E7)*Inputs!$B$49*Inputs!$B$50 | F11: =(F5+F7)*Inputs!$B$49*Inputs!$B$50 | G11: =(G5+G7)*Inputs!$B$49*Inputs!$B$50 | H11: =(H5+H7)*Inputs!$B$49*Inputs!$B$50 | I11: =(I5+I7)*Inputs!$B$49*Inputs!$B$50
A12: China erosion index (2026 = 1.00) | B12: 1 | C12: =MAX(0,B12*(1+Inputs!C118+Inputs!$B$75)) | D12: =MAX(0,C12*(1+Inputs!D118+Inputs!$B$75)) | E12: =MAX(0,D12*(1+Inputs!E118+Inputs!$B$75)) | F12: =MAX(0,E12*(1+Inputs!F118+Inputs!$B$75)) | G12: =MAX(0,F12*(1+Inputs!G118+Inputs!$B$75)) | H12: =MAX(0,G12*(1+Inputs!H118+Inputs!$B$75)) | I12: =MAX(0,H12*(1+Inputs!I118+Inputs!$B$75))
A13: Less: China localization / trade revenue loss | B13: =-B11*(1-B12) | C13: =-C11*(1-C12) | D13: =-D11*(1-D12) | E13: =-E11*(1-E12) | F13: =-F11*(1-F12) | G13: =-G11*(1-G12) | H13: =-H11*(1-H12) | I13: =-I11*(1-I12)
A14: Total revenue | B14: =SUM(B5,B7,B9,B10,B13) | C14: =SUM(C5,C7,C9,C10,C13) | D14: =SUM(D5,D7,D9,D10,D13) | E14: =SUM(E5,E7,E9,E10,E13) | F14: =SUM(F5,F7,F9,F10,F13) | G14: =SUM(G5,G7,G9,G10,G13) | H14: =SUM(H5,H7,H9,H10,H13) | I14: =SUM(I5,I7,I9,I10,I13) | J14: =I14*(1+Inputs!$B$63)
A15: growth | C15: =IF(B14=0,0,C14/B14-1) | D15: =IF(C14=0,0,D14/C14-1) | E15: =IF(D14=0,0,E14/D14-1) | F15: =IF(E14=0,0,F14/E14-1) | G15: =IF(F14=0,0,G14/F14-1) | H15: =IF(G14=0,0,H14/G14-1) | I15: =IF(H14=0,0,I14/H14-1)
A16: Non-GAAP gross margin | B16: =Inputs!$B$32+Inputs!$B$71 | C16: =Inputs!C106+Inputs!$B$71 | D16: =Inputs!D106+Inputs!$B$71 | E16: =Inputs!E106+Inputs!$B$71 | F16: =Inputs!F106+Inputs!$B$71 | G16: =Inputs!G106+Inputs!$B$71 | H16: =Inputs!H106+Inputs!$B$71 | I16: =Inputs!I106+Inputs!$B$71
A17: Gross profit | B17: =B14*B16 | C17: =C14*C16 | D17: =D14*D16 | E17: =E14*E16 | F17: =F14*F16 | G17: =G14*G16 | H17: =H14*H16 | I17: =I14*I16
A18: Non-GAAP opex | B18: =Inputs!$B$33 | C18: =B18*(1+Inputs!C112) | D18: =C18*(1+Inputs!D112) | E18: =D18*(1+Inputs!E112) | F18: =E18*(1+Inputs!F112) | G18: =F18*(1+Inputs!G112) | H18: =G18*(1+Inputs!H112) | I18: =H18*(1+Inputs!I112)
A19: Non-GAAP operating income | B19: =B17-B18 | C19: =C17-C18 | D19: =D17-D18 | E19: =E17-E18 | F19: =F17-F18 | G19: =G17-G18 | H19: =H17-H18 | I19: =I17-I18
A20: operating margin | B20: =IF(B14=0,0,B19/B14) | C20: =IF(C14=0,0,C19/C14) | D20: =IF(D14=0,0,D19/D14) | E20: =IF(E14=0,0,E19/E14) | F20: =IF(F14=0,0,F19/F14) | G20: =IF(G14=0,0,G19/G14) | H20: =IF(H14=0,0,H19/H14) | I20: =IF(I14=0,0,I19/I14)
A21: Stock-based compensation | B21: =Inputs!$B$34 | C21: =B21*(1+Inputs!C112) | D21: =C21*(1+Inputs!D112) | E21: =D21*(1+Inputs!E112) | F21: =E21*(1+Inputs!F112) | G21: =F21*(1+Inputs!G112) | H21: =G21*(1+Inputs!H112) | I21: =H21*(1+Inputs!I112)
A22: EBIT after SBC | C22: =C19-C21 | D22: =D19-D21 | E22: =E19-E21 | F22: =F19-F21 | G22: =G19-G21 | H22: =H19-H21 | I22: =I19-I21
A23: Taxes on EBIT | C23: =MAX(0,C22)*Inputs!$B$60 | D23: =MAX(0,D22)*Inputs!$B$60 | E23: =MAX(0,E22)*Inputs!$B$60 | F23: =MAX(0,F22)*Inputs!$B$60 | G23: =MAX(0,G22)*Inputs!$B$60 | H23: =MAX(0,H22)*Inputs!$B$60 | I23: =MAX(0,I22)*Inputs!$B$60
A24: NOPAT | C24: =C22-C23 | D24: =D22-D23 | E24: =E22-E23 | F24: =F22-F23 | G24: =G22-G23 | H24: =H22-H23 | I24: =I22-I23 | J24: =I24*(1+Inputs!$B$63)
A25: D&A | B25: =Inputs!$B$35 | C25: =B25+Inputs!$B$66*(B26-B25) | D25: =C25+Inputs!$B$66*(C26-C25) | E25: =D25+Inputs!$B$66*(D26-D25) | F25: =E25+Inputs!$B$66*(E26-E25) | G25: =F25+Inputs!$B$66*(F26-F25) | H25: =G25+Inputs!$B$66*(G26-G25) | I25: =H25+Inputs!$B$66*(H26-H25) | J25: =I25*(1+Inputs!$B$63)
A26: Capex | B26: =Inputs!$B$36 | C26: =Inputs!C124*Inputs!$B$74 | D26: =Inputs!D124*Inputs!$B$74 | E26: =Inputs!E124*Inputs!$B$74 | F26: =Inputs!F124*Inputs!$B$74 | G26: =Inputs!G124*Inputs!$B$74 | H26: =Inputs!H124*Inputs!$B$74 | I26: =Inputs!I124*Inputs!$B$74 | J26: =J25*Inputs!$B$64
A27: Change in net working capital | C27: =Inputs!$B$65*(C14-B14) | D27: =Inputs!$B$65*(D14-C14) | E27: =Inputs!$B$65*(E14-D14) | F27: =Inputs!$B$65*(F14-E14) | G27: =Inputs!$B$65*(G14-F14) | H27: =Inputs!$B$65*(H14-G14) | I27: =Inputs!$B$65*(I14-H14) | J27: =Inputs!$B$65*(J14-I14)
A28: Unlevered free cash flow | C28: =C24+C25-C26-C27 | D28: =D24+D25-D26-D27 | E28: =E24+E25-E26-E27 | F28: =F24+F25-F26-F27 | G28: =G24+G25-G26-G27 | H28: =H24+H25-H26-H27 | I28: =I24+I25-I26-I27 | J28: =J24+J25-J26-J27
A29: FCF margin | C29: =IF(C14=0,0,C28/C14) | D29: =IF(D14=0,0,D28/D14) | E29: =IF(E14=0,0,E28/E14) | F29: =IF(F14=0,0,F28/F14) | G29: =IF(G14=0,0,G28/G14) | H29: =IF(H14=0,0,H28/H14) | I29: =IF(I14=0,0,I28/I14) | J29: =IF(J14=0,0,J28/J14)
A30: Discount factor | C30: =1/(1+Inputs!$B$62)^C4 | D30: =1/(1+Inputs!$B$62)^D4 | E30: =1/(1+Inputs!$B$62)^E4 | F30: =1/(1+Inputs!$B$62)^F4 | G30: =1/(1+Inputs!$B$62)^G4 | H30: =1/(1+Inputs!$B$62)^H4 | I30: =1/(1+Inputs!$B$62)^I4
A31: PV of FCF | C31: =C28*C30 | D31: =D28*D30 | E31: =E28*E30 | F31: =F28*F30 | G31: =G28*G30 | H31: =H28*H30 | I31: =I28*I30
A33: VALUATION (value per share floored at $0: equity has limited liability)
A34: Sum of PV of explicit FCF (2027-2033) | B34: =SUM(C31:I31)
A35: Terminal value at end-2033 | B35: =IF(Inputs!$B$62<=Inputs!$B$63,0,J28/(Inputs!$B$62-Inputs!$B$63))
A36: PV of terminal value | B36: =B35*I30
A37: Enterprise value | B37: =B34+B36
A38: + Net cash (incl. Aug-26 raise) | B38: =Inputs!$B$16
A39: + Altera stake | B39: =Inputs!$B$14
A40: - Non-controlling interests | B40: =-Inputs!$B$15
A41: Equity value | B41: =B37+B38+B39+B40
A42: Diluted shares (bn) | B42: =Inputs!$B$9
A43: Value per share ($) | B43: =IF(B42=0,0,MAX(0,B41/B42))
A44: Current share price ($) | B44: =Inputs!$B$4
A45: Upside / (downside) vs price | B45: =IF(B44=0,0,B43/B44-1)
A46: Terminal value as % of EV | B46: =IF(B37=0,0,B36/B37)
A47: Implied P/E on 2027 NOPAT/share at value | B47: =IF(C24<=0,0,B43/(C24/B42))
A48: Market P/E on 2027 NOPAT/share | B48: =IF(C24<=0,0,B44/(C24/B42))
